Workbook
Name UPDATE: 'Data Sheet'!$E$1

Sheet Financials>>

Sheet Historicial Financials
B2: ="Historical Financial Statement-"&'Data Sheet'!B1 -> Historical Financial Statement-AVENUE SUPERMARTS LTD
B3: Years | C3: ='Data Sheet'!E16 -> 43921 | D3: ='Data Sheet'!F16 -> 44286 | E3: ='Data Sheet'!G16 -> 44651 | F3: ='Data Sheet'!H16 -> 45016 | G3: ='Data Sheet'!I16 -> 45382 | H3: ='Data Sheet'!J16 -> 45747 | I3: ='Data Sheet'!K16 -> 46112 | J3: LTM
A5: # | B5: Income Statements
B6: Sales | C6: =IFERROR('Data Sheet'!E17,0) -> 24870.2 | D6: =IFERROR('Data Sheet'!F17,0) -> 24143.06 | E6: =IFERROR('Data Sheet'!G17,0) -> 30976.27 | F6: =IFERROR('Data Sheet'!H17,0) -> 42839.56 | G6: =IFERROR('Data Sheet'!I17,0) -> 50788.83 | H6: =IFERROR('Data Sheet'!J17,0) -> 59358.05 | I6: =IFERROR('Data Sheet'!K17,0) -> 68820.74 | J6: =IFERROR(SUM(#REF!),0) -> 0
B7: Sales Growth | C7: - | D7: =IFERROR(D6/C6-1,0) -> -0.029237401 | E7: =IFERROR(E6/D6-1,0) -> 0.28302999 | F7: =IFERROR(F6/E6-1,0) -> 0.38297994 | G7: =IFERROR(G6/F6-1,0) -> 0.1855591 | H7: =IFERROR(H6/G6-1,0) -> 0.16872253 | I7: =IFERROR(I6/H6-1,0) -> 0.15941713
B9: COGS | C9: =IFERROR(SUM('Data Sheet'!E18,'Data Sheet'!E20,'Data Sheet'!E20:E22)-1*'Data Sheet'!E19,0) -> 22582.51 | D9: =IFERROR(SUM('Data Sheet'!F18,'Data Sheet'!F20,'Data Sheet'!F20:F22)-1*'Data Sheet'!F19,0) -> 22187.09 | E9: =IFERROR(SUM('Data Sheet'!G18,'Data Sheet'!G20,'Data Sheet'!G20:G22)-1*'Data Sheet'!G19,0) -> 28236.32 | F9: =IFERROR(SUM('Data Sheet'!H18,'Data Sheet'!H20,'Data Sheet'!H20:H22)-1*'Data Sheet'!H19,0) -> 38877.91 | G9: =IFERROR(SUM('Data Sheet'!I18,'Data Sheet'!I20,'Data Sheet'!I20:I22)-1*'Data Sheet'!I19,0) -> 46258.97 | H9: =IFERROR(SUM('Data Sheet'!J18,'Data Sheet'!J20,'Data Sheet'!J20:J22)-1*'Data Sheet'!J19,0) -> 54366.52 | I9: =IFERROR(SUM('Data Sheet'!K18,'Data Sheet'!K20,'Data Sheet'!K20:K22)-1*'Data Sheet'!K19,0) -> 60001.21 | J9: =IFERROR(SUM('Data Sheet'!H43:K43),0) -> 65868.68
B10: COGS % Sales | C10: =IFERROR(C9/C6,0) -> 0.90801481 | D10: =IFERROR(D9/D6,0) -> 0.91898417 | E10: =IFERROR(E9/E6,0) -> 0.91154681 | F10: =IFERROR(F9/F6,0) -> 0.90752356 | G10: =IFERROR(G9/G6,0) -> 0.91080992 | H10: =IFERROR(H9/H6,0) -> 0.91590812 | I10: =IFERROR(I9/I6,0) -> 0.87184779
B12: Gross Profit | C12: =IFERROR(C6-C9,0) -> 2287.69 | D12: =IFERROR(D6-D9,0) -> 1955.97 | E12: =IFERROR(E6-E9,0) -> 2739.95 | F12: =IFERROR(F6-F9,0) -> 3961.65 | G12: =IFERROR(G6-G9,0) -> 4529.86 | H12: =IFERROR(H6-H9,0) -> 4991.53 | I12: =IFERROR(I6-I9,0) -> 8819.53 | J12: =IFERROR(J6-J9,0) -> -65868.68
B13: Gross Margin | C13: =IFERROR(C12/C6,0) -> 0.091985187 | D13: =IFERROR(D12/D6,0) -> 0.081015828 | E13: =IFERROR(E12/E6,0) -> 0.088453193 | F13: =IFERROR(F12/F6,0) -> 0.09247644 | G13: =IFERROR(G12/G6,0) -> 0.089190084 | H13: =IFERROR(H12/H6,0) -> 0.08409188 | I13: =IFERROR(I12/I6,0) -> 0.12815221 | J13: =IFERROR(J12/J6,0) -> 0
B15: Selling & General Expenses | C15: =IFERROR(SUM('Data Sheet'!E23:E24),0) -> 347.62 | D15: =IFERROR(SUM('Data Sheet'!F23:F24),0) -> 385.34 | E15: =IFERROR(SUM('Data Sheet'!G23:G24),0) -> 445.46 | F15: =IFERROR(SUM('Data Sheet'!H23:H24),0) -> 637.5 | G15: =IFERROR(SUM('Data Sheet'!I23:I24),0) -> 800.81 | H15: =IFERROR(SUM('Data Sheet'!J23:J24),0) -> 944.77 | I15: =IFERROR(SUM('Data Sheet'!K23:K24),0) -> 3632.94
B16: S&G Exp. | C16: =C15/C6 -> 0.013977371 | D16: =D15/D6 -> 0.015960694 | E16: =E15/E6 -> 0.014380686 | F16: =F15/F6 -> 0.014881105 | G16: =G15/G6 -> 0.015767443 | H16: =H15/H6 -> 0.01591646 | I16: =I15/I6 -> 0.052788447 | J16: =J15/J6 -> #DIV/0!
B18: EBITDA | C18: =IFERROR(C12-C15,0) -> 1940.07 | D18: =IFERROR(D12-D15,0) -> 1570.63 | E18: =IFERROR(E12-E15,0) -> 2294.49 | F18: =IFERROR(F12-F15,0) -> 3324.15 | G18: =IFERROR(G12-G15,0) -> 3729.05 | H18: =IFERROR(H12-H15,0) -> 4046.76 | I18: =IFERROR(I12-I15,0) -> 5186.59 | J18: =IFERROR(SUM('Data Sheet'!H50:K50),0) -> 5386.89
B19: EBITDA Margin | C19: =C18/C6 -> 0.078007817 | D19: =D18/D6 -> 0.065055134 | E19: =E18/E6 -> 0.074072508 | F19: =F18/F6 -> 0.077595335 | G19: =G18/G6 -> 0.07342264 | H19: =H18/H6 -> 0.06817542 | I19: =I18/I6 -> 0.075363764 | J19: =J18/J6 -> #DIV/0!
B21: Interest | C21: =IFERROR('Data Sheet'!E27,0) -> 69.12 | D21: =IFERROR('Data Sheet'!F27,0) -> 41.65 | E21: =IFERROR('Data Sheet'!G27,0) -> 53.79 | F21: =IFERROR('Data Sheet'!H27,0) -> 67.41 | G21: =IFERROR('Data Sheet'!I27,0) -> 58.13 | H21: =IFERROR('Data Sheet'!J27,0) -> 69.45 | I21: =IFERROR('Data Sheet'!K27,0) -> 142.05 | J21: =IFERROR(SUM('Data Sheet'!H46:K46),0) -> 167.03
B22: Interest % Sales | C22: =IFERROR(C21/C6,0) -> 0.0027792298 | D22: =IFERROR(D21/D6,0) -> 0.0017251334 | E22: =IFERROR(E21/E6,0) -> 0.0017364905 | F22: =IFERROR(F21/F6,0) -> 0.0015735456 | G22: =IFERROR(G21/G6,0) -> 0.001144543 | H22: =IFERROR(H21/H6,0) -> 0.0011700182 | I22: =IFERROR(I21/I6,0) -> 0.002064058 | J22: =IFERROR(J21/J6,0) -> 0
B24: Depreciation | C24: =IFERROR('Data Sheet'!E26,0) -> 374.41 | D24: =IFERROR('Data Sheet'!F26,0) -> 414.16 | E24: =IFERROR('Data Sheet'!G26,0) -> 498.08 | F24: =IFERROR('Data Sheet'!H26,0) -> 638.87 | G24: =IFERROR('Data Sheet'!I26,0) -> 730.76 | H24: =IFERROR('Data Sheet'!J26,0) -> 869.52 | I24: =IFERROR('Data Sheet'!K26,0) -> 1037.02 | J24: =IFERROR(SUM('Data Sheet'!H45:K45),0) -> 1093.02
B25: Depreciation % Sales | C25: =IFERROR(C24/C6,0) -> 0.015054563 | D25: =IFERROR(D24/D6,0) -> 0.017154412 | E25: =IFERROR(E24/E6,0) -> 0.016079405 | F25: =IFERROR(F24/F6,0) -> 0.014913085 | G25: =IFERROR(G24/G6,0) -> 0.014388203 | H25: =IFERROR(H24/H6,0) -> 0.014648729 | I25: =IFERROR(I24/I6,0) -> 0.015068423 | J25: =IFERROR(J24/J6,0) -> 0
B27: EBT | C27: =IFERROR(C18-SUM(C21,C24),0) -> 1496.54 | D27: =IFERROR(D18-SUM(D21,D24),0) -> 1114.82 | E27: =IFERROR(E18-SUM(E21,E24),0) -> 1742.62 | F27: =IFERROR(F18-SUM(F21,F24),0) -> 2617.87 | G27: =IFERROR(G18-SUM(G21,G24),0) -> 2940.16 | H27: =IFERROR(H18-SUM(H21,H24),0) -> 3107.79 | I27: =IFERROR(I18-SUM(I21,I24),0) -> 4007.52 | J27: =IFERROR(J18-SUM(J21,J24),0) -> 4126.84
B28: EBT % Sales | C28: =IFERROR(C27/C6,0) -> 0.060174024 | D28: =IFERROR(D27/D6,0) -> 0.046175588 | E28: =IFERROR(E27/E6,0) -> 0.056256612 | F28: =IFERROR(F27/F6,0) -> 0.061108704 | G28: =IFERROR(G27/G6,0) -> 0.057889894 | H28: =IFERROR(H27/H6,0) -> 0.052356673 | I28: =IFERROR(I27/I6,0) -> 0.058231283 | J28: =IFERROR(J27/J6,0) -> 0
B30: Tax | C30: =IFERROR('Data Sheet'!E30-'Data Sheet'!E28,0) -> -443.69 | D30: =IFERROR('Data Sheet'!F30-'Data Sheet'!F28,0) -> -383.96 | E30: =IFERROR('Data Sheet'!G30-'Data Sheet'!G28,0) -> -571.57 | F30: =IFERROR('Data Sheet'!H30-'Data Sheet'!H28,0) -> -681.58 | G30: =IFERROR('Data Sheet'!I30-'Data Sheet'!I28,0) -> -925.16 | H30: =IFERROR('Data Sheet'!J30-'Data Sheet'!J28,0) -> -964.65 | I30: =IFERROR('Data Sheet'!K30-'Data Sheet'!K28,0) -> -1111.13 | J30: =IFERROR('Data Sheet'!L30-'Data Sheet'!L28,0) -> 0
B31: Effective Tax Rate | C31: =IFERROR(C30/C27,0) -> -0.29647721 | D31: =IFERROR(D30/D27,0) -> -0.34441434 | E31: =IFERROR(E30/E27,0) -> -0.32799463 | F31: =IFERROR(F30/F27,0) -> -0.2603567 | G31: =IFERROR(G30/G27,0) -> -0.31466315 | H31: =IFERROR(H30/H27,0) -> -0.31039742 | I31: =IFERROR(I30/I27,0) -> -0.27726125 | J31: =IFERROR(J30/J27,0) -> 0
B33: Net Profit | C33: =IFERROR(C27-C30,0) -> 1940.23 | D33: =IFERROR(D27-D30,0) -> 1498.78 | E33: =IFERROR(E27-E30,0) -> 2314.19 | F33: =IFERROR(F27-F30,0) -> 3299.45 | G33: =IFERROR(G27-G30,0) -> 3865.32 | H33: =IFERROR(H27-H30,0) -> 4072.44 | I33: =IFERROR(I27-I30,0) -> 5118.65 | J33: =IFERROR(J27-J30,0) -> 4126.84
B34: Net Margin | C34: =IFERROR(C33/C6,0) -> 0.07801425 | D34: =IFERROR(D33/D6,0) -> 0.062079123 | E34: =IFERROR(E33/E6,0) -> 0.074708478 | F34: =IFERROR(F33/F6,0) -> 0.077018765 | G34: =IFERROR(G33/G6,0) -> 0.076105711 | H34: =IFERROR(H33/H6,0) -> 0.068608049 | I34: =IFERROR(I33/I6,0) -> 0.074376561 | J34: =IFERROR(J33/J6,0) -> 0
B36: No. of Equity Shares | C36: =IFERROR('Data Sheet'!E93,0) -> 64.78 | D36: =IFERROR('Data Sheet'!F93,0) -> 64.78 | E36: =IFERROR('Data Sheet'!G93,0) -> 64.78 | F36: =IFERROR('Data Sheet'!H93,0) -> 64.83 | G36: =IFERROR('Data Sheet'!I93,0) -> 65.07 | H36: =IFERROR('Data Sheet'!J93,0) -> 65.07 | I36: =IFERROR('Data Sheet'!K93,0) -> 65.2
B38: EPS | C38: =IFERROR(C33/C36,0) -> 29.951065 | D38: =IFERROR(D33/D36,0) -> 23.136462 | E38: =IFERROR(E33/E36,0) -> 35.723835 | F38: =IFERROR(F33/F36,0) -> 50.893876 | G38: =IFERROR(G33/G36,0) -> 59.40249 | H38: =IFERROR(H33/H36,0) -> 62.585523 | I38: =IFERROR(I33/I36,0) -> 78.506902
B39: EPS Growth | D39: =IFERROR(D38/C38-1,0) -> -0.22752457 | E39: =IFERROR(E38/D38-1,0) -> 0.54404916 | F39: =IFERROR(F38/E38-1,0) -> 0.42464763 | G39: =IFERROR(G38/F38-1,0) -> 0.16718344 | H39: =IFERROR(H38/G38-1,0) -> 0.053584179 | I39: =IFERROR(I38/H38-1,0) -> 0.25439395
B41: Dividend per share | C41: 0 | D41: 0 | E41: 0 | F41: 0 | G41: 0 | H41: 0 | I41: 0
B42: Dividend payout ratio | C42: =IFERROR(C41/C38,0) -> 0 | D42: =IFERROR(D41/D38,0) -> 0 | E42: =IFERROR(E41/E38,0) -> 0 | F42: =IFERROR(F41/F38,0) -> 0 | G42: =IFERROR(G41/G38,0) -> 0 | H42: =IFERROR(H41/H38,0) -> 0 | I42: =IFERROR(I41/I38,0) -> 0
B44: Retained Earnings | C44: =IFERROR(IF(C38>C41,1-C42,0),0) -> 1 | D44: =IFERROR(IF(D38>D41,1-D42,0),0) -> 1 | E44: =IFERROR(IF(E38>E41,1-E42,0),0) -> 1 | F44: =IFERROR(IF(F38>F41,1-F42,0),0) -> 1 | G44: =IFERROR(IF(G38>G41,1-G42,0),0) -> 1 | H44: =IFERROR(IF(H38>H41,1-H42,0),0) -> 1 | I44: =IFERROR(IF(I38>I41,1-I42,0),0) -> 1
A46: # | B46: Balance Sheet
B47: Equity Share Capital | C47: =IFERROR('Data Sheet'!E57,0) -> 647.77 | D47: =IFERROR('Data Sheet'!F57,0) -> 647.77 | E47: =IFERROR('Data Sheet'!G57,0) -> 647.77 | F47: =IFERROR('Data Sheet'!H57,0) -> 648.26 | G47: =IFERROR('Data Sheet'!I57,0) -> 650.73 | H47: =IFERROR('Data Sheet'!J57,0) -> 650.73 | I47: =IFERROR('Data Sheet'!K57,0) -> 651.96
B48: Reserves | C48: =IFERROR('Data Sheet'!E58,0) -> 10431.97 | D48: =IFERROR('Data Sheet'!F58,0) -> 11535.94 | E48: =IFERROR('Data Sheet'!G58,0) -> 13029.87 | F48: =IFERROR('Data Sheet'!H58,0) -> 15430.44 | G48: =IFERROR('Data Sheet'!I58,0) -> 18047.09 | H48: =IFERROR('Data Sheet'!J58,0) -> 20777.02 | I48: =IFERROR('Data Sheet'!K58,0) -> 23812.08
B49: Borrowings | C49: =IFERROR('Data Sheet'!E59,0) -> 333.19 | D49: =IFERROR('Data Sheet'!F59,0) -> 392.71 | E49: =IFERROR('Data Sheet'!G59,0) -> 646.94 | F49: =IFERROR('Data Sheet'!H59,0) -> 642.98 | G49: =IFERROR('Data Sheet'!I59,0) -> 592.16 | H49: =IFERROR('Data Sheet'!J59,0) -> 819.62 | I49: =IFERROR('Data Sheet'!K59,0) -> 2424.99
B50: Other Liabilities | C50: =IFERROR('Data Sheet'!E60,0) -> 663.23 | D50: =IFERROR('Data Sheet'!F60,0) -> 1078.63 | E50: =IFERROR('Data Sheet'!G60,0) -> 1146.4 | F50: =IFERROR('Data Sheet'!H60,0) -> 1382.84 | G50: =IFERROR('Data Sheet'!I60,0) -> 1882.5 | H50: =IFERROR('Data Sheet'!J60,0) -> 2065.41 | I50: =IFERROR('Data Sheet'!K60,0) -> 2635.23
B51: Total Liabilities | C51: =IFERROR(SUM(C47:C50),0) -> 12076.16 | D51: =IFERROR(SUM(D47:D50),0) -> 13655.05 | E51: =IFERROR(SUM(E47:E50),0) -> 15470.98 | F51: =IFERROR(SUM(F47:F50),0) -> 18104.52 | G51: =IFERROR(SUM(G47:G50),0) -> 21172.48 | H51: =IFERROR(SUM(H47:H50),0) -> 24312.78 | I51: =IFERROR(SUM(I47:I50),0) -> 29524.26
B53: Fixed Assets Net Block | C53: =IFERROR('Data Sheet'!E62,0) -> 5948.03 | D53: =IFERROR('Data Sheet'!F62,0) -> 7008.8 | E53: =IFERROR('Data Sheet'!G62,0) -> 9260.02 | F53: =IFERROR('Data Sheet'!H62,0) -> 11340.48 | G53: =IFERROR('Data Sheet'!I62,0) -> 13415 | H53: =IFERROR('Data Sheet'!J62,0) -> 16206.46 | I53: =IFERROR('Data Sheet'!K62,0) -> 20090.31
B54: Capital Work in Progress | C54: =IFERROR('Data Sheet'!E63,0) -> 364.4 | D54: =IFERROR('Data Sheet'!F63,0) -> 1019.59 | E54: =IFERROR('Data Sheet'!G63,0) -> 1129.34 | F54: =IFERROR('Data Sheet'!H63,0) -> 829.16 | G54: =IFERROR('Data Sheet'!I63,0) -> 935.22 | H54: =IFERROR('Data Sheet'!J63,0) -> 1099.35 | I54: =IFERROR('Data Sheet'!K63,0) -> 1299.96
B55: Investments | C55: =IFERROR('Data Sheet'!E64,0) -> 14.68 | D55: =IFERROR('Data Sheet'!F64,0) -> 2.95 | E55: =IFERROR('Data Sheet'!G64,0) -> 5.94 | F55: =IFERROR('Data Sheet'!H64,0) -> 202.2 | G55: =IFERROR('Data Sheet'!I64,0) -> 106.67 | H55: =IFERROR('Data Sheet'!J64,0) -> 3.26 | I55: =IFERROR('Data Sheet'!K64,0) -> 4.01
B56: Other Assets | C56: =IFERROR('Data Sheet'!E65-SUM('Data Sheet'!E67:E69),0) -> 3674.22 | D56: =IFERROR('Data Sheet'!F65-SUM('Data Sheet'!F67:F69),0) -> 1886.27 | E56: =IFERROR('Data Sheet'!G65-SUM('Data Sheet'!G67:G69),0) -> 1967.55 | F56: =IFERROR('Data Sheet'!H65-SUM('Data Sheet'!H67:H69),0) -> 1018.71 | G56: =IFERROR('Data Sheet'!I65-SUM('Data Sheet'!I67:I69),0) -> 1983.73 | H56: =IFERROR('Data Sheet'!J65-SUM('Data Sheet'!J67:J69),0) -> 1447.35 | I56: =IFERROR('Data Sheet'!K65-SUM('Data Sheet'!K67:K69),0) -> 1776.22
B57: Total Non Current Assets | C57: =IFERROR(SUM(C53:C56),0) -> 10001.33 | D57: =IFERROR(SUM(D53:D56),0) -> 9917.61 | E57: =IFERROR(SUM(E53:E56),0) -> 12362.85 | F57: =IFERROR(SUM(F53:F56),0) -> 13390.55 | G57: =IFERROR(SUM(G53:G56),0) -> 16440.62 | H57: =IFERROR(SUM(H53:H56),0) -> 18756.42 | I57: =IFERROR(SUM(I53:I56),0) -> 23170.5
B59: Receivables | C59: =IFERROR('Data Sheet'!E67,0) -> 19.55 | D59: =IFERROR('Data Sheet'!F67,0) -> 43.58 | E59: =IFERROR('Data Sheet'!G67,0) -> 66.89 | F59: =IFERROR('Data Sheet'!H67,0) -> 62.16 | G59: =IFERROR('Data Sheet'!I67,0) -> 166.37 | H59: =IFERROR('Data Sheet'!J67,0) -> 153.79 | I59: =IFERROR('Data Sheet'!K67,0) -> 149.34
B60: Inventory | C60: =IFERROR('Data Sheet'!E68,0) -> 1947.4 | D60: =IFERROR('Data Sheet'!F68,0) -> 2248.28 | E60: =IFERROR('Data Sheet'!G68,0) -> 2742.66 | F60: =IFERROR('Data Sheet'!H68,0) -> 3243.48 | G60: =IFERROR('Data Sheet'!I68,0) -> 3927.31 | H60: =IFERROR('Data Sheet'!J68,0) -> 5044.37 | I60: =IFERROR('Data Sheet'!K68,0) -> 5900.64
B61: Cash & Bank | C61: =IFERROR('Data Sheet'!E69,0) -> 107.88 | D61: =IFERROR('Data Sheet'!F69,0) -> 1445.58 | E61: =IFERROR('Data Sheet'!G69,0) -> 298.58 | F61: =IFERROR('Data Sheet'!H69,0) -> 1408.33 | G61: =IFERROR('Data Sheet'!I69,0) -> 638.18 | H61: =IFERROR('Data Sheet'!J69,0) -> 358.2 | I61: =IFERROR('Data Sheet'!K69,0) -> 303.78
B62: Total Current Assets | C62: =IFERROR(SUM(C59:C61),0) -> 2074.83 | D62: =IFERROR(SUM(D59:D61),0) -> 3737.44 | E62: =IFERROR(SUM(E59:E61),0) -> 3108.13 | F62: =IFERROR(SUM(F59:F61),0) -> 4713.97 | G62: =IFERROR(SUM(G59:G61),0) -> 4731.86 | H62: =IFERROR(SUM(H59:H61),0) -> 5556.36 | I62: =IFERROR(SUM(I59:I61),0) -> 6353.76
B63: Total Assets | C63: =IFERROR(SUM(C62,C57),0) -> 12076.16 | D63: =IFERROR(SUM(D62,D57),0) -> 13655.05 | E63: =IFERROR(SUM(E62,E57),0) -> 15470.98 | F63: =IFERROR(SUM(F62,F57),0) -> 18104.52 | G63: =IFERROR(SUM(G62,G57),0) -> 21172.48 | H63: =IFERROR(SUM(H62,H57),0) -> 24312.78 | I63: =IFERROR(SUM(I62,I57),0) -> 29524.26
A65: # | B65: Cash Flow Statements
B66: Operating Activities
B67: Profit from operations | C67: =IFERROR(Cashflow!C3,0) -> 2149 | D67: =IFERROR(Cashflow!D3,0) -> 1764 | E67: =IFERROR(Cashflow!E3,0) -> 2515 | F67: =IFERROR(Cashflow!F3,0) -> 3659 | G67: =IFERROR(Cashflow!G3,0) -> 4131 | H67: =IFERROR(Cashflow!H3,0) -> 4535 | I67: =IFERROR(Cashflow!I3,0) -> 5233
B68: Receivables | C68: =IFERROR(Cashflow!C4,0) -> 45 | D68: =IFERROR(Cashflow!D4,0) -> -24 | E68: =IFERROR(Cashflow!E4,0) -> -23 | F68: =IFERROR(Cashflow!F4,0) -> 5 | G68: =IFERROR(Cashflow!G4,0) -> -104 | H68: =IFERROR(Cashflow!H4,0) -> 13 | I68: =IFERROR(Cashflow!I4,0) -> 4
B69: Inventory | C69: =IFERROR(Cashflow!C5,0) -> -339 | D69: =IFERROR(Cashflow!D5,0) -> -301 | E69: =IFERROR(Cashflow!E5,0) -> -494 | F69: =IFERROR(Cashflow!F5,0) -> -501 | G69: =IFERROR(Cashflow!G5,0) -> -684 | H69: =IFERROR(Cashflow!H5,0) -> -1117 | I69: =IFERROR(Cashflow!I5,0) -> -856
B70: Payables | C70: =IFERROR(Cashflow!C6,0) -> -30 | D70: =IFERROR(Cashflow!D6,0) -> 145 | E70: =IFERROR(Cashflow!E6,0) -> 11 | F70: =IFERROR(Cashflow!F6,0) -> 165 | G70: =IFERROR(Cashflow!G6,0) -> 231 | H70: =IFERROR(Cashflow!H6,0) -> 86 | I70: =IFERROR(Cashflow!I6,0) -> 267
B71: Other WC items | C71: =IFERROR(Cashflow!C7,0) -> 0 | D71: =IFERROR(Cashflow!D7,0) -> 0 | E71: =IFERROR(Cashflow!E7,0) -> 0 | F71: =IFERROR(Cashflow!F7,0) -> 0 | G71: =IFERROR(Cashflow!G7,0) -> 0 | H71: =IFERROR(Cashflow!H7,0) -> 0 | I71: =IFERROR(Cashflow!I7,0) -> 0
B72: Working capital changes | C72: =IFERROR(Cashflow!C8,0) -> 2 | D72: =IFERROR(Cashflow!D8,0) -> 12 | E72: =IFERROR(Cashflow!E8,0) -> -3 | F72: =IFERROR(Cashflow!F8,0) -> 0 | G72: =IFERROR(Cashflow!G8,0) -> 0 | H72: =IFERROR(Cashflow!H8,0) -> 0 | I72: =IFERROR(Cashflow!I8,0) -> 0
B73: Interest paid | C73: =IFERROR(Cashflow!C9,0) -> -54 | D73: =IFERROR(Cashflow!D9,0) -> 41 | E73: =IFERROR(Cashflow!E9,0) -> -73 | F73: =IFERROR(Cashflow!F9,0) -> 12 | G73: =IFERROR(Cashflow!G9,0) -> -87 | H73: =IFERROR(Cashflow!H9,0) -> -94 | I73: =IFERROR(Cashflow!I9,0) -> -114
B74: Direct taxes | C74: =IFERROR(Cashflow!C10,0) -> -376 | D74: =IFERROR(Cashflow!D10,0) -> -127 | E74: =IFERROR(Cashflow!E10,0) -> -582 | F74: =IFERROR(Cashflow!F10,0) -> -320 | G74: =IFERROR(Cashflow!G10,0) -> -644 | H74: =IFERROR(Cashflow!H10,0) -> -1113 | I74: =IFERROR(Cashflow!I10,0) -> -699
B75: Exceptional CF items | C75: =IFERROR(Cashflow!C11,0) -> -492 | D75: =IFERROR(Cashflow!D11,0) -> -262 | E75: =IFERROR(Cashflow!E11,0) -> -560 | F75: =IFERROR(Cashflow!F11,0) -> -709 | G75: =IFERROR(Cashflow!G11,0) -> -742 | H75: =IFERROR(Cashflow!H11,0) -> -959 | I75: =IFERROR(Cashflow!I11,0) -> -1068
B76: Cash From Operating Activities | C76: =IFERROR(SUM(C67:C75),0) -> 905 | D76: =IFERROR(SUM(D67:D75),0) -> 1248 | E76: =IFERROR(SUM(E67:E75),0) -> 791 | F76: =IFERROR(SUM(F67:F75),0) -> 2311 | G76: =IFERROR(SUM(G67:G75),0) -> 2101 | H76: =IFERROR(SUM(H67:H75),0) -> 1351 | I76: =IFERROR(SUM(I67:I75),0) -> 2767
B78: Investing Activities
B79: Fixed assets purchased | C79: =IFERROR(Cashflow!C13,0) -> -1712 | D79: =IFERROR(Cashflow!D13,0) -> -2029 | E79: =IFERROR(Cashflow!E13,0) -> -2410 | F79: =IFERROR(Cashflow!F13,0) -> -2212 | G79: =IFERROR(Cashflow!G13,0) -> -2731 | H79: =IFERROR(Cashflow!H13,0) -> -3423 | I79: =IFERROR(Cashflow!I13,0) -> -4113
B80: Fixed assets sold | C80: =IFERROR(Cashflow!C14,0) -> 6 | D80: =IFERROR(Cashflow!D14,0) -> 2 | E80: =IFERROR(Cashflow!E14,0) -> 21 | F80: =IFERROR(Cashflow!F14,0) -> 5 | G80: =IFERROR(Cashflow!G14,0) -> 9 | H80: =IFERROR(Cashflow!H14,0) -> 6 | I80: =IFERROR(Cashflow!I14,0) -> 0
B81: Investments purchased | C81: =IFERROR(Cashflow!C15,0) -> 0 | D81: =IFERROR(Cashflow!D15,0) -> 0 | E81: =IFERROR(Cashflow!E15,0) -> 0 | F81: =IFERROR(Cashflow!F15,0) -> -193 | G81: =IFERROR(Cashflow!G15,0) -> -4201 | H81: =IFERROR(Cashflow!H15,0) -> -4948 | I81: =IFERROR(Cashflow!I15,0) -> -3119
B82: Investments sold | C82: =IFERROR(Cashflow!C16,0) -> 232 | D82: =IFERROR(Cashflow!D16,0) -> 3 | E82: =IFERROR(Cashflow!E16,0) -> 4 | F82: =IFERROR(Cashflow!F16,0) -> 6 | G82: =IFERROR(Cashflow!G16,0) -> 4324 | H82: =IFERROR(Cashflow!H16,0) -> 5074 | I82: =IFERROR(Cashflow!I16,0) -> 3123
B83: Interest received | C83: =IFERROR(Cashflow!C17,0) -> 0 | D83: =IFERROR(Cashflow!D17,0) -> 0 | E83: =IFERROR(Cashflow!E17,0) -> 0 | F83: =IFERROR(Cashflow!F17,0) -> 0 | G83: =IFERROR(Cashflow!G17,0) -> 0 | H83: =IFERROR(Cashflow!H17,0) -> 0 | I83: =IFERROR(Cashflow!I17,0) -> 0
B84: Investment in group cos | C84: =IFERROR(Cashflow!C18,0) -> 12 | D84: =IFERROR(Cashflow!D18,0) -> 129 | E84: =IFERROR(Cashflow!E18,0) -> 43 | F84: =IFERROR(Cashflow!F18,0) -> 39 | G84: =IFERROR(Cashflow!G18,0) -> 262 | H84: =IFERROR(Cashflow!H18,0) -> 103 | I84: =IFERROR(Cashflow!I18,0) -> 44
B85: Redemp n Canc of Shares | C85: =IFERROR(Cashflow!C19,0) -> 0 | D85: =IFERROR(Cashflow!D19,0) -> 0 | E85: =IFERROR(Cashflow!E19,0) -> 0 | F85: =IFERROR(Cashflow!F19,0) -> 0 | G85: =IFERROR(Cashflow!G19,0) -> 0 | H85: =IFERROR(Cashflow!H19,0) -> 0 | I85: =IFERROR(Cashflow!I19,0) -> 0
B86: Acquisition of companies | C86: =IFERROR(Cashflow!#REF!,0) -> 0 | D86: =IFERROR(Cashflow!#REF!,0) -> 0 | E86: =IFERROR(Cashflow!#REF!,0) -> 0 | F86: =IFERROR(Cashflow!#REF!,0) -> 0 | G86: =IFERROR(Cashflow!#REF!,0) -> 0 | H86: =IFERROR(Cashflow!#REF!,0) -> 0 | I86: =IFERROR(Cashflow!#REF!,0) -> 0
B87: Inter corporate deposits | C87: =IFERROR(Cashflow!#REF!,0) -> 0 | D87: =IFERROR(Cashflow!#REF!,0) -> 0 | E87: =IFERROR(Cashflow!#REF!,0) -> 0 | F87: =IFERROR(Cashflow!#REF!,0) -> 0 | G87: =IFERROR(Cashflow!#REF!,0) -> 0 | H87: =IFERROR(Cashflow!#REF!,0) -> 0 | I87: =IFERROR(Cashflow!#REF!,0) -> 0
B88: Other investing items | C88: =IFERROR(Cashflow!#REF!,0) -> 0 | D88: =IFERROR(Cashflow!#REF!,0) -> 0 | E88: =IFERROR(Cashflow!#REF!,0) -> 0 | F88: =IFERROR(Cashflow!#REF!,0) -> 0 | G88: =IFERROR(Cashflow!#REF!,0) -> 0 | H88: =IFERROR(Cashflow!#REF!,0) -> 0 | I88: =IFERROR(Cashflow!#REF!,0) -> 0
B89: Cash From Investing Activities | C89: =IFERROR(SUM(C79:C88),0) -> -1462 | D89: =IFERROR(SUM(D79:D88),0) -> -1895 | E89: =IFERROR(SUM(E79:E88),0) -> -2342 | F89: =IFERROR(SUM(F79:F88),0) -> -2355 | G89: =IFERROR(SUM(G79:G88),0) -> -2337 | H89: =IFERROR(SUM(H79:H88),0) -> -3188 | I89: =IFERROR(SUM(I79:I88),0) -> -4065
B91: Financing Activities
B92: Proceeds from shares | C92: =IFERROR(Cashflow!C24,0) -> 110 | D92: =IFERROR(Cashflow!D24,0) -> 0 | E92: =IFERROR(Cashflow!E24,0) -> 0 | F92: =IFERROR(Cashflow!F24,0) -> 15 | G92: =IFERROR(Cashflow!G24,0) -> 75 | H92: =IFERROR(Cashflow!H24,0) -> 0 | I92: =IFERROR(Cashflow!I24,0) -> 37
B93: Proceeds from debentures | C93: =IFERROR(Cashflow!C25,0) -> 300 | D93: =IFERROR(Cashflow!D25,0) -> 0 | E93: =IFERROR(Cashflow!E25,0) -> 0 | F93: =IFERROR(Cashflow!F25,0) -> 0 | G93: =IFERROR(Cashflow!G25,0) -> 0 | H93: =IFERROR(Cashflow!H25,0) -> 0 | I93: =IFERROR(Cashflow!I25,0) -> 0
B94: Proceeds from borrowings | C94: =IFERROR(Cashflow!C26,0) -> -512 | D94: =IFERROR(Cashflow!D26,0) -> -34 | E94: =IFERROR(Cashflow!E26,0) -> 0 | F94: =IFERROR(Cashflow!F26,0) -> 0 | G94: =IFERROR(Cashflow!G26,0) -> 0 | H94: =IFERROR(Cashflow!H26,0) -> 0 | I94: =IFERROR(Cashflow!I26,0) -> 0
B95: Repayment of borrowings | C95: =IFERROR(Cashflow!C27,0) -> 1100 | D95: =IFERROR(Cashflow!D27,0) -> 200 | E95: =IFERROR(Cashflow!E27,0) -> 248 | F95: =IFERROR(Cashflow!F27,0) -> 0 | G95: =IFERROR(Cashflow!G27,0) -> 0 | H95: =IFERROR(Cashflow!H27,0) -> 0 | I95: =IFERROR(Cashflow!I27,0) -> 1588
B96: Interest paid fin | C96: =IFERROR(Cashflow!C28,0) -> -1550 | D96: =IFERROR(Cashflow!D28,0) -> -204 | E96: =IFERROR(Cashflow!E28,0) -> -248 | F96: =IFERROR(Cashflow!F28,0) -> 0 | G96: =IFERROR(Cashflow!G28,0) -> 0 | H96: =IFERROR(Cashflow!H28,0) -> 0 | I96: =IFERROR(Cashflow!I28,0) -> -1003
B97: Financial liabilities | C97: =IFERROR(Cashflow!C29,0) -> -68 | D97: =IFERROR(Cashflow!D29,0) -> -44 | E97: =IFERROR(Cashflow!E29,0) -> -54 | F97: =IFERROR(Cashflow!F29,0) -> -67 | G97: =IFERROR(Cashflow!G29,0) -> -58 | H97: =IFERROR(Cashflow!H29,0) -> -69 | I97: =IFERROR(Cashflow!I29,0) -> -141
B98: Other financing items | C98: =IFERROR(Cashflow!C30,0) -> -100 | D98: =IFERROR(Cashflow!D30,0) -> -98 | E98: =IFERROR(Cashflow!E30,0) -> -125 | F98: =IFERROR(Cashflow!F30,0) -> -153 | G98: =IFERROR(Cashflow!G30,0) -> -164 | H98: =IFERROR(Cashflow!H30,0) -> -190 | I98: =IFERROR(Cashflow!I30,0) -> -194
B99: Cash From Financing Activities | C99: =IFERROR(SUM(C92:C98),0) -> -720 | D99: =IFERROR(SUM(D92:D98),0) -> -180 | E99: =IFERROR(SUM(E92:E98),0) -> -179 | F99: =IFERROR(SUM(F92:F98),0) -> -205 | G99: =IFERROR(SUM(G92:G98),0) -> -147 | H99: =IFERROR(SUM(H92:H98),0) -> -259 | I99: =IFERROR(SUM(I92:I98),0) -> 287
B101: Net Cash Flow | C101: =IFERROR(SUM(C99,C89,C76),0) -> -1277 | D101: =IFERROR(SUM(D99,D89,D76),0) -> -827 | E101: =IFERROR(SUM(E99,E89,E76),0) -> -1730 | F101: =IFERROR(SUM(F99,F89,F76),0) -> -249 | G101: =IFERROR(SUM(G99,G89,G76),0) -> -383 | H101: =IFERROR(SUM(H99,H89,H76),0) -> -2096 | I101: =IFERROR(SUM(I99,I89,I76),0) -> -1011

Sheet Common Size Statement
A2: # | B2: ="Common Size P&L Statement-"&'Data Sheet'!B1 -> Common Size P&L Statement-AVENUE SUPERMARTS LTD
B4: Particular | C4: ='Data Sheet'!E16 -> 43921 | D4: ='Data Sheet'!F16 -> 44286 | E4: ='Data Sheet'!G16 -> 44651 | F4: ='Data Sheet'!H16 -> 45016 | G4: ='Data Sheet'!I16 -> 45382 | H4: ='Data Sheet'!J16 -> 45747 | I4: ='Data Sheet'!K16 -> 46112
B6: Sales | C6: ='Data Sheet'!E17/'Data Sheet'!E$17 -> 1 | D6: ='Data Sheet'!F17/'Data Sheet'!F$17 -> 1 | E6: ='Data Sheet'!G17/'Data Sheet'!G$17 -> 1 | F6: ='Data Sheet'!H17/'Data Sheet'!H$17 -> 1 | G6: ='Data Sheet'!I17/'Data Sheet'!I$17 -> 1 | H6: ='Data Sheet'!J17/'Data Sheet'!J$17 -> 1 | I6: ='Data Sheet'!K17/'Data Sheet'!K$17 -> 1
B7: Raw Material Cost | C7: ='Data Sheet'!E18/'Data Sheet'!E$17 -> 0.86214345 | D7: ='Data Sheet'!F18/'Data Sheet'!F$17 -> 0.86383251 | E7: ='Data Sheet'!G18/'Data Sheet'!G$17 -> 0.868141 | F7: ='Data Sheet'!H18/'Data Sheet'!H$17 -> 0.86099787 | G7: ='Data Sheet'!I18/'Data Sheet'!I$17 -> 0.86551137 | H7: ='Data Sheet'!J18/'Data Sheet'!J$17 -> 0.87045919 | I7: ='Data Sheet'!K18/'Data Sheet'!K$17 -> 0.8618912
B8: Change in Inventory | C8: ='Data Sheet'!E19/'Data Sheet'!E$17 -> 0.013620719 | D8: ='Data Sheet'!F19/'Data Sheet'!F$17 -> 0.01246238 | E8: ='Data Sheet'!G19/'Data Sheet'!G$17 -> 0.015959959 | F8: ='Data Sheet'!H19/'Data Sheet'!H$17 -> 0.011690596 | G8: ='Data Sheet'!I19/'Data Sheet'!I$17 -> 0.013463 | H8: ='Data Sheet'!J19/'Data Sheet'!J$17 -> 0.018819014 | I8: ='Data Sheet'!K19/'Data Sheet'!K$17 -> 0.012441889
B9: Power and Fuel | C9: ='Data Sheet'!E20/'Data Sheet'!E$17 -> 0.0075688977 | D9: ='Data Sheet'!F20/'Data Sheet'!F$17 -> 0.007215324 | E9: ='Data Sheet'!G20/'Data Sheet'!G$17 -> 0.0067102979 | F9: ='Data Sheet'!H20/'Data Sheet'!H$17 -> 0.0073441464 | G9: ='Data Sheet'!I20/'Data Sheet'!I$17 -> 0.0074148194 | H9: ='Data Sheet'!J20/'Data Sheet'!J$17 -> 0.007543206 | I9: ='Data Sheet'!K20/'Data Sheet'!K$17 -> 0
B10: Other Mfr. Exp | C10: ='Data Sheet'!E21/'Data Sheet'!E$17 -> 0.025973253 | D10: ='Data Sheet'!F21/'Data Sheet'!F$17 -> 0.030916959 | E10: ='Data Sheet'!G21/'Data Sheet'!G$17 -> 0.026015075 | F10: ='Data Sheet'!H21/'Data Sheet'!H$17 -> 0.02606376 | G10: ='Data Sheet'!I21/'Data Sheet'!I$17 -> 0.026057501 | H10: ='Data Sheet'!J21/'Data Sheet'!J$17 -> 0.029513267 | I10: ='Data Sheet'!K21/'Data Sheet'!K$17 -> 0
B11: Employee Cost | C11: ='Data Sheet'!E22/'Data Sheet'!E$17 -> 0.018381034 | D11: ='Data Sheet'!F22/'Data Sheet'!F$17 -> 0.02226644 | E11: ='Data Sheet'!G22/'Data Sheet'!G$17 -> 0.019930095 | F11: ='Data Sheet'!H22/'Data Sheet'!H$17 -> 0.017464232 | G11: ='Data Sheet'!I22/'Data Sheet'!I$17 -> 0.017874403 | H11: ='Data Sheet'!J22/'Data Sheet'!J$17 -> 0.019668267 | I11: ='Data Sheet'!K22/'Data Sheet'!K$17 -> 0.02239848
B12: Selling and admin | C12: ='Data Sheet'!E23/'Data Sheet'!E$17 -> 0.0026698619 | D12: ='Data Sheet'!F23/'Data Sheet'!F$17 -> 0.0045019148 | E12: ='Data Sheet'!G23/'Data Sheet'!G$17 -> 0.004629673 | F12: ='Data Sheet'!H23/'Data Sheet'!H$17 -> 0.0049496307 | G12: ='Data Sheet'!I23/'Data Sheet'!I$17 -> 0.0054033535 | H12: ='Data Sheet'!J23/'Data Sheet'!J$17 -> 0.0052643239 | I12: ='Data Sheet'!K23/'Data Sheet'!K$17 -> 0
B13: Other Expenses | C13: ='Data Sheet'!E24/'Data Sheet'!E$17 -> 0.011307509 | D13: ='Data Sheet'!F24/'Data Sheet'!F$17 -> 0.011458779 | E13: ='Data Sheet'!G24/'Data Sheet'!G$17 -> 0.0097510126 | F13: ='Data Sheet'!H24/'Data Sheet'!H$17 -> 0.0099314746 | G13: ='Data Sheet'!I24/'Data Sheet'!I$17 -> 0.01036409 | H13: ='Data Sheet'!J24/'Data Sheet'!J$17 -> 0.010652136 | I13: ='Data Sheet'!K24/'Data Sheet'!K$17 -> 0.052788447
B14: Other Income | C14: ='Data Sheet'!E25/'Data Sheet'!E$17 -> 0.0024121237 | D14: ='Data Sheet'!F25/'Data Sheet'!F$17 -> 0.0080532459 | E14: ='Data Sheet'!G25/'Data Sheet'!G$17 -> 0.0036686147 | F14: ='Data Sheet'!H25/'Data Sheet'!H$17 -> 0.0029785553 | G14: ='Data Sheet'!I25/'Data Sheet'!I$17 -> 0.0028466889 | H14: ='Data Sheet'!J25/'Data Sheet'!J$17 -> 0.0019732791 | I14: ='Data Sheet'!K25/'Data Sheet'!K$17 -> 0.0010767103
B15: Depreciation | C15: ='Data Sheet'!E26/'Data Sheet'!E$17 -> 0.015054563 | D15: ='Data Sheet'!F26/'Data Sheet'!F$17 -> 0.017154412 | E15: ='Data Sheet'!G26/'Data Sheet'!G$17 -> 0.016079405 | F15: ='Data Sheet'!H26/'Data Sheet'!H$17 -> 0.014913085 | G15: ='Data Sheet'!I26/'Data Sheet'!I$17 -> 0.014388203 | H15: ='Data Sheet'!J26/'Data Sheet'!J$17 -> 0.014648729 | I15: ='Data Sheet'!K26/'Data Sheet'!K$17 -> 0.015068423
B16: Interest | C16: ='Data Sheet'!E27/'Data Sheet'!E$17 -> 0.0027792298 | D16: ='Data Sheet'!F27/'Data Sheet'!F$17 -> 0.0017251334 | E16: ='Data Sheet'!G27/'Data Sheet'!G$17 -> 0.0017364905 | F16: ='Data Sheet'!H27/'Data Sheet'!H$17 -> 0.0015735456 | G16: ='Data Sheet'!I27/'Data Sheet'!I$17 -> 0.001144543 | H16: ='Data Sheet'!J27/'Data Sheet'!J$17 -> 0.0011700182 | I16: ='Data Sheet'!K27/'Data Sheet'!K$17 -> 0.002064058
B17: Profit before tax | C17: ='Data Sheet'!E28/'Data Sheet'!E$17 -> 0.070155045 | D17: ='Data Sheet'!F28/'Data Sheet'!F$17 -> 0.061444158 | E17: ='Data Sheet'!G28/'Data Sheet'!G$17 -> 0.066635525 | F17: ='Data Sheet'!H28/'Data Sheet'!H$17 -> 0.071431406 | G17: ='Data Sheet'!I28/'Data Sheet'!I$17 -> 0.068151403 | H17: ='Data Sheet'!J28/'Data Sheet'!J$17 -> 0.061873158 | I17: ='Data Sheet'!K28/'Data Sheet'!K$17 -> 0.059307993
... B20: Dividend Amount | C20: ='Data Sheet'!E31/'Data Sheet'!E$17 -> 0 | D20: ='Data Sheet'!F31/'Data Sheet'!F$17 -> 0 | E20: ='Data Sheet'!G31/'Data Sheet'!G$17 -> 0 | F20: ='Data Sheet'!H31/'Data Sheet'!H$17 -> 0 | G20: ='Data Sheet'!I31/'Data Sheet'!I$17 -> 0 | H20: ='Data Sheet'!J31/'Data Sheet'!J$17 -> 0 | I20: ='Data Sheet'!K31/'Data Sheet'!K$17 -> 0
B21: EBITDA | C21: ='Historicial Financials'!C18/'Historicial Financials'!C$6 -> 0.078007817 | D21: ='Historicial Financials'!D18/'Historicial Financials'!D$6 -> 0.065055134 | E21: ='Historicial Financials'!E18/'Historicial Financials'!E$6 -> 0.074072508 | F21: ='Historicial Financials'!F18/'Historicial Financials'!F$6 -> 0.077595335 | G21: ='Historicial Financials'!G18/'Historicial Financials'!G$6 -> 0.07342264 | H21: ='Historicial Financials'!H18/'Historicial Financials'!H$6 -> 0.06817542 | I21: ='Historicial Financials'!I18/'Historicial Financials'!I$6 -> 0.075363764
A23: # | B23: ="Common Size Balance sheet Statement-"&'Data Sheet'!B1 -> Common Size Balance sheet Statement-AVENUE SUPERMARTS LTD
B25: Particular | C25: ='Data Sheet'!E16 -> 43921 | D25: ='Data Sheet'!F16 -> 44286 | E25: ='Data Sheet'!G16 -> 44651 | F25: ='Data Sheet'!H16 -> 45016 | G25: ='Data Sheet'!I16 -> 45382 | H25: ='Data Sheet'!J16 -> 45747 | I25: ='Data Sheet'!K16 -> 46112
B27: Total Liabilities | C27: ='Data Sheet'!E61/'Data Sheet'!E$61 -> 1 | D27: ='Data Sheet'!F61/'Data Sheet'!F$61 -> 1 | E27: ='Data Sheet'!G61/'Data Sheet'!G$61 -> 1 | F27: ='Data Sheet'!H61/'Data Sheet'!H$61 -> 1 | G27: ='Data Sheet'!I61/'Data Sheet'!I$61 -> 1 | H27: ='Data Sheet'!J61/'Data Sheet'!J$61 -> 1 | I27: ='Data Sheet'!K61/'Data Sheet'!K$61 -> 1
B28: Equity Share Capital | C28: ='Data Sheet'!E57/'Data Sheet'!E$61 -> 0.053640396 | D28: ='Data Sheet'!F57/'Data Sheet'!F$61 -> 0.047438127 | E28: ='Data Sheet'!G57/'Data Sheet'!G$61 -> 0.041870004 | F28: ='Data Sheet'!H57/'Data Sheet'!H$61 -> 0.035806528 | G28: ='Data Sheet'!I57/'Data Sheet'!I$61 -> 0.030734708 | H28: ='Data Sheet'!J57/'Data Sheet'!J$61 -> 0.026764936 | I28: ='Data Sheet'!K57/'Data Sheet'!K$61 -> 0.022082179
B29: Reserves | C29: ='Data Sheet'!E58/'Data Sheet'!E$61 -> 0.86384828 | D29: ='Data Sheet'!F58/'Data Sheet'!F$61 -> 0.84481126 | E29: ='Data Sheet'!G58/'Data Sheet'!G$61 -> 0.84221362 | F29: ='Data Sheet'!H58/'Data Sheet'!H$61 -> 0.85229766 | G29: ='Data Sheet'!I58/'Data Sheet'!I$61 -> 0.85238432 | H29: ='Data Sheet'!J58/'Data Sheet'!J$61 -> 0.85457196 | I29: ='Data Sheet'!K58/'Data Sheet'!K$61 -> 0.80652589
B30: Borrowings | C30: ='Data Sheet'!E59/'Data Sheet'!E$61 -> 0.027590724 | D30: ='Data Sheet'!F59/'Data Sheet'!F$61 -> 0.028759323 | E30: ='Data Sheet'!G59/'Data Sheet'!G$61 -> 0.041816356 | F30: ='Data Sheet'!H59/'Data Sheet'!H$61 -> 0.035514888 | G30: ='Data Sheet'!I59/'Data Sheet'!I$61 -> 0.027968382 | H30: ='Data Sheet'!J59/'Data Sheet'!J$61 -> 0.033711488 | I30: ='Data Sheet'!K59/'Data Sheet'!K$61 -> 0.082135505
B31: Other Liabilities | C31: ='Data Sheet'!E60/'Data Sheet'!E$61 -> 0.054920604 | D31: ='Data Sheet'!F60/'Data Sheet'!F$61 -> 0.078991289 | E31: ='Data Sheet'!G60/'Data Sheet'!G$61 -> 0.074100025 | F31: ='Data Sheet'!H60/'Data Sheet'!H$61 -> 0.076380926 | G31: ='Data Sheet'!I60/'Data Sheet'!I$61 -> 0.088912588 | H31: ='Data Sheet'!J60/'Data Sheet'!J$61 -> 0.084951618 | I31: ='Data Sheet'!K60/'Data Sheet'!K$61 -> 0.089256428
B33: Total Assets | C33: ='Data Sheet'!E61/'Data Sheet'!E$61 -> 1 | D33: ='Data Sheet'!F61/'Data Sheet'!F$61 -> 1 | E33: ='Data Sheet'!G61/'Data Sheet'!G$61 -> 1 | F33: ='Data Sheet'!H61/'Data Sheet'!H$61 -> 1 | G33: ='Data Sheet'!I61/'Data Sheet'!I$61 -> 1 | H33: ='Data Sheet'!J61/'Data Sheet'!J$61 -> 1 | I33: ='Data Sheet'!K61/'Data Sheet'!K$61 -> 1
B34: Fixed Assets Net Block | C34: ='Data Sheet'!E62/'Data Sheet'!E$61 -> 0.49254316 | D34: ='Data Sheet'!F62/'Data Sheet'!F$61 -> 0.51327531 | E34: ='Data Sheet'!G62/'Data Sheet'!G$61 -> 0.59854127 | F34: ='Data Sheet'!H62/'Data Sheet'!H$61 -> 0.62638943 | G34: ='Data Sheet'!I62/'Data Sheet'!I$61 -> 0.63360551 | H34: ='Data Sheet'!J62/'Data Sheet'!J$61 -> 0.66658194 | I34: ='Data Sheet'!K62/'Data Sheet'!K$61 -> 0.68046786
B35: Capital Work in Progress | C35: ='Data Sheet'!E63/'Data Sheet'!E$61 -> 0.030175155 | D35: ='Data Sheet'!F63/'Data Sheet'!F$61 -> 0.074667614 | E35: ='Data Sheet'!G63/'Data Sheet'!G$61 -> 0.072997315 | F35: ='Data Sheet'!H63/'Data Sheet'!H$61 -> 0.045798508 | G35: ='Data Sheet'!I63/'Data Sheet'!I$61 -> 0.044171491 | H35: ='Data Sheet'!J63/'Data Sheet'!J$61 -> 0.04521696 | I35: ='Data Sheet'!K63/'Data Sheet'!K$61 -> 0.044030231
B36: Investments | C36: ='Data Sheet'!E64/'Data Sheet'!E$61 -> 0.0012156182 | D36: ='Data Sheet'!F64/'Data Sheet'!F$61 -> 0.00021603729 | E36: ='Data Sheet'!G64/'Data Sheet'!G$61 -> 0.00038394465 | F36: ='Data Sheet'!H64/'Data Sheet'!H$61 -> 0.011168482 | G36: ='Data Sheet'!I64/'Data Sheet'!I$61 -> 0.0050381439 | H36: ='Data Sheet'!J64/'Data Sheet'!J$61 -> 0.00013408586 | I36: ='Data Sheet'!K64/'Data Sheet'!K$61 -> 0.00013582051
B37: Other Assets | C37: ='Data Sheet'!E65/'Data Sheet'!E$61 -> 0.47606607 | D37: ='Data Sheet'!F65/'Data Sheet'!F$61 -> 0.41184104 | E37: ='Data Sheet'!G65/'Data Sheet'!G$61 -> 0.32807747 | F37: ='Data Sheet'!H65/'Data Sheet'!H$61 -> 0.31664358 | G37: ='Data Sheet'!I65/'Data Sheet'!I$61 -> 0.31718486 | H37: ='Data Sheet'!J65/'Data Sheet'!J$61 -> 0.28806702 | I37: ='Data Sheet'!K65/'Data Sheet'!K$61 -> 0.27536609
B38: Receivables | C38: ='Data Sheet'!E67/'Data Sheet'!E$61 -> 0.0016188921 | D38: ='Data Sheet'!F67/'Data Sheet'!F$61 -> 0.0031914933 | E38: ='Data Sheet'!G67/'Data Sheet'!G$61 -> 0.0043235787 | F38: ='Data Sheet'!H67/'Data Sheet'!H$61 -> 0.0034333967 | G38: ='Data Sheet'!I67/'Data Sheet'!I$61 -> 0.0078578419 | H38: ='Data Sheet'!J67/'Data Sheet'!J$61 -> 0.0063254799 | I38: ='Data Sheet'!K67/'Data Sheet'!K$61 -> 0.0050582131
B39: Inventory | C39: ='Data Sheet'!E68/'Data Sheet'!E$61 -> 0.16125987 | D39: ='Data Sheet'!F68/'Data Sheet'!F$61 -> 0.16464824 | E39: ='Data Sheet'!G68/'Data Sheet'!G$61 -> 0.17727772 | F39: ='Data Sheet'!H68/'Data Sheet'!H$61 -> 0.17915305 | G39: ='Data Sheet'!I68/'Data Sheet'!I$61 -> 0.18549126 | H39: ='Data Sheet'!J68/'Data Sheet'!J$61 -> 0.20747812 | I39: ='Data Sheet'!K68/'Data Sheet'!K$61 -> 0.19985734
B40: Cash & Bank | C40: ='Data Sheet'!E69/'Data Sheet'!E$61 -> 0.0089333033 | D40: ='Data Sheet'!F69/'Data Sheet'!F$61 -> 0.10586413 | E40: ='Data Sheet'!G69/'Data Sheet'!G$61 -> 0.019299359 | F40: ='Data Sheet'!H69/'Data Sheet'!H$61 -> 0.077788862 | G40: ='Data Sheet'!I69/'Data Sheet'!I$61 -> 0.030141958 | H40: ='Data Sheet'!J69/'Data Sheet'!J$61 -> 0.014732992 | I40: ='Data Sheet'!K69/'Data Sheet'!K$61 -> 0.010289166

Sheet Ratio Analysis
B2: Historical Financial Statement-SWIGGY LTD
B4: Years | C4: ='Historicial Financials'!C3 -> 43921 | D4: ='Historicial Financials'!D3 -> 44286 | E4: ='Historicial Financials'!E3 -> 44651 | F4: ='Historicial Financials'!F3 -> 45016 | G4: ='Historicial Financials'!G3 -> 45382 | H4: ='Historicial Financials'!H3 -> 45747 | I4: ='Historicial Financials'!I3 -> 46112 | J4: Trend | K4: Mean | L4: Median
B6: SalesGrowth | D6: =IFERROR('Historicial Financials'!D7,0) -> -0.029237401 | E6: =IFERROR('Historicial Financials'!E7,0) -> 0.28302999 | F6: =IFERROR('Historicial Financials'!F7,0) -> 0.38297994 | G6: =IFERROR('Historicial Financials'!G7,0) -> 0.1855591 | H6: =IFERROR('Historicial Financials'!H7,0) -> 0.16872253 | I6: =IFERROR('Historicial Financials'!I7,0) -> 0.15941713 | K6: =IFERROR(AVERAGE(D6:I6),0) -> 0.19174521 | L6: =IFERROR(MEDIAN(D6:I6),0) -> 0.17714081
B7: EBITDA Growth | D7: =IFERROR('Historicial Financials'!D18/'Historicial Financials'!C18-1,0) -> -0.19042612 | E7: =IFERROR('Historicial Financials'!E18/'Historicial Financials'!D18-1,0) -> 0.46087239 | F7: =IFERROR('Historicial Financials'!F18/'Historicial Financials'!E18-1,0) -> 0.44875332 | G7: =IFERROR('Historicial Financials'!G18/'Historicial Financials'!F18-1,0) -> 0.12180557 | H7: =IFERROR('Historicial Financials'!H18/'Historicial Financials'!G18-1,0) -> 0.085198643 | I7: =IFERROR('Historicial Financials'!I18/'Historicial Financials'!H18-1,0) -> 0.28166484 | K7: =IFERROR(AVERAGE(D7:I7),0) -> 0.20131144 | L7: =IFERROR(MEDIAN(D7:I7),0) -> 0.20173521
B8: EBT Growth | D8: =IFERROR('Historicial Financials'!D27/'Historicial Financials'!C27-1,0) -> -0.25506836 | E8: =IFERROR('Historicial Financials'!E27/'Historicial Financials'!D27-1,0) -> 0.56314024 | F8: =IFERROR('Historicial Financials'!F27/'Historicial Financials'!E27-1,0) -> 0.50226096 | G8: =IFERROR('Historicial Financials'!G27/'Historicial Financials'!F27-1,0) -> 0.12311154 | H8: =IFERROR('Historicial Financials'!H27/'Historicial Financials'!G27-1,0) -> 0.057013904 | I8: =IFERROR('Historicial Financials'!I27/'Historicial Financials'!H27-1,0) -> 0.28950798 | K8: =IFERROR(AVERAGE(D8:I8),0) -> 0.21332771 | L8: =IFERROR(MEDIAN(D8:I8),0) -> 0.20630976
B9: Net Profit Growth | D9: =IFERROR('Historicial Financials'!D33/'Historicial Financials'!C33-1,0) -> -0.22752457 | E9: =IFERROR('Historicial Financials'!E33/'Historicial Financials'!D33-1,0) -> 0.54404916 | F9: =IFERROR('Historicial Financials'!F33/'Historicial Financials'!E33-1,0) -> 0.42574724 | G9: =IFERROR('Historicial Financials'!G33/'Historicial Financials'!F33-1,0) -> 0.17150434 | H9: =IFERROR('Historicial Financials'!H33/'Historicial Financials'!G33-1,0) -> 0.053584179 | I9: =IFERROR('Historicial Financials'!I33/'Historicial Financials'!H33-1,0) -> 0.25690004 | K9: =IFERROR(AVERAGE(D9:I9),0) -> 0.2040434 | L9: =IFERROR(MEDIAN(D9:I9),0) -> 0.21420219
B10: Dividend Growth | D10: =IFERROR('Historicial Financials'!D41/'Historicial Financials'!D41-1,0) -> 0 | E10: =IFERROR('Historicial Financials'!E41/'Historicial Financials'!E41-1,0) -> 0 | F10: =IFERROR('Historicial Financials'!F41/'Historicial Financials'!F41-1,0) -> 0 | G10: =IFERROR('Historicial Financials'!G41/'Historicial Financials'!G41-1,0) -> 0 | H10: =IFERROR('Historicial Financials'!H41/'Historicial Financials'!H41-1,0) -> 0 | I10: =IFERROR('Historicial Financials'!I41/'Historicial Financials'!I41-1,0) -> 0 | K10: =IFERROR(AVERAGE(D10:I10),0) -> 0 | L10: =IFERROR(MEDIAN(D10:I10),0) -> 0
B12: Gross Margin | C12: =IFERROR('Historicial Financials'!C13,0) -> 0.091985187 | D12: =IFERROR('Historicial Financials'!D13,0) -> 0.081015828 | E12: =IFERROR('Historicial Financials'!E13,0) -> 0.088453193 | F12: =IFERROR('Historicial Financials'!F13,0) -> 0.09247644 | G12: =IFERROR('Historicial Financials'!G13,0) -> 0.089190084 | H12: =IFERROR('Historicial Financials'!H13,0) -> 0.08409188 | I12: =IFERROR('Historicial Financials'!I13,0) -> 0.12815221 | K12: =IFERROR(AVERAGE(C12:I12),0) -> 0.093623546 | L12: =IFERROR(MEDIAN(D12:I12),0) -> 0.088821639
B13: Operating Margin | C13: =IFERROR('Historicial Financials'!C19,0) -> 0.078007817 | D13: =IFERROR('Historicial Financials'!D19,0) -> 0.065055134 | E13: =IFERROR('Historicial Financials'!E19,0) -> 0.074072508 | F13: =IFERROR('Historicial Financials'!F19,0) -> 0.077595335 | G13: =IFERROR('Historicial Financials'!G19,0) -> 0.07342264 | H13: =IFERROR('Historicial Financials'!H19,0) -> 0.06817542 | I13: =IFERROR('Historicial Financials'!I19,0) -> 0.075363764 | K13: =IFERROR(AVERAGE(C13:I13),0) -> 0.073098945 | L13: =IFERROR(MEDIAN(D13:I13),0) -> 0.073747574
B14: EBITDA Margin | C14: =IFERROR('Historicial Financials'!C19,0) -> 0.078007817 | D14: =IFERROR('Historicial Financials'!D19,0) -> 0.065055134 | E14: =IFERROR('Historicial Financials'!E19,0) -> 0.074072508 | F14: =IFERROR('Historicial Financials'!F19,0) -> 0.077595335 | G14: =IFERROR('Historicial Financials'!G19,0) -> 0.07342264 | H14: =IFERROR('Historicial Financials'!H19,0) -> 0.06817542 | I14: =IFERROR('Historicial Financials'!I19,0) -> 0.075363764 | K14: =IFERROR(AVERAGE(C14:I14),0) -> 0.073098945 | L14: =IFERROR(MEDIAN(D14:I14),0) -> 0.073747574
B15: EBIT Margin | C15: =IFERROR(('Historicial Financials'!C18-'Historicial Financials'!C24)/'Historicial Financials'!C6,0) -> 0.062953253 | D15: =IFERROR(('Historicial Financials'!D18-'Historicial Financials'!D24)/'Historicial Financials'!D6,0) -> 0.047900722 | E15: =IFERROR(('Historicial Financials'!E18-'Historicial Financials'!E24)/'Historicial Financials'!E6,0) -> 0.057993102 | F15: =IFERROR(('Historicial Financials'!F18-'Historicial Financials'!F24)/'Historicial Financials'!F6,0) -> 0.06268225 | G15: =IFERROR(('Historicial Financials'!G18-'Historicial Financials'!G24)/'Historicial Financials'!G6,0) -> 0.059034437 | H15: =IFERROR(('Historicial Financials'!H18-'Historicial Financials'!H24)/'Historicial Financials'!H6,0) -> 0.053526691 | I15: =IFERROR(('Historicial Financials'!I18-'Historicial Financials'!I24)/'Historicial Financials'!I6,0) -> 0.060295341 | K15: =IFERROR(AVERAGE(C15:I15),0) -> 0.0577694 | L15: =IFERROR(MEDIAN(D15:I15),0) -> 0.05851377
B16: EBT Margin | C16: =IFERROR('Historicial Financials'!C28,0) -> 0.060174024 | D16: =IFERROR('Historicial Financials'!D28,0) -> 0.046175588 | E16: =IFERROR('Historicial Financials'!E28,0) -> 0.056256612 | F16: =IFERROR('Historicial Financials'!F28,0) -> 0.061108704 | G16: =IFERROR('Historicial Financials'!G28,0) -> 0.057889894 | H16: =IFERROR('Historicial Financials'!H28,0) -> 0.052356673 | I16: =IFERROR('Historicial Financials'!I28,0) -> 0.058231283 | K16: =IFERROR(AVERAGE(C16:I16),0) -> 0.05602754 | L16: =IFERROR(MEDIAN(D16:I16),0) -> 0.057073253
B17: Net Profit Margin | C17: =IFERROR('Historicial Financials'!C34,0) -> 0.07801425 | D17: =IFERROR('Historicial Financials'!D34,0) -> 0.062079123 | E17: =IFERROR('Historicial Financials'!E34,0) -> 0.074708478 | F17: =IFERROR('Historicial Financials'!F34,0) -> 0.077018765 | G17: =IFERROR('Historicial Financials'!G34,0) -> 0.076105711 | H17: =IFERROR('Historicial Financials'!H34,0) -> 0.068608049 | I17: =IFERROR('Historicial Financials'!I34,0) -> 0.074376561 | K17: =IFERROR(AVERAGE(C17:I17),0) -> 0.072987277 | L17: =IFERROR(MEDIAN(D17:I17),0) -> 0.07454252
B19: SalesExpenses%Sales | C19: =IFERROR('Historicial Financials'!C16,0) -> 0.013977371 | D19: =IFERROR('Historicial Financials'!D16,0) -> 0.015960694 | E19: =IFERROR('Historicial Financials'!E16,0) -> 0.014380686 | F19: =IFERROR('Historicial Financials'!F16,0) -> 0.014881105 | G19: =IFERROR('Historicial Financials'!G16,0) -> 0.015767443 | H19: =IFERROR('Historicial Financials'!H16,0) -> 0.01591646 | I19: =IFERROR('Historicial Financials'!I16,0) -> 0.052788447 | K19: =IFERROR(AVERAGE(C19:I19),0) -> 0.020524601 | L19: =IFERROR(MEDIAN(D19:I19),0) -> 0.015841951
B20: Depreciation%Sales | C20: =IFERROR('Historicial Financials'!C25,0) -> 0.015054563 | D20: =IFERROR('Historicial Financials'!D25,0) -> 0.017154412 | E20: =IFERROR('Historicial Financials'!E25,0) -> 0.016079405 | F20: =IFERROR('Historicial Financials'!F25,0) -> 0.014913085 | G20: =IFERROR('Historicial Financials'!G25,0) -> 0.014388203 | H20: =IFERROR('Historicial Financials'!H25,0) -> 0.014648729 | I20: =IFERROR('Historicial Financials'!I25,0) -> 0.015068423 | K20: =IFERROR(AVERAGE(C20:I20),0) -> 0.015329546 | L20: =IFERROR(MEDIAN(D20:I20),0) -> 0.014990754
B21: OperatingIncome%Sales | C21: =IFERROR(C15,0) -> 0.062953253 | D21: =IFERROR(D15,0) -> 0.047900722 | E21: =IFERROR(E15,0) -> 0.057993102 | F21: =IFERROR(F15,0) -> 0.06268225 | G21: =IFERROR(G15,0) -> 0.059034437 | H21: =IFERROR(H15,0) -> 0.053526691 | I21: =IFERROR(I15,0) -> 0.060295341 | K21: =IFERROR(AVERAGE(C21:I21),0) -> 0.0577694 | L21: =IFERROR(MEDIAN(D21:I21),0) -> 0.05851377
B23: Return on Capital Employed | C23: =IFERROR(('Historicial Financials'!C18-'Historicial Financials'!C24)/SUM('Historicial Financials'!C47:C49),0) -> 0.137183 | D23: =IFERROR(('Historicial Financials'!D18-'Historicial Financials'!D24)/SUM('Historicial Financials'!D47:D49),0) -> 0.091955421 | E23: =IFERROR(('Historicial Financials'!E18-'Historicial Financials'!E24)/SUM('Historicial Financials'!E47:E49),0) -> 0.12540752 | F23: =IFERROR(('Historicial Financials'!F18-'Historicial Financials'!F24)/SUM('Historicial Financials'!F47:F49),0) -> 0.16058674 | G23: =IFERROR(('Historicial Financials'!G18-'Historicial Financials'!G24)/SUM('Historicial Financials'!G47:G49),0) -> 0.15543251 | H23: =IFERROR(('Historicial Financials'!H18-'Historicial Financials'!H24)/SUM('Historicial Financials'!H47:H49),0) -> 0.14281418 | I23: =IFERROR(('Historicial Financials'!I18-'Historicial Financials'!I24)/SUM('Historicial Financials'!I47:I49),0) -> 0.15432204 | K23: =IFERROR(AVERAGE(C23:I23),0) -> 0.13824306 | L23: =IFERROR(MEDIAN(D23:I23),0) -> 0.14856811
B24: Retained Earnings% | C24: =IFERROR('Historicial Financials'!C44,0) -> 1 | D24: =IFERROR('Historicial Financials'!D44,0) -> 1 | E24: =IFERROR('Historicial Financials'!E44,0) -> 1 | F24: =IFERROR('Historicial Financials'!F44,0) -> 1 | G24: =IFERROR('Historicial Financials'!G44,0) -> 1 | H24: =IFERROR('Historicial Financials'!H44,0) -> 1 | I24: =IFERROR('Historicial Financials'!I44,0) -> 1 | K24: =IFERROR(AVERAGE(C24:I24),0) -> 1 | L24: =IFERROR(MEDIAN(D24:I24),0) -> 1
B25: Return on Equity% | C25: =IFERROR('Historicial Financials'!C33/SUM('Historicial Financials'!C47:C48),0) -> 0.17511512 | D25: =IFERROR('Historicial Financials'!D33/SUM('Historicial Financials'!D47:D48),0) -> 0.12301508 | E25: =IFERROR('Historicial Financials'!E33/SUM('Historicial Financials'!E47:E48),0) -> 0.16919512 | F25: =IFERROR('Historicial Financials'!F33/SUM('Historicial Financials'!F47:F48),0) -> 0.20520627 | G25: =IFERROR('Historicial Financials'!G33/SUM('Historicial Financials'!G47:G48),0) -> 0.2067257 | H25: =IFERROR('Historicial Financials'!H33/SUM('Historicial Financials'!H47:H48),0) -> 0.19005449 | I25: =IFERROR('Historicial Financials'!I33/SUM('Historicial Financials'!I47:I48),0) -> 0.20923159 | K25: =IFERROR(AVERAGE(C25:I25),0) -> 0.18264905 | L25: =IFERROR(MEDIAN(D25:I25),0) -> 0.19763038
B26: Self Sustained Growth Rate | C26: =IFERROR(C24*C25,0) -> 0.17511512 | D26: =IFERROR(D24*D25,0) -> 0.12301508 | E26: =IFERROR(E24*E25,0) -> 0.16919512 | F26: =IFERROR(F24*F25,0) -> 0.20520627 | G26: =IFERROR(G24*G25,0) -> 0.2067257 | H26: =IFERROR(H24*H25,0) -> 0.19005449 | I26: =IFERROR(I24*I25,0) -> 0.20923159 | K26: =IFERROR(AVERAGE(C26:I26),0) -> 0.18264905 | L26: =IFERROR(MEDIAN(D26:I26),0) -> 0.19763038
B27: Interest Coverage Ratio | C27: =IFERROR(('Historicial Financials'!C18-'Historicial Financials'!C24)/'Historicial Financials'!C21,0) -> 22.651331 | D27: =IFERROR(('Historicial Financials'!D18-'Historicial Financials'!D24)/'Historicial Financials'!D21,0) -> 27.766387 | E27: =IFERROR(('Historicial Financials'!E18-'Historicial Financials'!E24)/'Historicial Financials'!E21,0) -> 33.396728 | F27: =IFERROR(('Historicial Financials'!F18-'Historicial Financials'!F24)/'Historicial Financials'!F21,0) -> 39.835039 | G27: =IFERROR(('Historicial Financials'!G18-'Historicial Financials'!G24)/'Historicial Financials'!G21,0) -> 51.579047 | H27: =IFERROR(('Historicial Financials'!H18-'Historicial Financials'!H24)/'Historicial Financials'!H21,0) -> 45.748596 | I27: =IFERROR(('Historicial Financials'!I18-'Historicial Financials'!I24)/'Historicial Financials'!I21,0) -> 29.212038 | K27: =IFERROR(AVERAGE(C27:I27),0) -> 35.741309 | L27: =IFERROR(MEDIAN(D27:I27),0) -> 36.615884
B29: Debtor Turnover Ratio | C29: =IFERROR('Historicial Financials'!C6/'Historicial Financials'!C59,0) -> 1272.133 | D29: =IFERROR('Historicial Financials'!D6/'Historicial Financials'!D59,0) -> 553.99403 | E29: =IFERROR('Historicial Financials'!E6/'Historicial Financials'!E59,0) -> 463.09269 | F29: =IFERROR('Historicial Financials'!F6/'Historicial Financials'!F59,0) -> 689.18211 | G29: =IFERROR('Historicial Financials'!G6/'Historicial Financials'!G59,0) -> 305.27637 | H29: =IFERROR('Historicial Financials'!H6/'Historicial Financials'!H59,0) -> 385.9682 | I29: =IFERROR('Historicial Financials'!I6/'Historicial Financials'!I59,0) -> 460.8326 | K29: =IFERROR(AVERAGE(C29:I29),0) -> 590.06843 | L29: =IFERROR(MEDIAN(D29:I29),0) -> 461.96264
B30: Creditor Turnover Ratio | C30: =IFERROR('Historicial Financials'!C6/'Historicial Financials'!C50,0) -> 37.498605 | D30: =IFERROR('Historicial Financials'!D6/'Historicial Financials'!D50,0) -> 22.383079 | E30: =IFERROR('Historicial Financials'!E6/'Historicial Financials'!E50,0) -> 27.020473 | F30: =IFERROR('Historicial Financials'!F6/'Historicial Financials'!F50,0) -> 30.979405 | G30: =IFERROR('Historicial Financials'!G6/'Historicial Financials'!G50,0) -> 26.979458 | H30: =IFERROR('Historicial Financials'!H6/'Historicial Financials'!H50,0) -> 28.739112 | I30: =IFERROR('Historicial Financials'!I6/'Historicial Financials'!I50,0) -> 26.115648 | K30: =IFERROR(AVERAGE(C30:I30),0) -> 28.530826 | L30: =IFERROR(MEDIAN(D30:I30),0) -> 26.999965
B31: Inventory Turnover Ratio | C31: =IFERROR('Historicial Financials'!C6/'Historicial Financials'!C60,0) -> 12.770977 | D31: =IFERROR('Historicial Financials'!D6/'Historicial Financials'!D60,0) -> 10.738458 | E31: =IFERROR('Historicial Financials'!E6/'Historicial Financials'!E60,0) -> 11.294244 | F31: =IFERROR('Historicial Financials'!F6/'Historicial Financials'!F60,0) -> 13.2079 | G31: =IFERROR('Historicial Financials'!G6/'Historicial Financials'!G60,0) -> 12.932218 | H31: =IFERROR('Historicial Financials'!H6/'Historicial Financials'!H60,0) -> 11.767188 | I31: =IFERROR('Historicial Financials'!I6/'Historicial Financials'!I60,0) -> 11.663267 | K31: =IFERROR(AVERAGE(C31:I31),0) -> 12.053464 | L31: =IFERROR(MEDIAN(D31:I31),0) -> 11.715228
B32: Fixed Assets Turnover Ratio | C32: =IFERROR('Historicial Financials'!C6/'Historicial Financials'!C53,0) -> 4.1812499 | D32: =IFERROR('Historicial Financials'!D6/'Historicial Financials'!D53,0) -> 3.4446781 | E32: =IFERROR('Historicial Financials'!E6/'Historicial Financials'!E53,0) -> 3.3451623 | F32: =IFERROR('Historicial Financials'!F6/'Historicial Financials'!F53,0) -> 3.7775791 | G32: =IFERROR('Historicial Financials'!G6/'Historicial Financials'!G53,0) -> 3.7859732 | H32: =IFERROR('Historicial Financials'!H6/'Historicial Financials'!H53,0) -> 3.6626166 | I32: =IFERROR('Historicial Financials'!I6/'Historicial Financials'!I53,0) -> 3.4255688 | K32: =IFERROR(AVERAGE(C32:I32),0) -> 3.660404 | L32: =IFERROR(MEDIAN(D32:I32),0) -> 3.5536474
B33: Capital Turnover Ratio | C33: =IFERROR('Historicial Financials'!C6/SUM('Historicial Financials'!C47:C48),0) -> 2.2446556 | D33: =IFERROR('Historicial Financials'!D6/SUM('Historicial Financials'!D47:D48),0) -> 1.9815852 | E33: =IFERROR('Historicial Financials'!E6/SUM('Historicial Financials'!E47:E48),0) -> 2.2647379 | F33: =IFERROR('Historicial Financials'!F6/SUM('Historicial Financials'!F47:F48),0) -> 2.6643671 | G33: =IFERROR('Historicial Financials'!G6/SUM('Historicial Financials'!G47:G48),0) -> 2.7162969 | H33: =IFERROR('Historicial Financials'!H6/SUM('Historicial Financials'!H47:H48),0) -> 2.7701485 | I33: =IFERROR('Historicial Financials'!I6/SUM('Historicial Financials'!I47:I48),0) -> 2.8131388 | K33: =IFERROR(AVERAGE(C33:I33),0) -> 2.4935614 | L33: =IFERROR(MEDIAN(D33:I33),0) -> 2.690332
B35: Debtor Days | C35: =IFERROR(365/C29,0) -> 0.28691969 | D35: =IFERROR(365/D29,0) -> 0.65885186 | E35: =IFERROR(365/E29,0) -> 0.78817914 | F35: =IFERROR(365/F29,0) -> 0.52961328 | G35: =IFERROR(365/G29,0) -> 1.1956379 | H35: =IFERROR(365/H29,0) -> 0.94567375 | I35: =IFERROR(365/I29,0) -> 0.79204467 | K35: =IFERROR(AVERAGE(C35:I35),0) -> 0.74241718 | L35: =IFERROR(MEDIAN(D35:I35),0) -> 0.79011191
B36: Payable Days | C36: =IFERROR(365/C30,0) -> 9.7336953 | D36: =IFERROR(365/D30,0) -> 16.306962 | E36: =IFERROR(365/E30,0) -> 13.508276 | F36: =IFERROR(365/F30,0) -> 11.782021 | G36: =IFERROR(365/G30,0) -> 13.528811 | H36: =IFERROR(365/H30,0) -> 12.700462 | I36: =IFERROR(365/I30,0) -> 13.976295 | K36: =IFERROR(AVERAGE(C36:I36),0) -> 13.076646 | L36: =IFERROR(MEDIAN(D36:I36),0) -> 13.518544
B37: Inventory Days | C37: =IFERROR(365/C31,0) -> 28.58043 | D37: =IFERROR(365/D31,0) -> 33.989983 | E37: =IFERROR(365/E31,0) -> 32.317348 | F37: =IFERROR(365/F31,0) -> 27.634976 | G37: =IFERROR(365/G31,0) -> 28.224083 | H37: =IFERROR(365/H31,0) -> 31.018456 | I37: =IFERROR(365/I31,0) -> 31.294834 | K37: =IFERROR(AVERAGE(C37:I37),0) -> 30.437158 | L37: =IFERROR(MEDIAN(D37:I37),0) -> 31.156645
B38: Cash Conversion Cycle | C38: =IFERROR(SUM(C35,C37)-C36,0) -> 19.133654 | D38: =IFERROR(SUM(D35,D37)-D36,0) -> 18.341873 | E38: =IFERROR(SUM(E35,E37)-E36,0) -> 19.597251 | F38: =IFERROR(SUM(F35,F37)-F36,0) -> 16.382568 | G38: =IFERROR(SUM(G35,G37)-G36,0) -> 15.890909 | H38: =IFERROR(SUM(H35,H37)-H36,0) -> 19.263668 | I38: =IFERROR(SUM(I35,I37)-I36,0) -> 18.110583 | K38: =IFERROR(AVERAGE(C38:I38),0) -> 18.10293 | L38: =IFERROR(MEDIAN(D38:I38),0) -> 18.226228
B40: CFO/Sales | C40: =IFERROR('Historicial Financials'!C76/'Historicial Financials'!C6,0) -> 0.036388931 | D40: =IFERROR('Historicial Financials'!D76/'Historicial Financials'!D6,0) -> 0.051691873 | E40: =IFERROR('Historicial Financials'!E76/'Historicial Financials'!E6,0) -> 0.025535676 | F40: =IFERROR('Historicial Financials'!F76/'Historicial Financials'!F6,0) -> 0.053945465 | G40: =IFERROR('Historicial Financials'!G76/'Historicial Financials'!G6,0) -> 0.041367364 | H40: =IFERROR('Historicial Financials'!H76/'Historicial Financials'!H6,0) -> 0.022760182 | I40: =IFERROR('Historicial Financials'!I76/'Historicial Financials'!I6,0) -> 0.040205903 | K40: =IFERROR(AVERAGE(C40:I40),0) -> 0.038842199 | L40: =IFERROR(MEDIAN(D40:I40),0) -> 0.040786633
B41: CFO/Total Asset | C41: =IFERROR('Historicial Financials'!C76/'Historicial Financials'!C63,0) -> 0.074941041 | D41: =IFERROR('Historicial Financials'!D76/'Historicial Financials'!D63,0) -> 0.091394759 | E41: =IFERROR('Historicial Financials'!E76/'Historicial Financials'!E63,0) -> 0.051127983 | F41: =IFERROR('Historicial Financials'!F76/'Historicial Financials'!F63,0) -> 0.12764768 | G41: =IFERROR('Historicial Financials'!G76/'Historicial Financials'!G63,0) -> 0.099232589 | H41: =IFERROR('Historicial Financials'!H76/'Historicial Financials'!H63,0) -> 0.055567483 | I41: =IFERROR('Historicial Financials'!I76/'Historicial Financials'!I63,0) -> 0.093719538 | K41: =IFERROR(AVERAGE(C41:I41),0) -> 0.084804439 | L41: =IFERROR(MEDIAN(D41:I41),0) -> 0.092557148
B42: CFO/Total Debt | C42: =IFERROR('Historicial Financials'!C76/'Historicial Financials'!C49,0) -> 2.716168 | D42: =IFERROR('Historicial Financials'!D76/'Historicial Financials'!D49,0) -> 3.1779175 | E42: =IFERROR('Historicial Financials'!E76/'Historicial Financials'!E49,0) -> 1.2226791 | F42: =IFERROR('Historicial Financials'!F76/'Historicial Financials'!F49,0) -> 3.594202 | G42: =IFERROR('Historicial Financials'!G76/'Historicial Financials'!G49,0) -> 3.5480276 | H42: =IFERROR('Historicial Financials'!H76/'Historicial Financials'!H49,0) -> 1.6483248 | I42: =IFERROR('Historicial Financials'!I76/'Historicial Financials'!I49,0) -> 1.1410356 | K42: =IFERROR(AVERAGE(C42:I42),0) -> 2.4354792 | L42: =IFERROR(MEDIAN(D42:I42),0) -> 2.4131212

Sheet Forecasting
B2: ='Data Sheet'!B1 & " Forcaste" & "-" & 'Data Sheet'!A17 -> AVENUE SUPERMARTS LTD Forcaste-Sales | G2: ='Data Sheet'!B1 & " Forcaste" & "-" & 'Historicial Financials'!B18 -> AVENUE SUPERMARTS LTD Forcaste-EBITDA
B3: Year Weight | C3: Year | D3: Sales | E3: Sales Growth | G3: Year Weight | H3: Year | I3: EBITDA | J3: EBITDA Growth
B4: 1 | C4: ='Data Sheet'!E16 -> 43921 | D4: {=TRANSPOSE('Historicial Financials'!C6:I6)} -> 24870.2 | G4: 1 | H4: ='Data Sheet'!E16 -> 43921 | I4: {=TRANSPOSE('Historicial Financials'!C18:I18)} -> 1940.07
B5: =B4+1 -> 2 | C5: =C4+365 -> 44286 | D5: 24143.06 | E5: =IFERROR(D5/D4-1,0) -> -0.029237401 | G5: =G4+1 -> 2 | H5: =H4+365 -> 44286 | I5: 1570.63 | J5: =IFERROR(I5/I4-1,0) -> -0.19042612
B6: =B5+1 -> 3 | C6: =C5+365 -> 44651 | D6: 30976.27 | E6: =IFERROR(D6/D5-1,0) -> 0.28302999 | G6: =G5+1 -> 3 | H6: =H5+365 -> 44651 | I6: 2294.49 | J6: =IFERROR(I6/I5-1,0) -> 0.46087239
B7: =B6+1 -> 4 | C7: =C6+365 -> 45016 | D7: 42839.56 | E7: =IFERROR(D7/D6-1,0) -> 0.38297994 | G7: =G6+1 -> 4 | H7: =H6+365 -> 45016 | I7: 3324.15 | J7: =IFERROR(I7/I6-1,0) -> 0.44875332
B8: =B7+1 -> 5 | C8: =C7+365 -> 45381 | D8: 50788.83 | E8: =IFERROR(D8/D7-1,0) -> 0.1855591 | G8: =G7+1 -> 5 | H8: =H7+365 -> 45381 | I8: 3729.05 | J8: =IFERROR(I8/I7-1,0) -> 0.12180557
B9: =B8+1 -> 6 | C9: =C8+365 -> 45746 | D9: 59358.05 | E9: =IFERROR(D9/D8-1,0) -> 0.16872253 | G9: =G8+1 -> 6 | H9: =H8+365 -> 45746 | I9: 4046.76 | J9: =IFERROR(I9/I8-1,0) -> 0.085198643
B10: =B9+1 -> 7 | C10: =C9+365 -> 46111 | D10: 68820.74 | E10: =IFERROR(D10/D9-1,0) -> 0.15941713 | G10: =G9+1 -> 7 | H10: =H9+365 -> 46111 | I10: 5186.59 | J10: =IFERROR(I10/I9-1,0) -> 0.28166484
B11: =B10+1 -> 8 | C11: =C10+365 -> 46476 | D11: =FORECAST(B11,$D$4:$D$10,$B$4:$B$10) -> 74841.553 | E11: =IFERROR(D11/D10-1,0) -> 0.087485442 | G11: =G10+1 -> 8 | H11: =H10+365 -> 46476 | I11: =FORECAST(G11,$I$4:$I$10,$G$4:$G$10) -> 5459.7314 | J11: =IFERROR(I11/I10-1,0) -> 0.052663008
B12: =B11+1 -> 9 | C12: =C11+365 -> 46841 | D12: =FORECAST(B12,$D$4:$D$10,$B$4:$B$10) -> 82773.487 | E12: =IFERROR(D12/D11-1,0) -> 0.10598303 | G12: =G11+1 -> 9 | H12: =H11+365 -> 46841 | I12: =FORECAST(G12,$I$4:$I$10,$G$4:$G$10) -> 6035.6736 | J12: =IFERROR(I12/I11-1,0) -> 0.1054891
B13: =B12+1 -> 10 | C13: =C12+365 -> 47206 | D13: =FORECAST(B13,$D$4:$D$10,$B$4:$B$10) -> 90705.421 | E13: =IFERROR(D13/D12-1,0) -> 0.095826992 | G13: =G12+1 -> 10 | H13: =H12+365 -> 47206 | I13: =FORECAST(G13,$I$4:$I$10,$G$4:$G$10) -> 6611.6157 | J13: =IFERROR(I13/I12-1,0) -> 0.095423011
B14: =B13+1 -> 11 | C14: =C13+365 -> 47571 | D14: =FORECAST(B14,$D$4:$D$10,$B$4:$B$10) -> 98637.356 | E14: =IFERROR(D14/D13-1,0) -> 0.087447191 | G14: =G13+1 -> 11 | H14: =H13+365 -> 47571 | I14: =FORECAST(G14,$I$4:$I$10,$G$4:$G$10) -> 7187.5579 | J14: =IFERROR(I14/I13-1,0) -> 0.08711065
B15: =B14+1 -> 12 | C15: =C14+365 -> 47936 | D15: =FORECAST(B15,$D$4:$D$10,$B$4:$B$10) -> 106569.29 | E15: =IFERROR(D15/D14-1,0) -> 0.080415115 | G15: =G14+1 -> 12 | H15: =H14+365 -> 47936 | I15: =FORECAST(G15,$I$4:$I$10,$G$4:$G$10) -> 7763.5 | J15: =IFERROR(I15/I14-1,0) -> 0.080130436

Sheet WACC
B2: Weighted Average Cost of Capital
B4: All figures are in INR unless stated otherwise
B6: Peer Comps
G8: Debt/ | H8: Debt/ | I8: Levered | J8: Unlevered
B9: Name of Company | C9: Country | D9: Total Debt | E9: Total Equity | F9: Tax Rate 1 | G9: Equity | H9: Capital | I9: Beta 2 | J9: Beta 3
B11: Avenue Super. | C11: India | D11: 2424.99 | E11: 652.25 | F11: 0.3 | G11: =D11/E11 -> 3.7178842 | H11: =D11/(D11+E11) -> 0.78804058 | I11: =Beta!N7 -> 0.70010611 | J11: =I11/(1+(1-F11)*G11) -> 0.19433794
B12: Vishal Mega Mart | C12: India | D12: 1987.98 | E12: 4676.38 | F12: 0.3 | G12: =D12/E12 -> 0.42511088 | H12: =D12/(D12+E12) -> 0.29830021 | I12: =Beta!AK7 -> 1.1280229 | J12: =I12/(1+(1-F12)*G12) -> 0.8693298
E14: Average | F14: =AVERAGE(F11:F12) -> 0.3 | G14: =AVERAGE(G11:G12) -> 2.0714976 | H14: =AVERAGE(H11:H12) -> 0.5431704 | I14: =AVERAGE(I11:I11) -> 0.70010611 | J14: =AVERAGE(J11:J12) -> 0.53183387
E15: Median | F15: =MEDIAN(F11:F12) -> 0.3 | G15: =MEDIAN(G11:G12) -> 2.0714976 | H15: =MEDIAN(H11:H12) -> 0.5431704 | I15: =MEDIAN(I11:I11) -> 0.70010611 | J15: =MEDIAN(J11:J12) -> 0.53183387
B19: Cost of Debt | G19: Cost of Equity
B21: Pre Tax Cost of Debt | C21: =142/D11 -> 0.058556943 | G21: Risk Free Rate | I21: 0.0677 | J21: Taken from 10 yrs yield of govt. bond
B22: Tax Rate | C22: =F14 -> 0.3 | G22: Equity Risk Premium | I22: =Beta!Y9-WACC!I21 -> 0.083792308
B23: Post Tax Cost of Debt | C23: =C21*(1-C22) -> 0.04098986 | G23: Levered Beta 4 | I23: =J32 -> 0.97447919
G24: Cost of Equity | I24: =I21+(I22*I23) -> 0.14935386
B27: Capital Structure | G27: Levered Beta
D29: Current | E29: Target | G29: Comps Median Unlevered Beta | J29: =J15 -> 0.53183387
B30: Total Debt | C30: =D12 -> 1987.98 | D30: =C30/$C$32 -> 0.29830021 | E30: =H15 -> 0.5431704 | G30: Target Debt/Equity | J30: =E35 -> 1.189
B31: Market Capitalization | C31: =E12 -> 4676.38 | D31: =C31/$C$32 -> 0.70169979 | E31: =1-E30 -> 0.4568296 | G31: Tax Rate | J31: =F11 -> 0.3
B32: Total Capital | C32: =SUM(C30:C31) -> 6664.36 | D32: =SUM(D30:D31) -> 1 | E32: =SUM(E30:E31) -> 1 | G32: Levered Beta | J32: =J29*(1+(1-J31)*J30) -> 0.97447919
B35: Debt/Equity | D35: =D30/D31 -> 0.42511088 | E35: =E30/E31 -> 1.189 | G35: Weighted Average Cost of Capital
I36: Total Cost | J36: Total Weight
B37: Note: | G37: Debt | I37: =C23 -> 0.04098986 | J37: =E30 -> 0.5431704
B38: 1. Tax Rate Consider as Marginal Tax Rate for the company | G38: Equity | I38: =I24 -> 0.14935386 | J38: =E31 -> 0.4568296
B39: 2. Levered Beta is based on 5 year montly data | G39: Weighted Average Cost of Capital | J39: =SUMPRODUCT(I37:I38,J37:J38) -> 0.090493743

Sheet Beta
B2: ="Beta Calculation-"&'Data Sheet'!B1 -> Beta Calculation-AVENUE SUPERMARTS LTD
B4: Avenue Weekly Return | F4: Nifty Weekly Return | U4: Rm Calulation | AB4: Vishal Mega Mart Weekly Return
B6: Date | C6: Price | D6: Weekly Return | F6: Date | G6: Price | H6: Weekly Return | J6: Beta Drifting | U6: Year | V6: Annual | AB6: Date | AC6: Price | AD6: Weekly Return | AF6: Beta Drifting
B7: 46222 | C7: 4018.8 | F7: 46222 | G7: 23869.6 | M7: Beta 1 | N7: =SLOPE(D8:D110,H8:H110) -> 0.70010611 | U7: 2000 | V7: -0.1465 | X7: Average Return | Y7: =AVERAGE(V7:V32) -> 0.15149231 | AB7: 46222 | AC7: 108.04 | AJ7: Beta | AK7: =SLOPE(AD8:AD89,H8:H89) -> 1.1280229
B8: 46215 | C8: 3951.9 | D8: =C8/C7-1 -> -0.01664676 | F8: 46215 | G8: 24334.3 | H8: =G8/G7-1 -> 0.019468278 | J8: Levered Raw Beta | K8: =N10 -> 0.70010611 | M8: Beta 2 | N8: =_xlfn.COVARIANCE.S(D8:D110,H8:H110)/_xlfn.VAR.S(H8:H110) -> 0.70010611 | U8: 2001 | V8: -0.1618 | X8: Dividend Yield | Y8: 1.30 1 | AB8: 46215 | AC8: 110.33 | AD8: =AC8/AC7-1 -> 0.021195853 | AF8: Levered Raw Beta | AG8: =AK7 -> 1.1280229
B9: 46208 | C9: 4081.1 | D9: =C9/C8-1 -> 0.032693135 | F9: 46208 | G9: 24206.9 | H9: =G9/G8-1 -> -0.0052354085 | J9: Raw Beta Weight | K9: 0.75 | U9: 2002 | V9: 0.0325 | X9: Total Market Return | Y9: =SUM(Y7:Y8) -> 0.15149231 | AB9: 46208 | AC9: 118.79 | AD9: =AC9/AC8-1 -> 0.076679054 | AF9: Raw Beta Weight | AG9: 0.75
B10: 46201 | C10: 3994.4 | D10: =C10/C9-1 -> -0.021244272 | F10: 46201 | G10: 24270.85 | H10: =G10/G9-1 -> 0.0026418087 | J10: Market Beta | K10: 1 | M10: Beta 3 | N10: =K36 -> 0.70010611 | U10: 2003 | V10: 0.719 | AB10: 46201 | AC10: 120.57 | AD10: =AC10/AC9-1 -> 0.014984426 | AF10: Market Beta | AG10: 1
B11: 46194 | C11: 4294.6 | D11: =C11/C10-1 -> 0.075155217 | F11: 46194 | G11: 24056 | H11: =G11/G10-1 -> -0.0088521828 | J11: Market Beta Weight | K11: =1-K9 -> 0.25 | U11: 2004 | V11: 0.1068 | AB11: 46194 | AC11: 116.39 | AD11: =AC11/AC10-1 -> -0.034668657 | AF11: Market Beta Weight | AG11: =1-AG9 -> 0.25
B12: 46187 | C12: 4286.9 | D12: =C12/C11-1 -> -0.0017929493 | F12: 46187 | G12: 24013.1 | H12: =G12/G11-1 -> -0.0017833389 | U12: 2005 | V12: 0.3634 | AB12: 46187 | AC12: 118.66 | AD12: =AC12/AC11-1 -> 0.019503394
B13: 46180 | C13: 3993.6 | D13: =C13/C12-1 -> -0.068417738 | F13: 46180 | G13: 23622.9 | H13: =G13/G12-1 -> -0.016249464 | J13: Adjusted Beta | K13: =(K8*K9)+(K10*K11) -> 0.77507958 | U13: 2006 | V13: 0.3983 | AB13: 46180 | AC13: 119.77 | AD13: =AC13/AC12-1 -> 0.0093544581 | AF13: Adjusted Beta | AG13: =(AG8*AG9)+(AG10*AG11) -> 1.0960172
B14: 46173 | C14: 4144.2 | D14: =C14/C13-1 -> 0.037710337 | F14: 46173 | G14: 23366.7 | H14: =G14/G13-1 -> -0.010845408 | U14: 2007 | V14: 0.5477 | AB14: 46173 | AC14: 118.73 | AD14: =AC14/AC13-1 -> -0.0086833097
B15: 46166 | C15: 4054.5 | D15: =C15/C14-1 -> -0.021644708 | F15: 46166 | G15: 23547.75 | H15: =G15/G14-1 -> 0.0077482058 | U15: 2008 | V15: -0.5179 | AB15: 46166 | AC15: 121.77 | AD15: =AC15/AC14-1 -> 0.025604312
B16: 46159 | C16: 4117 | D16: =C16/C15-1 -> 0.015414971 | F16: 46159 | G16: 23719.3 | H16: =G16/G15-1 -> 0.0072851971 | U16: 2009 | V16: 0.7576 | AB16: 46159 | AC16: 121.66 | AD16: =AC16/AC15-1 -> -0.00090334237
B17: 46152 | C17: 4358.7 | D17: =C17/C16-1 -> 0.058707797 | F17: 46152 | G17: 23643.5 | H17: =G17/G16-1 -> -0.0031957098 | U17: 2010 | V17: 0.1795 | AB17: 46152 | AC17: 118.99 | AD17: =AC17/AC16-1 -> -0.021946408
B18: 46145 | C18: 4402.1 | D18: =C18/C17-1 -> 0.0099570973 | F18: 46145 | G18: 24176.15 | H18: =G18/G17-1 -> 0.02252839 | U18: 2011 | V18: -0.2462 | AB18: 46145 | AC18: 123.93 | AD18: =AC18/AC17-1 -> 0.041516094
B19: 46138 | C19: 4585.9 | D19: =C19/C18-1 -> 0.0417528 | F19: 46138 | G19: 23997.55 | H19: =G19/G18-1 -> -0.0073874459 | J19: SUMMARY OUTPUT | U19: 2012 | V19: 0.277 | AB19: 46138 | AC19: 122.29 | AD19: =AC19/AC18-1 -> -0.013233277
B20: 46131 | C20: 4443.5 | D20: =C20/C19-1 -> -0.031051702 | F20: 46131 | G20: 23897.95 | H20: =G20/G19-1 -> -0.0041504237 | U20: 2013 | V20: 0.0676 | AB20: 46131 | AC20: 123.34 | AD20: =AC20/AC19-1 -> 0.0085861477
B21: 46124 | C21: 4628.5 | D21: =C21/C20-1 -> 0.041633847 | F21: 46124 | G21: 24353.55 | H21: =G21/G20-1 -> 0.019064397 | J21: Regression Statistics | U21: 2014 | V21: 0.3139 | AB21: 46124 | AC21: 118.95 | AD21: =AC21/AC20-1 -> -0.035592671
B22: 46117 | C22: 4400.6 | D22: =C22/C21-1 -> -0.049238414 | F22: 46117 | G22: 24050.6 | H22: =G22/G21-1 -> -0.012439665 | J22: Multiple R | K22: 0.31165003 | U22: 2015 | V22: -0.0406 | AB22: 46117 | AC22: 114.5 | AD22: =AC22/AC21-1 -> -0.037410677
B23: 46110 | C23: 4362.4 | D23: =C23/C22-1 -> -0.0086806345 | F23: 46110 | G23: 22713.1 | H23: =G23/G22-1 -> -0.055611918 | J23: R Square | K23: 0.097125743 | U23: 2016 | V23: 0.0301 | AB23: 46110 | AC23: 107.88 | AD23: =AC23/AC22-1 -> -0.057816594
B24: 46103 | C24: 3903.2 | D24: =C24/C23-1 -> -0.10526316 | F24: 46103 | G24: 22819.6 | H24: =G24/G23-1 -> 0.004688924 | J24: Adjusted R Square | K24: 0.088186394 | U24: 2017 | V24: 0.2865 | AB24: 46103 | AC24: 106.37 | AD24: =AC24/AC23-1 -> -0.013997034
B25: 46096 | C25: 3770.8 | D25: =C25/C24-1 -> -0.033920885 | F25: 46096 | G25: 23114.5 | H25: =G25/G24-1 -> 0.012923101 | J25: Standard Error | K25: 0.03928925 | U25: 2018 | V25: 0.0315 | AB25: 46096 | AC25: 102.3 | AD25: =AC25/AC24-1 -> -0.038262668
B26: 46089 | C26: 3834.3 | D26: =C26/C25-1 -> 0.016839928 | F26: 46089 | G26: 23151.1 | H26: =G26/G25-1 -> 0.0015834217 | J26: Observations | K26: 103 | U26: 2019 | V26: 0.1202 | AB26: 46089 | AC26: 102.79 | AD26: =AC26/AC25-1 -> 0.0047898338
B27: 46082 | C27: 3875.8 | D27: =C27/C26-1 -> 0.010823358 | F27: 46082 | G27: 24450.45 | H27: =G27/G26-1 -> 0.056124763 | U27: 2020 | V27: 0.149 | AB27: 46082 | AC27: 111.85 | AD27: =AC27/AC26-1 -> 0.08814087
B28: 46075 | C28: 3847.6 | D28: =C28/C27-1 -> -0.0072759172 | F28: 46075 | G28: 25178.65 | H28: =G28/G27-1 -> 0.029782683 | J28: ANOVA | U28: 2021 | V28: 0.2412 | AB28: 46075 | AC28: 117.78 | AD28: =AC28/AC27-1 -> 0.053017434
B29: 46068 | C29: 3866.4 | D29: =C29/C28-1 -> 0.0048861628 | F29: 46068 | G29: 25571.25 | H29: =G29/G28-1 -> 0.015592575 | K29: df | L29: SS | M29: MS | N29: F | O29: Significance F | U29: 2022 | V29: 0.0432 | AB29: 46068 | AC29: 116.9 | AD29: =AC29/AC28-1 -> -0.0074715571
B30: 46061 | C30: 3909.2 | D30: =C30/C29-1 -> 0.011069729 | F30: 46061 | G30: 25471.1 | H30: =G30/G29-1 -> -0.0039165078 | J30: Regression | K30: 1 | L30: 0.016771656 | M30: 0.016771656 | N30: 10.864968 | O30: 0.0013529537 | P30: Upper 95% | U30: 2023 | V30: 0.1942 | AB30: 46061 | AC30: 121.91 | AD30: =AC30/AC29-1 -> 0.042857143
B31: 46054 | C31: 3889.9 | D31: =C31/C30-1 -> -0.0049370715 | F31: 46054 | G31: 25693.7 | H31: =G31/G30-1 -> 0.0087393163 | J31: Residual | K31: 101 | L31: 0.15590816 | M31: 0.0015436452 | P31: 0.010111791 | U31: 2024 | V31: 0.0875 | AB31: 46054 | AC31: 122.19 | AD31: =AC31/AC30-1 -> 0.0022967763
B32: 46047 | C32: 3689.5 | D32: =C32/C31-1 -> -0.051518034 | F32: 46047 | G32: 25320.65 | H32: =G32/G31-1 -> -0.014519123 | J32: Total | K32: 102 | L32: 0.17267982 | P32: 1.1214458 | U32: 2025 | V32: 0.1051 | AB32: 46047 | AC32: 125.95 | AD32: =AC32/AC31-1 -> 0.030771749
B33: 46040 | C33: 3665.6 | D33: =C33/C32-1 -> -0.0064778425 | F33: 46040 | G33: 25048.65 | H33: =G33/G32-1 -> -0.01074222 | AB33: 46040 | AC33: 124.58 | AD33: =AC33/AC32-1 -> -0.010877332
B34: 46033 | C34: 3775.7 | D34: =C34/C33-1 -> 0.03003601 | F34: 46033 | G34: 25694.35 | H34: =G34/G33-1 -> 0.025777836 | K34: Coefficients | L34: Standard Error | M34: t Stat | N34: P-value | O34: Lower 95% | Q34: Lower 95.0% | R34: Upper 95.0% | AB34: 46033 | AC34: 129.54 | AD34: =AC34/AC33-1 -> 0.039813774
B35: 46026 | C35: 3801.3 | D35: =C35/C34-1 -> 0.0067801997 | F35: 46026 | G35: 25683.3 | H35: =G35/G34-1 -> -0.00043005563 | J35: Intercept | K35: 0.0024292594 | L35: 0.0038727691 | M35: 0.62726678 | N35: 0.53189987 | O35: -0.0052532727 | Q35: -0.0052532727 | R35: 0.010111791 | AB35: 46026 | AC35: 129.19 | AD35: =AC35/AC34-1 -> -0.0027018681
B36: 46019 | C36: 3719.8 | D36: =C36/C35-1 -> -0.021440034 | F36: 46019 | G36: 26328.55 | H36: =G36/G35-1 -> 0.025123329 | J36: X Variable 1 | K36: 0.70010611 | L36: 0.21239762 | M36: 3.2962051 | N36: 0.0013529537 | O36: 0.27876637 | Q36: 0.27876637 | R36: 1.1214458 | AB36: 46019 | AC36: 135.95 | AD36: =AC36/AC35-1 -> 0.052326031
B37: 46012 | C37: 3787.4 | D37: =C37/C36-1 -> 0.01817302 | F37: 46012 | G37: 26042.3 | H37: =G37/G36-1 -> -0.010872228 | AB37: 46012 | AC37: 136.26 | AD37: =AC37/AC36-1 -> 0.0022802501
B38: 46005 | C38: 3819.5 | D38: =C38/C37-1 -> 0.0084754713 | F38: 46005 | G38: 25966.4 | H38: =G38/G37-1 -> -0.0029144891 | AB38: 46005 | AC38: 138.07 | AD38: =AC38/AC37-1 -> 0.013283429
B39: 45998 | C39: 3843 | D39: =C39/C38-1 -> 0.0061526378 | F39: 45998 | G39: 26046.95 | H39: =G39/G38-1 -> 0.0031020858 | AB39: 45998 | AC39: 134.77 | AD39: =AC39/AC38-1 -> -0.02390092
B40: 45991 | C40: 3952.1 | D40: =C40/C39-1 -> 0.028389279 | F40: 45991 | G40: 26186.45 | H40: =G40/G39-1 -> 0.0053557134 | AB40: 45991 | AC40: 133.03 | AD40: =AC40/AC39-1 -> -0.012910885
B41: 45984 | C41: 3996.5 | D41: =C41/C40-1 -> 0.011234534 | F41: 45984 | G41: 26202.95 | H41: =G41/G40-1 -> 0.00063009686 | AB41: 45984 | AC41: 135.8 | AD41: =AC41/AC40-1 -> 0.020822371
B42: 45977 | C42: 4038 | D42: =C42/C41-1 -> 0.010384086 | F42: 45977 | G42: 26068.15 | H42: =G42/G41-1 -> -0.0051444589 | AB42: 45977 | AC42: 130.92 | AD42: =AC42/AC41-1 -> -0.035935199
B43: 45970 | C43: 4053.7 | D43: =C43/C42-1 -> 0.0038880634 | F43: 45970 | G43: 25910.05 | H43: =G43/G42-1 -> -0.0060648723 | AB43: 45970 | AC43: 136.94 | AD43: =AC43/AC42-1 -> 0.045982279
B44: 45963 | C44: 4011 | D44: =C44/C43-1 -> -0.010533587 | F44: 45963 | G44: 25492.3 | H44: =G44/G43-1 -> -0.016123087 | AB44: 45963 | AC44: 143.18 | AD44: =AC44/AC43-1 -> 0.045567402
B45: 45956 | C45: 4153.5 | D45: =C45/C44-1 -> 0.0355273 | F45: 45956 | G45: 25722.1 | H45: =G45/G44-1 -> 0.0090144867 | AB45: 45956 | AC45: 144.69 | AD45: =AC45/AC44-1 -> 0.010546166
B46: 45949 | C46: 4213.9 | D46: =C46/C45-1 -> 0.014541953 | F46: 45949 | G46: 25795.15 | H46: =G46/G45-1 -> 0.0028399703 | AB46: 45949 | AC46: 148.29 | AD46: =AC46/AC45-1 -> 0.02488078
B47: 45942 | C47: 4302.5 | D47: =C47/C46-1 -> 0.021025653 | F47: 45942 | G47: 25709.85 | H47: =G47/G46-1 -> -0.0033068232 | AB47: 45942 | AC47: 148.43 | AD47: =AC47/AC46-1 -> 0.00094409603
B48: 45935 | C48: 4320.4 | D48: =C48/C47-1 -> 0.0041603719 | F48: 45935 | G48: 25285.35 | H48: =G48/G47-1 -> -0.016511182 | AB48: 45935 | AC48: 146.2 | AD48: =AC48/AC47-1 -> -0.015023917
... B89: 45648 | C89: 3568.35 | D89: =C89/C88-1 -> -0.11349747 | F89: 45648 | G89: 23813.4 | H89: =G89/G88-1 -> -0.007971339 | AB89: 45648 | AC89: 106.14 | AD89: =AC89/AC88-1 -> -0.05384204
B90: 45641 | C90: 3408.3 | D90: =C90/C89-1 -> -0.044852663 | F90: 45641 | G90: 23587.5 | H90: =G90/G89-1 -> -0.0094862556
B91: 45634 | C91: 3652.3 | D91: =C91/C90-1 -> 0.071589942 | F91: 45634 | G91: 24768.3 | H91: =G91/G90-1 -> 0.050060413
B92: 45627 | C92: 3805.55 | D92: =C92/C91-1 -> 0.041959861 | F92: 45627 | G92: 24677.8 | H92: =G92/G91-1 -> -0.003653864
B93: 45620 | C93: 3709.6 | D93: =C93/C92-1 -> -0.025213175 | F93: 45620 | G93: 24131.1 | H93: =G93/G92-1 -> -0.022153514
B94: 45613 | C94: 3613.65 | D94: =C94/C93-1 -> -0.025865322 | F94: 45613 | G94: 23907.25 | H94: =G94/G93-1 -> -0.0092764109
B95: 45606 | C95: 3823.85 | D95: =C95/C94-1 -> 0.058168334 | F95: 45606 | G95: 23532.7 | H95: =G95/G94-1 -> -0.015666796
B96: 45599 | C96: 3874.5 | D96: =C96/C95-1 -> 0.013245812 | F96: 45599 | G96: 24148.2 | H96: =G96/G95-1 -> 0.026155095
B97: 45592 | C97: 4001.6 | D97: =C97/C96-1 -> 0.032804233 | F97: 45592 | G97: 24304.35 | H97: =G97/G96-1 -> 0.0064663205
B98: 45585 | C98: 4052.2 | D98: =C98/C97-1 -> 0.012644942 | F98: 45585 | G98: 24180.8 | H98: =G98/G97-1 -> -0.0050834521
B99: 45578 | C99: 3986.7 | D99: =C99/C98-1 -> -0.016164059 | F99: 45578 | G99: 24854.05 | H99: =G99/G98-1 -> 0.027842338
B100: 45571 | C100: 4572.7 | D100: =C100/C99-1 -> 0.14698874 | F100: 45571 | G100: 24964.25 | H100: =G100/G99-1 -> 0.004433885
B101: 45564 | C101: 4737.55 | D101: =C101/C100-1 -> 0.036050911 | F101: 45564 | G101: 25014.6 | H101: =G101/G100-1 -> 0.0020168841
... B110: 45501 | C110: 4909.7 | D110: =C110/C109-1 -> -0.016082325 | F110: 45501 | G110: 24717.7 | H110: =G110/G109-1 -> 0.014371602

Sheet Intrinsic Growth
B2: Calculation of ROIC | C2: ='Data Sheet'!E16 -> 43921 | D2: ='Data Sheet'!F16 -> 44286 | E2: ='Data Sheet'!G16 -> 44651 | F2: ='Data Sheet'!H16 -> 45016 | G2: ='Data Sheet'!I16 -> 45382 | H2: ='Data Sheet'!J16 -> 45747 | I2: ='Data Sheet'!K16 -> 46112
B4: Current Assets
B5: ='Data for IG'!B35 -> Inventories | C5: ='Data for IG'!C35 -> 1947 | D5: ='Data for IG'!D35 -> 2248 | E5: ='Data for IG'!E35 -> 2743 | F5: ='Data for IG'!F35 -> 3243 | G5: ='Data for IG'!G35 -> 3927 | H5: ='Data for IG'!H35 -> 5044 | I5: ='Data for IG'!I35 -> 5901
B6: ='Data for IG'!B36 -> Trade receivables | C6: ='Data for IG'!C36 -> 20 | D6: ='Data for IG'!D36 -> 44 | E6: ='Data for IG'!E36 -> 67 | F6: ='Data for IG'!F36 -> 62 | G6: ='Data for IG'!G36 -> 166 | H6: ='Data for IG'!H36 -> 154 | I6: ='Data for IG'!I36 -> 149
B7: ='Data for IG'!B38 -> Loans n Advances | C7: ='Data for IG'!C37 -> 108 | D7: ='Data for IG'!D37 -> 1446 | E7: ='Data for IG'!E37 -> 299 | F7: ='Data for IG'!F37 -> 1408 | G7: ='Data for IG'!G37 -> 638 | H7: ='Data for IG'!H37 -> 358 | I7: ='Data for IG'!I37 -> 304
B8: ='Data for IG'!B39 -> Other asset items | C8: ='Data for IG'!C38 -> 101 | D8: ='Data for IG'!D38 -> 81 | E8: ='Data for IG'!E38 -> 109 | F8: ='Data for IG'!F38 -> 97 | G8: ='Data for IG'!G38 -> 105 | H8: ='Data for IG'!H38 -> 126 | I8: ='Data for IG'!I38 -> 197
B9: Total Current Assets | C9: =SUM(C5:C8) -> 2176 | D9: =SUM(D5:D8) -> 3819 | E9: =SUM(E5:E8) -> 3218 | F9: =SUM(F5:F8) -> 4810 | G9: =SUM(G5:G8) -> 4836 | H9: =SUM(H5:H8) -> 5682 | I9: =SUM(I5:I8) -> 6551
B11: Current Liabilites
B12: ='Data for IG'!B13 -> Trade Payables | C12: ='Data for IG'!C13 -> 433 | D12: ='Data for IG'!D13 -> 578 | E12: ='Data for IG'!E13 -> 589 | F12: ='Data for IG'!F13 -> 754 | G12: ='Data for IG'!G13 -> 985 | H12: ='Data for IG'!H13 -> 1071 | I12: ='Data for IG'!I13 -> 1338
B13: ='Data for IG'!B14 -> Other liability items | C13: ='Data for IG'!C14 -> 229 | D13: ='Data for IG'!D14 -> 500 | E13: ='Data for IG'!E14 -> 557 | F13: ='Data for IG'!F14 -> 629 | G13: ='Data for IG'!G14 -> 898 | H13: ='Data for IG'!H14 -> 996 | I13: ='Data for IG'!I14 -> 1299
B14: Total Current Liabilities | C14: =SUM(C12:C13) -> 662 | D14: =SUM(D12:D13) -> 1078 | E14: =SUM(E12:E13) -> 1146 | F14: =SUM(F12:F13) -> 1383 | G14: =SUM(G12:G13) -> 1883 | H14: =SUM(H12:H13) -> 2067 | I14: =SUM(I12:I13) -> 2637
A16: # | B16: Net Working Capital | C16: =C9-C14 -> 1514 | D16: =D9-D14 -> 2741 | E16: =E9-E14 -> 2072 | F16: =F9-F14 -> 3427 | G16: =G9-G14 -> 2953 | H16: =H9-H14 -> 3615 | I16: =I9-I14 -> 3914
B19: Non current Asset
B20: Land | C20: ='Data for IG'!C18 -> 2740 | D20: ='Data for IG'!D18 -> 3483 | E20: ='Data for IG'!E18 -> 4527 | F20: ='Data for IG'!F18 -> 5519 | G20: ='Data for IG'!G18 -> 6904 | H20: ='Data for IG'!H18 -> 8595 | I20: ='Data for IG'!I18 -> 10432
B21: Building | C21: ='Data for IG'!C19 -> 3139 | D21: ='Data for IG'!D19 -> 3649 | E21: ='Data for IG'!E19 -> 4938 | F21: ='Data for IG'!F19 -> 6201 | G21: ='Data for IG'!G19 -> 7062 | H21: ='Data for IG'!H19 -> 16206 | I21: ='Data for IG'!I19 -> 10391
B22: Plant Machinery | C22: ='Data for IG'!C20 -> 272 | D22: ='Data for IG'!D20 -> 352 | E22: ='Data for IG'!E20 -> 491 | F22: ='Data for IG'!F20 -> 656 | G22: ='Data for IG'!G20 -> 870 | H22: ='Data for IG'!H20 -> 1141 | I22: ='Data for IG'!I20 -> 1446
B23: Equipments | C23: ='Data for IG'!C21 -> 39 | D23: ='Data for IG'!D21 -> 50 | E23: ='Data for IG'!E21 -> 73 | F23: ='Data for IG'!F21 -> 85 | G23: ='Data for IG'!G21 -> 97 | H23: ='Data for IG'!H21 -> 115 | I23: ='Data for IG'!I21 -> 140
B24: Computers | C24: ='Data for IG'!C22 -> 95 | D24: ='Data for IG'!D22 -> 119 | E24: ='Data for IG'!E22 -> 153 | F24: ='Data for IG'!F22 -> 190 | G24: ='Data for IG'!G22 -> 219 | H24: ='Data for IG'!H22 -> 276 | I24: ='Data for IG'!I22 -> 372
B25: Furniture n fittings | C25: ='Data for IG'!C23 -> 476 | D25: ='Data for IG'!D23 -> 581 | E25: ='Data for IG'!E23 -> 772 | F25: ='Data for IG'!F23 -> 968 | G25: ='Data for IG'!G23 -> 1205 | H25: ='Data for IG'!H23 -> 1515 | I25: ='Data for IG'!I23 -> 1954
B26: Vehicles | C26: ='Data for IG'!C24 -> 4 | D26: ='Data for IG'!D24 -> 4 | E26: ='Data for IG'!E24 -> 3 | F26: ='Data for IG'!F24 -> 15 | G26: ='Data for IG'!G24 -> 17 | H26: ='Data for IG'!H24 -> 6 | I26: ='Data for IG'!I24 -> 8
B27: Intangible Assets | C27: ='Data for IG'!C25 -> 78 | D27: ='Data for IG'!D25 -> 78 | E27: ='Data for IG'!E25 -> 78 | F27: ='Data for IG'!F25 -> 78 | G27: ='Data for IG'!G25 -> 78 | H27: ='Data for IG'!H25 -> 78 | I27: ='Data for IG'!I25 -> 78
B28: Other fixed assets | C28: ='Data for IG'!C26 -> 82 | D28: ='Data for IG'!D26 -> 81 | E28: ='Data for IG'!E26 -> 91 | F28: ='Data for IG'!F26 -> 105 | G28: ='Data for IG'!G26 -> 119 | H28: ='Data for IG'!H26 -> 124 | I28: ='Data for IG'!I26 -> 140
A29: # | B29: ='Data for IG'!B27 -> Gross Block | C29: ='Data for IG'!C27 -> 6927 | D29: ='Data for IG'!D27 -> 8396 | E29: ='Data for IG'!E27 -> 11127 | F29: ='Data for IG'!F27 -> 13816 | G29: ='Data for IG'!G27 -> 16571 | H29: ='Data for IG'!H27 -> 20106 | I29: ='Data for IG'!I27 -> 24960
A31: # | B31: Invested Capital | C31: =C29+C16 -> 8441 | D31: =D29+D16 -> 11137 | E31: =E29+E16 -> 13199 | F31: =F29+F16 -> 17243 | G31: =G29+G16 -> 19524 | H31: =H29+H16 -> 23721 | I31: =I29+I16 -> 28874
B32: EBIT | C32: ='Historicial Financials'!C18-'Historicial Financials'!C24 -> 1565.66 | D32: ='Historicial Financials'!D18-'Historicial Financials'!D24 -> 1156.47 | E32: ='Historicial Financials'!E18-'Historicial Financials'!E24 -> 1796.41 | F32: ='Historicial Financials'!F18-'Historicial Financials'!F24 -> 2685.28 | G32: ='Historicial Financials'!G18-'Historicial Financials'!G24 -> 2998.29 | H32: ='Historicial Financials'!H18-'Historicial Financials'!H24 -> 3177.24 | I32: ='Historicial Financials'!I18-'Historicial Financials'!I24 -> 4149.57
A34: # | B34: ROIC | C34: =C32/C31 -> 0.18548276 | D34: =D32/D31 -> 0.10384035 | E34: =E32/E31 -> 0.13610198 | F34: =F32/F31 -> 0.1557316 | G34: =G32/G31 -> 0.15356945 | H34: =H32/H31 -> 0.13394208 | I34: =I32/I31 -> 0.14371303
B36: Calculation of Reinvestment Rate | C36: ='Data Sheet'!E16 -> 43921 | D36: ='Data Sheet'!F16 -> 44286 | E36: ='Data Sheet'!G16 -> 44651 | F36: ='Data Sheet'!H16 -> 45016 | G36: ='Data Sheet'!I16 -> 45382 | H36: ='Data Sheet'!J16 -> 45747 | I36: ='Data Sheet'!K16 -> 46112
B38: Net Capex | D38: ='Data Sheet'!F62-'Data Sheet'!E62+'Data Sheet'!E26 -> 1435.18 | E38: ='Data Sheet'!G62-'Data Sheet'!F62+'Data Sheet'!F26 -> 2665.38 | F38: ='Data Sheet'!H62-'Data Sheet'!G62+'Data Sheet'!G26 -> 2578.54 | G38: ='Data Sheet'!I62-'Data Sheet'!H62+'Data Sheet'!H26 -> 2713.39 | H38: ='Data Sheet'!J62-'Data Sheet'!I62+'Data Sheet'!I26 -> 3522.22 | I38: ='Data Sheet'!K62-'Data Sheet'!J62+'Data Sheet'!J26 -> 4753.37 | K38: Net Capex = Ending PPE - Open. PPE +Depr.
B39: Change in working Capital | D39: =D16-C16 -> 1227 | E39: =E16-D16 -> -669 | F39: =F16-E16 -> 1355 | G39: =G16-F16 -> -474 | H39: =H16-G16 -> 662 | I39: =I16-H16 -> 299
B41: EBIT | C41: =C32 -> 1565.66 | D41: =D32 -> 1156.47 | E41: =E32 -> 1796.41 | F41: =F32 -> 2685.28 | G41: =G32 -> 2998.29 | H41: =H32 -> 3177.24 | I41: =I32 -> 4149.57
B42: Marginal Tax Rate | C42: 0.25 | D42: 0.25 | E42: 0.25 | F42: 0.25 | G42: 0.25 | H42: 0.25 | I42: 0.25
B43: EBIT(1-TR) | C43: =C41*(1-C42) -> 1174.245 | D43: =D41*(1-D42) -> 867.3525 | E43: =E41*(1-E42) -> 1347.3075 | F43: =F41*(1-F42) -> 2013.96 | G43: =G41*(1-G42) -> 2248.7175 | H43: =H41*(1-H42) -> 2382.93 | I43: =I41*(1-I42) -> 3112.1775
B45: Reinvestment | D45: =SUM(D38:D39) -> 2662.18 | E45: =SUM(E38:E39) -> 1996.38 | F45: =SUM(F38:F39) -> 3933.54 | G45: =SUM(G38:G39) -> 2239.39 | H45: =SUM(H38:H39) -> 4184.22 | I45: =SUM(I38:I39) -> 5052.37
B46: Reinvestment Rate | D46: =D45/D43 -> 3.0693173 | E46: =E45/E43 -> 1.4817553 | F46: =F45/F43 -> 1.9531371 | G46: =G45/G43 -> 0.99585208 | H46: =H45/H43 -> 1.7559139 | I46: =I45/I43 -> 1.6234196
H48: 5 year Average | I48: =AVERAGE(D46:I46) -> 1.8132325
H49: 5 year Median | I49: =MEDIAN(D46:I46) -> 1.6896668
B51: Calculation of Growth Rate | C51: ='Data Sheet'!E16 -> 43921 | D51: ='Data Sheet'!F16 -> 44286 | E51: ='Data Sheet'!G16 -> 44651 | F51: ='Data Sheet'!H16 -> 45016 | G51: ='Data Sheet'!I16 -> 45382 | H51: ='Data Sheet'!J16 -> 45747 | I51: ='Data Sheet'!K16 -> 46112
B53: Reinvestment Rate | D53: =D46 -> 3.0693173 | E53: =E46 -> 1.4817553 | F53: =F46 -> 1.9531371 | G53: =G46 -> 0.99585208 | H53: =H46 -> 1.7559139 | I53: =I46 -> 1.6234196
B54: ROIC | D54: =D34 -> 0.10384035 | E54: =E34 -> 0.13610198 | F54: =F34 -> 0.1557316 | G54: =G34 -> 0.15356945 | H54: =H34 -> 0.13394208 | I54: =I34 -> 0.14371303
B56: Intrinsic Growth | D56: =D53*D54 -> 0.31871898 | E56: =E53*E54 -> 0.20166982 | F56: =F53*F54 -> 0.30416517 | G56: =G53*G54 -> 0.15293246 | H56: =H53*H54 -> 0.23519076 | I56: =I53*I54 -> 0.23330655
B58: Forward looking Reinvestment Rate
B59: Normalised ROIC | C59: =AVERAGE(E34:I34) -> 0.14461163
B60: Forecast Growth | C60: =DCF!D19 -> 0.06
B61: Terminal Growth | C61: =DCF!D20 -> 0.065
B62: Reinvestment Rate (Based on expected Growth) | C62: =C60/C59 -> 0.4149044
B63: Reinvestment Rate (Based on TerminalGrowth) | C63: =C61/C59 -> 0.44947976

Sheet DCF
B2: Calculation of PV of FCFF | D2: ='Data Sheet'!K16 -> 46112 | E2: =D2+365 -> 46477 | F2: =E2+365 -> 46842 | G2: =F2+365 -> 47207 | H2: =G2+365 -> 47572 | I2: =H2+365 -> 47937
B4: ='Intrinsic Growth'!B41 -> EBIT | D4: ='Intrinsic Growth'!I41 -> 4149.57 | E4: =D4*(1+$D$19) -> 4398.5442 | F4: =E4*(1+$D$19) -> 4662.4569 | G4: =F4*(1+$D$19) -> 4942.2043 | H4: =G4*(1+$D$19) -> 5238.7365 | I4: =H4*(1+$D$19) -> 5553.0607 | Y4: Industry Name | Z4: Number of Firms | AA4: Capital Expenditures | AB4: Depreciation & Amort | AC4: CapEx/Deprecn | AD4: Acquisitions | AE4: Net R&D | AF4: Net Cap Ex/Sales | AG4: Net Cap Ex/ EBIT (1-t) | AH4: Sales/ Invested Capital | AI4: Reinvestment Rate | AJ4: Expected EBIT Growth
Y5: Retail (Online) | Z5: 13 | AA5: $35.31 | AB5: $47.83 | AC5: 0.7382 | AD5: $26.27 | AE5: $0.43 | AF5: 0.0083 | AG5: NA | AH5: 0.9 | AI5: 1.1076 | AJ5: 0.06
B6: ='Intrinsic Growth'!B42 -> Marginal Tax Rate | D6: ='Intrinsic Growth'!C42 -> 0.25 | E6: =D6 -> 0.25 | F6: =E6 -> 0.25 | G6: =F6 -> 0.25 | H6: =G6 -> 0.25 | I6: =H6 -> 0.25
B8: ='Intrinsic Growth'!B43 -> EBIT(1-TR) | D8: =D4*(1-D6) -> 3112.1775 | E8: =E4*(1-E6) -> 3298.9082 | F8: =F4*(1-F6) -> 3496.8426 | G8: =G4*(1-G6) -> 3706.6532 | H8: =H4*(1-H6) -> 3929.0524 | I8: =I4*(1-I6) -> 4164.7955
B10: Less: Reinvesment Rate | D10: ='Intrinsic Growth'!C63 -> 0.44947976 | E10: =D10 -> 0.44947976 | F10: =E10 -> 0.44947976 | G10: =F10 -> 0.44947976 | H10: =G10 -> 0.44947976 | I10: ='Intrinsic Growth'!C62 -> 0.4149044
B12: Free Cash Flow to Firm | D12: =D8*(1-D10) -> 1713.3167 | E12: =E8*(1-E10) -> 1816.1157 | F12: =F8*(1-F10) -> 1925.0826 | G12: =G8*(1-G10) -> 2040.5876 | H12: =H8*(1-H10) -> 2163.0229 | I12: =I8*(1-I10) -> 2436.8036
B14: Mid Year Convention | E14: 0.5 | F14: =E14+1 -> 1.5 | G14: =F14+1 -> 2.5 | H14: =G14+1 -> 3.5 | I14: =H14+1 -> 4.5
B15: Discounting Factor | E15: =1/(1+$D$21)^E14 -> 0.95760942 | F15: =1/(1+$D$21)^F14 -> 0.87814298 | G15: =1/(1+$D$21)^G14 -> 0.80527099 | H15: =1/(1+$D$21)^H14 -> 0.73844623 | I15: =1/(1+$D$21)^I14 -> 0.67716686
B17: PV of FCFF | E17: =E12*E15 -> 1739.1295 | F17: =F12*F15 -> 1690.4978 | G17: =G12*G15 -> 1643.226 | H17: =H12*H15 -> 1597.2761 | I17: =I12*I15 -> 1650.1226
B19: Expected Growth | D19: 0.06
B20: Terminal Growth | D20: 0.065
B21: WACC | D21: =WACC!J39 -> 0.090493743
B23: Calculation of Terminal Value | K23: Sensitivity Analysis Of Value of Operating Assest
K24: =C35 -> 76930.419 | L24: 0.07 | M24: 0.09 | N24: 0.11 | O24: 0.13 | P24: 0.15
B25: FCFF(N+1) | C25: =I12*(1+D19) -> 2583.0118 | K25: 0.025 | L25: 47189.807 | M25: 35229.944 | N25: 28898.252 | O25: 24978.633 | P25: 22313.292
B26: WACC | C26: =D21 -> 0.090493743 | K26: 0.045 | L26: 78285.451 | M26: 47189.807 | N26: 35229.944 | O26: 28898.252 | P26: 24978.633
B27: Terminal Growth Rate | C27: =D20 -> 0.065 | K27: 0.065 | L27: 358146.25 | M27: 78285.451 | N27: 47189.807 | O27: 35229.944 | P27: 28898.252
K28: 0.085 | L28: -108288.41 | M28: 358146.25 | N28: 78285.451 | O28: 47189.807 | P28: 35229.944
B29: Terminal Value | C29: =C25/(C26-C27) -> 101319.44 | K29: 0.105 | L29: -41654.89 | M29: -108288.41 | N29: 358146.25 | O29: 78285.451 | P29: 47189.807
K30: 0.125 | L30: -23482.111 | M30: -41654.89 | N30: -108288.41 | O30: 358146.25 | P30: 78285.451
B31: Calculation of Equity Value
B33: PV of FCFF | C33: =SUM(E17:I17) -> 8320.252
B34: PV of Terminal Value | C34: =C29*I15 -> 68610.167 | K34: Sensitivity Analysis Of Share Price
B35: Value of Operating Asset | C35: =SUM(C33:C34) -> 76930.419 | K35: =C42 -> 1170.1662 | L35: 0.07 | M35: 0.09 | N35: 0.11 | O35: 0.13 | P35: 0.15
K36: 0.025 | L36: 714.19384 | M36: 530.82954 | N36: 433.75432 | O36: 373.66014 | P36: 332.79609
B37: Add: Cash | C37: ='Data Sheet'!J69 -> 358.2 | K37: 0.045 | L37: 1190.941 | M37: 714.19384 | N37: 530.82954 | O37: 433.75432 | P37: 373.66014
B38: Less: Debt | C38: =SUM('Data for IG'!I7:I8) -> 965 | K38: 0.065 | L38: 5481.6657 | M38: 1190.941 | N38: 714.19384 | O38: 530.82954 | P38: 433.75432
B39: Value of Equity | C39: =C35+C37-C38 -> 76323.619 | K39: 0.085 | L39: -1669.5421 | M39: 5481.6657 | N39: 1190.941 | O39: 714.19384 | P39: 530.82954
B40: No. of Share | C40: ='Data Sheet'!B6 -> 65.2246 | K40: 0.105 | L40: -647.94097 | M40: -1669.5421 | N40: 5481.6657 | O40: 1190.941 | P40: 714.19384
K41: 0.125 | L41: -369.32249 | M41: -647.94097 | N41: -1669.5421 | O41: 5481.6657 | P41: 1190.941
B42: Equity Value per share | C42: =C39/C40 -> 1170.1662
B44: Share Price | C44: 250
B45: Discount/Premium | C45: =C44/C42 -> 0.21364487

Sheet Relative Comps
B2: Comparable Company Valuation
B4: Amt. In Crores
D5: Market Data | K5: Financials | O5: Valuation
B6: Company | C6: Ticker | D6: Share Price | E6: Share O/S | F6: Equity Value | G6: Net Debt | H6: Enterprise Value | K6: Revenue | L6: EBITDA | M6: Net Income | O6: EV/Revenue | P6: EV/EBITDA | Q6: P/E
B7: ='Data_Relative Comps'!C2 -> Avenue Super. | D7: ='Data_Relative Comps'!D2 -> 4018.8 | E7: ='Data_Relative Comps'!E2 -> 65.22 | F7: =E7*D7 -> 262106.14 | G7: ='Data_Relative Comps'!I2 -> 2121.21 | H7: =F7+G7 -> 264227.35 | K7: ='Data_Relative Comps'!L2 -> 71255.57 | L7: ='Data_Relative Comps'!N2 -> 5465.3022 | M7: ='Data_Relative Comps'!M2 -> 3057.49 | O7: =H7/K7 -> 3.7081641 | P7: =H7/L7 -> 48.346338 | Q7: =F7/M7 -> 85.725918
B8: ='Data_Relative Comps'!C3 -> Vishal Mega Mart | D8: ='Data_Relative Comps'!D3 -> 108.04 | E8: ='Data_Relative Comps'!E3 -> 468.43 | F8: =E8*D8 -> 50609.177 | G8: ='Data_Relative Comps'!I3 -> 1393.09 | H8: =F8+G8 -> 52002.267 | K8: ='Data_Relative Comps'!L3 -> 13493.01 | L8: ='Data_Relative Comps'!N3 -> 2071.177 | M8: ='Data_Relative Comps'!M3 -> 891.92 | O8: =H8/K8 -> 3.8540153 | P8: =H8/L8 -> 25.107592 | Q8: =F8/M8 -> 56.741835
B9: ='Data_Relative Comps'!C4 -> V-Mart Retail | D9: ='Data_Relative Comps'!D4 -> 724.65 | E9: ='Data_Relative Comps'!E4 -> 7.95 | F9: =E9*D9 -> 5760.9675 | G9: ='Data_Relative Comps'!I4 -> 938.06 | H9: =F9+G9 -> 6699.0275 | K9: ='Data_Relative Comps'!L4 -> 3992.95 | L9: ='Data_Relative Comps'!N4 -> 562.60665 | M9: ='Data_Relative Comps'!M4 -> 137.61 | O9: =H9/K9 -> 1.6777138 | P9: =H9/L9 -> 11.907125 | Q9: =F9/M9 -> 41.864454
B10: ='Data_Relative Comps'!C5 -> Electronics Mart | D10: ='Data_Relative Comps'!D5 -> 129.64 | E10: ='Data_Relative Comps'!E5 -> 38.47 | F10: =E10*D10 -> 4987.2508 | G10: ='Data_Relative Comps'!I5 -> 1947.23 | H10: =F10+G10 -> 6934.4808 | K10: ='Data_Relative Comps'!L5 -> 7183.26 | L10: ='Data_Relative Comps'!N5 -> 446.08045 | M10: ='Data_Relative Comps'!M5 -> 107.14 | O10: =H10/K10 -> 0.96536681 | P10: =H10/L10 -> 15.545359 | Q10: =F10/M10 -> 46.548915
B11: ='Data_Relative Comps'!C6 -> Shoppers Stop | D11: ='Data_Relative Comps'!D6 -> 377.75 | E11: ='Data_Relative Comps'!E6 -> 11.02 | F11: =E11*D11 -> 4162.805 | G11: ='Data_Relative Comps'!I6 -> 3303.97 | H11: =F11+G11 -> 7466.775 | K11: ='Data_Relative Comps'!L6 -> 5173.64 | L11: ='Data_Relative Comps'!N6 -> 807.6052 | M11: ='Data_Relative Comps'!M6 -> -34.59 | O11: =H11/K11 -> 1.4432344 | P11: =H11/L11 -> 9.2455756 | Q11: =F11/M11 -> -120.34707
B12: ='Data_Relative Comps'!C7 -> Keto Motors | D12: ='Data_Relative Comps'!D7 -> 227.65 | E12: ='Data_Relative Comps'!E7 -> 7.04 | F12: =E12*D12 -> 1602.656 | G12: ='Data_Relative Comps'!I7 -> 37.54 | H12: =F12+G12 -> 1640.196 | K12: ='Data_Relative Comps'!L7 -> 2.13 | L12: ='Data_Relative Comps'!N7 -> 0.59001 | M12: ='Data_Relative Comps'!M7 -> -0.18 | O12: =H12/K12 -> 770.04507 | P12: =H12/L12 -> 2779.9461 | Q12: =F12/M12 -> -8903.6444
B13: ='Data_Relative Comps'!C8 -> Patel Retail | D13: ='Data_Relative Comps'!D8 -> 223.44 | E13: ='Data_Relative Comps'!E8 -> 3.34 | F13: =E13*D13 -> 746.2896 | G13: ='Data_Relative Comps'!I8 -> 139.43 | H13: =F13+G13 -> 885.7196 | K13: ='Data_Relative Comps'!L8 -> 1048.33 | L13: ='Data_Relative Comps'!N8 -> 83.027736 | M13: ='Data_Relative Comps'!M8 -> 39.05 | O13: =H13/K13 -> 0.84488625 | P13: =H13/L13 -> 10.667756 | Q13: =F13/M13 -> 19.111129
B15: High | O15: =MAX(O7:O13) -> 770.04507 | P15: =MAX(P7:P13) -> 2779.9461 | Q15: =MAX(Q7:Q13) -> 85.725918
B16: Q3 | O16: =QUARTILE(O7:O13,3) -> 3.7810897 | P16: =QUARTILE(P7:P13,3) -> 36.726965 | Q16: =QUARTILE(Q7:Q13,3) -> 51.645375
B17: Average | O17: =AVERAGE(O7:O13) -> 111.79121 | P17: =AVERAGE(P7:P13) -> 414.39512 | Q17: =AVERAGE(Q7:Q13) -> -1253.4285
B18: Median | O18: =MEDIAN(O7:O13) -> 1.6777138 | P18: =MEDIAN(P7:P13) -> 15.545359 | Q18: =MEDIAN(Q7:Q13) -> 41.864454
B19: Q1 | O19: =QUARTILE(O7:O13,1) -> 1.2043006 | P19: =QUARTILE(P7:P13,1) -> 11.28744 | Q19: =QUARTILE(Q7:Q13,1) -> -50.617968
B20: Low | O20: =MIN(O7:O13) -> 0.84488625 | P20: =MIN(P7:P13) -> 9.2455756 | Q20: =MIN(Q7:Q13) -> -8903.6444
B22: Comparable Company Valuation | O22: EV/Revenue | P22: EV/EBITDA | Q22: P/E
B23: Implied Enterprise Value | O23: =O18*K$7 -> 119546.46 | P23: =P18*L$7 -> 84960.087 | Q23: =Q25+Q24 -> 130121.36
B24: Net Debt | O24: =G7 -> 2121.21 | P24: =G7 -> 2121.21 | Q24: =G7 -> 2121.21
B25: Implied Market Value | O25: =O23-O24 -> 117425.25 | P25: =P23-P24 -> 82838.877 | Q25: =Q18*M7 -> 128000.15
B26: Share Outstanding | O26: =E7 -> 65.22 | P26: =E7 -> 65.22 | Q26: =E7 -> 65.22
B27: Implied Value Per Share | O27: =O25/O26 -> 1800.4484 | P27: =P25/P26 -> 1270.1453 | Q27: =Q25/Q26 -> 1962.5904
O29: =IF(O27>D7,"Under Valued",IF(O27=D7,"Normal Value","Over Valued")) -> Over Valued | P29: =IF(O27>D7,"Under Valued",IF(O27=D7,"Normal Value","Over Valued")) -> Over Valued | Q29: =IF(O27>D7,"Under Valued",IF(O27=D7,"Normal Value","Over Valued")) -> Over Valued

Sheet Football Field Analysis
B2: Football Field Analysis
C3: Open Low | D3: Low | E3: Open High | F3: High
B4: Comps | C4: 1270.1453 | D4: =MIN('Relative Comps'!O27:Q27) -> 1270.1453 | E4: 1962.5904 | F4: =MAX('Relative Comps'!O27:Q27) -> 1962.5904
B5: DCF Bear | C5: 332.79609 | D5: =MIN(DCF!P36:P41) -> 332.79609 | E5: 1190.941 | F5: =MAX(DCF!P36:P41) -> 1190.941
B6: DCF Base | C6: -1669.5421 | D6: =MIN(DCF!M36:M41) -> -1669.5421 | E6: 5481.6657 | F6: =MAX(DCF!M36:M41) -> 5481.6657
B7: DCF Bull | C7: -1669.5421 | D7: =MIN(DCF!L36:L41) -> -1669.5421 | E7: 5481.6657 | F7: =MAX(DCF!L36:L41) -> 5481.6657
B8: 52W H/L | C8: 3403.95 | D8: =MIN(Beta!C7:C110) -> 3403.95 | E8: 5320.55 | F8: =MAX(Beta!C7:C110) -> 5320.55

Sheet Data >>

Sheet Data Sheet
A1: COMPANY NAME | B1: AVENUE SUPERMARTS LTD | E1: =IF(B2<>B3, "A NEW VERSION OF THE WORKSHEET IS AVAILABLE", "")
A2: LATEST VERSION | B2: 2.1 | E2: PLEASE DO NOT MAKE ANY CHANGES TO THIS SHEET
A3: CURRENT VERSION | B3: 2.1
A5: META
A6: Number of shares | B6: =IF(B9>0, B9/B8, 0) -> 65.2246
A7: Face Value | B7: 10
A8: Current Price | B8: 4054.55
A9: Market Capitalization | B9: 264456.4
A15: PROFIT & LOSS
A16: Report Date | B16: 42825 | C16: 43190 | D16: 43555 | E16: 43921 | F16: 44286 | G16: 44651 | H16: 45016 | I16: 45382 | J16: 45747 | K16: 46112
A17: Sales | B17: 11897.7 | C17: 15033.2 | D17: 20004.52 | E17: 24870.2 | F17: 24143.06 | G17: 30976.27 | H17: 42839.56 | I17: 50788.83 | J17: 59358.05 | K17: 68820.74
A18: Raw Material Cost | B18: 10357.25 | C18: 12846.95 | D18: 17445.49 | E18: 21441.68 | F18: 20855.56 | G18: 26891.77 | H18: 36884.77 | I18: 43958.31 | J18: 51668.76 | K18: 59315.99
A19: Change in Inventory | B19: 276.22 | C19: 211.31 | D19: 444.65 | E19: 338.75 | F19: 300.88 | G19: 494.38 | H19: 500.82 | I19: 683.77 | J19: 1117.06 | K19: 856.26
A20: Power and Fuel | B20: 99.41 | C20: 121.26 | D20: 152.8 | E20: 188.24 | F20: 174.2 | G20: 207.86 | H20: 314.62 | I20: 376.59 | J20: 447.75
A21: Other Mfr. Exp | B21: 332.9 | C21: 373.72 | D21: 499.72 | E21: 645.96 | F21: 746.43 | G21: 805.85 | H21: 1116.56 | I21: 1323.43 | J21: 1751.85
A22: Employee Cost | B22: 192.67 | C22: 283.14 | D22: 356.17 | E22: 457.14 | F22: 537.58 | G22: 617.36 | H22: 748.16 | I22: 907.82 | J22: 1167.47 | K22: 1541.48
A23: Selling and admin | B23: 71.24 | C23: 96 | D23: 135.84 | E23: 66.4 | F23: 108.69 | G23: 143.41 | H23: 212.04 | I23: 274.43 | J23: 312.48
A24: Other Expenses | B24: 151.27 | C24: 170.58 | D24: 225.84 | E24: 281.22 | F24: 276.65 | G24: 302.05 | H24: 425.46 | I24: 526.38 | J24: 632.29 | K24: 3632.94
A25: Other Income | B25: 27.7 | C25: 87.75 | D25: 48.33 | E25: 59.99 | F25: 194.43 | G25: 113.64 | H25: 127.6 | I25: 144.58 | J25: 117.13 | K25: 74.1
A26: Depreciation | B26: 127.82 | C26: 159 | D26: 212.49 | E26: 374.41 | F26: 414.16 | G26: 498.08 | H26: 638.87 | I26: 730.76 | J26: 869.52 | K26: 1037.02
A27: Interest | B27: 121.98 | C27: 59.54 | D27: 47.21 | E27: 69.12 | F27: 41.65 | G27: 53.79 | H27: 67.41 | I27: 58.13 | J27: 69.45 | K27: 142.05
A28: Profit before tax | B28: 747.08 | C28: 1222.07 | D28: 1421.94 | E28: 1744.77 | F28: 1483.45 | G28: 2064.12 | H28: 3060.09 | I28: 3461.33 | J28: 3672.67 | K28: 4081.62
A29: Tax | B29: 268.28 | C29: 415.79 | D29: 519.48 | E29: 443.79 | F29: 384.02 | G29: 571.72 | H29: 681.75 | I29: 925.72 | J29: 965.22 | K29: 1111.76
A30: Net profit | B30: 478.75 | C30: 806.26 | D30: 902.54 | E30: 1301.08 | F30: 1099.49 | G30: 1492.55 | H30: 2378.51 | I30: 2536.17 | J30: 2708.02 | K30: 2970.49
A31: Dividend Amount
A40: Quarters
A41: Report Date | B41: 45382 | C41: 45473 | D41: 45565 | E41: 45657 | F41: 45747 | G41: 45838 | H41: 45930 | I41: 46022 | J41: 46112 | K41: 46203
A42: Sales | B42: 12726.55 | C42: 14069.14 | D42: 14444.5 | E42: 15972.55 | F42: 14871.86 | G42: 16359.7 | H42: 16676.3 | I42: 18100.88 | J42: 17683.86 | K42: 18794.53
A43: Expenses | B43: 11782.91 | C43: 12847.89 | D43: 13350.73 | E43: 14755.31 | F43: 13916.79 | G43: 15060.66 | H43: 15462.65 | I43: 16637.51 | J43: 16473.33 | K43: 17295.19
A44: Other Income | B44: 37.87 | C44: 41.6 | D44: 33.52 | E44: 24.14 | F44: 25.05 | G44: 19.43 | H44: 19.57 | I44: 16.93 | J44: 18.17 | K44: 25.78
A45: Depreciation | B45: 204.89 | C45: 192.76 | D45: 207.78 | E45: 228.12 | F45: 240.86 | G45: 231.7 | H45: 253.47 | I45: 268.29 | J45: 283.56 | K45: 287.7
A46: Interest | B46: 13.42 | C46: 15.96 | D46: 16.32 | E46: 18.21 | F46: 18.96 | G46: 29.3 | H46: 34.96 | I46: 36.82 | J46: 40.97 | K46: 54.28
A47: Profit before tax | B47: 763.2 | C47: 1054.13 | D47: 903.19 | E47: 995.05 | F47: 720.3 | G47: 1057.47 | H47: 944.79 | I47: 1175.19 | J47: 904.17 | K47: 1183.14
A48: Tax | B48: 200.06 | C48: 280.45 | D48: 243.75 | E48: 271.51 | F48: 169.51 | G48: 284.66 | H48: 259.94 | I48: 319.41 | J48: 247.75 | K48: 322.7
A49: Net profit | B49: 563.25 | C49: 773.82 | D49: 659.58 | E49: 723.72 | F49: 550.9 | G49: 772.97 | H49: 685.01 | I49: 855.92 | J49: 656.59 | K49: 860.61
A50: Operating Profit | B50: 943.64 | C50: 1221.25 | D50: 1093.77 | E50: 1217.24 | F50: 955.07 | G50: 1299.04 | H50: 1213.65 | I50: 1463.37 | J50: 1210.53 | K50: 1499.34
A55: BALANCE SHEET
A56: Report Date | B56: 42825 | C56: 43190 | D56: 43555 | E56: 43921 | F56: 44286 | G56: 44651 | H56: 45016 | I56: 45382 | J56: 45747 | K56: 46112
A57: Equity Share Capital | B57: 624.08 | C57: 624.08 | D57: 624.08 | E57: 647.77 | F57: 647.77 | G57: 647.77 | H57: 648.26 | I57: 650.73 | J57: 650.73 | K57: 651.96
A58: Reserves | B58: 3217.7 | C58: 4044.97 | D58: 4963.37 | E58: 10431.97 | F58: 11535.94 | G58: 13029.87 | H58: 15430.44 | I58: 18047.09 | J58: 20777.02 | K58: 23812.08
A59: Borrowings | B59: 1497.32 | C59: 439.25 | D59: 700.15 | E59: 333.19 | F59: 392.71 | G59: 646.94 | H59: 642.98 | I59: 592.16 | J59: 819.62 | K59: 2424.99
A60: Other Liabilities | B60: 480.18 | C60: 539.92 | D60: 717.9 | E60: 663.23 | F60: 1078.63 | G60: 1146.4 | H60: 1382.84 | I60: 1882.5 | J60: 2065.41 | K60: 2635.23
A61: Total | B61: 5819.28 | C61: 5648.22 | D61: 7005.5 | E61: 12076.16 | F61: 13655.05 | G61: 15470.98 | H61: 18104.52 | I61: 21172.48 | J61: 24312.78 | K61: 29524.26
A62: Net Block | B62: 2577.75 | C62: 3399.97 | D62: 4400.37 | E62: 5948.03 | F62: 7008.8 | G62: 9260.02 | H62: 11340.48 | I62: 13415 | J62: 16206.46 | K62: 20090.31
A63: Capital Work in Progress | B63: 152.89 | C63: 147.07 | D63: 376.84 | E63: 364.4 | F63: 1019.59 | G63: 1129.34 | H63: 829.16 | I63: 935.22 | J63: 1099.35 | K63: 1299.96
A64: Investments | B64: 25.69 | C64: 68.18 | D64: 16.53 | E64: 14.68 | F64: 2.95 | G64: 5.94 | H64: 202.2 | I64: 106.67 | J64: 3.26 | K64: 4.01
A65: Other Assets | B65: 3062.95 | C65: 2033 | D65: 2211.76 | E65: 5749.05 | F65: 5623.71 | G65: 5075.68 | H65: 5732.68 | I65: 6715.59 | J65: 7003.71 | K65: 8129.98
A66: Total | B66: 5819.28 | C66: 5648.22 | D66: 7005.5 | E66: 12076.16 | F66: 13655.05 | G66: 15470.98 | H66: 18104.52 | I66: 21172.48 | J66: 24312.78 | K66: 29524.26
A67: Receivables | B67: 21 | C67: 33.52 | D67: 64.37 | E67: 19.55 | F67: 43.58 | G67: 66.89 | H67: 62.16 | I67: 166.37 | J67: 153.79 | K67: 149.34
... A69: Cash & Bank | B69: 1884.29 | C69: 560.18 | D69: 219.07 | E69: 107.88 | F69: 1445.58 | G69: 298.58 | H69: 1408.33 | I69: 638.18 | J69: 358.2 | K69: 303.78
A70: No. of Equity Shares | B70: 624084486 | C70: 624084486 | D70: 624084486 | E70: 647774691 | F70: 647774691 | G70: 647774691 | H70: 648263978 | I70: 650733068 | J70: 650733068
A71: New Bonus Shares
A72: Face value | B72: 10 | C72: 10 | D72: 10 | E72: 10 | F72: 10 | G72: 10 | H72: 10 | I72: 10 | J72: 10 | K72: 10
A80: CASH FLOW:
A81: Report Date | B81: 42825 | C81: 43190 | D81: 43555 | E81: 43921 | F81: 44286 | G81: 44651 | H81: 45016 | I81: 45382 | J81: 45747 | K81: 46112
A82: Cash from Operating Activity | B82: 455.28 | C82: 729.99 | D82: 806.84 | E82: 1280.14 | F82: 1375.14 | G82: 1372.35 | H82: 2630.27 | I82: 2745.84 | J82: 2462.97 | K82: 3466.74
A83: Cash from Investing Activity | B83: -2481.61 | C83: 463.55 | D83: -958.37 | E83: -4656.56 | F83: -1110 | G83: -1289.49 | H83: -2313.1 | I83: -2468.23 | J83: -2185.31 | K83: -4206.96
A84: Cash from Financing Activity | B84: 2025.26 | C84: -1159.06 | D84: 208.98 | E84: 3357.42 | F84: -179.5 | G84: -179.24 | H84: -205.14 | I84: -147.64 | J84: -259.3 | K84: 288.18
A85: Net Cash Flow | B85: -1.07 | C85: 34.48 | D85: 57.45 | E85: -19 | F85: 85.64 | G85: -96.38 | H85: 112.03 | I85: 129.97 | J85: 18.36 | K85: -452.04
A90: PRICE: | B90: 637.85 | C90: 1324.8 | D90: 1471.1 | E90: 2187.5 | F90: 2859.05 | G90: 4003.35 | H90: 3401.05 | I90: 4525.6 | J90: 4083.2 | K90: 3956.8
A92: DERIVED:
A93: Adjusted Equity Shares in Cr | B93: 62.41 | C93: 62.41 | D93: 62.41 | E93: 64.78 | F93: 64.78 | G93: 64.78 | H93: 64.83 | I93: 65.07 | J93: 65.07 | K93: 65.2

Sheet Data for IG
B3: Particulars | C3: 43891 | D3: 44256 | E3: 44621 | F3: 44986 | G3: 45352 | H3: 45717 | I3: 46082
B4: Equity Capital | C4: 648 | D4: 648 | E4: 648 | F4: 648 | G4: 651 | H4: 651 | I4: 652
B5: Reserves | C5: 10432 | D5: 11536 | E5: 13030 | F5: 15430 | G5: 18047 | H5: 20777 | I5: 23812
B6: Borrowings -
B7: Long term Borrowings | C7: 0 | D7: 0 | E7: 0 | F7: 0 | G7: 0 | H7: 0 | I7: 0
B8: Short term Borrowings | C8: 4 | D8: 0 | E8: 0 | F8: 0 | G8: 0 | H8: 0 | I8: 965
B9: Lease Liabilities | C9: 295 | D9: 393 | E9: 647 | F9: 643 | G9: 592 | H9: 820 | I9: 1460
B10: Other Borrowings | C10: 34 | D10: 0 | E10: 0 | F10: 0 | G10: 0 | H10: 0
B11: Other Liabilities -
B12: Non controlling int | C12: 0 | D12: 0 | E12: 0 | F12: 0 | G12: 0 | H12: -1 | I12: -2
B13: Trade Payables | C13: 433 | D13: 578 | E13: 589 | F13: 754 | G13: 985 | H13: 1071 | I13: 1338
B14: Other liability items | C14: 229 | D14: 500 | E14: 557 | F14: 629 | G14: 898 | H14: 996 | I14: 1299
B15: Total Liabilities | C15: 12076 | D15: 13655 | E15: 15471 | F15: 18105 | G15: 21172 | H15: 24313 | I15: 29524
B17: Fixed Assets -
B18: Land | C18: 2740 | D18: 3483 | E18: 4527 | F18: 5519 | G18: 6904 | H18: 8595 | I18: 10432
B19: Building | C19: 3139 | D19: 3649 | E19: 4938 | F19: 6201 | G19: 7062 | H19: 16206 | I19: 10391
B20: Plant Machinery | C20: 272 | D20: 352 | E20: 491 | F20: 656 | G20: 870 | H20: 1141 | I20: 1446
B21: Equipments | C21: 39 | D21: 50 | E21: 73 | F21: 85 | G21: 97 | H21: 115 | I21: 140
B22: Computers | C22: 95 | D22: 119 | E22: 153 | F22: 190 | G22: 219 | H22: 276 | I22: 372
B23: Furniture n fittings | C23: 476 | D23: 581 | E23: 772 | F23: 968 | G23: 1205 | H23: 1515 | I23: 1954
B24: Vehicles | C24: 4 | D24: 4 | E24: 3 | F24: 15 | G24: 17 | H24: 6 | I24: 8
B25: Intangible Assets | C25: 78 | D25: 78 | E25: 78 | F25: 78 | G25: 78 | H25: 78 | I25: 78
B26: Other fixed assets | C26: 82 | D26: 81 | E26: 91 | F26: 105 | G26: 119 | H26: 124 | I26: 140
B27: Gross Block | C27: 6927 | D27: 8396 | E27: 11127 | F27: 13816 | G27: 16571 | H27: 20106 | I27: 24960
B28: Accumulated Depreciation | C28: 979 | D28: 1387 | E28: 1867 | F28: 2476 | G28: 3156 | H28: 3900 | I28: 4870
B29: Net Block | C29: =C27-C28 -> 5948 | D29: =D27-D28 -> 7009 | E29: =E27-E28 -> 9260 | F29: =F27-F28 -> 11340 | G29: =G27-G28 -> 13415 | H29: =H27-H28 -> 16206 | I29: =I27-I28 -> 20090
B31: CWIP | C31: 364 | D31: 1020 | E31: 1129 | F31: 829 | G31: 935 | H31: 1099 | I31: 1300
B32: Investments | C32: 15 | D32: 3 | E32: 6 | F32: 202 | G32: 107 | H32: 3 | I32: 4
B34: Other Assets -
B35: Inventories | C35: 1947 | D35: 2248 | E35: 2743 | F35: 3243 | G35: 3927 | H35: 5044 | I35: 5901
B36: Trade receivables | C36: 20 | D36: 44 | E36: 67 | F36: 62 | G36: 166 | H36: 154 | I36: 149
B37: Cash Equivalents | C37: 108 | D37: 1446 | E37: 299 | F37: 1408 | G37: 638 | H37: 358 | I37: 304
B38: Loans n Advances | C38: 101 | D38: 81 | E38: 109 | F38: 97 | G38: 105 | H38: 126 | I38: 197
B39: Other asset items | C39: 3574 | D39: 1806 | E39: 1859 | F39: 922 | G39: 1879 | H39: 1321 | I39: 1580
B40: Total Assets | C40: 12076 | D40: 13655 | E40: 15471 | F40: 18105 | G40: 21172 | H40: 24313 | I40: 29524

Sheet Cashflow
C1: 43891 | D1: 44256 | E1: 44621 | F1: 44986 | G1: 45352 | H1: 45717 | I1: 46082
B2: Cash from Operating Activity - | C2: 1280 | D2: 1375 | E2: 1372 | F2: 2630 | G2: 2746 | H2: 2463 | I2: 3467
B3: Profit from operations | C3: 2149 | D3: 1764 | E3: 2515 | F3: 3659 | G3: 4131 | H3: 4535 | I3: 5233
B4: Receivables | C4: 45 | D4: -24 | E4: -23 | F4: 5 | G4: -104 | H4: 13 | I4: 4
B5: Inventory | C5: -339 | D5: -301 | E5: -494 | F5: -501 | G5: -684 | H5: -1117 | I5: -856
B6: Payables | C6: -30 | D6: 145 | E6: 11 | F6: 165 | G6: 231 | H6: 86 | I6: 267
B7: Loans Advances | C7: 0 | D7: 0 | E7: 0 | F7: 0 | G7: 0 | H7: 0 | I7: 0
B8: Operating investments | C8: 2 | D8: 12 | E8: -3 | F8: 0 | G8: 0 | H8: 0 | I8: 0
B9: Other WC items | C9: -54 | D9: 41 | E9: -73 | F9: 12 | G9: -87 | H9: -94 | I9: -114
B10: Working capital changes | C10: -376 | D10: -127 | E10: -582 | F10: -320 | G10: -644 | H10: -1113 | I10: -699
B11: Direct taxes | C11: -492 | D11: -262 | E11: -560 | F11: -709 | G11: -742 | H11: -959 | I11: -1068
B12: Cash from Investing Activity - | C12: -4657 | D12: -1110 | E12: -1289 | F12: -2313 | G12: -2468 | H12: -2185 | I12: -4207
B13: Fixed assets purchased | C13: -1712 | D13: -2029 | E13: -2410 | F13: -2212 | G13: -2731 | H13: -3423 | I13: -4113
... B36: CFO/OP | C36: 0.83 | D36: 0.94 | E36: 0.77 | F36: 0.92 | G36: 0.85 | H36: 0.76 | I36: 0.87

Sheet Data_Relative Comps
B1: S.No. | C1: Name | D1: CMP Rs. | E1: No. Eq. Shares Cr. | F1: Market Cap | G1: Debt Rs.Cr. | H1: Cash End Rs.Cr. | I1: Net Debt | J1: EV | K1: EV Rs.Cr. | L1: Sales Rs.Cr. | M1: NP 12M Rs.Cr. | N1: EBITDA
B2: 1 | C2: Avenue Super. | D2: 4018.8 | E2: 65.22 | F2: =E2*D2 -> 262106.14 | G2: 2424.99 | H2: 303.78 | I2: =G2-H2 -> 2121.21 | J2: =F2+G2-H2 -> 264227.35 | K2: 264245.82 | L2: 71255.57 | M2: 3057.49 | N2: 5465.3022
B3: 2 | C3: Vishal Mega Mart | D3: 108.04 | E3: 468.43 | F3: =E3*D3 -> 50609.177 | G3: 1987.98 | H3: 594.89 | I3: =G3-H3 -> 1393.09 | J3: =F3+G3-H3 -> 52002.267 | K3: 52002.36 | L3: 13493.01 | M3: 891.92 | N3: 2071.177
B4: 3 | C4: V-Mart Retail | D4: 724.65 | E4: 7.95 | F4: =E4*D4 -> 5760.9675 | G4: 957.59 | H4: 19.53 | I4: =G4-H4 -> 938.06 | J4: =F4+G4-H4 -> 6699.0275 | K4: 6702.51 | L4: 3992.95 | M4: 137.61 | N4: 562.60665
B5: 4 | C5: Electronics Mart | D5: 129.64 | E5: 38.47 | F5: =E5*D5 -> 4987.2508 | G5: 1996.98 | H5: 49.75 | I5: =G5-H5 -> 1947.23 | J5: =F5+G5-H5 -> 6934.4808 | K5: 6935.11 | L5: 7183.26 | M5: 107.14 | N5: 446.08045
B6: 5 | C6: Shoppers Stop | D6: 377.75 | E6: 11.02 | F6: =E6*D6 -> 4162.805 | G6: 3316.68 | H6: 12.71 | I6: =G6-H6 -> 3303.97 | J6: =F6+G6-H6 -> 7466.775 | K6: 7466.99 | L6: 5173.64 | M6: -34.59 | N6: 807.6052
B7: 6 | C7: Keto Motors | D7: 227.65 | E7: 7.04 | F7: =E7*D7 -> 1602.656 | G7: 37.97 | H7: 0.43 | I7: =G7-H7 -> 37.54 | J7: =F7+G7-H7 -> 1640.196 | K7: 1640.98 | L7: 2.13 | M7: -0.18 | N7: 0.59001
B8: 7 | C8: Patel Retail | D8: 223.44 | E8: 3.34 | F8: =E8*D8 -> 746.2896 | G8: 163.49 | H8: 24.06 | I8: =G8-H8 -> 139.43 | J8: =F8+G8-H8 -> 885.7196 | K8: 885.73 | L8: 1048.33 | M8: 39.05 | N8: 83.027736
