Workbook
Name BoxPlot: "BoxPlot"
Name Bubble: "Bubble"
Name Candlestick: "Candlestick"
Name Chart: "Chart"
Name ChartImage: "ChartImage"
Name ColumnRange: "ColumnRange"
Name Dumbbell: "Dumbbell"
Name Heatmap: "Heatmap"
Name Histogram: "Histogram"
Name Map: "Map"
Name OHLC: "OHLC"
Name PieChart: "PieChart"
Name Scatter: "Scatter"
Name Series: "Series"
Name Stripe: "Stripe"
Name Table: "Table"
Name TreeMap: "TreeMap"
Name UPDATE: 'Data Sheet'!$E$1
Name Waterfall: "Waterfall"

Sheet Teaser
B2: ='Data Sheet'!B1&"- One Page" -> INDIAN HOTELS CO LTD- One Page
B4: #VALUE! | C4: IHCL is one of India’s leading hospitality companies. IHCL and its subsidiaries comprise diversified portfolio across luxury, upscale/upper upscale and lean luxury/midscale segments. IHCL’s operations are spread across four continents, 12 countries and over 100 cities.
B6: Key Metrics | C6: ='Data Sheet'!G16 -> 44651 | D6: ='Data Sheet'!H16 -> 45016 | E6: ='Data Sheet'!I16 -> 45382 | F6: ='Data Sheet'!J16 -> 45747 | G6: ='Data Sheet'!K16 -> 46112 | I6: Share Price 5 Years
B8: Total Sales | C8: ='Data Sheet'!G17 -> 3056.22 | D8: ='Data Sheet'!H17 -> 5809.91 | E8: ='Data Sheet'!I17 -> 6768.75 | F8: ='Data Sheet'!J17 -> 8334.54 | G8: ='Data Sheet'!K17 -> 9689.22
B9: Sales Growth | C9: ='Historicial Financials'!E8 -> 0.94026004 | D9: ='Historicial Financials'!F8 -> 0.90101171 | E9: ='Historicial Financials'!G8 -> 0.16503526 | F9: ='Historicial Financials'!H8 -> 0.23132632 | G9: ='Historicial Financials'!I8 -> 0.16253806
B10: Gross Margin | C10: ='Historicial Financials'!E14 -> 0.27696959 | D10: ='Historicial Financials'!F14 -> 0.41304254 | E10: ='Historicial Financials'!G14 -> 0.425306 | F10: ='Historicial Financials'!H14 -> 0.47245799 | G10: ='Historicial Financials'!I14 -> 0.47542836
B11: EBITDA Margin | C11: ='Historicial Financials'!E20 -> 0.13243484 | D11: ='Historicial Financials'!F20 -> 0.31060034 | E11: ='Historicial Financials'!G20 -> 0.31904118 | F11: ='Historicial Financials'!H20 -> 0.33227149 | G11: ='Historicial Financials'!I20 -> 0.32983047
B12: EBIT Margin | C12: ='Ratio Analysis'!E15 -> -0.00042536205 | D12: ='Ratio Analysis'!F15 -> 0.23898821 | E12: ='Ratio Analysis'!G15 -> 0.25192392 | F12: ='Ratio Analysis'!H15 -> 0.27010129 | G12: ='Ratio Analysis'!I15 -> 0.26737343
B13: Net Profit Margin | C13: ='Historicial Financials'!E35 -> -0.13693386 | D13: ='Historicial Financials'!F35 -> 0.14809179 | E13: ='Historicial Financials'!G35 -> 0.15933961 | F13: ='Historicial Financials'!H35 -> 0.16465576 | G13: ='Historicial Financials'!I35 -> 0.15768142
B14: EPS | C14: ='Historicial Financials'!E39 -> -2.9463531 | D14: ='Historicial Financials'!F39 -> 6.0574486 | E14: ='Historicial Financials'!G39 -> 7.5771392 | F14: ='Historicial Financials'!H39 -> 9.6412112 | G14: ='Historicial Financials'!I39 -> 10.733525
B15: EPS Growth | C15: ='Historicial Financials'!E40 -> -0.6273559 | D15: ='Historicial Financials'!F40 -> -3.055914 | E15: ='Historicial Financials'!G40 -> 0.25087966 | F15: ='Historicial Financials'!H40 -> 0.27240781 | G15: ='Historicial Financials'!I40 -> 0.11329636
B17: Income Segment | C17: =C6 -> 44651 | D17: =D6 -> 45016 | E17: =E6 -> 45382 | F17: =F6 -> 45747 | G17: =G6 -> 46112 | I17: RevPAR
B19: Room Income | C19: 848.19 | D19: 1594.04 | E19: 1952.72 | F19: 2238.42 | G19: 2374.64
B20: Food, Beverage & Banqueting Income | C20: 714.47 | D20: 1381.47 | E20: 1562.9 | F20: 1650.32 | G20: 1803.48
B21: Other Operating Income | C21: 242.03 | D21: 338.08 | E21: 426.7 | F21: 483.94 | G21: 557.22
B22: Management & Reimbursable Fees | C22: 198.65 | D22: 390.65 | E22: 463.28 | F22: 543.86 | G22: 644.21
B23: Non-operating Income | C23: 149.08 | D23: 107.08 | E23: 184.51 | F23: 228.55 | G23: 260.61
B24: Total Income | C24: 2152.42 | D24: 3811.32 | E24: 4590.11 | F24: 5145.09 | G24: 5640.16
B27: Other Ratios | C27: =C17 -> 44651 | D27: =D17 -> 45016 | E27: =E17 -> 45382 | F27: =F17 -> 45747 | G27: =G17 -> 46112 | I27: Like for Like Growth
B29: Inventory Turnover | C29: ='Ratio Analysis'!E32 -> 22.81493 | D29: ='Ratio Analysis'!F32 -> 32.471624 | E29: ='Ratio Analysis'!G32 -> 34.47782 | F29: ='Ratio Analysis'!H32 -> 34.907864 | G29: ='Ratio Analysis'!I32 -> 35.642987
B30: Working Capital | C30: ='Ratio Analysis'!E31 -> 0.75245624 | D30: ='Ratio Analysis'!F31 -> 0.67295813 | E30: ='Ratio Analysis'!G31 -> 0.81809379 | F30: ='Ratio Analysis'!H31 -> 0.88042421 | G30: ='Ratio Analysis'!I31 -> 0.62507272
B31: Inventory Days | C31: ='Ratio Analysis'!E38 -> 15.998296 | D31: ='Ratio Analysis'!F38 -> 11.240583 | E31: ='Ratio Analysis'!G38 -> 10.586516 | F31: ='Ratio Analysis'!H38 -> 10.456097 | G31: ='Ratio Analysis'!I38 -> 10.240444
B32: Cash Conversion Cycle | C32: ='Ratio Analysis'!E39 -> -198.56469 | D32: ='Ratio Analysis'!F39 -> -110.92763 | E32: ='Ratio Analysis'!G39 -> -100.71752 | F32: ='Ratio Analysis'!H39 -> -108.66791 | G32: ='Ratio Analysis'!I39 -> -125.5648
B36: Category | C36: # of Shares | D36: % of holding | E36: Value (CMP) | I36: Holding Share
B38: Promoters | C38: 5076.5531 | D38: 0.3566 | E38: =C38*'Data Sheet'!$B$8 -> 3644965.1
B39: Other Entities of the Promoter Group | C39: 349.02429 | D39: 0.0245 | E39: =C39*'Data Sheet'!$B$8 -> 250599.44
B40: Mutual Funds & UTI | C40: 1844.814 | D40: 0.1296 | E40: =C40*'Data Sheet'!$B$8 -> 1324576.4
B41: Banks, Financial Institutions, States and Central Government | C41: 659.6312 | D41: 0.0464 | E41: =C41*'Data Sheet'!$B$8 -> 473615.2
B42: Insurance Companies | C42: 704.90071 | D42: 0.0495 | E42: =C42*'Data Sheet'!$B$8 -> 506118.71
B43: Foreign Institutional Investors and Foreign Portfolio Investors – Corporate | C43: 3308.4461 | D43: 0.2324 | E43: =C43*'Data Sheet'!$B$8 -> 2375464.3
B44: NRI's / OCB's / Foreign Nationals | C44: 123.35274 | D44: 0.0087 | E44: =C44*'Data Sheet'!$B$8 -> 88567.267
B45: Corporate Bodies / Trust | C45: 149.28531 | D45: 0.0105 | E45: =C45*'Data Sheet'!$B$8 -> 107186.85
B46: Indian Public & Others | C46: 1967.2175 | D46: 0.1382 | E46: =C46*'Data Sheet'!$B$8 -> 1412462.2
B47: Alternate Investment Fund | C47: 18.59488 | D47: 0.0013 | E47: =C47*'Data Sheet'!$B$8 -> 13351.124
B48: IEPF account | C48: 32.50242 | D48: 0.0023 | E48: =C48*'Data Sheet'!$B$8 -> 23336.738
B50: Top Shareholders | C50: Designation | D50: Remuneration | E50: X of Median Salary | I50: Capital Structure
B52: Mr. Puneet Chhatwal | C52: MD & CEO | E52: 521.17
B53: Mr. Nasser Munjee | C53: Non Executive | D53: 6.14 | E53: 18.7 | I53: Share Price | J53: ='Data Sheet'!B8 -> 718
B54: Mr. Venkataramanan | C54: Non Executive | D54: 2.57 | E54: 17.8 | I54: No. of Share O/S | J54: ='Data Sheet'!B6 -> 142.34322
B55: Ms. Hema Ravichandar | C55: Non Executive | D55: 5.3 | E55: 17 | I55: Market Capitalization | J55: =J53*J54 -> 102202.43
B56: Mr. Anupam Narayan | C56: Non Executive | D56: 1.2 | E56: 17.6 | I56: Less: Cash & Equivalents | J56: ='Historicial Financials'!I62 -> 1831.19
I57: Add: Total Debt | J57: =WACC!C15 -> 2837
B58: As a policy, Mr. N Chandrasekaran, Chairman, has abstained from receiving commission from the Company. | I58: Enterprise Value | J58: =J55-J56+J57 -> 103208.24
B59: Mr. Ankur Dalwani appointed w.e.f. July 1, 2024.
B60: Mr. Beejal Desai superannuated on February 12, 2026.
B61: Ms. Melisa Alva appointed w.e.f. February 13, 2026.

Sheet Global, Indian And Industry 
B2: Global Outlook
B3: IMF, World Economic Outlook
B4: (Real GDP, annual percent change) | C4: 2025 | D4: 2026 (PROJECTIONS) | E4: 2027 (PROJECTIONS) | G4: Inflation
B5: World Output | C5: 3.4 | D5: 3.1 | E5: 3.2
B6: Advanced Economies | C6: 1.9 | D6: 1.8 | E6: 1.7
B7: United States | C7: 2.1 | D7: 2.3 | E7: 2.1
B8: Euro Area | C8: 1.4 | D8: 1.1 | E8: 1.2
B9: Other Advanced Economies | C9: 3 | D9: 2.6 | E9: 2.2
B10: Emerging Market and Developing Economies | C10: 4.4 | D10: 3.9 | E10: 4.2
B11: Emerging and Developing Asia | C11: 5.5 | D11: 4.9 | E11: 4.8
B12: China | C12: 5 | D12: 4.4 | E12: 4
B13: India | C13: 7.6 | D13: 6.5 | E13: 6.5
B14: Latin America and the Caribbean | C14: 2.4 | D14: 2.3 | E14: 2.7
B15: Emerging Market and Middle-Income Economies | C15: 4.4 | D15: 3.8 | E15: 4.1
B16: Low-Income Developing Countries | C16: 4.8 | D16: 4.8 | E16: 4.9
B18: India's Outlook & Key Risks &Opporunity
B19: PIB, Trading view
B20: Key Indicator | C20: 2025-2026 | E20: Macroeconomic Outlook
B21: Real GDP | C21: 0.078
B22: Nominal GDP | C22: 0.103
B23: GDP in Amount | C23: 4 Trillion USD
B24: Inflation Rate | C24: 0.0482
B25: Food Inflation | C25: 0.0595
B26: Unemployement Rate | C26: 0.05
B27: RBI Interest Rate | C27: 0.0525
B34: India Tourism Data
B35: Ministry of Tourism, Statistics 2025-2026 | C35: (in Lakhs)
B36: Year | C36: FTAs | D36: NRI Arrivals | E36: ITA | G36: % Break Down of Purpose of visit
B37: 2019 | C37: 109.3 | D37: 69.8 | E37: 179.1
B38: 2020 | C38: 27.4 | D38: 35.9 | E38: 63.3
B39: 2021 | C39: 15.2 | D39: 54.8 | E39: 70
B40: 2022 | C40: 64.4 | D40: 78.9 | E40: 143.3
B41: 2023 | C41: 95.1 | D41: 93.8 | E41: 188.9
B42: 2024 | C42: 99.5 | D42: 106.2 | E42: 205.7
B43: 2025 | C43: 91.5 | D43: 110.7 | E43: 202.2
B46: Year (Tourist Visit ) | C46: Domestic | D46: Foreign | G46: Forex Earning From Tourism
B47: 2019 | C47: 0.2526 | D47: 0.0886
B48: 2020 | C48: -0.7372 | D48: -0.7717
B49: 2021 | C49: 0.1105 | D49: -0.8529
B50: 2022 | C50: 1.5545 | D50: 7.1426
B51: 2023 | C51: 0.4493 | D51: 1.2406
B52: 2024 | C52: 0.174 | D52: 0.0822
B53: 2025 | C53: 0.4551 | D53: 0.2163
B55: Industry Outlook

Sheet Financials>>

Sheet Historicial Financials
B1: #VALUE!
C2: ="Historical Financial Statement-"&'Data Sheet'!B1 -> Historical Financial Statement-INDIAN HOTELS CO LTD
B4: Years | C4: ='Data Sheet'!E16 -> 43921 | D4: ='Data Sheet'!F16 -> 44286 | E4: ='Data Sheet'!G16 -> 44651 | F4: ='Data Sheet'!H16 -> 45016 | G4: ='Data Sheet'!I16 -> 45382 | H4: ='Data Sheet'!J16 -> 45747 | I4: ='Data Sheet'!K16 -> 46112
A6: # | B6: Income Statements
B7: Sales | C7: =IFERROR('Data Sheet'!E17,0) -> 4463.14 | D7: =IFERROR('Data Sheet'!F17,0) -> 1575.16 | E7: =IFERROR('Data Sheet'!G17,0) -> 3056.22 | F7: =IFERROR('Data Sheet'!H17,0) -> 5809.91 | G7: =IFERROR('Data Sheet'!I17,0) -> 6768.75 | H7: =IFERROR('Data Sheet'!J17,0) -> 8334.54 | I7: =IFERROR('Data Sheet'!K17,0) -> 9689.22
B8: Sales Growth | C8: - | D8: =IFERROR(D7/C7-1,0) -> -0.64707358 | E8: =IFERROR(E7/D7-1,0) -> 0.94026004 | F8: =IFERROR(F7/E7-1,0) -> 0.90101171 | G8: =IFERROR(G7/F7-1,0) -> 0.16503526 | H8: =IFERROR(H7/G7-1,0) -> 0.23132632 | I8: =IFERROR(I7/H7-1,0) -> 0.16253806
B10: COGS | C10: =IFERROR(SUM('Data Sheet'!E18,'Data Sheet'!E20,'Data Sheet'!E21:E22)-1*'Data Sheet'!E19,0) -> 2947.21 | D10: =IFERROR(SUM('Data Sheet'!F18,'Data Sheet'!F20,'Data Sheet'!F21:F22)-1*'Data Sheet'!F19,0) -> 1572.93 | E10: =IFERROR(SUM('Data Sheet'!G18,'Data Sheet'!G20,'Data Sheet'!G21:G22)-1*'Data Sheet'!G19,0) -> 2209.74 | F10: =IFERROR(SUM('Data Sheet'!H18,'Data Sheet'!H20,'Data Sheet'!H21:H22)-1*'Data Sheet'!H19,0) -> 3410.17 | G10: =IFERROR(SUM('Data Sheet'!I18,'Data Sheet'!I20,'Data Sheet'!I21:I22)-1*'Data Sheet'!I19,0) -> 3889.96 | H10: =IFERROR(SUM('Data Sheet'!J18,'Data Sheet'!J20,'Data Sheet'!J21:J22)-1*'Data Sheet'!J19,0) -> 4396.82 | I10: =IFERROR(SUM('Data Sheet'!K18,'Data Sheet'!K20,'Data Sheet'!K21:K22)-1*'Data Sheet'!K19,0) -> 5082.69
B11: COGS % Sales | C11: =IFERROR(C10/C7,0) -> 0.66034451 | D11: =IFERROR(D10/D7,0) -> 0.99858427 | E11: =IFERROR(E10/E7,0) -> 0.72303041 | F11: =IFERROR(F10/F7,0) -> 0.58695746 | G11: =IFERROR(G10/G7,0) -> 0.574694 | H11: =IFERROR(H10/H7,0) -> 0.52754201 | I11: =IFERROR(I10/I7,0) -> 0.52457164
B13: Gross Profit | C13: =IFERROR(C7-C10,0) -> 1515.93 | D13: =IFERROR(D7-D10,0) -> 2.23 | E13: =IFERROR(E7-E10,0) -> 846.48 | F13: =IFERROR(F7-F10,0) -> 2399.74 | G13: =IFERROR(G7-G10,0) -> 2878.79 | H13: =IFERROR(H7-H10,0) -> 3937.72 | I13: =IFERROR(I7-I10,0) -> 4606.53
B14: Gross Margin | C14: =IFERROR(C13/C7,0) -> 0.33965549 | D14: =IFERROR(D13/D7,0) -> 0.0014157292 | E14: =IFERROR(E13/E7,0) -> 0.27696959 | F14: =IFERROR(F13/F7,0) -> 0.41304254 | G14: =IFERROR(G13/G7,0) -> 0.425306 | H14: =IFERROR(H13/H7,0) -> 0.47245799 | I14: =IFERROR(I13/I7,0) -> 0.47542836
B16: Selling & General Expenses | C16: =IFERROR(SUM('Data Sheet'!E23:E24),0) -> 548.4 | D16: =IFERROR(SUM('Data Sheet'!F23:F24),0) -> 363.99 | E16: =IFERROR(SUM('Data Sheet'!G23:G24),0) -> 441.73 | F16: =IFERROR(SUM('Data Sheet'!H23:H24),0) -> 595.18 | G16: =IFERROR(SUM('Data Sheet'!I23:I24),0) -> 719.28 | H16: =IFERROR(SUM('Data Sheet'!J23:J24),0) -> 1168.39 | I16: =IFERROR(SUM('Data Sheet'!K23:K24),0) -> 1410.73
B17: S&G Exp. | C17: =C16/C7 -> 0.12287313 | D17: =D16/D7 -> 0.23108129 | E17: =E16/E7 -> 0.14453475 | F17: =F16/F7 -> 0.10244221 | G17: =G16/G7 -> 0.10626482 | H17: =H16/H7 -> 0.1401865 | I17: =I16/I7 -> 0.14559789
B19: EBITDA | C19: =IFERROR(C13-C16,0) -> 967.53 | D19: =IFERROR(D13-D16,0) -> -361.76 | E19: =IFERROR(E13-E16,0) -> 404.75 | F19: =IFERROR(F13-F16,0) -> 1804.56 | G19: =IFERROR(G13-G16,0) -> 2159.51 | H19: =IFERROR(H13-H16,0) -> 2769.33 | I19: =IFERROR(I13-I16,0) -> 3195.8
B20: EBITDA Margin | C20: =C19/C7 -> 0.21678236 | D20: =D19/D7 -> -0.22966556 | E20: =E19/E7 -> 0.13243484 | F20: =F19/F7 -> 0.31060034 | G20: =G19/G7 -> 0.31904118 | H20: =H19/H7 -> 0.33227149 | I20: =I19/I7 -> 0.32983047
B22: Interest | C22: =IFERROR('Data Sheet'!E27,0) -> 341.12 | D22: =IFERROR('Data Sheet'!F27,0) -> 402.82 | E22: =IFERROR('Data Sheet'!G27,0) -> 427.66 | F22: =IFERROR('Data Sheet'!H27,0) -> 236.05 | G22: =IFERROR('Data Sheet'!I27,0) -> 220.22 | H22: =IFERROR('Data Sheet'!J27,0) -> 208.38 | I22: =IFERROR('Data Sheet'!K27,0) -> 221.35
B23: Interest % Sales | C23: =IFERROR(C22/C7,0) -> 0.076430495 | D23: =IFERROR(D22/D7,0) -> 0.25573275 | E23: =IFERROR(E22/E7,0) -> 0.13993103 | F23: =IFERROR(F22/F7,0) -> 0.040628857 | G23: =IFERROR(G22/G7,0) -> 0.032534811 | H23: =IFERROR(H22/H7,0) -> 0.02500198 | I23: =IFERROR(I22/I7,0) -> 0.022844976
B25: Depreciation | C25: =IFERROR('Data Sheet'!E26,0) -> 404.24 | D25: =IFERROR('Data Sheet'!F26,0) -> 409.63 | E25: =IFERROR('Data Sheet'!G26,0) -> 406.05 | F25: =IFERROR('Data Sheet'!H26,0) -> 416.06 | G25: =IFERROR('Data Sheet'!I26,0) -> 454.3 | H25: =IFERROR('Data Sheet'!J26,0) -> 518.16 | I25: =IFERROR('Data Sheet'!K26,0) -> 605.16
B26: Depreciation % Sales | C26: =IFERROR(C25/C7,0) -> 0.090573005 | D26: =IFERROR(D25/D7,0) -> 0.26005612 | E26: =IFERROR(E25/E7,0) -> 0.1328602 | F26: =IFERROR(F25/F7,0) -> 0.071612125 | G26: =IFERROR(G25/G7,0) -> 0.067117267 | H26: =IFERROR(H25/H7,0) -> 0.062170198 | I26: =IFERROR(I25/I7,0) -> 0.06245704
B28: EBT | C28: =IFERROR(C19-SUM(C22,C25),0) -> 222.17 | D28: =IFERROR(D19-SUM(D22,D25),0) -> -1174.21 | E28: =IFERROR(E19-SUM(E22,E25),0) -> -428.96 | F28: =IFERROR(F19-SUM(F22,F25),0) -> 1152.45 | G28: =IFERROR(G19-SUM(G22,G25),0) -> 1484.99 | H28: =IFERROR(H19-SUM(H22,H25),0) -> 2042.79 | I28: =IFERROR(I19-SUM(I22,I25),0) -> 2369.29
B29: EBT % Sales | C29: =IFERROR(C28/C7,0) -> 0.049778855 | D29: =IFERROR(D28/D7,0) -> -0.74545443 | E29: =IFERROR(E28/E7,0) -> -0.14035639 | F29: =IFERROR(F28/F7,0) -> 0.19835935 | G29: =IFERROR(G28/G7,0) -> 0.2193891 | H29: =IFERROR(H28/H7,0) -> 0.24509931 | I29: =IFERROR(I28/I7,0) -> 0.24452846
B31: Tax | C31: =IFERROR('Data Sheet'!E28-'Data Sheet'!E30,0) -> 41.12 | D31: =IFERROR('Data Sheet'!F28-'Data Sheet'!F30,0) -> -129.43 | E31: =IFERROR('Data Sheet'!G28-'Data Sheet'!G30,0) -> -10.46 | F31: =IFERROR('Data Sheet'!H28-'Data Sheet'!H30,0) -> 292.05 | G31: =IFERROR('Data Sheet'!I28-'Data Sheet'!I30,0) -> 406.46 | H31: =IFERROR('Data Sheet'!J28-'Data Sheet'!J30,0) -> 670.46 | I31: =IFERROR('Data Sheet'!K28-'Data Sheet'!K30,0) -> 841.48
B32: Effective Tax Rate | C32: =IFERROR(C31/C28,0) -> 0.18508349 | D32: =IFERROR(D31/D28,0) -> 0.1102273 | E32: =IFERROR(E31/E28,0) -> 0.024384558 | F32: =IFERROR(F31/F28,0) -> 0.25341663 | G32: =IFERROR(G31/G28,0) -> 0.27371228 | H32: =IFERROR(H31/H28,0) -> 0.32820799 | I32: =IFERROR(I31/I28,0) -> 0.35516125
B34: Net Profit | C34: =IFERROR(C28-C31,0) -> 181.05 | D34: =IFERROR(D28-D31,0) -> -1044.78 | E34: =IFERROR(E28-E31,0) -> -418.5 | F34: =IFERROR(F28-F31,0) -> 860.4 | G34: =IFERROR(G28-G31,0) -> 1078.53 | H34: =IFERROR(H28-H31,0) -> 1372.33 | I34: =IFERROR(I28-I31,0) -> 1527.81
B35: Net Margin | C35: =IFERROR(C34/C7,0) -> 0.040565611 | D35: =IFERROR(D34/D7,0) -> -0.663285 | E35: =IFERROR(E34/E7,0) -> -0.13693386 | F35: =IFERROR(F34/F7,0) -> 0.14809179 | G35: =IFERROR(G34/G7,0) -> 0.15933961 | H35: =IFERROR(H34/H7,0) -> 0.16465576 | I35: =IFERROR(I34/I7,0) -> 0.15768142
B37: No. of Equity Shares | C37: =IFERROR('Data Sheet'!E93,0) -> 132.14 | D37: =IFERROR('Data Sheet'!F93,0) -> 132.14 | E37: =IFERROR('Data Sheet'!G93,0) -> 142.04 | F37: =IFERROR('Data Sheet'!H93,0) -> 142.04 | G37: =IFERROR('Data Sheet'!I93,0) -> 142.34 | H37: =IFERROR('Data Sheet'!J93,0) -> 142.34 | I37: =IFERROR('Data Sheet'!K93,0) -> 142.34
B39: EPS | C39: =IFERROR(C34/C37,0) -> 1.3701377 | D39: =IFERROR(D34/D37,0) -> -7.9066142 | E39: =IFERROR(E34/E37,0) -> -2.9463531 | F39: =IFERROR(F34/F37,0) -> 6.0574486 | G39: =IFERROR(G34/G37,0) -> 7.5771392 | H39: =IFERROR(H34/H37,0) -> 9.6412112 | I39: =IFERROR(I34/I37,0) -> 10.733525
B40: EPS Growth | D40: =IFERROR(D39/C39-1,0) -> -6.7706711 | E40: =IFERROR(E39/D39-1,0) -> -0.6273559 | F40: =IFERROR(F39/E39-1,0) -> -3.055914 | G40: =IFERROR(G39/F39-1,0) -> 0.25087966 | H40: =IFERROR(H39/G39-1,0) -> 0.27240781 | I40: =IFERROR(I39/H39-1,0) -> 0.11329636
B42: Dividend per share | C42: ='Data Sheet'!E31/'Data Sheet'!E93 -> 0.4499773 | D42: ='Data Sheet'!F31/'Data Sheet'!F93 -> 0.35999697 | E42: ='Data Sheet'!G31/'Data Sheet'!G93 -> 0.40002816 | F42: ='Data Sheet'!H31/'Data Sheet'!H93 -> 1 | G42: ='Data Sheet'!I31/'Data Sheet'!I93 -> 1.7500351 | H42: ='Data Sheet'!J31/'Data Sheet'!J93 -> 2.2499649 | I42: ='Data Sheet'!K31/'Data Sheet'!K93 -> 3.2499649
B43: Dividend payout ratio | C43: ='Data Sheet'!E31/'Data Sheet'!E30 -> 0.16776706 | D43: ='Data Sheet'!F31/'Data Sheet'!F30 -> -0.066059352 | E43: ='Data Sheet'!G31/'Data Sheet'!G30 -> -0.22937187 | F43: ='Data Sheet'!H31/'Data Sheet'!H30 -> 0.14167307 | G43: ='Data Sheet'!I31/'Data Sheet'!I30 -> 0.19784444 | H43: ='Data Sheet'!J31/'Data Sheet'!J30 -> 0.16788723 | I43: ='Data Sheet'!K31/'Data Sheet'!K30 -> 0.2219365
B45: Retained Earnings | C45: =IFERROR(IF(C39>C42,1-C43,0),0) -> 0.83223294 | D45: =IFERROR(IF(D39>D42,1-D43,0),0) -> 0 | E45: =IFERROR(IF(E39>E42,1-E43,0),0) -> 0 | F45: =IFERROR(IF(F39>F42,1-F43,0),0) -> 0.85832693 | G45: =IFERROR(IF(G39>G42,1-G43,0),0) -> 0.80215556 | H45: =IFERROR(IF(H39>H42,1-H43,0),0) -> 0.83211277 | I45: =IFERROR(IF(I39>I42,1-I43,0),0) -> 0.7780635
A47: # | B47: Balance Sheet
B48: Equity Share Capital | C48: =IFERROR('Data Sheet'!E57,0) -> 118.93 | D48: =IFERROR('Data Sheet'!F57,0) -> 118.93 | E48: =IFERROR('Data Sheet'!G57,0) -> 142.04 | F48: =IFERROR('Data Sheet'!H57,0) -> 142.04 | G48: =IFERROR('Data Sheet'!I57,0) -> 142.34 | H48: =IFERROR('Data Sheet'!J57,0) -> 142.34 | I48: =IFERROR('Data Sheet'!K57,0) -> 142.34
B49: Reserves | C49: =IFERROR('Data Sheet'!E58,0) -> 4237.88 | D49: =IFERROR('Data Sheet'!F58,0) -> 3529.51 | E49: =IFERROR('Data Sheet'!G58,0) -> 6920.21 | F49: =IFERROR('Data Sheet'!H58,0) -> 7839.92 | G49: =IFERROR('Data Sheet'!I58,0) -> 9314.31 | H49: =IFERROR('Data Sheet'!J58,0) -> 11018.37 | I49: =IFERROR('Data Sheet'!K58,0) -> 12909.95
B50: Borrowings | C50: =IFERROR('Data Sheet'!E59,0) -> 4500.78 | D50: =IFERROR('Data Sheet'!F59,0) -> 5518.33 | E50: =IFERROR('Data Sheet'!G59,0) -> 3887.87 | F50: =IFERROR('Data Sheet'!H59,0) -> 3139.01 | G50: =IFERROR('Data Sheet'!I59,0) -> 2736.23 | H50: =IFERROR('Data Sheet'!J59,0) -> 3084.27 | I50: =IFERROR('Data Sheet'!K59,0) -> 2836.55
B51: Other Liabilities | C51: =IFERROR('Data Sheet'!E60,0) -> 2584.17 | D51: =IFERROR('Data Sheet'!F60,0) -> 2267.89 | E51: =IFERROR('Data Sheet'!G60,0) -> 2051.92 | F51: =IFERROR('Data Sheet'!H60,0) -> 2391.07 | G51: =IFERROR('Data Sheet'!I60,0) -> 2540.54 | H51: =IFERROR('Data Sheet'!J60,0) -> 3371 | I51: =IFERROR('Data Sheet'!K60,0) -> 4331.88
B52: Total Liabilities | C52: =IFERROR(SUM(C48:C51),0) -> 11441.76 | D52: =IFERROR(SUM(D48:D51),0) -> 11434.66 | E52: =IFERROR(SUM(E48:E51),0) -> 13002.04 | F52: =IFERROR(SUM(F48:F51),0) -> 13512.04 | G52: =IFERROR(SUM(G48:G51),0) -> 14733.42 | H52: =IFERROR(SUM(H48:H51),0) -> 17615.98 | I52: =IFERROR(SUM(I48:I51),0) -> 20220.72
B54: Fixed Assets Net Block | C54: =IFERROR('Data Sheet'!E62,0) -> 8058.85 | D54: =IFERROR('Data Sheet'!F62,0) -> 8437.7 | E54: =IFERROR('Data Sheet'!G62,0) -> 8415.34 | F54: =IFERROR('Data Sheet'!H62,0) -> 8818.53 | G54: =IFERROR('Data Sheet'!I62,0) -> 9311.34 | H54: =IFERROR('Data Sheet'!J62,0) -> 10918.18 | I54: =IFERROR('Data Sheet'!K62,0) -> 12210.06
B55: Capital Work in Progress | C55: =IFERROR('Data Sheet'!E63,0) -> 244.08 | D55: =IFERROR('Data Sheet'!F63,0) -> 164.99 | E55: =IFERROR('Data Sheet'!G63,0) -> 193.54 | F55: =IFERROR('Data Sheet'!H63,0) -> 332.05 | G55: =IFERROR('Data Sheet'!I63,0) -> 255.52 | H55: =IFERROR('Data Sheet'!J63,0) -> 632.57 | I55: =IFERROR('Data Sheet'!K63,0) -> 787.31
B56: Investments | C56: =IFERROR('Data Sheet'!E64,0) -> 1426.59 | D56: =IFERROR('Data Sheet'!F64,0) -> 1483.17 | E56: =IFERROR('Data Sheet'!G64,0) -> 1966.8 | F56: =IFERROR('Data Sheet'!H64,0) -> 1891.04 | G56: =IFERROR('Data Sheet'!I64,0) -> 2261.2 | H56: =IFERROR('Data Sheet'!J64,0) -> 2278.76 | I56: =IFERROR('Data Sheet'!K64,0) -> 3606.43
B57: Other Assets | C57: =IFERROR('Data Sheet'!E65-SUM('Data Sheet'!E67:E69),0) -> 1013.03 | D57: =IFERROR('Data Sheet'!F65-SUM('Data Sheet'!F67:F69),0) -> 882.45 | E57: =IFERROR('Data Sheet'!G65-SUM('Data Sheet'!G67:G69),0) -> 882.38 | F57: =IFERROR('Data Sheet'!H65-SUM('Data Sheet'!H67:H69),0) -> 861.33 | G57: =IFERROR('Data Sheet'!I65-SUM('Data Sheet'!I67:I69),0) -> 826.96 | H57: =IFERROR('Data Sheet'!J65-SUM('Data Sheet'!J67:J69),0) -> 818.56 | I57: =IFERROR('Data Sheet'!K65-SUM('Data Sheet'!K67:K69),0) -> 909.18
B58: Total Non Current Assets | C58: =IFERROR(SUM(C54:C57),0) -> 10742.55 | D58: =IFERROR(SUM(D54:D57),0) -> 10968.31 | E58: =IFERROR(SUM(E54:E57),0) -> 11458.06 | F58: =IFERROR(SUM(F54:F57),0) -> 11902.95 | G58: =IFERROR(SUM(G54:G57),0) -> 12655.02 | H58: =IFERROR(SUM(H54:H57),0) -> 14648.07 | I58: =IFERROR(SUM(I54:I57),0) -> 17512.98
B60: Receivables | C60: =IFERROR('Data Sheet'!E67,0) -> 290.02 | D60: =IFERROR('Data Sheet'!F67,0) -> 219.84 | E60: =IFERROR('Data Sheet'!G67,0) -> 255.34 | F60: =IFERROR('Data Sheet'!H67,0) -> 446.45 | G60: =IFERROR('Data Sheet'!I67,0) -> 476.46 | H60: =IFERROR('Data Sheet'!J67,0) -> 650.88 | I60: =IFERROR('Data Sheet'!K67,0) -> 726.82
B61: Inventory | C61: =IFERROR('Data Sheet'!E68,0) -> 93.61 | D61: =IFERROR('Data Sheet'!F68,0) -> 92.88 | E61: =IFERROR('Data Sheet'!G68,0) -> 100.83 | F61: =IFERROR('Data Sheet'!H68,0) -> 109.21 | G61: =IFERROR('Data Sheet'!I68,0) -> 116.44 | H61: =IFERROR('Data Sheet'!J68,0) -> 135.47 | I61: =IFERROR('Data Sheet'!K68,0) -> 149.73
B62: Cash & Bank | C62: =IFERROR('Data Sheet'!E69,0) -> 315.58 | D62: =IFERROR('Data Sheet'!F69,0) -> 153.63 | E62: =IFERROR('Data Sheet'!G69,0) -> 1187.81 | F62: =IFERROR('Data Sheet'!H69,0) -> 1053.43 | G62: =IFERROR('Data Sheet'!I69,0) -> 1485.5 | H62: =IFERROR('Data Sheet'!J69,0) -> 2181.56 | I62: =IFERROR('Data Sheet'!K69,0) -> 1831.19
B63: Total Current Assets | C63: =IFERROR(SUM(C60:C62),0) -> 699.21 | D63: =IFERROR(SUM(D60:D62),0) -> 466.35 | E63: =IFERROR(SUM(E60:E62),0) -> 1543.98 | F63: =IFERROR(SUM(F60:F62),0) -> 1609.09 | G63: =IFERROR(SUM(G60:G62),0) -> 2078.4 | H63: =IFERROR(SUM(H60:H62),0) -> 2967.91 | I63: =IFERROR(SUM(I60:I62),0) -> 2707.74
B64: Total Assets | C64: =IFERROR(SUM(C63,C58),0) -> 11441.76 | D64: =IFERROR(SUM(D63,D58),0) -> 11434.66 | E64: =IFERROR(SUM(E63,E58),0) -> 13002.04 | F64: =IFERROR(SUM(F63,F58),0) -> 13512.04 | G64: =IFERROR(SUM(G63,G58),0) -> 14733.42 | H64: =IFERROR(SUM(H63,H58),0) -> 17615.98 | I64: =IFERROR(SUM(I63,I58),0) -> 20220.72
A66: # | B66: Cash Flow Statements
B67: Operating Activities
B68: =Cashflow!B3 -> Profit from operations | C68: =Cashflow!C3 -> 1006 | D68: =Cashflow!D3 -> -265 | E68: =Cashflow!E3 -> 495 | F68: =Cashflow!F3 -> 1845 | G68: =Cashflow!G3 -> 2208 | H68: =Cashflow!H3 -> 2829 | I68: =Cashflow!I3 -> 3201
B69: =Cashflow!B4 -> Receivables | C69: =Cashflow!C4 -> 0 | D69: =Cashflow!D4 -> 0 | E69: =Cashflow!E4 -> 0 | F69: =Cashflow!F4 -> 0 | G69: =Cashflow!G4 -> 0 | H69: =Cashflow!H4 -> -82 | I69: =Cashflow!I4 -> -146
B70: =Cashflow!B5 -> Inventory | C70: =Cashflow!C5 -> -13 | D70: =Cashflow!D5 -> 12 | E70: =Cashflow!E5 -> -8 | F70: =Cashflow!F5 -> -8 | G70: =Cashflow!G5 -> -7 | H70: =Cashflow!H5 -> -7 | I70: =Cashflow!I5 -> -10
B71: =Cashflow!B6 -> Payables | C71: =Cashflow!C6 -> 0 | D71: =Cashflow!D6 -> 0 | E71: =Cashflow!E6 -> 0 | F71: =Cashflow!F6 -> 0 | G71: =Cashflow!G6 -> 0 | H71: =Cashflow!H6 -> 36 | I71: =Cashflow!I6 -> 92
B72: =Cashflow!B7 -> Other WC items | C72: =Cashflow!C7 -> 37 | D72: =Cashflow!D7 -> -88 | E72: =Cashflow!E7 -> 129 | F72: =Cashflow!F7 -> 32 | G72: =Cashflow!G7 -> 43 | H72: =Cashflow!H7 -> 0 | I72: =Cashflow!I7 -> 0
B73: =Cashflow!B8 -> Working capital changes | C73: =Cashflow!C8 -> 23 | D73: =Cashflow!D8 -> -77 | E73: =Cashflow!E8 -> 121 | F73: =Cashflow!F8 -> 24 | G73: =Cashflow!G8 -> 36 | H73: =Cashflow!H8 -> -53 | I73: =Cashflow!I8 -> -63
B74: =Cashflow!B9 -> Direct taxes | C74: =Cashflow!C9 -> -206 | D74: =Cashflow!D9 -> 23 | E74: =Cashflow!E9 -> 55 | F74: =Cashflow!F9 -> -250 | G74: =Cashflow!G9 -> -309 | H74: =Cashflow!H9 -> -581 | I74: =Cashflow!I9 -> -667
B75: Cash From Operating Activities | C75: =IFERROR(SUM(C68:C74),0) -> 847 | D75: =IFERROR(SUM(D68:D74),0) -> -395 | E75: =IFERROR(SUM(E68:E74),0) -> 792 | F75: =IFERROR(SUM(F68:F74),0) -> 1643 | G75: =IFERROR(SUM(G68:G74),0) -> 1971 | H75: =IFERROR(SUM(H68:H74),0) -> 2142 | I75: =IFERROR(SUM(I68:I74),0) -> 2407
B77: Investing Activities
B78: =Cashflow!B11 -> Fixed assets purchased | C78: =Cashflow!C11 -> -487 | D78: =Cashflow!D11 -> -215 | E78: =Cashflow!E11 -> -318 | F78: =Cashflow!F11 -> -471 | G78: =Cashflow!G11 -> -637 | H78: =Cashflow!H11 -> -1074 | I78: =Cashflow!I11 -> -1037
B79: =Cashflow!B12 -> Fixed assets sold | C79: =Cashflow!C12 -> 175 | D79: =Cashflow!D12 -> 28 | E79: =Cashflow!E12 -> 33 | F79: =Cashflow!F12 -> 43 | G79: =Cashflow!G12 -> 4 | H79: =Cashflow!H12 -> 12 | I79: =Cashflow!I12 -> 9
B80: =Cashflow!B13 -> Investments purchased | C80: =Cashflow!C13 -> -1938 | D80: =Cashflow!D13 -> -1512 | E80: =Cashflow!E13 -> -2339 | F80: =Cashflow!F13 -> -2069 | G80: =Cashflow!G13 -> -2525 | H80: =Cashflow!H13 -> -3156 | I80: =Cashflow!I13 -> -5438
B81: =Cashflow!B14 -> Investments sold | C81: =Cashflow!C14 -> 1712 | D81: =Cashflow!D14 -> 1591 | E81: =Cashflow!E14 -> 1893 | F81: =Cashflow!F14 -> 2250 | G81: =Cashflow!G14 -> 2597 | H81: =Cashflow!H14 -> 3037 | I81: =Cashflow!I14 -> 4568
B82: =Cashflow!B15 -> Subsidy received | C82: =Cashflow!C15 -> 0 | D82: =Cashflow!D15 -> 0 | E82: =Cashflow!E15 -> 0 | F82: =Cashflow!F15 -> 0 | G82: =Cashflow!G15 -> 0 | H82: =Cashflow!H15 -> 5 | I82: =Cashflow!I15 -> 0
B83: =Cashflow!B16 -> Interest received | C83: =Cashflow!C16 -> 16 | D83: =Cashflow!D16 -> 18 | E83: =Cashflow!E16 -> 12 | F83: =Cashflow!F16 -> 30 | G83: =Cashflow!G16 -> 53 | H83: =Cashflow!H16 -> 109 | I83: =Cashflow!I16 -> 107
B84: =Cashflow!B17 -> Dividends received | C84: =Cashflow!C17 -> 14 | D84: =Cashflow!D17 -> 7 | E84: =Cashflow!E17 -> 8 | F84: =Cashflow!F17 -> 5 | G84: =Cashflow!G17 -> 27 | H84: =Cashflow!H17 -> 44 | I84: =Cashflow!I17 -> 45
B85: =Cashflow!B18 -> Investment in group cos | C85: =Cashflow!C18 -> 0 | D85: =Cashflow!D18 -> -73 | E85: =Cashflow!E18 -> -544 | F85: =Cashflow!F18 -> 0 | G85: =Cashflow!G18 -> 0 | H85: =Cashflow!H18 -> 0 | I85: =Cashflow!I18 -> 0
B86: =Cashflow!B19 -> Redemp n Canc of Shares | C86: =Cashflow!C19 -> 30 | D86: =Cashflow!D19 -> 0 | E86: =Cashflow!E19 -> 0 | F86: =Cashflow!F19 -> 0 | G86: =Cashflow!G19 -> 0 | H86: =Cashflow!H19 -> 0 | I86: =Cashflow!I19 -> 0
B87: =Cashflow!B20 -> Acquisition of companies | C87: =Cashflow!C20 -> 0 | D87: =Cashflow!D20 -> 0 | E87: =Cashflow!E20 -> 0 | F87: =Cashflow!F20 -> 0 | G87: =Cashflow!G20 -> 0 | H87: =Cashflow!H20 -> -18 | I87: =Cashflow!I20 -> -412
B88: =Cashflow!B21 -> Other investing items | C88: =Cashflow!C21 -> -18 | D88: =Cashflow!D21 -> 39 | E88: =Cashflow!E21 -> -385 | F88: =Cashflow!F21 -> 73 | G88: =Cashflow!G21 -> -727 | H88: =Cashflow!H21 -> -829 | I88: =Cashflow!I21 -> 811
B89: Cash From Investing Activities | C89: =IFERROR(SUM(C78:C88),0) -> -496 | D89: =IFERROR(SUM(D78:D88),0) -> -117 | E89: =IFERROR(SUM(E78:E88),0) -> -1640 | F89: =IFERROR(SUM(F78:F88),0) -> -139 | G89: =IFERROR(SUM(G78:G88),0) -> -1208 | H89: =IFERROR(SUM(H78:H88),0) -> -1870 | I89: =IFERROR(SUM(I78:I88),0) -> -1347
B91: Financing Activities
B92: =Cashflow!B23 -> Proceeds from shares | C92: =Cashflow!C23 -> 0 | D92: =Cashflow!D23 -> 0 | E92: =Cashflow!E23 -> 3982 | F92: =Cashflow!F23 -> 1 | G92: =Cashflow!G23 -> 6 | H92: =Cashflow!H23 -> 0 | I92: =Cashflow!I23 -> 0
B93: =Cashflow!B24 -> Redemption of debentures | C93: =Cashflow!C24 -> 0 | D93: =Cashflow!D24 -> 0 | E93: =Cashflow!E24 -> 0 | F93: =Cashflow!F24 -> 0 | G93: =Cashflow!G24 -> 0 | H93: =Cashflow!H24 -> 0 | I93: =Cashflow!I24 -> 0
B94: =Cashflow!B25 -> Proceeds from borrowings | C94: =Cashflow!C25 -> 1015 | D94: =Cashflow!D25 -> 1141 | E94: =Cashflow!E25 -> 1520 | F94: =Cashflow!F25 -> 59 | G94: =Cashflow!G25 -> 138 | H94: =Cashflow!H25 -> 275 | I94: =Cashflow!I25 -> 99
B95: =Cashflow!B26 -> Repayment of borrowings | C95: =Cashflow!C26 -> -793 | D95: =Cashflow!D26 -> -428 | E95: =Cashflow!E26 -> -3176 | F95: =Cashflow!F26 -> -1253 | G95: =Cashflow!G26 -> -709 | H95: =Cashflow!H26 -> -325 | I95: =Cashflow!I26 -> -461
B96: =Cashflow!B27 -> Interest paid fin | C96: =Cashflow!C27 -> -155 | D96: =Cashflow!D27 -> -232 | E96: =Cashflow!E27 -> -281 | F96: =Cashflow!F27 -> -83 | G96: =Cashflow!G27 -> -67 | H96: =Cashflow!H27 -> -27 | I96: =Cashflow!I27 -> -22
B97: =Cashflow!B28 -> Dividends paid | C97: =Cashflow!C28 -> -76 | D97: =Cashflow!D28 -> -60 | E97: =Cashflow!E28 -> -52 | F97: =Cashflow!F28 -> -64 | G97: =Cashflow!G28 -> -155 | H97: =Cashflow!H28 -> -252 | I97: =Cashflow!I28 -> -342
B98: =Cashflow!B29 -> Financial liabilities | C98: =Cashflow!C29 -> -136 | D98: =Cashflow!D29 -> -139 | E98: =Cashflow!E29 -> -151 | F98: =Cashflow!F29 -> -187 | G98: =Cashflow!G29 -> -198 | H98: =Cashflow!H29 -> -218 | I98: =Cashflow!I29 -> -263
B99: =Cashflow!B30 -> Other financing items | C99: =Cashflow!C30 -> -121 | D99: =Cashflow!D30 -> -1 | E99: =Cashflow!E30 -> -184 | F99: =Cashflow!F30 -> -1 | G99: =Cashflow!G30 -> 0 | H99: =Cashflow!H30 -> 0 | I99: =Cashflow!I30 -> 13
B100: Cash From Financing Activities | C100: =IFERROR(SUM(C92:C99),0) -> -266 | D100: =IFERROR(SUM(D92:D99),0) -> 281 | E100: =IFERROR(SUM(E92:E99),0) -> 1658 | F100: =IFERROR(SUM(F92:F99),0) -> -1528 | G100: =IFERROR(SUM(G92:G99),0) -> -985 | H100: =IFERROR(SUM(H92:H99),0) -> -547 | I100: =IFERROR(SUM(I92:I99),0) -> -976
B102: Net Cash Flow | C102: =IFERROR(SUM(C100,C89,C75),0) -> 85 | D102: =IFERROR(SUM(D100,D89,D75),0) -> -231 | E102: =IFERROR(SUM(E100,E89,E75),0) -> 810 | F102: =IFERROR(SUM(F100,F89,F75),0) -> -24 | G102: =IFERROR(SUM(G100,G89,G75),0) -> -222 | H102: =IFERROR(SUM(H100,H89,H75),0) -> -275 | I102: =IFERROR(SUM(I100,I89,I75),0) -> 84

Sheet Common Size Statement
A2: # | B2: ="Common Size P&L Statement-"&'Data Sheet'!B1 -> Common Size P&L Statement-INDIAN HOTELS CO LTD
B4: Particular | C4: ='Data Sheet'!E16 -> 43921 | D4: ='Data Sheet'!F16 -> 44286 | E4: ='Data Sheet'!G16 -> 44651 | F4: ='Data Sheet'!H16 -> 45016 | G4: ='Data Sheet'!I16 -> 45382 | H4: ='Data Sheet'!J16 -> 45747 | I4: ='Data Sheet'!K16 -> 46112
B6: Sales | C6: ='Data Sheet'!E17/'Data Sheet'!E$17 -> 1 | D6: ='Data Sheet'!F17/'Data Sheet'!F$17 -> 1 | E6: ='Data Sheet'!G17/'Data Sheet'!G$17 -> 1 | F6: ='Data Sheet'!H17/'Data Sheet'!H$17 -> 1 | G6: ='Data Sheet'!I17/'Data Sheet'!I$17 -> 1 | H6: ='Data Sheet'!J17/'Data Sheet'!J$17 -> 1 | I6: ='Data Sheet'!K17/'Data Sheet'!K$17 -> 1
B7: Raw Material Cost | C7: ='Data Sheet'!E18/'Data Sheet'!E$17 -> 0.083026748 | D7: ='Data Sheet'!F18/'Data Sheet'!F$17 -> 0.09130501 | E7: ='Data Sheet'!G18/'Data Sheet'!G$17 -> 0.084166061 | F7: ='Data Sheet'!H18/'Data Sheet'!H$17 -> 0.081393688 | G7: ='Data Sheet'!I18/'Data Sheet'!I$17 -> 0.07694626 | H7: ='Data Sheet'!J18/'Data Sheet'!J$17 -> 0.092836557 | I7: ='Data Sheet'!K18/'Data Sheet'!K$17 -> 0.098138963
B8: Change in Inventory | C8: ='Data Sheet'!E19/'Data Sheet'!E$17 -> 0 | D8: ='Data Sheet'!F19/'Data Sheet'!F$17 -> 0 | E8: ='Data Sheet'!G19/'Data Sheet'!G$17 -> 0 | F8: ='Data Sheet'!H19/'Data Sheet'!H$17 -> 0 | G8: ='Data Sheet'!I19/'Data Sheet'!I$17 -> 0 | H8: ='Data Sheet'!J19/'Data Sheet'!J$17 -> 0 | I8: ='Data Sheet'!K19/'Data Sheet'!K$17 -> 0
B9: Power and Fuel | C9: ='Data Sheet'!E20/'Data Sheet'!E$17 -> 0.060466398 | D9: ='Data Sheet'!F20/'Data Sheet'!F$17 -> 0.10973488 | E9: ='Data Sheet'!G20/'Data Sheet'!G$17 -> 0.073551642 | F9: ='Data Sheet'!H20/'Data Sheet'!H$17 -> 0.052167762 | G9: ='Data Sheet'!I20/'Data Sheet'!I$17 -> 0.045649492 | H9: ='Data Sheet'!J20/'Data Sheet'!J$17 -> 0.043272934 | I9: ='Data Sheet'!K20/'Data Sheet'!K$17 -> 0.038919542
B10: Other Mfr. Exp | C10: ='Data Sheet'!E21/'Data Sheet'!E$17 -> 0.18106311 | D10: ='Data Sheet'!F21/'Data Sheet'!F$17 -> 0.22863074 | E10: ='Data Sheet'!G21/'Data Sheet'!G$17 -> 0.18791841 | F10: ='Data Sheet'!H21/'Data Sheet'!H$17 -> 0.17995115 | G10: ='Data Sheet'!I21/'Data Sheet'!I$17 -> 0.18453333 | H10: ='Data Sheet'!J21/'Data Sheet'!J$17 -> 0.13266959 | I10: ='Data Sheet'!K21/'Data Sheet'!K$17 -> 0.13034589
B11: Employee Cost | C11: ='Data Sheet'!E22/'Data Sheet'!E$17 -> 0.33578826 | D11: ='Data Sheet'!F22/'Data Sheet'!F$17 -> 0.56891363 | E11: ='Data Sheet'!G22/'Data Sheet'!G$17 -> 0.3773943 | F11: ='Data Sheet'!H22/'Data Sheet'!H$17 -> 0.27344486 | G11: ='Data Sheet'!I22/'Data Sheet'!I$17 -> 0.26756491 | H11: ='Data Sheet'!J22/'Data Sheet'!J$17 -> 0.25876293 | I11: ='Data Sheet'!K22/'Data Sheet'!K$17 -> 0.25716724
B12: Selling and admin | C12: ='Data Sheet'!E23/'Data Sheet'!E$17 -> 0.095495548 | D12: ='Data Sheet'!F23/'Data Sheet'!F$17 -> 0.16739887 | E12: ='Data Sheet'!G23/'Data Sheet'!G$17 -> 0.10831027 | F12: ='Data Sheet'!H23/'Data Sheet'!H$17 -> 0.081402294 | G12: ='Data Sheet'!I23/'Data Sheet'!I$17 -> 0.084067221 | H12: ='Data Sheet'!J23/'Data Sheet'!J$17 -> 0.11861722 | I12: ='Data Sheet'!K23/'Data Sheet'!K$17 -> 0.12122751
B13: Other Expenses | C13: ='Data Sheet'!E24/'Data Sheet'!E$17 -> 0.027377586 | D13: ='Data Sheet'!F24/'Data Sheet'!F$17 -> 0.06368242 | E13: ='Data Sheet'!G24/'Data Sheet'!G$17 -> 0.036224486 | F13: ='Data Sheet'!H24/'Data Sheet'!H$17 -> 0.021039913 | G13: ='Data Sheet'!I24/'Data Sheet'!I$17 -> 0.022197599 | H13: ='Data Sheet'!J24/'Data Sheet'!J$17 -> 0.021569277 | I13: ='Data Sheet'!K24/'Data Sheet'!K$17 -> 0.024370383
B14: Other Income | C14: ='Data Sheet'!E25/'Data Sheet'!E$17 -> 0.038844849 | D14: ='Data Sheet'!F25/'Data Sheet'!F$17 -> 0.20611874 | E14: ='Data Sheet'!G25/'Data Sheet'!G$17 -> 0.055879485 | F14: ='Data Sheet'!H25/'Data Sheet'!H$17 -> 0.024473701 | G14: ='Data Sheet'!I25/'Data Sheet'!I$17 -> 0.026672576 | H14: ='Data Sheet'!J25/'Data Sheet'!J$17 -> 0.064221901 | I14: ='Data Sheet'!K25/'Data Sheet'!K$17 -> 0.057442188
B15: Depreciation | C15: ='Data Sheet'!E26/'Data Sheet'!E$17 -> 0.090573005 | D15: ='Data Sheet'!F26/'Data Sheet'!F$17 -> 0.26005612 | E15: ='Data Sheet'!G26/'Data Sheet'!G$17 -> 0.1328602 | F15: ='Data Sheet'!H26/'Data Sheet'!H$17 -> 0.071612125 | G15: ='Data Sheet'!I26/'Data Sheet'!I$17 -> 0.067117267 | H15: ='Data Sheet'!J26/'Data Sheet'!J$17 -> 0.062170198 | I15: ='Data Sheet'!K26/'Data Sheet'!K$17 -> 0.06245704
B16: Interest | C16: ='Data Sheet'!E27/'Data Sheet'!E$17 -> 0.076430495 | D16: ='Data Sheet'!F27/'Data Sheet'!F$17 -> 0.25573275 | E16: ='Data Sheet'!G27/'Data Sheet'!G$17 -> 0.13993103 | F16: ='Data Sheet'!H27/'Data Sheet'!H$17 -> 0.040628857 | G16: ='Data Sheet'!I27/'Data Sheet'!I$17 -> 0.032534811 | H16: ='Data Sheet'!J27/'Data Sheet'!J$17 -> 0.02500198 | I16: ='Data Sheet'!K27/'Data Sheet'!K$17 -> 0.022844976
B17: Profit before tax | C17: ='Data Sheet'!E28/'Data Sheet'!E$17 -> 0.088623704 | D17: ='Data Sheet'!F28/'Data Sheet'!F$17 -> -0.53933569 | E17: ='Data Sheet'!G28/'Data Sheet'!G$17 -> -0.084476903 | F17: ='Data Sheet'!H28/'Data Sheet'!H$17 -> 0.22283306 | G17: ='Data Sheet'!I28/'Data Sheet'!I$17 -> 0.24606168 | H17: ='Data Sheet'!J28/'Data Sheet'!J$17 -> 0.30932121 | I17: ='Data Sheet'!K28/'Data Sheet'!K$17 -> 0.30197064
... B20: Dividend Amount | C20: ='Data Sheet'!E31/'Data Sheet'!E$17 -> 0.013322459 | D20: ='Data Sheet'!F31/'Data Sheet'!F$17 -> 0.030200107 | E20: ='Data Sheet'!G31/'Data Sheet'!G$17 -> 0.018591594 | F20: ='Data Sheet'!H31/'Data Sheet'!H$17 -> 0.024447883 | G20: ='Data Sheet'!I31/'Data Sheet'!I$17 -> 0.036801477 | H20: ='Data Sheet'!J31/'Data Sheet'!J$17 -> 0.038425636 | I20: ='Data Sheet'!K31/'Data Sheet'!K$17 -> 0.047743781
B21: EBITDA | C21: ='Historicial Financials'!C19/'Historicial Financials'!C$7 -> 0.21678236 | D21: ='Historicial Financials'!D19/'Historicial Financials'!D$7 -> -0.22966556 | E21: ='Historicial Financials'!E19/'Historicial Financials'!E$7 -> 0.13243484 | F21: ='Historicial Financials'!F19/'Historicial Financials'!F$7 -> 0.31060034 | G21: ='Historicial Financials'!G19/'Historicial Financials'!G$7 -> 0.31904118 | H21: ='Historicial Financials'!H19/'Historicial Financials'!H$7 -> 0.33227149 | I21: ='Historicial Financials'!I19/'Historicial Financials'!I$7 -> 0.32983047
A23: # | B23: ="Common Size Balance sheet Statement-"&'Data Sheet'!B1 -> Common Size Balance sheet Statement-INDIAN HOTELS CO LTD
B25: Particular | C25: ='Data Sheet'!E16 -> 43921 | D25: ='Data Sheet'!F16 -> 44286 | E25: ='Data Sheet'!G16 -> 44651 | F25: ='Data Sheet'!H16 -> 45016 | G25: ='Data Sheet'!I16 -> 45382 | H25: ='Data Sheet'!J16 -> 45747 | I25: ='Data Sheet'!K16 -> 46112
B27: Total Liabilities | C27: ='Data Sheet'!E61/'Data Sheet'!E$61 -> 1 | D27: ='Data Sheet'!F61/'Data Sheet'!F$61 -> 1 | E27: ='Data Sheet'!G61/'Data Sheet'!G$61 -> 1 | F27: ='Data Sheet'!H61/'Data Sheet'!H$61 -> 1 | G27: ='Data Sheet'!I61/'Data Sheet'!I$61 -> 1 | H27: ='Data Sheet'!J61/'Data Sheet'!J$61 -> 1 | I27: ='Data Sheet'!K61/'Data Sheet'!K$61 -> 1
B28: Equity Share Capital | C28: ='Data Sheet'!E57/'Data Sheet'!E$61 -> 0.01039438 | D28: ='Data Sheet'!F57/'Data Sheet'!F$61 -> 0.010400834 | E28: ='Data Sheet'!G57/'Data Sheet'!G$61 -> 0.01092444 | F28: ='Data Sheet'!H57/'Data Sheet'!H$61 -> 0.010512106 | G28: ='Data Sheet'!I57/'Data Sheet'!I$61 -> 0.0096610291 | H28: ='Data Sheet'!J57/'Data Sheet'!J$61 -> 0.0080801636 | I28: ='Data Sheet'!K57/'Data Sheet'!K$61 -> 0.0070393141
B29: Reserves | C29: ='Data Sheet'!E58/'Data Sheet'!E$61 -> 0.37038707 | D29: ='Data Sheet'!F58/'Data Sheet'!F$61 -> 0.30866768 | E29: ='Data Sheet'!G58/'Data Sheet'!G$61 -> 0.53224033 | F29: ='Data Sheet'!H58/'Data Sheet'!H$61 -> 0.58021735 | G29: ='Data Sheet'!I58/'Data Sheet'!I$61 -> 0.63218927 | H29: ='Data Sheet'!J58/'Data Sheet'!J$61 -> 0.62547585 | I29: ='Data Sheet'!K58/'Data Sheet'!K$61 -> 0.63845155
B30: Borrowings | C30: ='Data Sheet'!E59/'Data Sheet'!E$61 -> 0.39336431 | D30: ='Data Sheet'!F59/'Data Sheet'!F$61 -> 0.48259677 | E30: ='Data Sheet'!G59/'Data Sheet'!G$61 -> 0.29902 | F30: ='Data Sheet'!H59/'Data Sheet'!H$61 -> 0.23231207 | G30: ='Data Sheet'!I59/'Data Sheet'!I$61 -> 0.18571588 | H30: ='Data Sheet'!J59/'Data Sheet'!J$61 -> 0.17508365 | I30: ='Data Sheet'!K59/'Data Sheet'!K$61 -> 0.14027938
B31: Other Liabilities | C31: ='Data Sheet'!E60/'Data Sheet'!E$61 -> 0.22585424 | D31: ='Data Sheet'!F60/'Data Sheet'!F$61 -> 0.19833471 | E31: ='Data Sheet'!G60/'Data Sheet'!G$61 -> 0.15781524 | F31: ='Data Sheet'!H60/'Data Sheet'!H$61 -> 0.17695848 | G31: ='Data Sheet'!I60/'Data Sheet'!I$61 -> 0.17243383 | H31: ='Data Sheet'!J60/'Data Sheet'!J$61 -> 0.19136034 | I31: ='Data Sheet'!K60/'Data Sheet'!K$61 -> 0.21422976
B33: Total Assets | C33: ='Data Sheet'!E61/'Data Sheet'!E$61 -> 1 | D33: ='Data Sheet'!F61/'Data Sheet'!F$61 -> 1 | E33: ='Data Sheet'!G61/'Data Sheet'!G$61 -> 1 | F33: ='Data Sheet'!H61/'Data Sheet'!H$61 -> 1 | G33: ='Data Sheet'!I61/'Data Sheet'!I$61 -> 1 | H33: ='Data Sheet'!J61/'Data Sheet'!J$61 -> 1 | I33: ='Data Sheet'!K61/'Data Sheet'!K$61 -> 1
B34: Fixed Assets Net Block | C34: ='Data Sheet'!E62/'Data Sheet'!E$61 -> 0.70433657 | D34: ='Data Sheet'!F62/'Data Sheet'!F$61 -> 0.73790563 | E34: ='Data Sheet'!G62/'Data Sheet'!G$61 -> 0.64723228 | F34: ='Data Sheet'!H62/'Data Sheet'!H$61 -> 0.65264238 | G34: ='Data Sheet'!I62/'Data Sheet'!I$61 -> 0.63198769 | H34: ='Data Sheet'!J62/'Data Sheet'!J$61 -> 0.6197884 | I34: ='Data Sheet'!K62/'Data Sheet'!K$61 -> 0.60383903
B35: Capital Work in Progress | C35: ='Data Sheet'!E63/'Data Sheet'!E$61 -> 0.021332382 | D35: ='Data Sheet'!F63/'Data Sheet'!F$61 -> 0.014428938 | E35: ='Data Sheet'!G63/'Data Sheet'!G$61 -> 0.014885356 | F35: ='Data Sheet'!H63/'Data Sheet'!H$61 -> 0.02457438 | G35: ='Data Sheet'!I63/'Data Sheet'!I$61 -> 0.017342884 | H35: ='Data Sheet'!J63/'Data Sheet'!J$61 -> 0.035908874 | I35: ='Data Sheet'!K63/'Data Sheet'!K$61 -> 0.038935804
B36: Investments | C36: ='Data Sheet'!E64/'Data Sheet'!E$61 -> 0.12468274 | D36: ='Data Sheet'!F64/'Data Sheet'!F$61 -> 0.12970827 | E36: ='Data Sheet'!G64/'Data Sheet'!G$61 -> 0.15126857 | F36: ='Data Sheet'!H64/'Data Sheet'!H$61 -> 0.13995222 | G36: ='Data Sheet'!I64/'Data Sheet'!I$61 -> 0.15347421 | H36: ='Data Sheet'!J64/'Data Sheet'!J$61 -> 0.12935755 | I36: ='Data Sheet'!K64/'Data Sheet'!K$61 -> 0.17835319
B37: Other Assets | C37: ='Data Sheet'!E65/'Data Sheet'!E$61 -> 0.14964831 | D37: ='Data Sheet'!F65/'Data Sheet'!F$61 -> 0.11795716 | E37: ='Data Sheet'!G65/'Data Sheet'!G$61 -> 0.18661379 | F37: ='Data Sheet'!H65/'Data Sheet'!H$61 -> 0.18283102 | G37: ='Data Sheet'!I65/'Data Sheet'!I$61 -> 0.19719522 | H37: ='Data Sheet'!J65/'Data Sheet'!J$61 -> 0.21494518 | I37: ='Data Sheet'!K65/'Data Sheet'!K$61 -> 0.17887197
B38: Receivables | C38: ='Data Sheet'!E67/'Data Sheet'!E$61 -> 0.025347499 | D38: ='Data Sheet'!F67/'Data Sheet'!F$61 -> 0.019225757 | E38: ='Data Sheet'!G67/'Data Sheet'!G$61 -> 0.019638457 | F38: ='Data Sheet'!H67/'Data Sheet'!H$61 -> 0.033040903 | G38: ='Data Sheet'!I67/'Data Sheet'!I$61 -> 0.032338724 | H38: ='Data Sheet'!J67/'Data Sheet'!J$61 -> 0.036948271 | I38: ='Data Sheet'!K67/'Data Sheet'!K$61 -> 0.035944319
B39: Inventory | C39: ='Data Sheet'!E68/'Data Sheet'!E$61 -> 0.0081814336 | D39: ='Data Sheet'!F68/'Data Sheet'!F$61 -> 0.0081226726 | E39: ='Data Sheet'!G68/'Data Sheet'!G$61 -> 0.0077549369 | F39: ='Data Sheet'!H68/'Data Sheet'!H$61 -> 0.0080824213 | G39: ='Data Sheet'!I68/'Data Sheet'!I$61 -> 0.0079031209 | H39: ='Data Sheet'!J68/'Data Sheet'!J$61 -> 0.0076901768 | I39: ='Data Sheet'!K68/'Data Sheet'!K$61 -> 0.0074047808
B40: Cash & Bank | C40: ='Data Sheet'!E69/'Data Sheet'!E$61 -> 0.027581421 | D40: ='Data Sheet'!F69/'Data Sheet'!F$61 -> 0.013435467 | E40: ='Data Sheet'!G69/'Data Sheet'!G$61 -> 0.091355664 | F40: ='Data Sheet'!H69/'Data Sheet'!H$61 -> 0.077962321 | G40: ='Data Sheet'!I69/'Data Sheet'!I$61 -> 0.1008252 | H40: ='Data Sheet'!J69/'Data Sheet'!J$61 -> 0.12383983 | I40: ='Data Sheet'!K69/'Data Sheet'!K$61 -> 0.090560079

Sheet Ratio Analysis
B2: ="Ratio Analysis-"&'Data Sheet'!B1 -> Ratio Analysis-INDIAN HOTELS CO LTD
B4: Years | C4: ='Historicial Financials'!C4 -> 43921 | D4: ='Historicial Financials'!D4 -> 44286 | E4: ='Historicial Financials'!E4 -> 44651 | F4: ='Historicial Financials'!F4 -> 45016 | G4: ='Historicial Financials'!G4 -> 45382 | H4: ='Historicial Financials'!H4 -> 45747 | I4: ='Historicial Financials'!I4 -> 46112 | J4: Trend | K4: Mean | L4: Median
B6: SalesGrowth | D6: =IFERROR('Historicial Financials'!D8,0) -> -0.64707358 | E6: =IFERROR('Historicial Financials'!E8,0) -> 0.94026004 | F6: =IFERROR('Historicial Financials'!F8,0) -> 0.90101171 | G6: =IFERROR('Historicial Financials'!G8,0) -> 0.16503526 | H6: =IFERROR('Historicial Financials'!H8,0) -> 0.23132632 | I6: =IFERROR('Historicial Financials'!I8,0) -> 0.16253806 | K6: =IFERROR(AVERAGE(D6:I6),0) -> 0.29218297 | L6: =IFERROR(MEDIAN(D6:I6),0) -> 0.19818079
B7: EBITDA Growth | D7: =IFERROR('Historicial Financials'!D19/'Historicial Financials'!C19-1,0) -> -1.3739006 | E7: =IFERROR('Historicial Financials'!E19/'Historicial Financials'!D19-1,0) -> -2.1188357 | F7: =IFERROR('Historicial Financials'!F19/'Historicial Financials'!E19-1,0) -> 3.4584558 | G7: =IFERROR('Historicial Financials'!G19/'Historicial Financials'!F19-1,0) -> 0.19669615 | H7: =IFERROR('Historicial Financials'!H19/'Historicial Financials'!G19-1,0) -> 0.28238813 | I7: =IFERROR('Historicial Financials'!I19/'Historicial Financials'!H19-1,0) -> 0.15399754 | K7: =IFERROR(AVERAGE(D7:I7),0) -> 0.099800236 | L7: =IFERROR(MEDIAN(D7:I7),0) -> 0.17534684
B8: EBT Growth | D8: =IFERROR('Historicial Financials'!D28/'Historicial Financials'!C28-1,0) -> -6.285187 | E8: =IFERROR('Historicial Financials'!E28/'Historicial Financials'!D28-1,0) -> -0.63468204 | F8: =IFERROR('Historicial Financials'!F28/'Historicial Financials'!E28-1,0) -> -3.6866141 | G8: =IFERROR('Historicial Financials'!G28/'Historicial Financials'!F28-1,0) -> 0.28855048 | H8: =IFERROR('Historicial Financials'!H28/'Historicial Financials'!G28-1,0) -> 0.37562543 | I8: =IFERROR('Historicial Financials'!I28/'Historicial Financials'!H28-1,0) -> 0.15983043 | K8: =IFERROR(AVERAGE(D8:I8),0) -> -1.6304128 | L8: =IFERROR(MEDIAN(D8:I8),0) -> -0.23742581
B9: Net Profit Growth | D9: =IFERROR('Historicial Financials'!D34/'Historicial Financials'!C34-1,0) -> -6.7706711 | E9: =IFERROR('Historicial Financials'!E34/'Historicial Financials'!D34-1,0) -> -0.5994372 | F9: =IFERROR('Historicial Financials'!F34/'Historicial Financials'!E34-1,0) -> -3.055914 | G9: =IFERROR('Historicial Financials'!G34/'Historicial Financials'!F34-1,0) -> 0.25352162 | H9: =IFERROR('Historicial Financials'!H34/'Historicial Financials'!G34-1,0) -> 0.27240781 | I9: =IFERROR('Historicial Financials'!I34/'Historicial Financials'!H34-1,0) -> 0.11329636 | K9: =IFERROR(AVERAGE(D9:I9),0) -> -1.6311327 | L9: =IFERROR(MEDIAN(D9:I9),0) -> -0.24307042
B10: Dividend Growth | D10: =IFERROR('Historicial Financials'!D42/'Historicial Financials'!C42-1,0) -> -0.19996636 | E10: =IFERROR('Historicial Financials'!E42/'Historicial Financials'!D42-1,0) -> 0.11119868 | F10: =IFERROR('Historicial Financials'!F42/'Historicial Financials'!E42-1,0) -> 1.499824 | G10: =IFERROR('Historicial Financials'!G42/'Historicial Financials'!F42-1,0) -> 0.75003513 | H10: =IFERROR('Historicial Financials'!H42/'Historicial Financials'!G42-1,0) -> 0.28566841 | I10: =IFERROR('Historicial Financials'!I42/'Historicial Financials'!H42-1,0) -> 0.44445138 | K10: =IFERROR(AVERAGE(D10:I10),0) -> 0.48186854 | L10: =IFERROR(MEDIAN(D10:I10),0) -> 0.36505989
B12: Gross Margin | C12: =IFERROR('Historicial Financials'!C14,0) -> 0.33965549 | D12: =IFERROR('Historicial Financials'!D14,0) -> 0.0014157292 | E12: =IFERROR('Historicial Financials'!E14,0) -> 0.27696959 | F12: =IFERROR('Historicial Financials'!F14,0) -> 0.41304254 | G12: =IFERROR('Historicial Financials'!G14,0) -> 0.425306 | H12: =IFERROR('Historicial Financials'!H14,0) -> 0.47245799 | I12: =IFERROR('Historicial Financials'!I14,0) -> 0.47542836 | K12: =IFERROR(AVERAGE(C12:I12),0) -> 0.34346796 | L12: =IFERROR(MEDIAN(D12:I12),0) -> 0.41917427
B13: Operating Margin | C13: =IFERROR('Historicial Financials'!C20,0) -> 0.21678236 | D13: =IFERROR('Historicial Financials'!D20,0) -> -0.22966556 | E13: =IFERROR('Historicial Financials'!E20,0) -> 0.13243484 | F13: =IFERROR('Historicial Financials'!F20,0) -> 0.31060034 | G13: =IFERROR('Historicial Financials'!G20,0) -> 0.31904118 | H13: =IFERROR('Historicial Financials'!H20,0) -> 0.33227149 | I13: =IFERROR('Historicial Financials'!I20,0) -> 0.32983047 | K13: =IFERROR(AVERAGE(C13:I13),0) -> 0.20161359 | L13: =IFERROR(MEDIAN(D13:I13),0) -> 0.31482076
B14: EBITDA Margin | C14: =IFERROR('Historicial Financials'!C20,0) -> 0.21678236 | D14: =IFERROR('Historicial Financials'!D20,0) -> -0.22966556 | E14: =IFERROR('Historicial Financials'!E20,0) -> 0.13243484 | F14: =IFERROR('Historicial Financials'!F20,0) -> 0.31060034 | G14: =IFERROR('Historicial Financials'!G20,0) -> 0.31904118 | H14: =IFERROR('Historicial Financials'!H20,0) -> 0.33227149 | I14: =IFERROR('Historicial Financials'!I20,0) -> 0.32983047 | K14: =IFERROR(AVERAGE(C14:I14),0) -> 0.20161359 | L14: =IFERROR(MEDIAN(D14:I14),0) -> 0.31482076
B15: EBIT Margin | C15: =IFERROR(('Historicial Financials'!C19-'Historicial Financials'!C25)/'Historicial Financials'!C7,0) -> 0.12620935 | D15: =IFERROR(('Historicial Financials'!D19-'Historicial Financials'!D25)/'Historicial Financials'!D7,0) -> -0.48972168 | E15: =IFERROR(('Historicial Financials'!E19-'Historicial Financials'!E25)/'Historicial Financials'!E7,0) -> -0.00042536205 | F15: =IFERROR(('Historicial Financials'!F19-'Historicial Financials'!F25)/'Historicial Financials'!F7,0) -> 0.23898821 | G15: =IFERROR(('Historicial Financials'!G19-'Historicial Financials'!G25)/'Historicial Financials'!G7,0) -> 0.25192392 | H15: =IFERROR(('Historicial Financials'!H19-'Historicial Financials'!H25)/'Historicial Financials'!H7,0) -> 0.27010129 | I15: =IFERROR(('Historicial Financials'!I19-'Historicial Financials'!I25)/'Historicial Financials'!I7,0) -> 0.26737343 | K15: =IFERROR(AVERAGE(C15:I15),0) -> 0.094921308 | L15: =IFERROR(MEDIAN(D15:I15),0) -> 0.24545606
B16: EBT Margin | C16: =IFERROR('Historicial Financials'!C29,0) -> 0.049778855 | D16: =IFERROR('Historicial Financials'!D29,0) -> -0.74545443 | E16: =IFERROR('Historicial Financials'!E29,0) -> -0.14035639 | F16: =IFERROR('Historicial Financials'!F29,0) -> 0.19835935 | G16: =IFERROR('Historicial Financials'!G29,0) -> 0.2193891 | H16: =IFERROR('Historicial Financials'!H29,0) -> 0.24509931 | I16: =IFERROR('Historicial Financials'!I29,0) -> 0.24452846 | K16: =IFERROR(AVERAGE(C16:I16),0) -> 0.010192037 | L16: =IFERROR(MEDIAN(D16:I16),0) -> 0.20887423
B17: Net Profit Margin | C17: =IFERROR('Historicial Financials'!C35,0) -> 0.040565611 | D17: =IFERROR('Historicial Financials'!D35,0) -> -0.663285 | E17: =IFERROR('Historicial Financials'!E35,0) -> -0.13693386 | F17: =IFERROR('Historicial Financials'!F35,0) -> 0.14809179 | G17: =IFERROR('Historicial Financials'!G35,0) -> 0.15933961 | H17: =IFERROR('Historicial Financials'!H35,0) -> 0.16465576 | I17: =IFERROR('Historicial Financials'!I35,0) -> 0.15768142 | K17: =IFERROR(AVERAGE(C17:I17),0) -> -0.018554951 | L17: =IFERROR(MEDIAN(D17:I17),0) -> 0.15288661
B19: SalesExpenses%Sales | C19: =IFERROR('Historicial Financials'!C17,0) -> 0.12287313 | D19: =IFERROR('Historicial Financials'!D17,0) -> 0.23108129 | E19: =IFERROR('Historicial Financials'!E17,0) -> 0.14453475 | F19: =IFERROR('Historicial Financials'!F17,0) -> 0.10244221 | G19: =IFERROR('Historicial Financials'!G17,0) -> 0.10626482 | H19: =IFERROR('Historicial Financials'!H17,0) -> 0.1401865 | I19: =IFERROR('Historicial Financials'!I17,0) -> 0.14559789 | K19: =IFERROR(AVERAGE(C19:I19),0) -> 0.14185437 | L19: =IFERROR(MEDIAN(D19:I19),0) -> 0.14236063
B20: Depreciation%Sales | C20: =IFERROR('Historicial Financials'!C26,0) -> 0.090573005 | D20: =IFERROR('Historicial Financials'!D26,0) -> 0.26005612 | E20: =IFERROR('Historicial Financials'!E26,0) -> 0.1328602 | F20: =IFERROR('Historicial Financials'!F26,0) -> 0.071612125 | G20: =IFERROR('Historicial Financials'!G26,0) -> 0.067117267 | H20: =IFERROR('Historicial Financials'!H26,0) -> 0.062170198 | I20: =IFERROR('Historicial Financials'!I26,0) -> 0.06245704 | K20: =IFERROR(AVERAGE(C20:I20),0) -> 0.10669228 | L20: =IFERROR(MEDIAN(D20:I20),0) -> 0.069364696
B21: OperatingIncome%Sales | C21: =IFERROR(C15,0) -> 0.12620935 | D21: =IFERROR(D15,0) -> -0.48972168 | E21: =IFERROR(E15,0) -> -0.00042536205 | F21: =IFERROR(F15,0) -> 0.23898821 | G21: =IFERROR(G15,0) -> 0.25192392 | H21: =IFERROR(H15,0) -> 0.27010129 | I21: =IFERROR(I15,0) -> 0.26737343 | K21: =IFERROR(AVERAGE(C21:I21),0) -> 0.094921308 | L21: =IFERROR(MEDIAN(D21:I21),0) -> 0.24545606
B23: Return on Capital Employed | C23: =IFERROR(('Historicial Financials'!C19-'Historicial Financials'!C25)/SUM('Historicial Financials'!C48:C50),0) -> 0.063594048 | D23: =IFERROR(('Historicial Financials'!D19-'Historicial Financials'!D25)/SUM('Historicial Financials'!D48:D50),0) -> -0.084150688 | E23: =IFERROR(('Historicial Financials'!E19-'Historicial Financials'!E25)/SUM('Historicial Financials'!E48:E50),0) -> -0.00011872016 | F23: =IFERROR(('Historicial Financials'!F19-'Historicial Financials'!F25)/SUM('Historicial Financials'!F48:F50),0) -> 0.12485422 | G23: =IFERROR(('Historicial Financials'!G19-'Historicial Financials'!G25)/SUM('Historicial Financials'!G48:G50),0) -> 0.13985293 | H23: =IFERROR(('Historicial Financials'!H19-'Historicial Financials'!H25)/SUM('Historicial Financials'!H48:H50),0) -> 0.15803251 | I23: =IFERROR(('Historicial Financials'!I19-'Historicial Financials'!I25)/SUM('Historicial Financials'!I48:I50),0) -> 0.16304777 | K23: =IFERROR(AVERAGE(C23:I23),0) -> 0.080730296 | L23: =IFERROR(MEDIAN(D23:I23),0) -> 0.13235357
B24: Retained Earnings% | C24: =IFERROR('Historicial Financials'!C45,0) -> 0.83223294 | D24: =IFERROR('Historicial Financials'!D45,0) -> 0 | E24: =IFERROR('Historicial Financials'!E45,0) -> 0 | F24: =IFERROR('Historicial Financials'!F45,0) -> 0.85832693 | G24: =IFERROR('Historicial Financials'!G45,0) -> 0.80215556 | H24: =IFERROR('Historicial Financials'!H45,0) -> 0.83211277 | I24: =IFERROR('Historicial Financials'!I45,0) -> 0.7780635 | K24: =IFERROR(AVERAGE(C24:I24),0) -> 0.58612739 | L24: =IFERROR(MEDIAN(D24:I24),0) -> 0.79010953
B25: Return on Equity% | C25: =IFERROR('Historicial Financials'!C34/SUM('Historicial Financials'!C48:C49),0) -> 0.041555634 | D25: =IFERROR('Historicial Financials'!D34/SUM('Historicial Financials'!D48:D49),0) -> -0.28636349 | E25: =IFERROR('Historicial Financials'!E34/SUM('Historicial Financials'!E48:E49),0) -> -0.059258735 | F25: =IFERROR('Historicial Financials'!F34/SUM('Historicial Financials'!F48:F49),0) -> 0.10779307 | G25: =IFERROR('Historicial Financials'!G34/SUM('Historicial Financials'!G48:G49),0) -> 0.1140499 | H25: =IFERROR('Historicial Financials'!H34/SUM('Historicial Financials'!H48:H49),0) -> 0.12296082 | I25: =IFERROR('Historicial Financials'!I34/SUM('Historicial Financials'!I48:I49),0) -> 0.11705302 | K25: =IFERROR(AVERAGE(C25:I25),0) -> 0.022541461 | L25: =IFERROR(MEDIAN(D25:I25),0) -> 0.11092149
B26: Self Sustained Growth Rate | C26: =IFERROR(C24*C25,0) -> 0.034583967 | D26: =IFERROR(D24*D25,0) -> 0 | E26: =IFERROR(E24*E25,0) -> 0 | F26: =IFERROR(F24*F25,0) -> 0.092521698 | G26: =IFERROR(G24*G25,0) -> 0.091485762 | H26: =IFERROR(H24*H25,0) -> 0.10231726 | I26: =IFERROR(I24*I25,0) -> 0.091074685 | K26: =IFERROR(AVERAGE(C26:I26),0) -> 0.058854768 | L26: =IFERROR(MEDIAN(D26:I26),0) -> 0.091280224
B27: Interest Coverage Ratio | C27: =IFERROR(('Historicial Financials'!C19-'Historicial Financials'!C25)/'Historicial Financials'!C22,0) -> 1.6512957 | D27: =IFERROR(('Historicial Financials'!D19-'Historicial Financials'!D25)/'Historicial Financials'!D22,0) -> -1.9149744 | E27: =IFERROR(('Historicial Financials'!E19-'Historicial Financials'!E25)/'Historicial Financials'!E22,0) -> -0.003039798 | F27: =IFERROR(('Historicial Financials'!F19-'Historicial Financials'!F25)/'Historicial Financials'!F22,0) -> 5.8822283 | G27: =IFERROR(('Historicial Financials'!G19-'Historicial Financials'!G25)/'Historicial Financials'!G22,0) -> 7.7432113 | H27: =IFERROR(('Historicial Financials'!H19-'Historicial Financials'!H25)/'Historicial Financials'!H22,0) -> 10.803196 | I27: =IFERROR(('Historicial Financials'!I19-'Historicial Financials'!I25)/'Historicial Financials'!I22,0) -> 11.703817 | K27: =IFERROR(AVERAGE(C27:I27),0) -> 5.1236764 | L27: =IFERROR(MEDIAN(D27:I27),0) -> 6.8127198
B29: Debtor Turnover Ratio | C29: =IFERROR('Historicial Financials'!C7/'Historicial Financials'!C60,0) -> 15.389077 | D29: =IFERROR('Historicial Financials'!D7/'Historicial Financials'!D60,0) -> 7.1650291 | E29: =IFERROR('Historicial Financials'!E7/'Historicial Financials'!E60,0) -> 11.969218 | F29: =IFERROR('Historicial Financials'!F7/'Historicial Financials'!F60,0) -> 13.013574 | G29: =IFERROR('Historicial Financials'!G7/'Historicial Financials'!G60,0) -> 14.206334 | H29: =IFERROR('Historicial Financials'!H7/'Historicial Financials'!H60,0) -> 12.805033 | I29: =IFERROR('Historicial Financials'!I7/'Historicial Financials'!I60,0) -> 13.330976 | K29: =IFERROR(AVERAGE(C29:I29),0) -> 12.554177 | L29: =IFERROR(MEDIAN(D29:I29),0) -> 12.909303
B30: Creditor Turnover Ratio | C30: =IFERROR('Historicial Financials'!C7/'Historicial Financials'!C51,0) -> 1.7271077 | D30: =IFERROR('Historicial Financials'!D7/'Historicial Financials'!D51,0) -> 0.69454868 | E30: =IFERROR('Historicial Financials'!E7/'Historicial Financials'!E51,0) -> 1.489444 | F30: =IFERROR('Historicial Financials'!F7/'Historicial Financials'!F51,0) -> 2.4298369 | G30: =IFERROR('Historicial Financials'!G7/'Historicial Financials'!G51,0) -> 2.6642958 | H30: =IFERROR('Historicial Financials'!H7/'Historicial Financials'!H51,0) -> 2.4724236 | I30: =IFERROR('Historicial Financials'!I7/'Historicial Financials'!I51,0) -> 2.236724 | K30: =IFERROR(AVERAGE(C30:I30),0) -> 1.9591972 | L30: =IFERROR(MEDIAN(D30:I30),0) -> 2.3332804
B31: Working Capital | C31: ='Historicial Financials'!C63/'Historicial Financials'!C51 -> 0.2705743 | D31: ='Historicial Financials'!D63/'Historicial Financials'!D51 -> 0.20563167 | E31: ='Historicial Financials'!E63/'Historicial Financials'!E51 -> 0.75245624 | F31: ='Historicial Financials'!F63/'Historicial Financials'!F51 -> 0.67295813 | G31: ='Historicial Financials'!G63/'Historicial Financials'!G51 -> 0.81809379 | H31: ='Historicial Financials'!H63/'Historicial Financials'!H51 -> 0.88042421 | I31: ='Historicial Financials'!I63/'Historicial Financials'!I51 -> 0.62507272 | K31: =AVERAGE(C31:I31) -> 0.60360158 | L31: =IFERROR(MEDIAN(D31:I31),0) -> 0.71270718
B32: Inventory Turnover Ratio | C32: =IFERROR('Historicial Financials'!C10/'Historicial Financials'!C61,0) -> 31.483923 | D32: =IFERROR('Historicial Financials'!D10/AVERAGE('Historicial Financials'!D61,'Historicial Financials'!C61),0) -> 16.868787 | E32: =IFERROR('Historicial Financials'!E10/AVERAGE('Historicial Financials'!E61,'Historicial Financials'!D61),0) -> 22.81493 | F32: =IFERROR('Historicial Financials'!F10/AVERAGE('Historicial Financials'!F61,'Historicial Financials'!E61),0) -> 32.471624 | G32: =IFERROR('Historicial Financials'!G10/AVERAGE('Historicial Financials'!G61,'Historicial Financials'!F61),0) -> 34.47782 | H32: =IFERROR('Historicial Financials'!H10/AVERAGE('Historicial Financials'!H61,'Historicial Financials'!G61),0) -> 34.907864 | I32: =IFERROR('Historicial Financials'!I10/AVERAGE('Historicial Financials'!I61,'Historicial Financials'!H61),0) -> 35.642987 | K32: =IFERROR(AVERAGE(C32:I32),0) -> 29.809705 | L32: =IFERROR(MEDIAN(D32:I32),0) -> 33.474722
B33: Fixed Assets Turnover Ratio | C33: =IFERROR('Historicial Financials'!C7/'Historicial Financials'!C54,0) -> 0.55381847 | D33: =IFERROR('Historicial Financials'!D7/'Historicial Financials'!D54,0) -> 0.1866812 | E33: =IFERROR('Historicial Financials'!E7/'Historicial Financials'!E54,0) -> 0.36317249 | F33: =IFERROR('Historicial Financials'!F7/'Historicial Financials'!F54,0) -> 0.65882976 | G33: =IFERROR('Historicial Financials'!G7/'Historicial Financials'!G54,0) -> 0.72693619 | H33: =IFERROR('Historicial Financials'!H7/'Historicial Financials'!H54,0) -> 0.76336349 | I33: =IFERROR('Historicial Financials'!I7/'Historicial Financials'!I54,0) -> 0.79354401 | K33: =IFERROR(AVERAGE(C33:I33),0) -> 0.57804937 | L33: =IFERROR(MEDIAN(D33:I33),0) -> 0.69288297
B34: Capital Turnover Ratio | C34: =IFERROR('Historicial Financials'!C7/SUM('Historicial Financials'!C48:C49),0) -> 1.0244055 | D34: =IFERROR('Historicial Financials'!D7/SUM('Historicial Financials'!D48:D49),0) -> 0.43173521 | E34: =IFERROR('Historicial Financials'!E7/SUM('Historicial Financials'!E48:E49),0) -> 0.43275443 | F34: =IFERROR('Historicial Financials'!F7/SUM('Historicial Financials'!F48:F49),0) -> 0.72788012 | G34: =IFERROR('Historicial Financials'!G7/SUM('Historicial Financials'!G48:G49),0) -> 0.71576615 | H34: =IFERROR('Historicial Financials'!H7/SUM('Historicial Financials'!H48:H49),0) -> 0.74677507 | I34: =IFERROR('Historicial Financials'!I7/SUM('Historicial Financials'!I48:I49),0) -> 0.7423387 | K34: =IFERROR(AVERAGE(C34:I34),0) -> 0.68880788 | L34: =IFERROR(MEDIAN(D34:I34),0) -> 0.72182314
B36: Debtor Days | C36: =IFERROR(365/C29,0) -> 23.718122 | D36: =IFERROR(365/D29,0) -> 50.941873 | E36: =IFERROR(365/E29,0) -> 30.494892 | F36: =IFERROR(365/F29,0) -> 28.047638 | G36: =IFERROR(365/G29,0) -> 25.692765 | H36: =IFERROR(365/H29,0) -> 28.504417 | I36: =IFERROR(365/I29,0) -> 27.379841 | K36: =IFERROR(AVERAGE(C36:I36),0) -> 30.682792 | L36: =IFERROR(MEDIAN(D36:I36),0) -> 28.276027
B37: Payable Days | C37: =IFERROR(365/C30,0) -> 211.33598 | D37: =IFERROR(365/D30,0) -> 525.52112 | E37: =IFERROR(365/E30,0) -> 245.05788 | F37: =IFERROR(365/F30,0) -> 150.21585 | G37: =IFERROR(365/G30,0) -> 136.9968 | H37: =IFERROR(365/H30,0) -> 147.62842 | I37: =IFERROR(365/I30,0) -> 163.18509 | K37: =IFERROR(AVERAGE(C37:I37),0) -> 225.70588 | L37: =IFERROR(MEDIAN(D37:I37),0) -> 156.70047
B38: Inventory Days | C38: =IFERROR(365/C32,0) -> 11.593219 | D38: =IFERROR(365/D32,0) -> 21.637597 | E38: =IFERROR(365/E32,0) -> 15.998296 | F38: =IFERROR(365/F32,0) -> 11.240583 | G38: =IFERROR(365/G32,0) -> 10.586516 | H38: =IFERROR(365/H32,0) -> 10.456097 | I38: =IFERROR(365/I32,0) -> 10.240444 | K38: =IFERROR(AVERAGE(C38:I38),0) -> 13.107536 | L38: =IFERROR(MEDIAN(D38:I38),0) -> 10.91355
B39: Cash Conversion Cycle | C39: =IFERROR(SUM(C36,C38)-C37,0) -> -176.02464 | D39: =IFERROR(SUM(D36,D38)-D37,0) -> -452.94165 | E39: =IFERROR(SUM(E36,E38)-E37,0) -> -198.56469 | F39: =IFERROR(SUM(F36,F38)-F37,0) -> -110.92763 | G39: =IFERROR(SUM(G36,G38)-G37,0) -> -100.71752 | H39: =IFERROR(SUM(H36,H38)-H37,0) -> -108.66791 | I39: =IFERROR(SUM(I36,I38)-I37,0) -> -125.5648 | K39: =IFERROR(AVERAGE(C39:I39),0) -> -181.91555 | L39: =IFERROR(MEDIAN(D39:I39),0) -> -118.24621
B41: CFO/Sales | C41: =IFERROR('Historicial Financials'!C75/'Historicial Financials'!C7,0) -> 0.1897767 | D41: =IFERROR('Historicial Financials'!D75/'Historicial Financials'!D7,0) -> -0.25076818 | E41: =IFERROR('Historicial Financials'!E75/'Historicial Financials'!E7,0) -> 0.25914365 | F41: =IFERROR('Historicial Financials'!F75/'Historicial Financials'!F7,0) -> 0.28279268 | G41: =IFERROR('Historicial Financials'!G75/'Historicial Financials'!G7,0) -> 0.29119114 | H41: =IFERROR('Historicial Financials'!H75/'Historicial Financials'!H7,0) -> 0.25700279 | I41: =IFERROR('Historicial Financials'!I75/'Historicial Financials'!I7,0) -> 0.24842041 | K41: =IFERROR(AVERAGE(C41:I41),0) -> 0.18250845 | L41: =IFERROR(MEDIAN(D41:I41),0) -> 0.25807322
B42: CFO/Total Asset | C42: =IFERROR('Historicial Financials'!C75/'Historicial Financials'!C64,0) -> 0.074027073 | D42: =IFERROR('Historicial Financials'!D75/'Historicial Financials'!D64,0) -> -0.034544097 | E42: =IFERROR('Historicial Financials'!E75/'Historicial Financials'!E64,0) -> 0.060913518 | F42: =IFERROR('Historicial Financials'!F75/'Historicial Financials'!F64,0) -> 0.12159526 | G42: =IFERROR('Historicial Financials'!G75/'Historicial Financials'!G64,0) -> 0.13377749 | H42: =IFERROR('Historicial Financials'!H75/'Historicial Financials'!H64,0) -> 0.12159414 | I42: =IFERROR('Historicial Financials'!I75/'Historicial Financials'!I64,0) -> 0.11903632 | K42: =IFERROR(AVERAGE(C42:I42),0) -> 0.085199958 | L42: =IFERROR(MEDIAN(D42:I42),0) -> 0.12031523
B43: CFO/Total Debt | C43: =IFERROR('Historicial Financials'!C75/'Historicial Financials'!C50,0) -> 0.1881896 | D43: =IFERROR('Historicial Financials'!D75/'Historicial Financials'!D50,0) -> -0.071579626 | E43: =IFERROR('Historicial Financials'!E75/'Historicial Financials'!E50,0) -> 0.20371052 | F43: =IFERROR('Historicial Financials'!F75/'Historicial Financials'!F50,0) -> 0.52341343 | G43: =IFERROR('Historicial Financials'!G75/'Historicial Financials'!G50,0) -> 0.72033418 | H43: =IFERROR('Historicial Financials'!H75/'Historicial Financials'!H50,0) -> 0.69449173 | I43: =IFERROR('Historicial Financials'!I75/'Historicial Financials'!I50,0) -> 0.84856604 | K43: =IFERROR(AVERAGE(C43:I43),0) -> 0.44387512 | L43: =IFERROR(MEDIAN(D43:I43),0) -> 0.60895258

Sheet Forecasting
B1: Assumption For DCF
B3: Particulars | C3: ='Data Sheet'!G16 -> 44651 | D3: ='Data Sheet'!H16 -> 45016 | E3: ='Data Sheet'!I16 -> 45382 | F3: ='Data Sheet'!J16 -> 45747 | G3: ='Data Sheet'!K16 -> 46112 | H3: =G3+365 -> 46477 | I3: =H3+365 -> 46842 | J3: =I3+365 -> 47207 | K3: =J3+365 -> 47572 | L3: =K3+365 -> 47937
B4: Sales | C4: ='Data Sheet'!G17 -> 3056.22 | D4: ='Data Sheet'!H17 -> 5809.91 | E4: ='Data Sheet'!I17 -> 6768.75 | F4: ='Data Sheet'!J17 -> 8334.54 | G4: ='Data Sheet'!K17 -> 9689.22 | H4: =G4*1.1 -> 10658.142 | I4: =H4*1.1 -> 11723.956 | J4: =I4*1.1 -> 12896.352 | K4: =J4*1.1 -> 14185.987 | L4: =K4*1.1 -> 15604.586
B5: Sales Growth | C5: ='Historicial Financials'!E8 -> 0.94026004 | D5: ='Historicial Financials'!F8 -> 0.90101171 | E5: ='Historicial Financials'!G8 -> 0.16503526 | F5: ='Historicial Financials'!H8 -> 0.23132632 | G5: ='Historicial Financials'!I8 -> 0.16253806 | H5: =H4/G4-1 -> 0.1 | I5: =I4/H4-1 -> 0.1 | J5: =J4/I4-1 -> 0.1 | K5: =K4/J4-1 -> 0.1 | L5: =L4/K4-1 -> 0.1
B6: EBITDA | C6: ='Historicial Financials'!E19 -> 404.75 | D6: ='Historicial Financials'!F19 -> 1804.56 | E6: ='Historicial Financials'!G19 -> 2159.51 | F6: ='Historicial Financials'!H19 -> 2769.33 | G6: ='Historicial Financials'!I19 -> 3195.8 | H6: =H4*0.35 -> 3730.3497 | I6: =I4*0.35 -> 4103.3847 | J6: =J4*0.35 -> 4513.7231 | K6: =K4*0.35 -> 4965.0955 | L6: =L4*0.35 -> 5461.605
B7: EBITDA Margin | C7: ='Historicial Financials'!E20 -> 0.13243484 | D7: ='Historicial Financials'!F20 -> 0.31060034 | E7: ='Historicial Financials'!G20 -> 0.31904118 | F7: ='Historicial Financials'!H20 -> 0.33227149 | G7: ='Historicial Financials'!I20 -> 0.32983047 | H7: =H6/H4 -> 0.35 | I7: =I6/I4 -> 0.35 | J7: =J6/J4 -> 0.35 | K7: =K6/K4 -> 0.35 | L7: =L6/L4 -> 0.35
B8: D&A | C8: ='Historicial Financials'!E25 -> 406.05 | D8: ='Historicial Financials'!F25 -> 416.06 | E8: ='Historicial Financials'!G25 -> 454.3 | F8: ='Historicial Financials'!H25 -> 518.16 | G8: ='Historicial Financials'!I25 -> 605.16 | H8: =H4*$G$9 -> 665.676 | I8: =I4*$G$9 -> 732.2436 | J8: =J4*$G$9 -> 805.46796 | K8: =K4*$G$9 -> 886.01476 | L8: =L4*$G$9 -> 974.61623
B9: D&A % Sales | C9: ='Historicial Financials'!E26 -> 0.1328602 | D9: ='Historicial Financials'!F26 -> 0.071612125 | E9: ='Historicial Financials'!G26 -> 0.067117267 | F9: ='Historicial Financials'!H26 -> 0.062170198 | G9: ='Historicial Financials'!I26 -> 0.06245704 | H9: =H8/H4 -> 0.06245704 | I9: =I8/I4 -> 0.06245704 | J9: =J8/J4 -> 0.06245704 | K9: =K8/K4 -> 0.06245704 | L9: =L8/L4 -> 0.06245704
B10: EBIT | C10: =C6-C8 -> -1.3 | D10: =D6-D8 -> 1388.5 | E10: =E6-E8 -> 1705.21 | F10: =F6-F8 -> 2251.17 | G10: =G6-G8 -> 2590.64 | H10: =H6-H8 -> 3064.6737 | I10: =I6-I8 -> 3371.1411 | J10: =J6-J8 -> 3708.2552 | ... L10: =L6-L8 -> 4486.9888
B11: Tax Rate | C11: 0.25 | D11: 0.25 | E11: 0.25 | F11: 0.25 | G11: 0.25 | H11: 0.25 | I11: 0.25 | J11: 0.25 | K11: 0.25 | L11: 0.25
B12: NOPAT | C12: =C10*(1-C11) -> -0.975 | D12: =D10*(1-D11) -> 1041.375 | E12: =E10*(1-E11) -> 1278.9075 | F12: =F10*(1-F11) -> 1688.3775 | G12: =G10*(1-G11) -> 1942.98 | H12: =H10*(1-H11) -> 2298.5053 | I12: =I10*(1-I11) -> 2528.3558 | J12: =J10*(1-J11) -> 2781.1914 | ... L12: =L10*(1-L11) -> 3365.2416
B13: Capex | C13: =IFERROR(('Historicial Financials'!E78*-1)-'Historicial Financials'!E79,0) -> 285 | D13: =IFERROR(('Historicial Financials'!F78*-1)-'Historicial Financials'!F79,0) -> 428 | E13: =IFERROR(('Historicial Financials'!G78*-1)-'Historicial Financials'!G79,0) -> 633 | F13: =IFERROR(('Historicial Financials'!H78*-1)-'Historicial Financials'!H79,0) -> 1062 | G13: =IFERROR(('Historicial Financials'!I78*-1)-'Historicial Financials'!I79,0) -> 1028 | H13: =H4*0.1 -> 1065.8142 | I13: =I4*0.1 -> 1172.3956 | J13: =J4*0.1 -> 1289.6352 | K13: =K4*0.1 -> 1418.5987 | L13: =L4*0.1 -> 1560.4586
B14: Capex % of sales | C14: =C13/C4 -> 0.093252449 | D14: =D13/D4 -> 0.073667234 | E14: =E13/E4 -> 0.093518006 | F14: =F13/F4 -> 0.12742155 | G14: =G13/G4 -> 0.10609729 | H14: =H13/H4 -> 0.1 | I14: =I13/I4 -> 0.1 | J14: =J13/J4 -> 0.1 | ... L14: =L13/L4 -> 0.1
B15: Net Working Capital | C15: =C30 -> -76 | D15: =D30 -> -2 | E15: =E30 -> -6 | F15: =F30 -> 86 | G15: =G30 -> 58 | H15: =H4*$C$31 -> -20.875987 | I15: =I4*$C$31 -> -22.963586 | J15: =J4*$C$31 -> -25.259945 | K15: =K4*$C$31 -> -27.785939 | L15: =L4*$C$31 -> -30.564533
B16: NWC % of sales | C16: =C15/C4 -> -0.02486732 | D16: =D15/D4 -> -0.00034423941 | E16: =E15/E4 -> -0.00088642659 | F16: =F15/F4 -> 0.010318506 | G16: =G15/G4 -> 0.005986034 | H16: =H15/H4 -> -0.0019586892 | I16: =I15/I4 -> -0.0019586892 | J16: =J15/J4 -> -0.0019586892 | ... L16: =L15/L4 -> -0.0019586892
B17: FCFF | C17: =(C12+C8)-(C13+C15) -> 196.075 | D17: =(D12+D8)-(D13+D15) -> 1031.435 | E17: =(E12+E8)-(E13+E15) -> 1106.2075 | F17: =(F12+F8)-(F13+F15) -> 1058.5375 | G17: =(G12+G8)-(G13+G15) -> 1462.14 | H17: =(H12+H8)-(H13+H15) -> 1919.2431 | I17: =(I12+I8)-(I13+I15) -> 2111.1674 | J17: =(J12+J8)-(J13+J15) -> 2322.2841 | ... L17: =(L12+L8)-(L13+L15) -> 2809.9638
B19: Notes
B20: Sales Growth | C20: 0.1 | D20: (From Mgnt Discussion , Firm's Revenue target)
B21: EBITDA Margin | C21: 0.35 | D21: (From Mgnt Discussion , To maintain Margin of 35%)
B22: D&A | C22: 0.0625 | D22: (Assume to be constant)
B23: Tax Rate | C23: 0.25 | D23: (Assume as per the Indian Corporate Tax)
B24: Average Capex%of Sales | C24: =AVERAGE(C14:G14) -> 0.098791306 | D24: (Taken as approx 10%)
B25: Trade receivables | C25: ='Data for IG'!E36 -> 255 | D25: ='Data for IG'!F36 -> 446 | E25: ='Data for IG'!G36 -> 476 | F25: ='Data for IG'!H36 -> 651 | G25: ='Data for IG'!I36 -> 727
B26: Inventories | C26: ='Data for IG'!E35 -> 101 | D26: ='Data for IG'!F35 -> 109 | E26: ='Data for IG'!G35 -> 116 | F26: ='Data for IG'!H35 -> 135 | G26: ='Data for IG'!I35 -> 150
B27: Loans & advances | C27: ='Data for IG'!E38 -> 138 | D27: ='Data for IG'!F38 -> 144 | E27: ='Data for IG'!G38 -> 173 | F27: ='Data for IG'!H38 -> 176 | G27: ='Data for IG'!I38 -> 218
B28: Trade payables | C28: ='Data for IG'!E13 -> 387 | D28: ='Data for IG'!F13 -> 477 | E28: ='Data for IG'!G13 -> 519 | F28: ='Data for IG'!H13 -> 578 | G28: ='Data for IG'!I13 -> 720
B29: Advances from customers | C29: ='Data for IG'!E14 -> 183 | D29: ='Data for IG'!F14 -> 224 | E29: ='Data for IG'!G14 -> 252 | F29: ='Data for IG'!H14 -> 298 | G29: ='Data for IG'!I14 -> 317
B30: Net Working Capital | C30: =(SUM(C25:C27))-(SUM(C28:C29)) -> -76 | D30: =(SUM(D25:D27))-(SUM(D28:D29)) -> -2 | E30: =(SUM(E25:E27))-(SUM(E28:E29)) -> -6 | F30: =(SUM(F25:F27))-(SUM(F28:F29)) -> 86 | G30: =(SUM(G25:G27))-(SUM(G28:G29)) -> 58
B31: Average NWC % Sales | C31: =AVERAGE(C16:G16) -> -0.0019586892

Sheet Beta & WACC Inputs
B2: ="Beta Calculation-"&'Data Sheet'!B1 -> Beta Calculation-INDIAN HOTELS CO LTD
B4: IHCL Weekly Return | F4: Nifty Weekly Return | S4: Rm Calulation | Y4: ITC Hotels Weekly Return | AF4: Leea Hotels Weekly Return | AM4: EIHO Hotels Weekly Return | AT4: EIHO Hotels Weekly Return
B6: Date | C6: Price | D6: Weekly Return | F6: Date | G6: Price | H6: Weekly Return | J6: Beta Drifting | S6: Year | T6: Annual | Y6: Date | Z6: Price | AA6: Weekly Return | AC6: Beta Drifting | AF6: Date | AG6: Price | AH6: Weekly Return | AJ6: Beta Drifting | AM6: Date | AN6: Price | AO6: Weekly Return | AQ6: Beta Drifting | AT6: Date | AU6: Price | AV6: Weekly Return | AX6: Beta Drifting
B7: 46292 | C7: 718 | D7: =C7/C8-1 -> -0.01210787 | F7: Sep 27,2026 | G7: 22421.95 | H7: =G7/G8-1 -> -0.031051619 | M7: Beta 1 | N7: =SLOPE(D7:D188,H7:H188) -> 1.3202787 | S7: 2000 | T7: -0.1465 | V7: Average Return | W7: =AVERAGE(T7:T32) -> 0.15149231 | Y7: 46292 | Z7: 158.51 | AA7: =Z7/Z8-1 -> -0.020938851 | AF7: 46292 | AG7: 568.95 | AH7: =AG7/AG8-1 -> 0.041746773 | AM7: 46292 | AN7: 297.85 | AO7: =AN7/AN8-1 -> 0.010688836 | AT7: 46292 | AU7: 830.25 | AV7: =AU7/AU8-1 -> -0.057979236
B8: 46285 | C8: 726.8 | D8: =C8/C9-1 -> -0.0081200955 | F8: 46285 | G8: 23140.5 | H8: =G8/G9-1 -> -0.0088193469 | J8: Levered Raw Beta | K8: =N10 -> 1.3202787 | M8: Beta 2 | N8: =_xlfn.COVARIANCE.S(D7:D188,H7:H188)/_xlfn.VAR.S(H7:H188) -> 1.3202787 | S8: 2001 | T8: -0.1618 | V8: Dividend Yield | W8: 1.30 1 | Y8: 46285 | Z8: 161.9 | AA8: =Z8/Z9-1 -> 0.019521411 | AC8: Levered Raw Beta | AD8: =SLOPE(AA7:AA92,H7:H92) -> 0.21838624 | AF8: 46285 | AG8: 546.15 | AH8: =AG8/AG9-1 -> 0.010359819 | AJ8: Levered Raw Beta | AK8: =SLOPE(AH7:AH75,H7:H75) -> 0.27759895 | AM8: 46285 | AN8: 294.7 | AO8: =AN8/AN9-1 -> -0.072978924 | AQ8: Levered Raw Beta | AR8: =SLOPE(AO7:AO213,H7:H213) -> 0.12666542 | AT8: 46285 | AU8: 881.35 | AV8: =AU8/AU9-1 -> 0.01813666 | AX8: Levered Raw Beta | AY8: =SLOPE(AV7:AV213,H7:H213) -> 0.56239527
B9: 46278 | C9: 732.75 | D9: =C9/C10-1 -> 0.019832985 | F9: 46278 | G9: 23346.4 | H9: =G9/G10-1 -> -0.0022095811 | J9: Raw Beta Weight | K9: 0.75 | S9: 2002 | T9: 0.0325 | V9: Total Market Return | W9: =SUM(W7:W8) -> 0.15149231 | Y9: 46278 | Z9: 158.8 | AA9: =Z9/Z10-1 -> 0.033248747 | AC9: Raw Beta Weight | AD9: 0.75 | AF9: 46278 | AG9: 540.55 | AH9: =AG9/AG10-1 -> -0.0032269961 | AJ9: Raw Beta Weight | AK9: 0.75 | AM9: 46278 | AN9: 317.9 | AO9: =AN9/AN10-1 -> 0.10979228 | AQ9: Raw Beta Weight | AR9: 0.75 | AT9: 46278 | AU9: 865.65 | AV9: =AU9/AU10-1 -> -0.01322314 | AX9: Raw Beta Weight | AY9: 0.75
B10: 46271 | C10: 718.5 | D10: =C10/C11-1 -> -0.0020833333 | F10: 46271 | G10: 23398.1 | H10: =G10/G11-1 -> -0.020905778 | J10: Market Beta | K10: 1 | M10: Beta 3 | N10: =K34 -> 1.3202787 | S10: 2003 | T10: 0.719 | Y10: 46271 | Z10: 153.69 | AA10: =Z10/Z11-1 -> -0.04676549 | AC10: Market Beta | AD10: 1 | AF10: 46271 | AG10: 542.3 | AH10: =AG10/AG11-1 -> -0.021207472 | AJ10: Market Beta | AK10: 1 | AM10: 46271 | AN10: 286.45 | AO10: =AN10/AN11-1 -> -0.018670778 | AQ10: Market Beta | AR10: 1 | AT10: 46271 | AU10: 877.25 | AV10: =AU10/AU11-1 -> -0.021745191 | AX10: Market Beta | AY10: 1
B11: 46264 | C11: 720 | D11: =C11/C12-1 -> 0.019252548 | F11: 46264 | G11: 23897.7 | H11: =G11/G12-1 -> -0.011497106 | J11: Market Beta Weight | K11: =1-K9 -> 0.25 | S11: 2004 | T11: 0.1068 | Y11: 46264 | Z11: 161.23 | AA11: =Z11/Z12-1 -> -0.0092177226 | AC11: Market Beta Weight | AD11: =1-AD9 -> 0.25 | AF11: 46264 | AG11: 554.05 | AH11: =AG11/AG12-1 -> -0.0021611887 | AJ11: Market Beta Weight | AK11: =1-AK9 -> 0.25 | AM11: 46264 | AN11: 291.9 | AO11: =AN11/AN12-1 -> -0.019811954 | AQ11: Market Beta Weight | AR11: =1-AR9 -> 0.25 | AT11: 46264 | AU11: 896.75 | AV11: =AU11/AU12-1 -> -0.0049378606 | AX11: Market Beta Weight | AY11: =1-AY9 -> 0.25
B12: 46257 | C12: 706.4 | D12: =C12/C13-1 -> -0.032328767 | F12: 46257 | G12: 24175.65 | H12: =G12/G13-1 -> -0.003148194 | S12: 2005 | T12: 0.3634 | Y12: 46257 | Z12: 162.73 | AA12: =Z12/Z13-1 -> -0.013638017 | AF12: 46257 | AG12: 555.25 | AH12: =AG12/AG13-1 -> -0.011482998 | AM12: 46257 | AN12: 297.8 | AO12: =AN12/AN13-1 -> -0.016350124 | AT12: 46257 | AU12: 901.2 | AV12: =AU12/AU13-1 -> 0.045536284
B13: 46250 | C13: 730 | D13: =C13/C14-1 -> 0.013888889 | F13: 46250 | G13: 24252 | H13: =G13/G14-1 -> -0.0046786506 | J13: Adjusted Beta | K13: =(K8*K9)+(K10*K11) -> 1.2402091 | S13: 2006 | T13: 0.3983 | Y13: 46250 | Z13: 164.98 | AA13: =Z13/Z14-1 -> 0.00030315892 | AC13: Adjusted Beta | AD13: =(AD8*AD9)+(AD10*AD11) -> 0.41378968 | AF13: 46250 | AG13: 561.7 | AH13: =AG13/AG14-1 -> 0.10126458 | AJ13: Adjusted Beta | AK13: =(AK8*AK9)+(AK10*AK11) -> 0.45819921 | AM13: 46250 | AN13: 302.75 | AO13: =AN13/AN14-1 -> 0.0079906775 | AQ13: Adjusted Beta | AR13: =(AR8*AR9)+(AR10*AR11) -> 0.34499907 | AT13: 46250 | AU13: 861.95 | AV13: =AU13/AU14-1 -> 0.044661253 | AX13: Adjusted Beta | AY13: =(AY8*AY9)+(AY10*AY11) -> 0.67179645
B14: 46243 | C14: 720 | D14: =C14/C15-1 -> -0.01504788 | F14: 46243 | G14: 24366 | H14: =G14/G15-1 -> -0.008329043 | S14: 2007 | T14: 0.5477 | Y14: 46243 | Z14: 164.93 | AA14: =Z14/Z15-1 -> -0.033518898 | AF14: 46243 | AG14: 510.05 | AH14: =AG14/AG15-1 -> -0.01534749 | AM14: 46243 | AN14: 300.35 | AO14: =AN14/AN15-1 -> -0.020225086 | AT14: 46243 | AU14: 825.1 | AV14: =AU14/AU15-1 -> -0.040246598
B15: 46236 | C15: 731 | D15: =C15/C16-1 -> -0.010222734 | F15: 46236 | G15: 24570.65 | H15: =G15/G16-1 -> 0.0076711396 | S15: 2008 | T15: -0.5179 | Y15: 46236 | Z15: 170.65 | AA15: =Z15/Z16-1 -> 0.050994642 | AF15: 46236 | AG15: 518 | AH15: =AG15/AG16-1 -> 0.047310958 | AM15: 46236 | AN15: 306.55 | AO15: =AN15/AN16-1 -> -0.062538226 | AT15: 46236 | AU15: 859.7 | AV15: =AU15/AU16-1 -> 0.059526744
B16: 46229 | C16: 738.55 | D16: =C16/C17-1 -> 0.015258781 | F16: 46229 | G16: 24383.6 | H16: =G16/G17-1 -> 0.02592411 | S16: 2009 | T16: 0.7576 | Y16: 46229 | Z16: 162.37 | AA16: =Z16/Z17-1 -> 0.01532016 | AF16: 46229 | AG16: 494.6 | AH16: =AG16/AG17-1 -> 0.041921213 | AM16: 46229 | AN16: 327 | AO16: =AN16/AN17-1 -> 0.0018382353 | AT16: 46229 | AU16: 811.4 | AV16: =AU16/AU17-1 -> -0.0036836935
B17: 46222 | C17: 727.45 | D17: =C17/C18-1 -> -0.00061821679 | F17: 46222 | G17: 23767.45 | H17: =G17/G18-1 -> -0.02329428 | J17: SUMMARY OUTPUT | S17: 2010 | T17: 0.1795 | Y17: 46222 | Z17: 159.92 | AA17: =Z17/Z18-1 -> -0.072443594 | AF17: 46222 | AG17: 474.7 | AH17: =AG17/AG18-1 -> -0.022547102 | AM17: 46222 | AN17: 326.4 | AO17: =AN17/AN18-1 -> -0.036457565 | AT17: 46222 | AU17: 814.4 | AV17: =AU17/AU18-1 -> -0.055877579
B18: 46215 | C18: 727.9 | D18: =C18/C19-1 -> -0.032433869 | F18: 46215 | G18: 24334.3 | H18: =G18/G19-1 -> 0.0052629622 | S18: 2011 | T18: -0.2462 | Y18: 46215 | Z18: 172.41 | AA18: =Z18/Z19-1 -> -0.078957209 | AF18: 46215 | AG18: 485.65 | AH18: =AG18/AG19-1 -> -0.030638723 | AM18: 46215 | AN18: 338.75 | AO18: =AN18/AN19-1 -> 0.027293404 | AT18: 46215 | AU18: 862.6 | AV18: =AU18/AU19-1 -> 0.027210479
B19: 46208 | C19: 752.3 | D19: =C19/C20-1 -> 0.032528136 | F19: 46208 | G19: 24206.9 | H19: =G19/G20-1 -> -0.002634848 | J19: Regression Statistics | S19: 2012 | T19: 0.277 | Y19: 46208 | Z19: 187.19 | AA19: =Z19/Z20-1 -> 0.04797895 | AF19: 46208 | AG19: 501 | AH19: =AG19/AG20-1 -> 0.05318478 | AM19: 46208 | AN19: 329.75 | AO19: =AN19/AN20-1 -> 0.0010625379 | AT19: 46208 | AU19: 839.75 | AV19: =AU19/AU20-1 -> 0.0060500779
B20: 46201 | C20: 728.6 | D20: =C20/C21-1 -> 0.011031707 | F20: 46201 | G20: 24270.85 | H20: =G20/G21-1 -> 0.0089312438 | J20: Multiple R | K20: 0.56909171 | S20: 2013 | T20: 0.0676 | Y20: 46201 | Z20: 178.62 | AA20: =Z20/Z21-1 -> 0.028443114 | AF20: 46201 | AG20: 475.7 | AH20: =AG20/AG21-1 -> -0.01694565 | AM20: 46201 | AN20: 329.4 | AO20: =AN20/AN21-1 -> 0.0090366059 | AT20: 46201 | AU20: 834.7 | AV20: =AU20/AU21-1 -> 0.019231943
B21: 46194 | C21: 720.65 | D21: =C21/C22-1 -> -0.0056571231 | F21: 46194 | G21: 24056 | H21: =G21/G22-1 -> 0.0017865249 | J21: R Square | K21: 0.32386537 | S21: 2014 | T21: 0.3139 | Y21: 46194 | Z21: 173.68 | AA21: =Z21/Z22-1 -> 0.016147905 | AF21: 46194 | AG21: 483.9 | AH21: =AG21/AG22-1 -> -0.020841764 | AM21: 46194 | AN21: 326.45 | AO21: =AN21/AN22-1 -> 0.014292372 | AT21: 46194 | AU21: 818.95 | AV21: =AU21/AU22-1 -> 0.020689225
B22: 46187 | C22: 724.75 | D22: =C22/C23-1 -> 0.066671573 | F22: 46187 | G22: 24013.1 | H22: =G22/G23-1 -> 0.01651787 | J22: Adjusted R Square | K22: 0.32010907 | S22: 2015 | T22: -0.0406 | Y22: 46187 | Z22: 170.92 | AA22: =Z22/Z23-1 -> 0.1095099 | AF22: 46187 | AG22: 494.2 | AH22: =AG22/AG23-1 -> 0.14983713 | AM22: 46187 | AN22: 321.85 | AO22: =AN22/AN23-1 -> 0.089355221 | AT22: 46187 | AU22: 802.35 | AV22: =AU22/AU23-1 -> 0.098056658
B23: 46180 | C23: 679.45 | D23: =C23/C24-1 -> 0.033226886 | F23: 46180 | G23: 23622.9 | H23: =G23/G24-1 -> 0.010964321 | J23: Standard Error | K23: 0.033317349 | S23: 2016 | T23: 0.0301 | Y23: 46180 | Z23: 154.05 | AA23: =Z23/Z24-1 -> 0.0056795926 | AF23: 46180 | AG23: 429.8 | AH23: =AG23/AG24-1 -> 0.024919518 | AM23: 46180 | AN23: 295.45 | AO23: =AN23/AN24-1 -> 0.011988354 | AT23: 46180 | AU23: 730.7 | AV23: =AU23/AU24-1 -> -0.060132484
B24: 46173 | C24: 657.6 | D24: =C24/C25-1 -> 0.0051203668 | F24: 46173 | G24: 23366.7 | H24: =G24/G25-1 -> -0.0076886327 | J24: Observations | K24: 182 | S24: 2017 | T24: 0.2865 | Y24: 46173 | Z24: 153.18 | AA24: =Z24/Z25-1 -> -0.01078463 | AF24: 46173 | AG24: 419.35 | AH24: =AG24/AG25-1 -> 0.01439284 | AM24: 46173 | AN24: 291.95 | AO24: =AN24/AN25-1 -> -0.014348413 | AT24: 46173 | AU24: 777.45 | AV24: =AU24/AU25-1 -> -0.0091129238
B25: 46166 | C25: 654.25 | D25: =C25/C26-1 -> 0.0061514802 | F25: 46166 | G25: 23547.75 | H25: =G25/G26-1 -> -0.0072325069 | S25: 2018 | T25: 0.0315 | Y25: 46166 | Z25: 154.85 | AA25: =Z25/Z26-1 -> 0.0036295288 | AF25: 46166 | AG25: 413.4 | AH25: =AG25/AG26-1 -> -0.0056524354 | AM25: 46166 | AN25: 296.2 | AO25: =AN25/AN26-1 -> -0.070890841 | AT25: 46166 | AU25: 784.6 | AV25: =AU25/AU26-1 -> -0.013143827
B26: 46159 | C26: 650.25 | D26: =C26/C27-1 -> -0.0091428571 | F26: 46159 | G26: 23719.3 | H26: =G26/G27-1 -> 0.0032059551 | J26: ANOVA | S26: 2019 | T26: 0.1202 | Y26: 46159 | Z26: 154.29 | AA26: =Z26/Z27-1 -> -0.0076537175 | AF26: 46159 | AG26: 415.75 | AH26: =AG26/AG27-1 -> 0.0038633345 | AM26: 46159 | AN26: 318.8 | AO26: =AN26/AN27-1 -> 0.0085416008 | AT26: 46159 | AU26: 795.05 | AV26: =AU26/AU27-1 -> 0.013254317
B27: 46152 | C27: 656.25 | D27: =C27/C28-1 -> -0.024960998 | F27: 46152 | G27: 23643.5 | H27: =G27/G28-1 -> -0.022032044 | K27: df | L27: SS | M27: MS | N27: F | O27: Significance F | S27: 2020 | T27: 0.149 | Y27: 46152 | Z27: 155.48 | AA27: =Z27/Z28-1 -> -0.054832827 | AF27: 46152 | AG27: 414.15 | AH27: =AG27/AG28-1 -> -0.021962451 | AM27: 46152 | AN27: 316.1 | AO27: =AN27/AN28-1 -> -0.057543232 | AT27: 46152 | AU27: 784.65 | AV27: =AU27/AU28-1 -> -0.005765332
B28: 46145 | C28: 673.05 | D28: =C28/C29-1 -> 0.058504364 | F28: 46145 | G28: 24176.15 | H28: =G28/G29-1 -> 0.0074424264 | J28: Regression | K28: 1 | L28: 0.09570722 | M28: 0.09570722 | N28: 86.21917 | O28: 5.2078278e-17 | S28: 2021 | T28: 0.2412 | Y28: 46145 | Z28: 164.5 | AA28: =Z28/Z29-1 -> 0.024475307 | AF28: 46145 | AG28: 423.45 | AH28: =AG28/AG29-1 -> -0.011208406 | AM28: 46145 | AN28: 335.4 | AO28: =AN28/AN29-1 -> 0.051575482 | AT28: 46145 | AU28: 789.2 | AV28: =AU28/AU29-1 -> 0.041573182
B29: 46138 | C29: 635.85 | D29: =C29/C30-1 -> 0.00078696781 | F29: 46138 | G29: 23997.55 | H29: =G29/G30-1 -> 0.0041677215 | J29: Residual | K29: 180 | L29: 0.19980823 | M29: 0.0011100457 | S29: 2022 | T29: 0.0432 | Y29: 46138 | Z29: 160.57 | AA29: =Z29/Z30-1 -> 0.014147666 | AF29: 46138 | AG29: 428.25 | AH29: =AG29/AG30-1 -> -0.0018645845 | AM29: 46138 | AN29: 318.95 | AO29: =AN29/AN30-1 -> -0.022824755 | AT29: 46138 | AU29: 757.7 | AV29: =AU29/AU30-1 -> -0.050025075
B30: 46131 | C30: 635.35 | D30: =C30/C31-1 -> -0.036326407 | F30: 46131 | G30: 23897.95 | H30: =G30/G31-1 -> -0.018707745 | J30: Total | K30: 181 | L30: 0.29551545 | S30: 2023 | T30: 0.1942 | Y30: 46131 | Z30: 158.33 | AA30: =Z30/Z31-1 -> -0.025781442 | AF30: 46131 | AG30: 429.05 | AH30: =AG30/AG31-1 -> 0.0050363083 | AM30: 46131 | AN30: 326.4 | AO30: =AN30/AN31-1 -> 0.013979497 | AT30: 46131 | AU30: 797.6 | AV30: =AU30/AU31-1 -> 0.022629656
B31: 46124 | C31: 659.3 | D31: =C31/C32-1 -> 0.027747467 | F31: 46124 | G31: 24353.55 | H31: =G31/G32-1 -> 0.012596359 | S31: 2024 | T31: 0.0875 | Y31: 46124 | Z31: 162.52 | AA31: =Z31/Z32-1 -> 0.04858378 | AF31: 46124 | AG31: 426.9 | AH31: =AG31/AG32-1 -> -0.0062849162 | AM31: 46124 | AN31: 321.9 | AO31: =AN31/AN32-1 -> 0.031069827 | AT31: 46124 | AU31: 779.95 | AV31: =AU31/AU32-1 -> 0.01265905
B32: 46117 | C32: 641.5 | D32: =C32/C33-1 -> 0.1008151 | F32: 46117 | G32: 24050.6 | H32: =G32/G33-1 -> 0.058886722 | K32: Coefficients | L32: Standard Error | M32: t Stat | N32: P-value | O32: Lower 95% | P32: Upper 95% | Q32: Lower 95.0% | S32: 2025 | T32: 0.1051 | Y32: 46117 | Z32: 154.99 | AA32: =Z32/Z33-1 -> 0.046593288 | AF32: 46117 | AG32: 429.6 | AH32: =AG32/AG33-1 -> 0.032940611 | AM32: 46117 | AN32: 312.2 | AO32: =AN32/AN33-1 -> 0.083275503 | AT32: 46117 | AU32: 770.2 | AV32: =AU32/AU33-1 -> 0.057240906
B33: 46110 | C33: 582.75 | D33: =C33/C34-1 -> -0.01379252 | F33: 46110 | G33: 22713.1 | H33: =G33/G34-1 -> -0.0046670406 | J33: Intercept | K33: 0.0035842921 | L33: 0.0024776817 | M33: 1.4466314 | N33: 0.14973932 | O33: -0.0013047457 | P33: 0.00847333 | Q33: -0.0013047457 | Y33: 46110 | Z33: 148.09 | AA33: =Z33/Z34-1 -> 0.044579248 | AF33: 46110 | AG33: 415.9 | AH33: =AG33/AG34-1 -> 0.023879862 | AM33: 46110 | AN33: 288.2 | AO33: =AN33/AN34-1 -> 0.013717904 | AT33: 46110 | AU33: 728.5 | AV33: =AU33/AU34-1 -> 0.0048968894
B34: 46103 | C34: 590.9 | D34: =C34/C35-1 -> -0.040045488 | F34: 46103 | G34: 22819.6 | H34: =G34/G35-1 -> -0.012758225 | J34: X Variable 1 | K34: 1.3202787 | L34: 0.14218825 | M34: 9.2854278 | N34: 5.2078278e-17 | O34: 1.0397085 | P34: 1.600849 | Q34: 1.0397085 | Y34: 46103 | Z34: 141.77 | AA34: =Z34/Z35-1 -> -0.048587343 | AF34: 46103 | AG34: 406.2 | AH34: =AG34/AG35-1 -> 0.01728024 | AM34: 46103 | AN34: 284.3 | AO34: =AN34/AN35-1 -> -0.081421648 | AT34: 46103 | AU34: 724.95 | AV34: =AU34/AU35-1 -> 0.0020041465
B35: 46096 | C35: 615.55 | D35: =C35/C36-1 -> 0.0093465606 | F35: 46096 | G35: 23114.5 | H35: =G35/G36-1 -> -0.0015809184 | Y35: 46096 | Z35: 149.01 | AA35: =Z35/Z36-1 -> -0.026841693 | AF35: 46096 | AG35: 399.3 | AH35: =AG35/AG36-1 -> -0.076122166 | AM35: 46096 | AN35: 309.5 | AO35: =AN35/AN36-1 -> -0.026117055 | AT35: 46096 | AU35: 723.5 | AV35: =AU35/AU36-1 -> -0.013498773
B36: 46089 | C36: 609.85 | D36: =C36/C37-1 -> -0.022441292 | F36: 46089 | G36: 23151.1 | H36: =G36/G37-1 -> -0.053142171 | Y36: 46089 | Z36: 153.12 | AA36: =Z36/Z37-1 -> -0.08492201 | AF36: 46089 | AG36: 432.2 | AH36: =AG36/AG37-1 -> -0.0038031578 | AM36: 46089 | AN36: 317.8 | AO36: =AN36/AN37-1 -> -0.035069075 | AT36: 46089 | AU36: 733.4 | AV36: =AU36/AU37-1 -> -0.039863848
B37: 46082 | C37: 623.85 | D37: =C37/C38-1 -> -0.16182991 | F37: 46082 | G37: 24450.45 | H37: =G37/G38-1 -> -0.066881782 | Y37: 46082 | Z37: 167.33 | AA37: =Z37/Z38-1 -> -0.049585369 | AF37: 46082 | AG37: 433.85 | AH37: =AG37/AG38-1 -> -0.043435123 | AM37: 46082 | AN37: 329.35 | AO37: =AN37/AN38-1 -> 0.050390687 | AT37: 46082 | AU37: 763.85 | AV37: =AU37/AU38-1 -> -0.054758074
B38: 45984 | C38: 744.3 | D38: =C38/C39-1 -> 0.015139116 | F38: 45984 | G38: 26202.95 | H38: =G38/G39-1 -> 0.0051710612 | Y38: 46075 | Z38: 176.06 | AA38: =Z38/Z39-1 -> -0.0035091691 | AF38: 46075 | AG38: 453.55 | AH38: =AG38/AG39-1 -> 0.041566196 | AM38: 46075 | AN38: 313.55 | AO38: =AN38/AN39-1 -> -0.039957134 | AT38: 46075 | AU38: 808.1 | AV38: =AU38/AU39-1 -> -0.064536667
B39: 45977 | C39: 733.2 | D39: =C39/C40-1 -> 0.017203108 | F39: 45977 | G39: 26068.15 | H39: =G39/G40-1 -> 0.0061018794 | Y39: 46068 | Z39: 176.68 | AA39: =Z39/Z40-1 -> -0.019152834 | AF39: 46068 | AG39: 435.45 | AH39: =AG39/AG40-1 -> -0.022010107 | AM39: 46068 | AN39: 326.6 | AO39: =AN39/AN40-1 -> -0.011052233 | AT39: 46068 | AU39: 863.85 | AV39: =AU39/AU40-1 -> 0.0063490214
B40: 45970 | C40: 720.8 | D40: =C40/C41-1 -> 0.042673224 | F40: 45970 | G40: 25910.05 | H40: =G40/G41-1 -> 0.016387301 | Y40: 46061 | Z40: 180.13 | AA40: =Z40/Z41-1 -> -0.0037057522 | AF40: 46061 | AG40: 445.25 | AH40: =AG40/AG41-1 -> 0.026631312 | AM40: 46061 | AN40: 330.25 | AO40: =AN40/AN41-1 -> -0.051142077 | AT40: 46061 | AU40: 858.4 | AV40: =AU40/AU41-1 -> 0.011012308
B41: 45963 | C41: 691.3 | D41: =C41/C42-1 -> -0.068077649 | F41: 45963 | G41: 25492.3 | H41: =G41/G42-1 -> -0.0089339517 | Y41: 46054 | Z41: 180.8 | AA41: =Z41/Z42-1 -> 0.0002212879 | AF41: 46054 | AG41: 433.7 | AH41: =AG41/AG42-1 -> 0.030166271 | AM41: 46054 | AN41: 348.05 | AO41: =AN41/AN42-1 -> 0.10650135 | AT41: 46054 | AU41: 849.05 | AV41: =AU41/AU42-1 -> -0.025424702
B42: 45956 | C42: 741.8 | D42: =C42/C43-1 -> 0.0080173937 | F42: 45956 | G42: 25722.1 | H42: =G42/G43-1 -> -0.0028319277 | Y42: 46047 | Z42: 180.76 | AA42: =Z42/Z43-1 -> -0.0079578508 | AF42: 46047 | AG42: 421 | AH42: =AG42/AG43-1 -> 0.031736307 | AM42: 46047 | AN42: 314.55 | AO42: =AN42/AN43-1 -> -0.024348635 | AT42: 46047 | AU42: 871.2 | AV42: =AU42/AU43-1 -> 0.062374245
B43: 45949 | C43: 735.9 | D43: =C43/C44-1 -> 0.00067990209 | F43: 45949 | G43: 25795.15 | H43: =G43/G44-1 -> 0.0033177945 | Y43: 46040 | Z43: 182.21 | AA43: =Z43/Z44-1 -> -0.025093633 | AF43: 46040 | AG43: 408.05 | AH43: =AG43/AG44-1 -> -0.074926321 | AM43: 46040 | AN43: 322.4 | AO43: =AN43/AN44-1 -> -0.054129382 | AT43: 46040 | AU43: 820.05 | AV43: =AU43/AU44-1 -> -0.065257039
B44: 45942 | C44: 735.4 | D44: =C44/C45-1 -> -0.00020392903 | F44: 45942 | G44: 25709.85 | H44: =G44/G45-1 -> 0.016788377 | Y44: 46033 | Z44: 186.9 | AA44: =Z44/Z45-1 -> -0.03907455 | AF44: 46033 | AG44: 441.1 | AH44: =AG44/AG45-1 -> 0.028444859 | AM44: 46033 | AN44: 340.85 | AO44: =AN44/AN45-1 -> -0.016589729 | AT44: 46033 | AU44: 877.3 | AV44: =AU44/AU45-1 -> 0.0072908893
B45: 45935 | C45: 735.55 | D45: =C45/C46-1 -> 0.015321968 | F45: 45935 | G45: 25285.35 | H45: =G45/G46-1 -> 0.015710455 | Y45: 46026 | Z45: 194.5 | AA45: =Z45/Z46-1 -> -0.021088127 | AF45: 46026 | AG45: 428.9 | AH45: =AG45/AG46-1 -> -0.036504549 | AM45: 46026 | AN45: 346.6 | AO45: =AN45/AN46-1 -> -0.056357201 | AT45: 46026 | AU45: 870.95 | AV45: =AU45/AU46-1 -> -0.034958449
B46: 45928 | C46: 724.45 | D46: =C46/C47-1 -> 0.020639617 | F46: 45928 | G46: 24894.25 | H46: =G46/G47-1 -> 0.0097162002 | Y46: 46019 | Z46: 198.69 | AA46: =Z46/Z47-1 -> 0.0010076074 | AF46: 46019 | AG46: 445.15 | AH46: =AG46/AG47-1 -> 0.024039568 | AM46: 46019 | AN46: 367.3 | AO46: =AN46/AN47-1 -> 0.00054481068 | AT46: 46019 | AU46: 902.5 | AV46: =AU46/AU47-1 -> 0.041486354
... B76: 45718 | C76: 744.3 | D76: =C76/C77-1 -> 0.039379975 | F76: 45718 | G76: 22552.5 | H76: =G76/G77-1 -> 0.019335855 | Y76: 45809 | Z76: 218.25 | AA76: =Z76/Z77-1 -> 0.0082228484 | AF76: 45809 | AG76: 432.45 | AH76: =AG76/AG77-1 -> #DIV/0! | AM76: 45809 | AN76: 374.6 | AO76: =AN76/AN77-1 -> 0.013528139 | AT76: 45809 | AU76: 920.85 | AV76: =AU76/AU77-1 -> 0.0034324943
B77: 45711 | C77: 716.1 | D77: =C77/C78-1 -> -0.05471586 | F77: 45711 | G77: 22124.7 | H77: =G77/G78-1 -> -0.029443891 | Y77: 45802 | Z77: 216.47 | AA77: =Z77/Z78-1 -> 0.0066499256 | AM77: 45802 | AN77: 369.6 | AO77: =AN77/AN78-1 -> -0.01083902 | AT77: 45802 | AU77: 917.7 | AV77: =AU77/AU78-1 -> 0.033096927
B78: 45704 | C78: 757.55 | D78: =C78/C79-1 -> 0.06667136 | F78: 45704 | G78: 22795.9 | H78: =G78/G79-1 -> -0.0058157157 | Y78: 45795 | Z78: 215.04 | AA78: =Z78/Z79-1 -> 0.06051191 | AM78: 45795 | AN78: 373.65 | AO78: =AN78/AN79-1 -> -0.0041311301 | AT78: 45795 | AU78: 888.3 | AV78: =AU78/AU79-1 -> -0.016170119
B79: 45697 | C79: 710.2 | D79: =C79/C80-1 -> -0.10305633 | F79: 45697 | G79: 22929.25 | H79: =G79/G80-1 -> -0.026770006 | Y79: 45788 | Z79: 202.77 | AA79: =Z79/Z80-1 -> 0.10833561 | AM79: 45788 | AN79: 375.2 | AO79: =AN79/AN80-1 -> 0.07816092 | AT79: 45788 | AU79: 902.9 | AV79: =AU79/AU80-1 -> 0.13088677
B80: 45690 | C80: 791.8 | D80: =C80/C81-1 -> 0.035438734 | F80: 45690 | G80: 23559.95 | H80: =G80/G81-1 -> 0.0021928332 | Y80: 45781 | Z80: 182.95 | AA80: =Z80/Z81-1 -> -0.053200849 | AM80: 45781 | AN80: 348 | AO80: =AN80/AN81-1 -> -0.04526749 | AT80: 45781 | AU80: 798.4 | AV80: =AU80/AU81-1 -> -0.002997003
B81: 45683 | C81: 764.7 | D81: =C81/C82-1 -> -0.021121352 | F81: 45683 | G81: 23508.4 | H81: =G81/G82-1 -> 0.018023402 | Y81: 45774 | Z81: 193.23 | AA81: =Z81/Z82-1 -> -0.0099907777 | AM81: 45774 | AN81: 364.5 | AO81: =AN81/AN82-1 -> -0.050286608 | AT81: 45774 | AU81: 800.8 | AV81: =AU81/AU82-1 -> -0.029980013
B82: 45676 | C82: 781.2 | D82: =C82/C83-1 -> -0.039527879 | F82: 45676 | G82: 23092.2 | H82: =G82/G83-1 -> -0.0047838229 | Y82: 45767 | Z82: 195.18 | AA82: =Z82/Z83-1 -> -0.027503737 | AM82: 45767 | AN82: 383.8 | AO82: =AN82/AN83-1 -> 0.028954424 | AT82: 45767 | AU82: 825.55 | AV82: =AU82/AU83-1 -> 0.017438994
B83: 45669 | C83: 813.35 | D83: =C83/C84-1 -> 0.0092443231 | F83: 45669 | G83: 23203.2 | H83: =G83/G84-1 -> -0.0097432943 | Y83: 45760 | Z83: 200.7 | AA83: =Z83/Z84-1 -> 0.002898261 | AM83: 45760 | AN83: 373 | AO83: =AN83/AN84-1 -> 0.03224021 | AT83: 45760 | AU83: 811.4 | AV83: =AU83/AU84-1 -> -0.010246402
B84: 45662 | C84: 805.9 | D84: =C84/C85-1 -> -0.076279443 | F84: 45662 | G84: 23431.5 | H84: =G84/G85-1 -> -0.02388069 | Y84: 45753 | Z84: 200.12 | AA84: =Z84/Z85-1 -> -0.0014968566 | AM84: 45753 | AN84: 361.35 | AO84: =AN84/AN85-1 -> -0.012704918 | AT84: 45753 | AU84: 819.8 | AV84: =AU84/AU85-1 -> -0.0087660964
B85: 45655 | C85: 872.45 | D85: =C85/C86-1 -> 0.013769463 | F85: 45655 | G85: 24004.75 | H85: =G85/G86-1 -> 0.0080353918 | Y85: 45746 | Z85: 200.42 | AA85: =Z85/Z86-1 -> 0.014733431 | AM85: 45746 | AN85: 366 | AO85: =AN85/AN86-1 -> 0.035360679 | AT85: 45746 | AU85: 827.05 | AV85: =AU85/AU86-1 -> 0.0092745134
B86: 45648 | C86: 860.6 | D86: =C86/C87-1 -> 0.0076103501 | F86: 45648 | G86: 23813.4 | H86: =G86/G87-1 -> 0.0095771065 | Y86: 45739 | Z86: 197.51 | AA86: =Z86/Z87-1 -> -0.0069385087 | AM86: 45739 | AN86: 353.5 | AO86: =AN86/AN87-1 -> -0.082175776 | AT86: 45739 | AU86: 819.45 | AV86: =AU86/AU87-1 -> 0.0044125758
B87: 45641 | C87: 854.1 | D87: =C87/C88-1 -> -0.0017531557 | F87: 45641 | G87: 23587.5 | H87: =G87/G88-1 -> -0.047673841 | Y87: 45732 | Z87: 198.89 | AA87: =Z87/Z88-1 -> 0.1928867 | AM87: 45732 | AN87: 385.15 | AO87: =AN87/AN88-1 -> 0.072542467 | AT87: 45732 | AU87: 815.85 | AV87: =AU87/AU88-1 -> 0.063273817
B88: 45634 | C88: 855.6 | D88: =C88/C89-1 -> 0.035020867 | F88: 45634 | G88: 24768.3 | H88: =G88/G89-1 -> 0.0036672637 | Y88: 45725 | Z88: 166.73 | AA88: =Z88/Z89-1 -> -0.037355658 | AM88: 45725 | AN88: 359.1 | AO88: =AN88/AN89-1 -> 0.056953642 | AT88: 45725 | AU88: 767.3 | AV88: =AU88/AU89-1 -> -0.029102872
... B92: 45606 | C92: 741.35 | D92: =C92/C93-1 -> 0.01152954 | F92: 45606 | G92: 23532.7 | H92: =G92/G93-1 -> -0.025488442 | Y92: 45697 | Z92: 164.67 | AA92: =Z92/Z93-1 -> -0.046220678 | AM92: 45697 | AN92: 335.4 | AO92: =AN92/AN93-1 -> -0.12735788 | AT92: 45697 | AU92: 693.65 | AV92: =AU92/AU93-1 -> -0.060413139
B93: 45599 | C93: 732.9 | D93: =C93/C94-1 -> 0.065881326 | F93: 45599 | G93: 24148.2 | H93: =G93/G94-1 -> -0.0064247758 | Y93: 45690 | Z93: 172.65 | AM93: 45690 | AN93: 384.35 | AO93: =AN93/AN94-1 -> 0.037381916 | AT93: 45690 | AU93: 738.25 | AV93: =AU93/AU94-1 -> -0.042415202
B94: 45592 | C94: 687.6 | D94: =C94/C95-1 -> -0.0052802893 | F94: 45592 | G94: 24304.35 | H94: =G94/G95-1 -> 0.0051094257 | AM94: 45683 | AN94: 370.5 | AO94: =AN94/AN95-1 -> -0.023329379 | AT94: 45683 | AU94: 770.95 | AV94: =AU94/AU95-1 -> 0.0094932565
B95: 45585 | C95: 691.25 | D95: =C95/C96-1 -> 0.0066258919 | F95: 45585 | G95: 24180.8 | H95: =G95/G96-1 -> -0.027088141 | AM95: 45676 | AN95: 379.35 | AO95: =AN95/AN96-1 -> -0.049843456 | AT95: 45676 | AU95: 763.7 | AV95: =AU95/AU96-1 -> -0.063921064
B96: 45578 | C96: 686.7 | D96: =C96/C97-1 -> -0.030837626 | F96: 45578 | G96: 24854.05 | H96: =G96/G97-1 -> -0.0044143125 | AM96: 45669 | AN96: 399.25 | AO96: =AN96/AN97-1 -> -0.028943208 | AT96: 45669 | AU96: 815.85 | AV96: =AU96/AU97-1 -> -0.085933561
B97: 45571 | C97: 708.55 | D97: =C97/C98-1 -> 0.071207196 | F97: 45571 | G97: 24964.25 | H97: =G97/G98-1 -> -0.0020128245 | AM97: 45662 | AN97: 411.15 | AO97: =AN97/AN98-1 -> -0.04015408 | AT97: 45662 | AU97: 892.55 | AV97: =AU97/AU98-1 -> -0.10093176
B98: 45564 | C98: 661.45 | D98: =C98/C99-1 -> -0.068773758 | F98: 45564 | G98: 25014.6 | H98: =G98/G99-1 -> -0.044476574 | AM98: 45655 | AN98: 428.35 | AO98: =AN98/AN99-1 -> 0.041580547 | AT98: 45655 | AU98: 992.75 | AV98: =AU98/AU99-1 -> 0.0036902234
B99: 45557 | C99: 710.3 | D99: =C99/C100-1 -> 0.010743508 | F99: 45557 | G99: 26178.95 | H99: =G99/G100-1 -> 0.015044037 | AM99: 45648 | AN99: 411.25 | AO99: =AN99/AN100-1 -> -0.0024257126 | AT99: 45648 | AU99: 989.1 | AV99: =AU99/AU100-1 -> 0.012695812
B100: 45550 | C100: 702.75 | D100: =C100/C101-1 -> 0.019882447 | F100: 45550 | G100: 25790.95 | H100: =G100/G101-1 -> 0.017133674 | AM100: 45641 | AN100: 412.25 | AO100: =AN100/AN101-1 -> -0.040944516 | AT100: 45641 | AU100: 976.7 | AV100: =AU100/AU101-1 -> -0.030618828
B101: 45543 | C101: 689.05 | D101: =C101/C102-1 -> 0.048383416 | F101: 45543 | G101: 25356.5 | H101: =G101/G102-1 -> 0.020294019 | AM101: 45634 | AN101: 429.85 | AO101: =AN101/AN102-1 -> 0.044719893 | AT101: 45634 | AU101: 1007.55 | AV101: =AU101/AU102-1 -> 0.12199332
B102: 45536 | C102: 657.25 | D102: =C102/C103-1 -> 0.015057915 | F102: 45536 | G102: 24852.15 | H102: =G102/G103-1 -> -0.015206511 | AM102: 45627 | AN102: 411.45 | AO102: =AN102/AN103-1 -> 0.084475488 | AT102: 45627 | AU102: 898 | AV102: =AU102/AU103-1 -> 0.0088754073
B103: 45529 | C103: 647.5 | D103: =C103/C104-1 -> 0.0087241003 | F103: 45529 | G103: 25235.9 | H103: =G103/G104-1 -> 0.016627624 | AM103: 45620 | AN103: 379.4 | AO103: =AN103/AN104-1 -> 0.034351145 | AT103: 45620 | AU103: 890.1 | AV103: =AU103/AU104-1 -> 0.057000356
B104: 45522 | C104: 641.9 | D104: =C104/C105-1 -> 0.030006418 | F104: 45522 | G104: 24823.15 | H104: =G104/G105-1 -> 0.011490904 | AM104: 45613 | AN104: 366.8 | AO104: =AN104/AN105-1 -> 0.025583671 | AT104: 45613 | AU104: 842.1 | AV104: =AU104/AU105-1 -> -0.0024284784
B105: 45515 | C105: 623.2 | D105: =C105/C106-1 -> 0.0076804916 | F105: 45515 | G105: 24541.15 | H105: =G105/G106-1 -> 0.0071262953 | AM105: 45606 | AN105: 357.65 | AO105: =AN105/AN106-1 -> -0.0043151448 | AT105: 45606 | AU105: 844.15 | AV105: =AU105/AU106-1 -> -0.053696542
... B188: 44934 | C188: 309.35 | D188: =C188/C189-1 -> -0.0030615533 | F188: 44934 | G188: 17956.6 | H188: =G188/G189-1 -> 0.0054396972 | AM188: 45025 | AN188: 171 | AO188: =AN188/AN189-1 -> 0.043637473 | AT188: 45025 | AU188: 361.15 | AV188: =AU188/AU189-1 -> -0.0033117152
B189: 44927 | C189: 310.3 | F189: 44927 | G189: 17859.45 | AM189: 45018 | AN189: 163.85 | AO189: =AN189/AN190-1 -> -0.010866284 | AT189: 45018 | AU189: 362.35 | AV189: =AU189/AU190-1 -> -0.0022029464
AM190: 45011 | AN190: 165.65 | AO190: =AN190/AN191-1 -> 0.062880975 | AT190: 45011 | AU190: 363.15 | AV190: =AU190/AU191-1 -> 0.0055378652
AM191: 45004 | AN191: 155.85 | AO191: =AN191/AN192-1 -> -0.042690418 | AT191: 45004 | AU191: 361.15 | AV191: =AU191/AU192-1 -> -0.014059514
AM192: 44997 | AN192: 162.8 | AO192: =AN192/AN193-1 -> -0.018981621 | AT192: 44997 | AU192: 366.3 | AV192: =AU192/AU193-1 -> -0.026186362
AM193: 44990 | AN193: 165.95 | AO193: =AN193/AN194-1 -> 0.033634382 | AT193: 44990 | AU193: 376.15 | AV193: =AU193/AU194-1 -> 0.042544346
AM194: 44983 | AN194: 160.55 | AO194: =AN194/AN195-1 -> -0.012 | AT194: 44983 | AU194: 360.8 | AV194: =AU194/AU195-1 -> -0.0066079295
AM195: 44976 | AN195: 162.5 | AO195: =AN195/AN196-1 -> -0.0082392432 | AT195: 44976 | AU195: 363.2 | AV195: =AU195/AU196-1 -> 0.0012405238
AM196: 44969 | AN196: 163.85 | AO196: =AN196/AN197-1 -> -0.046552226 | AT196: 44969 | AU196: 362.75 | AV196: =AU196/AU197-1 -> 0.0070794003
AM197: 44962 | AN197: 171.85 | AO197: =AN197/AN198-1 -> 0.029350105 | AT197: 44962 | AU197: 360.2 | AV197: =AU197/AU198-1 -> -0.004284727
AM198: 44955 | AN198: 166.95 | AO198: =AN198/AN199-1 -> 0.039215686 | AT198: 44955 | AU198: 361.75 | AV198: =AU198/AU199-1 -> 0.031508412
AM199: 44948 | AN199: 160.65 | AO199: =AN199/AN200-1 -> -0.044318858 | AT199: 44948 | AU199: 350.7 | AV199: =AU199/AU200-1 -> 0.031015728
AM200: 44941 | AN200: 168.1 | AO200: =AN200/AN201-1 -> -0.038604518 | AT200: 44941 | AU200: 340.15 | AV200: =AU200/AU201-1 -> 0.0090477603
AM201: 44934 | AN201: 174.85 | AO201: =AN201/AN202-1 -> -0.011867759 | AT201: 44934 | AU201: 337.1 | AV201: =AU201/AU202-1 -> 0.0091303697
... AM214: 44843 | AN214: 182.25 | AO214: =AN214/AN215-1 -> #DIV/0! | AT214: 44843 | AU214: 386.85 | AV214: =AU214/AU215-1 -> #DIV/0!

Sheet WACC
B2: Weighted Average Cost of Capital
B4: Cost of Debt | G4: Cost of Equity
B6: Pre Tax Cost of Debt | C6: =221/D35 -> 0.077911547 | G6: Risk Free Rate | I6: 0.0677 | J6: Taken from 10 yrs yield of govt. bond
B7: Tax Rate | C7: 0.25 | G7: Equity Risk Premium | I7: ='Beta & WACC Inputs'!W9-WACC!I6 -> 0.083792308
B8: Post Tax Cost of Debt | C8: =C6*(1-C7) -> 0.058433661 | G8: Adjusted Beta | I8: ='Beta & WACC Inputs'!K13 -> 1.2402091
G9: Cost of Equity | I9: =I6+(I7*I8) -> 0.17161998
B12: Capital Structure
D14: Current
B15: Total Debt (incl. Lease) | C15: =SUM('Data for IG'!I7:I10) -> 2837 | D15: =C15/$C$17 -> 0.027008905
B16: Market Capitalization | C16: ='Data Sheet'!B6*'Data Sheet'!B8 -> 102202.43 | D16: =C16/$C$17 -> 0.97299109
B17: Total Capital | C17: =SUM(C15:C16) -> 105039.43 | D17: =SUM(D15:D16) -> 1
B20: Debt/Equity | D20: =D15/D16 -> 0.027758635 | G20: Weighted Average Cost of Capital
I21: Total Cost | J21: Total Weight
B22: Note: | G22: Debt | I22: =C8 -> 0.058433661 | J22: =D15 -> 0.027008905
B23: 1. Tax Rate Consider as Marginal Tax Rate for the company | G23: Equity | I23: =I9 -> 0.17161998 | J23: =D16 -> 0.97299109
B24: 2. Levered Beta is based on 5 year montly data | G24: Weighted Average Cost of Capital | J24: =SUMPRODUCT(I22:I23,J22:J23) -> 0.16856294
B28: All figures are in INR unless stated otherwise
B30: Peer Comps
G32: Debt/ | H32: Debt/ | I32: Levered | J32: Unlevered
B33: Name of Company | C33: Country | D33: Total Debt | E33: Total Equity | F33: Tax Rate 1 | G33: Equity | H33: Capital | I33: Beta 2 | J33: Beta 3
B35: Indian Hotel | C35: India | D35: 2836.55 | E35: 142.34 | F35: 0.3 | G35: =D35/E35 -> 19.927989 | H35: =D35/(D35+E35) -> 0.9522171 | I35: ='Beta & WACC Inputs'!K8 -> 1.3202787 | J35: =I35/(1+(1 -F35)*G35) -> 0.088315366
B36: ITC Hotels | C36: India | D36: 74.19 | E36: 208.3 | F36: 0.3 | G36: =D36/E36 -> 0.35616899 | H36: =D36/(D36+E36) -> 0.26262877 | I36: ='Beta & WACC Inputs'!AD8 -> 0.21838624 | J36: =I36/(1+(1-F36)*G36) -> 0.17480433
B37: Leela Hotels | C37: India | D37: 1810.95 | E37: 333.96 | F37: 0.3 | G37: =D37/E37 -> 5.4226554 | H37: =D37/(D37+E37) -> 0.84430116 | I37: ='Beta & WACC Inputs'!AK8 -> 0.27759895 | J37: =I37/(1+(1-F37)*G37) -> 0.057883054
B38: EIH | C38: India | D38: 252.42 | E38: 125.07 | F38: 0.3 | G38: =D38/E38 -> 2.0182298 | H38: =D38/(D38+E38) -> 0.66867997 | I38: ='Beta & WACC Inputs'!AR8 -> 0.12666542 | J38: =I38/(1+(1-F38)*G38) -> 0.052498125
B39: Chalet Hotels | C39: India | D39: 2367.68 | E39: 218.99 | F39: 0.3 | G39: =D39/E39 -> 10.811818 | H39: =D39/(D39+E39) -> 0.91533903 | I39: ='Beta & WACC Inputs'!AY8 -> 0.56239527 | J39: =I39/(1+(1-F39)*G39) -> 0.065636949
E41: Average | F41: =AVERAGE(F35:F39) -> 0.3 | G41: =AVERAGE(G35:G39) -> 7.7073723 | H41: =AVERAGE(H35:H39) -> 0.7286332 | I41: =AVERAGE(I35:I39) -> 0.50106493 | J41: =AVERAGE(J35:J39) -> 0.087827565
E42: Median | F42: =MEDIAN(F35:F39) -> 0.3 | G42: =MEDIAN(G35:G39) -> 5.4226554 | H42: =MEDIAN(H35:H39) -> 0.84430116 | I42: =MEDIAN(I35:I39) -> 0.27759895 | J42: =MEDIAN(J35:J39) -> 0.065636949
B45: Levered Beta | G45: Cost of Equity
B47: Comps Median Unlevered Beta | E47: =J42 -> 0.065636949 | G47: Risk Free Rate | I47: 0.0677
B48: Target Debt/Equity | E48: =E20 -> 0 | G48: Equity Risk Premium | I48: ='Beta & WACC Inputs'!W9-WACC!I6 -> 0.083792308
B49: Tax Rate | E49: =F35 -> 0.3 | G49: Levered Beta 4 | I49: =E50 -> 0.065636949
B50: Levered Beta | E50: =E47*(1+(1-E49)*E48) -> 0.065636949 | G50: Cost of Equity | I50: =I47+(I48*I49) -> 0.073199871

Sheet Intrinsic Growth
B2: Calculation of ROIC | C2: ='Data Sheet'!E16 -> 43921 | D2: ='Data Sheet'!F16 -> 44286 | E2: ='Data Sheet'!G16 -> 44651 | F2: ='Data Sheet'!H16 -> 45016 | G2: ='Data Sheet'!I16 -> 45382 | H2: ='Data Sheet'!J16 -> 45747 | I2: ='Data Sheet'!K16 -> 46112
B4: Current Assets
B5: ='Data for IG'!B35 -> Inventories | C5: ='Data for IG'!C35 -> 94 | D5: ='Data for IG'!D35 -> 93 | E5: ='Data for IG'!E35 -> 101 | F5: ='Data for IG'!F35 -> 109 | G5: ='Data for IG'!G35 -> 116 | H5: ='Data for IG'!H35 -> 135 | I5: ='Data for IG'!I35 -> 150
B6: ='Data for IG'!B36 -> Trade receivables | C6: ='Data for IG'!C36 -> 290 | D6: ='Data for IG'!D36 -> 220 | E6: ='Data for IG'!E36 -> 255 | F6: ='Data for IG'!F36 -> 446 | G6: ='Data for IG'!G36 -> 476 | H6: ='Data for IG'!H36 -> 651 | I6: ='Data for IG'!I36 -> 727
B7: ='Data for IG'!B38 -> Loans n Advances | C7: ='Data for IG'!C37 -> 316 | D7: ='Data for IG'!D37 -> 154 | E7: ='Data for IG'!E37 -> 1188 | F7: ='Data for IG'!F37 -> 1053 | G7: ='Data for IG'!G37 -> 1486 | H7: ='Data for IG'!H37 -> 2182 | I7: ='Data for IG'!I37 -> 1831
B8: ='Data for IG'!B39 -> Other asset items | C8: ='Data for IG'!C38 -> 134 | D8: ='Data for IG'!D38 -> 144 | E8: ='Data for IG'!E38 -> 138 | F8: ='Data for IG'!F38 -> 144 | G8: ='Data for IG'!G38 -> 173 | H8: ='Data for IG'!H38 -> 176 | I8: ='Data for IG'!I38 -> 218
B9: Total Current Assets | C9: =SUM(C5:C8) -> 834 | D9: =SUM(D5:D8) -> 611 | E9: =SUM(E5:E8) -> 1682 | F9: =SUM(F5:F8) -> 1752 | G9: =SUM(G5:G8) -> 2251 | H9: =SUM(H5:H8) -> 3144 | I9: =SUM(I5:I8) -> 2926
B11: Current Liabilites
B12: ='Data for IG'!B13 -> Trade Payables | C12: ='Data for IG'!C13 -> 389 | D12: ='Data for IG'!D13 -> 318 | E12: ='Data for IG'!E13 -> 387 | F12: ='Data for IG'!F13 -> 477 | G12: ='Data for IG'!G13 -> 519 | H12: ='Data for IG'!H13 -> 578 | I12: ='Data for IG'!I13 -> 720
B13: ='Data for IG'!B14 -> Advance from Customers | C13: ='Data for IG'!C14 -> 124 | D13: ='Data for IG'!D14 -> 144 | E13: ='Data for IG'!E14 -> 183 | F13: ='Data for IG'!F14 -> 224 | G13: ='Data for IG'!G14 -> 252 | H13: ='Data for IG'!H14 -> 298 | I13: ='Data for IG'!I14 -> 317
B14: Total Current Liabilities | C14: =SUM(C12:C13) -> 513 | D14: =SUM(D12:D13) -> 462 | E14: =SUM(E12:E13) -> 570 | F14: =SUM(F12:F13) -> 701 | G14: =SUM(G12:G13) -> 771 | H14: =SUM(H12:H13) -> 876 | I14: =SUM(I12:I13) -> 1037
A16: # | B16: Net Working Capital | C16: =C9-C14 -> 321 | D16: =D9-D14 -> 149 | E16: =E9-E14 -> 1112 | F16: =F9-F14 -> 1051 | G16: =G9-G14 -> 1480 | H16: =H9-H14 -> 2268 | I16: =I9-I14 -> 1889
B19: Non current Asset
B20: Land | C20: ='Data for IG'!C19 -> 460 | D20: ='Data for IG'!D19 -> 552 | E20: ='Data for IG'!E19 -> 569 | F20: ='Data for IG'!F19 -> 836 | G20: ='Data for IG'!G19 -> 871 | H20: ='Data for IG'!H19 -> 1482 | I20: ='Data for IG'!I19 -> 1410
B21: Building | C21: ='Data for IG'!C20 -> 5634 | D21: ='Data for IG'!D20 -> 6218 | E21: ='Data for IG'!E20 -> 6464 | F21: ='Data for IG'!F20 -> 6779 | G21: ='Data for IG'!G20 -> 7276 | H21: ='Data for IG'!H20 -> 8298 | I21: ='Data for IG'!I20 -> 9247
B22: Plant Machinery | C22: ='Data for IG'!C21 -> 1402 | D22: ='Data for IG'!D21 -> 1527 | E22: ='Data for IG'!E21 -> 1574 | F22: ='Data for IG'!F21 -> 1683 | G22: ='Data for IG'!G21 -> 1947 | H22: ='Data for IG'!H21 -> 2249 | I22: ='Data for IG'!I21 -> 2620
B23: Equipments | C23: ='Data for IG'!C22 -> 88 | D23: ='Data for IG'!D22 -> 93 | E23: ='Data for IG'!E22 -> 101 | F23: ='Data for IG'!F22 -> 106 | G23: ='Data for IG'!G22 -> 119 | H23: ='Data for IG'!H22 -> 139 | I23: ='Data for IG'!I22 -> 159
B24: Furniture n fittings | C24: ='Data for IG'!C23 -> 671 | D24: ='Data for IG'!D23 -> 743 | E24: ='Data for IG'!E23 -> 792 | F24: ='Data for IG'!F23 -> 856 | G24: ='Data for IG'!G23 -> 970 | H24: ='Data for IG'!H23 -> 1111 | I24: ='Data for IG'!I23 -> 1272
B25: Vehicles | C25: ='Data for IG'!C24 -> 14 | D25: ='Data for IG'!D24 -> 14 | E25: ='Data for IG'!E24 -> 15 | F25: ='Data for IG'!F24 -> 16 | G25: ='Data for IG'!G24 -> 16 | H25: ='Data for IG'!H24 -> 89 | I25: ='Data for IG'!I24 -> 102
B26: Intangible Assets | C26: ='Data for IG'!C25 -> 1259 | D26: ='Data for IG'!D25 -> 1255 | E26: ='Data for IG'!E25 -> 1269 | F26: ='Data for IG'!F25 -> 1306 | G26: ='Data for IG'!G25 -> 1317 | H26: ='Data for IG'!H25 -> 1366 | I26: ='Data for IG'!I25 -> 1891
B27: Other fixed assets | C27: ='Data for IG'!C26 -> 80 | D27: ='Data for IG'!D26 -> 84 | E27: ='Data for IG'!E26 -> 86 | F27: ='Data for IG'!F26 -> 94 | G27: ='Data for IG'!G26 -> 97 | H27: ='Data for IG'!H26 -> 161 | I27: ='Data for IG'!I26 -> 226
A28: # | B28: ='Data for IG'!B27 -> Gross Block | C28: ='Data for IG'!C27 -> 9608 | D28: ='Data for IG'!D27 -> 10486 | E28: ='Data for IG'!E27 -> 10870 | F28: ='Data for IG'!F27 -> 11676 | G28: ='Data for IG'!G27 -> 12613 | H28: ='Data for IG'!H27 -> 14895 | I28: ='Data for IG'!I27 -> 16927
A30: # | B30: Invested Capital | C30: =C28+C16 -> 9929 | D30: =D28+D16 -> 10635 | E30: =E28+E16 -> 11982 | F30: =F28+F16 -> 12727 | G30: =G28+G16 -> 14093 | H30: =H28+H16 -> 17163 | I30: =I28+I16 -> 18816
B31: EBIT | C31: ='Historicial Financials'!C19-'Historicial Financials'!C25 -> 563.29 | D31: ='Historicial Financials'!D19-'Historicial Financials'!D25 -> -771.39 | E31: ='Historicial Financials'!E19-'Historicial Financials'!E25 -> -1.3 | F31: ='Historicial Financials'!F19-'Historicial Financials'!F25 -> 1388.5 | G31: ='Historicial Financials'!G19-'Historicial Financials'!G25 -> 1705.21 | H31: ='Historicial Financials'!H19-'Historicial Financials'!H25 -> 2251.17 | I31: ='Historicial Financials'!I19-'Historicial Financials'!I25 -> 2590.64
A33: # | B33: ROIC | C33: =C31/C30 -> 0.056731796 | D33: =D31/D30 -> -0.072533145 | E33: =E31/E30 -> -0.00010849608 | F33: =F31/F30 -> 0.10909877 | G33: =G31/G30 -> 0.12099695 | H33: =H31/H30 -> 0.13116413 | I33: =I31/I30 -> 0.13768282
B35: Calculation of Reinvestment Rate | C35: ='Data Sheet'!E16 -> 43921 | D35: ='Data Sheet'!F16 -> 44286 | E35: ='Data Sheet'!G16 -> 44651 | F35: ='Data Sheet'!H16 -> 45016 | G35: ='Data Sheet'!I16 -> 45382 | H35: ='Data Sheet'!J16 -> 45747 | I35: ='Data Sheet'!K16 -> 46112
B37: Net Capex | D37: ='Data Sheet'!F62-'Data Sheet'!E62+'Data Sheet'!E26 -> 783.09 | E37: ='Data Sheet'!G62-'Data Sheet'!F62+'Data Sheet'!F26 -> 387.27 | F37: ='Data Sheet'!H62-'Data Sheet'!G62+'Data Sheet'!G26 -> 809.24 | G37: ='Data Sheet'!I62-'Data Sheet'!H62+'Data Sheet'!H26 -> 908.87 | H37: ='Data Sheet'!J62-'Data Sheet'!I62+'Data Sheet'!I26 -> 2061.14 | I37: ='Data Sheet'!K62-'Data Sheet'!J62+'Data Sheet'!J26 -> 1810.04 | K37: Net Capex = Ending PPE - Open. PPE +Depr.
B38: Change in working Capital | D38: =D16-C16 -> -172 | E38: =E16-D16 -> 963 | F38: =F16-E16 -> -61 | G38: =G16-F16 -> 429 | H38: =H16-G16 -> 788 | I38: =I16-H16 -> -379
B40: EBIT | C40: =C31 -> 563.29 | D40: =D31 -> -771.39 | E40: =E31 -> -1.3 | F40: =F31 -> 1388.5 | G40: =G31 -> 1705.21 | H40: =H31 -> 2251.17 | I40: =I31 -> 2590.64
B41: Marginal Tax Rate | C41: 0.25 | D41: 0.25 | E41: 0.25 | F41: 0.25 | G41: 0.25 | H41: 0.25 | I41: 0.25
B42: EBIT(1-TR) [NOPAT] | C42: =C40*(1-C41) -> 422.4675 | D42: =D40*(1-D41) -> -578.5425 | E42: =E40*(1-E41) -> -0.975 | F42: =F40*(1-F41) -> 1041.375 | G42: =G40*(1-G41) -> 1278.9075 | H42: =H40*(1-H41) -> 1688.3775 | I42: =I40*(1-I41) -> 1942.98
B44: Reinvestment | D44: =SUM(D37:D38) -> 611.09 | E44: =SUM(E37:E38) -> 1350.27 | F44: =SUM(F37:F38) -> 748.24 | G44: =SUM(G37:G38) -> 1337.87 | H44: =SUM(H37:H38) -> 2849.14 | I44: =SUM(I37:I38) -> 1431.04
B45: Reinvestment Rate | D45: =D44/D42 -> -1.0562578 | E45: =E44/E42 -> -1384.8923 | F45: =F44/F42 -> 0.71851158 | G45: =G44/G42 -> 1.0461038 | H45: =H44/H42 -> 1.6875018 | I45: =I44/I42 -> 0.73651813
H47: 5 year Average | I47: =AVERAGE(D45:I45) -> -230.29332
H48: 5 year Median | I48: =MEDIAN(D45:I45) -> 0.72751486
B50: Calculation of Growth Rate | C50: ='Data Sheet'!E16 -> 43921 | D50: ='Data Sheet'!F16 -> 44286 | E50: ='Data Sheet'!G16 -> 44651 | F50: ='Data Sheet'!H16 -> 45016 | G50: ='Data Sheet'!I16 -> 45382 | H50: ='Data Sheet'!J16 -> 45747 | I50: ='Data Sheet'!K16 -> 46112
B52: Reinvestment Rate | D52: =D45 -> -1.0562578 | E52: =E45 -> -1384.8923 | F52: =F45 -> 0.71851158 | G52: =G45 -> 1.0461038 | H52: =H45 -> 1.6875018 | I52: =I45 -> 0.73651813 | J52: =I52*I53 -> 0.1014059
B53: ROIC | D53: =D33 -> -0.072533145 | E53: =E33 -> -0.00010849608 | F53: =F33 -> 0.10909877 | G53: =G33 -> 0.12099695 | H53: =H33 -> 0.13116413 | I53: =I33 -> 0.13768282
B55: Intrinsic Growth | D55: =D52*D53 -> 0.076613697 | E55: =E52*E53 -> 0.15025538 | F55: =F52*F53 -> 0.078388727 | G55: =G52*G53 -> 0.12657537 | H55: =H52*H53 -> 0.2213397 | I55: =I52*I53 -> 0.1014059
B57: Forward looking Reinvestment Rate | E57: Average | F57: =AVERAGE(D55:I55) -> 0.12576313
B58: Normalised ROIC (3 YEARS ) | C58: =AVERAGE(G33:I33) -> 0.12994797
B59: Forecast Growth | C59: 0.1
B60: Terminal Growth | C60: =DCF!D12 -> 0.12994797
B61: Reinvestment Rate (Based on expected Growth) | C61: =C59/C58 -> 0.76953877
B62: Reinvestment Rate (Based on TerminalGrowth) | C62: =C60/C58 -> 1

Sheet DCF
B2: Calculation of PV of FCFF | D2: ='Data Sheet'!K16 -> 46112 | E2: =D2+365 -> 46477 | F2: =E2+365 -> 46842 | G2: =F2+365 -> 47207 | H2: =G2+365 -> 47572 | I2: =H2+365 -> 47937
B5: Free Cash Flow to Firm | D5: =Forecasting!G17 -> 1462.14 | E5: =Forecasting!H17 -> 1919.2431 | F5: =Forecasting!I17 -> 2111.1674 | G5: =Forecasting!J17 -> 2322.2841 | H5: =Forecasting!K17 -> 2554.5125 | I5: =Forecasting!L17 -> 2809.9638
B7: Mid Year Convention | E7: 0.5 | F7: =E7+1 -> 1.5 | G7: =F7+1 -> 2.5 | H7: =G7+1 -> 3.5 | I7: =H7+1 -> 4.5
B8: Discounting Factor | E8: =1/(1+$D$13)^E7 -> 0.92506861 | F8: =1/(1+$D$13)^F7 -> 0.79162926 | G8: =1/(1+$D$13)^G7 -> 0.67743827 | H8: =1/(1+$D$13)^H7 -> 0.57971911 | I8: =1/(1+$D$13)^I7 -> 0.49609575
B10: PV of FCFF | E10: =E5*E8 -> 1775.4315 | F10: =F5*F8 -> 1671.2619 | G10: =G5*G8 -> 1573.2041 | H10: =H5*H8 -> 1480.8997 | I10: =I5*I8 -> 1394.0111
B12: Terminal Growth | D12: ='Intrinsic Growth'!C58 -> 0.12994797
B13: WACC | D13: =WACC!J24 -> 0.16856294
B15: Calculation of Terminal Value | K15: Sensitivity Analysis Of Value of Operating Assest
K16: =C27 -> 48686.24 | L16: 0.1 | M16: =L16+1% -> 0.11 | N16: =M16+1% -> 0.12 | O16: =N16+1% -> 0.13 | P16: =O16+1% -> 0.14
B17: FCFF(N+1) | C17: =I5*(1+D12) -> 3175.1128 | K17: 0.1 | L17: #DIV/0! | M17: -193972.2 | N17: -93326.249 | O17: -59777.598 | P17: -43003.272
B18: WACC | C18: =D13 -> 0.16856294 | K18: =K17+3% -> 0.13 | L18: 68006.112 | M18: 98539.494 | N18: 190139.64 | O18: #DIV/0! | P18: -176260.95
B19: Terminal Growth Rate | C19: =D12 -> 0.12994797 | K19: =K18+2% -> 0.15 | L19: 41163.178 | M19: 49777.642 | N19: 64135.083 | O19: 92849.965 | P19: 178994.61
K20: =K19+2% -> 0.17 | L20: 29656.84 | M20: 33518.739 | N20: 38925.397 | O20: 47035.385 | P20: 60552.032
B21: Terminal Value | C21: =C17/(C18-C19) -> 82224.916 | K21: =K20+2% -> 0.19 | L21: 23262.744 | M21: 25385.763 | N21: 28115.359 | O21: 31754.82 | P21: 36850.065
K22: =K21+2% -> 0.21 | L22: 19192.431 | M22: 20503.299 | N22: 22105.472 | O22: 24108.189 | P22: 26683.11
B23: Calculation of Equity Value
B25: PV of FCFF | C25: =SUM(E10:I10) -> 7894.8083
B26: PV of Terminal Value | C26: =C21*I8 -> 40791.432 | K26: Sensitivity Analysis Of Share Price
B27: Value of Operating Asset | C27: =SUM(C25:C26) -> 48686.24 | K27: =C34 -> 337.4295 | L27: 0.07 | M27: 0.09 | N27: 0.11 | O27: 0.13 | P27: 0.15
K28: 0.025 | L28: 296.76808 | M28: 221.10361 | N28: 181.04595 | O28: 156.24835 | P28: 139.38598
B29: Add: Cash | C29: ='Data Sheet'!J69 -> 2181.56 | K29: 0.045 | L29: 493.49572 | M29: 296.76808 | N29: 221.10361 | O29: 181.04595 | P29: 156.24835
B30: Less: Debt | C30: =WACC!C15 -> 2837 | K30: 0.065 | L30: 2264.0444 | M30: 493.49572 | N30: 296.76808 | O30: 221.10361 | P30: 181.04595
B31: Value of Equity | C31: =C27+C29-C30 -> 48030.8 | K31: 0.085 | L31: -686.87009 | M31: 2264.0444 | N31: 493.49572 | O31: 296.76808 | P31: 221.10361
B32: No. of Share | C32: ='Data Sheet'!B6 -> 142.34322 | K32: 0.105 | L32: -265.31087 | M32: -686.87009 | N32: 2264.0444 | O32: 493.49572 | P32: 296.76808
K33: 0.125 | L33: 0.025 | M33: 0.025 | N33: 0.025 | O33: 0.025 | P33: 0.025
B34: Equity Value per share | C34: =C31/C32 -> 337.4295
B36: Share Price | C36: ='Data Sheet'!B8 -> 718
B37: Discount/Premium | C37: =C36/C34 -> 2.1278519

Sheet Relative Comps
B2: Comparable Company Valuation
B4: Amt. In Crores
D5: Market Data | K5: Financials | O5: Valuation
B6: Company | C6: Ticker | D6: Share Price | E6: Share O/S | F6: Equity Value | G6: Net Debt | H6: Enterprise Value | K6: Revenue | L6: EBITDA | M6: Net Income | O6: EV/Revenue | P6: EV/EBITDA | Q6: P/E
B7: ='Data_Relative Comps'!C2 -> Indian Hotels Co | D7: ='Data_Relative Comps'!D2 -> 718 | E7: ='Data_Relative Comps'!E2 -> 142.34 | F7: =E7*D7 -> 102200.12 | G7: ='Data_Relative Comps'!I2 -> 1005.36 | H7: =F7+G7 -> 103205.48 | K7: ='Data_Relative Comps'!E11 -> 9987.33 | L7: ='Data_Relative Comps'!G11 -> 359244.26 | M7: ='Data_Relative Comps'!H11 -> 1943.44 | O7: =H7/K7 -> 10.333641 | P7: =H7/L7 -> 0.28728498 | Q7: =F7/M7 -> 52.587227
B8: ='Data_Relative Comps'!C3 -> ITC Hotels | D8: ='Data_Relative Comps'!D3 -> 158.51 | E8: ='Data_Relative Comps'!E3 -> 208.31 | F8: =E8*D8 -> 33019.218 | G8: ='Data_Relative Comps'!I3 -> -691.17 | H8: =F8+G8 -> 32328.048 | K8: ='Data_Relative Comps'!E12 -> 4259.88 | L8: ='Data_Relative Comps'!G12 -> 168904.24 | M8: ='Data_Relative Comps'!H12 -> 921.57 | O8: =H8/K8 -> 7.5889575 | P8: =H8/L8 -> 0.19139867 | Q8: =F8/M8 -> 35.829311
B9: ='Data_Relative Comps'!C4 -> Leela Palaces Hotels | D9: ='Data_Relative Comps'!D4 -> 568.95 | E9: ='Data_Relative Comps'!E4 -> 33.4 | F9: =E9*D9 -> 19002.93 | G9: ='Data_Relative Comps'!I4 -> 1525.38 | H9: =F9+G9 -> 20528.31 | K9: ='Data_Relative Comps'!E13 -> 1604.46 | L9: ='Data_Relative Comps'!G13 -> 81891.638 | M9: ='Data_Relative Comps'!H13 -> 448.62 | O9: =H9/K9 -> 12.794529 | P9: =H9/L9 -> 0.25067651 | Q9: =F9/M9 -> 42.358633
B10: ='Data_Relative Comps'!C5 -> EIH | D10: ='Data_Relative Comps'!D5 -> 297.85 | E10: ='Data_Relative Comps'!E5 -> 62.54 | F10: =E10*D10 -> 18627.539 | G10: ='Data_Relative Comps'!I5 -> -681.54 | H10: =F10+G10 -> 17945.999 | K10: ='Data_Relative Comps'!E14 -> 3023.01 | L10: ='Data_Relative Comps'!G14 -> 125454.92 | M10: ='Data_Relative Comps'!H14 -> 726.07 | O10: =H10/K10 -> 5.936467 | P10: =H10/L10 -> 0.1430474 | Q10: =F10/M10 -> 25.655294
B11: ='Data_Relative Comps'!C6 -> Chalet Hotels | D11: ='Data_Relative Comps'!D6 -> 830.25 | E11: ='Data_Relative Comps'!E6 -> 21.9 | F11: =E11*D11 -> 18182.475 | G11: ='Data_Relative Comps'!I6 -> 2059.18 | H11: =F11+G11 -> 20241.655 | K11: ='Data_Relative Comps'!E15 -> 2387.48 | L11: ='Data_Relative Comps'!G15 -> 110206.08 | M11: ='Data_Relative Comps'!H15 -> 535.27 | O11: =H11/K11 -> 8.4782511 | P11: =H11/L11 -> 0.18367095 | Q11: =F11/M11 -> 33.968791
B12: ='Data_Relative Comps'!C7 -> Ventive Hospital | D12: ='Data_Relative Comps'!D7 -> 552.2 | E12: ='Data_Relative Comps'!E7 -> 23.35 | F12: =E12*D12 -> 12893.87 | G12: ='Data_Relative Comps'!I7 -> 2153.16 | H12: =F12+G12 -> 15047.03 | K12: ='Data_Relative Comps'!E16 -> 2496.42 | L12: ='Data_Relative Comps'!G16 -> 138426.49 | M12: ='Data_Relative Comps'!H16 -> 484.72 | O12: =H12/K12 -> 6.0274433 | P12: =H12/L12 -> 0.10870051 | Q12: =F12/M12 -> 26.600656
B13: ='Data_Relative Comps'!C8 -> Lemon Tree Hotel | D13: ='Data_Relative Comps'!D8 -> 107.67 | E13: ='Data_Relative Comps'!E8 -> 79.22 | F13: =E13*D13 -> 8529.6174 | G13: ='Data_Relative Comps'!I8 -> 1905.85 | H13: =F13+G13 -> 10435.467 | K13: ='Data_Relative Comps'!E17 -> 1473.34 | L13: ='Data_Relative Comps'!G17 -> 70823.454 | M13: ='Data_Relative Comps'!H17 -> 255.91 | O13: =H13/K13 -> 7.0828644 | P13: =H13/L13 -> 0.1473448 | Q13: =F13/M13 -> 33.330536
B15: High | O15: =MAX(O7:O13) -> 12.794529 | P15: =MAX(P7:P13) -> 0.28728498 | Q15: =MAX(Q7:Q13) -> 52.587227
B16: Q3 | O16: =QUARTILE(O7:O13,3) -> 9.4059459 | P16: =QUARTILE(P7:P13,3) -> 0.22103759 | Q16: =QUARTILE(Q7:Q13,3) -> 39.093972
B17: Average | O17: =AVERAGE(O7:O13) -> 8.3203076 | P17: =AVERAGE(P7:P13) -> 0.18744626 | Q17: =AVERAGE(Q7:Q13) -> 35.761493
B18: Median | O18: =MEDIAN(O7:O13) -> 7.5889575 | P18: =MEDIAN(P7:P13) -> 0.18367095 | Q18: =MEDIAN(Q7:Q13) -> 33.968791
B19: Q1 | O19: =QUARTILE(O7:O13,1) -> 6.5551538 | P19: =QUARTILE(P7:P13,1) -> 0.1451961 | Q19: =QUARTILE(Q7:Q13,1) -> 29.965596
B20: Low | O20: =MIN(O7:O13) -> 5.936467 | P20: =MIN(P7:P13) -> 0.10870051 | Q20: =MIN(Q7:Q13) -> 25.655294
B22: Comparable Company Valuation | O22: EV/Revenue | P22: EV/EBITDA | Q22: P/E
B23: Implied Enterprise Value | O23: =O18*K$7 -> 75793.422 | P23: =P18*L$7 -> 65982.735 | Q23: =Q25+Q24 -> 67021.668
B24: Net Debt | O24: =G7 -> 1005.36 | P24: =G7 -> 1005.36 | Q24: =G7 -> 1005.36
B25: Implied Market Value | O25: =O23-O24 -> 74788.062 | P25: =P23-P24 -> 64977.375 | Q25: =Q18*M7 -> 66016.308
B26: Share Outstanding | O26: =E7 -> 142.34 | P26: =E7 -> 142.34 | Q26: =E7 -> 142.34
B27: Implied Value Per Share | O27: =O25/O26 -> 525.41845 | P27: =P25/P26 -> 456.49413 | Q27: =Q25/Q26 -> 463.79309
O29: =IF(O27>D7,"Under Valued",IF(O27=D7,"Normal Value","Over Valued")) -> Over Valued | P29: =IF(O27>D7,"Under Valued",IF(O27=D7,"Normal Value","Over Valued")) -> Over Valued | Q29: =IF(O27>D7,"Under Valued",IF(O27=D7,"Normal Value","Over Valued")) -> Over Valued

Sheet Football Field Analysis
B2: Football Field Analysis
C3: Open Low | D3: Low | E3: Open High | F3: High
B4: Comps | C4: 1270.1453 | D4: =MIN('Relative Comps'!O27:Q27) -> 456.49413 | E4: 1962.5904 | F4: =MAX('Relative Comps'!O27:Q27) -> 525.41845
B5: DCF Bear | C5: 332.79609 | D5: =MIN(DCF!P28:P33) -> 0.025 | E5: 1190.941 | F5: =MAX(DCF!P28:P33) -> 296.76808
B6: DCF Base | C6: -1669.5421 | D6: =MIN(DCF!M28:M33) -> -686.87009 | E6: 5481.6657 | F6: =MAX(DCF!M28:M33) -> 2264.0444
B7: DCF Bull | C7: -1669.5421 | D7: =MIN(DCF!L28:L33) -> -686.87009 | E7: 5481.6657 | F7: =MAX(DCF!L28:L33) -> 2264.0444
B8: 52W H/L | C8: 3403.95 | D8: =MIN('Beta & WACC Inputs'!C7:C97) -> 582.75 | E8: 5320.55 | F8: =MAX('Beta & WACC Inputs'!C7:C97) -> 872.45

Sheet Historical VAR
B1: VAR- Historical Appoarch
A3: # | B3: Date | C3: Price | D3: Return | E3: Sorted Return | G3: Calculation of Value At Risk- Dmart(Historical)
B4: 42832 | C4: 751.2 | D4: =C4/C5-1 -> -0.81337573 | E4: 0.13064419 | G4: Mean | I4: =AVERAGE(E4:E2332) -> 0.00098532491
B5: 45660 | C5: 4025.2 | D5: =C5/C6-1 -> 0.1303249 | E5: 0.1146742 | G5: SD | I5: =_xlfn.STDEV.S(E4:E2332) -> 0.019700728
B6: 44697 | C6: 3561.1 | D6: =C6/C7-1 -> -0.11497981 | E6: 0.10230298 | G6: Min | I6: =MIN(E4:E2332) -> -0.11087074
B7: 45689 | C7: 4023.75 | D7: =C7/C8-1 -> 1.0989828 | E7: 0.097990258 | G7: Max | I7: =MAX(E4:E2332) -> 0.13064419
B8: 43731 | C8: 1917 | D8: =C8/C9-1 -> 0.088462412 | E8: 0.088462412 | G8: CMP | I8: ='Data_Relative Comps'!#REF! -> #REF!
B9: 43728 | C9: 1761.2 | D9: =C9/C10-1 -> -0.29088237 | E9: 0.087596875
B10: 43871 | C10: 2483.65 | D10: =C10/C11-1 -> 1.2253931 | E10: 0.085891046
B11: 43004 | C11: 1116.05 | D11: =C11/C12-1 -> -0.78190008 | E11: 0.084596696 | G11: Percentile | H11: Confidence | I11: VAR % | J11: Stock Price | K11: VAR (INR)
B12: 44482 | C12: 5117.15 | D12: =C12/C13-1 -> 0.19808714 | E12: 0.079795315 | G12: 0.05 | H12: =100%-G12 -> 0.95 | I12: =_xlfn.PERCENTILE.INC($E$4:$E$2332,G12) -> -0.028962118 | J12: =$I$8*(1-I12) -> #REF! | K12: =$I$8-J12 -> #REF!
B13: 46113 | C13: 4271.1 | D13: =C13/C14-1 -> -0.095000477 | E13: 0.079432875 | G13: 0.01 | H13: =100%-G13 -> 0.99 | I13: =_xlfn.PERCENTILE.INC($E$4:$E$2332,G13) -> -0.049634577 | J13: =$I$8*(1-I13) -> #REF! | K13: =$I$8-J13 -> #REF!
B14: 44480 | C14: 4719.45 | D14: =C14/C15-1 -> 0.10231466 | E14: 0.070667771 | G14: 0.005 | H14: =100%-G14 -> 0.995 | I14: =_xlfn.PERCENTILE.INC($E$4:$E$2332,G14) -> -0.053467858 | J14: =$I$8*(1-I14) -> #REF! | K14: =$I$8-J14 -> #REF!
B15: 45868 | C15: 4281.4 | D15: =C15/C16-1 -> 1.927453 | E15: 0.070617654
B16: 43406 | C16: 1462.5 | D16: =C16/C17-1 -> -0.69921333 | E16: 0.070565844
B17: 45448 | C17: 4862.25 | D17: =C17/C18-1 -> 2.6888324 | E17: 0.068920033
B18: 43605 | C18: 1318.1 | D18: =C18/C19-1 -> -0.066303039 | E18: 0.067935994
B19: 43385 | C19: 1411.7 | D19: =C19/C20-1 -> -0.25067013 | E19: 0.064550185
B20: 43816 | C20: 1883.95 | D20: =C20/C21-1 -> -0.62614847 | E20: 0.064138048
B21: 45461 | C21: 5039.3 | D21: =C21/C22-1 -> 2.3650295 | E21: 0.063154675
B22: 43245 | C22: 1497.55 | D22: =C22/C23-1 -> 0.26412865 | E22: 0.06216753
B23: 43018 | C23: 1184.65 | D23: =C23/C24-1 -> -0.57871622 | E23: 0.060801433
B24: 44228 | C24: 2812 | D24: =C24/C25-1 -> 0.15877529 | E24: 0.060531774
B25: 44166 | C25: 2426.7 | D25: =C25/C26-1 -> -0.38058044 | E25: 0.060064651
B26: 45092 | C26: 3917.7 | D26: =C26/C27-1 -> 0.27467057 | E26: 0.057451719
... B2332: 43479 | C2332: 1397.4 | D2332: =C2332/C2333-1 -> 1.1883956 | E2332: -0.11087074
B2333: 42816 | C2333: 638.55

Sheet MonteCarlo VAR
B1: VAR- Monte Carlo Appoarch
A3: # | B3: Date | C3: Price | D3: Return | E3: Sorted Return | F3: Replication | G3: Stimulated Returns | I3: Calculation of Value At Risk- Dmart(Stimulation)
B4: 42832 | C4: 751.2 | D4: =C4/C5-1 -> -0.81337573 | E4: 0.13064419 | F4: 1 | G4: =_xlfn.NORM.INV(RAND(),K$6,K$7) -> 0.0032891296
B5: 45660 | C5: 4025.2 | D5: =C5/C6-1 -> 0.1303249 | E5: 0.1146742 | F5: 2 | G5: =_xlfn.NORM.INV(RAND(),K$6,K$7) -> 0.01025843 | I5: Historical Appoarch
B6: 44697 | C6: 3561.1 | D6: =C6/C7-1 -> -0.11497981 | E6: 0.10230298 | F6: 3 | G6: =_xlfn.NORM.INV(RAND(),K$6,K$7) -> -0.00033360738 | I6: Mean | K6: =AVERAGE(E4:E2332) -> 0.00098532491
B7: 45689 | C7: 4023.75 | D7: =C7/C8-1 -> 1.0989828 | E7: 0.097990258 | F7: 4 | G7: =_xlfn.NORM.INV(RAND(),K$6,K$7) -> 0.01153658 | I7: SD | K7: =_xlfn.STDEV.S(E4:E2332) -> 0.019700728
B8: 43731 | C8: 1917 | D8: =C8/C9-1 -> 0.088462412 | E8: 0.088462412 | F8: 5 | G8: =_xlfn.NORM.INV(RAND(),K$6,K$7) -> 0.029378726 | I8: Min | K8: =MIN(E4:E2332) -> -0.11087074
B9: 43728 | C9: 1761.2 | D9: =C9/C10-1 -> -0.29088237 | E9: 0.087596875 | F9: 6 | G9: =_xlfn.NORM.INV(RAND(),K$6,K$7) -> 0.0041853045 | I9: Max | K9: =MAX(E4:E2332) -> 0.13064419
B10: 43871 | C10: 2483.65 | D10: =C10/C11-1 -> 1.2253931 | E10: 0.085891046 | F10: 7 | G10: =_xlfn.NORM.INV(RAND(),K$6,K$7) -> -0.014451699 | I10: CMP | K10: ='Data_Relative Comps'!#REF! -> #REF!
B11: 43004 | C11: 1116.05 | D11: =C11/C12-1 -> -0.78190008 | E11: 0.084596696 | F11: 8 | G11: =_xlfn.NORM.INV(RAND(),K$6,K$7) -> 0.029594041
B12: 44482 | C12: 5117.15 | D12: =C12/C13-1 -> 0.19808714 | E12: 0.079795315 | F12: 9 | G12: =_xlfn.NORM.INV(RAND(),K$6,K$7) -> -0.031640912 | I12: Monte Carlo Appoarch
B13: 46113 | C13: 4271.1 | D13: =C13/C14-1 -> -0.095000477 | E13: 0.079432875 | F13: 10 | G13: =_xlfn.NORM.INV(RAND(),K$6,K$7) -> 0.02298848 | I13: Mean | K13: =AVERAGE(G4:G10003) -> 0.0012032339
B14: 44480 | C14: 4719.45 | D14: =C14/C15-1 -> 0.10231466 | E14: 0.070667771 | F14: 11 | G14: =_xlfn.NORM.INV(RAND(),K$6,K$7) -> 0.013118436 | I14: SD | K14: =_xlfn.STDEV.S(G4:G10003) -> 0.019588734
B15: 45868 | C15: 4281.4 | D15: =C15/C16-1 -> 1.927453 | E15: 0.070617654 | F15: 12 | G15: =_xlfn.NORM.INV(RAND(),K$6,K$7) -> -0.012309128 | I15: Min | K15: =MIN(G4:G10003) -> -0.07808704
B16: 43406 | C16: 1462.5 | D16: =C16/C17-1 -> -0.69921333 | E16: 0.070565844 | F16: 13 | G16: =_xlfn.NORM.INV(RAND(),K$6,K$7) -> -0.021221951 | I16: Max | K16: =MAX(G4:G10003) -> 0.075417403
B17: 45448 | C17: 4862.25 | D17: =C17/C18-1 -> 2.6888324 | E17: 0.068920033 | F17: 14 | G17: =_xlfn.NORM.INV(RAND(),K$6,K$7) -> -0.029008916 | I17: CMP | K17: ='Data_Relative Comps'!#REF! -> #REF!
B18: 43605 | C18: 1318.1 | D18: =C18/C19-1 -> -0.066303039 | E18: 0.067935994 | F18: 15 | G18: =_xlfn.NORM.INV(RAND(),K$6,K$7) -> 0.02925142
B19: 43385 | C19: 1411.7 | D19: =C19/C20-1 -> -0.25067013 | E19: 0.064550185 | F19: 16 | G19: =_xlfn.NORM.INV(RAND(),K$6,K$7) -> 0.014628688 | I19: Percentile | J19: Confidence | K19: VAR % | L19: Stock Price | M19: VAR (INR)
B20: 43816 | C20: 1883.95 | D20: =C20/C21-1 -> -0.62614847 | E20: 0.064138048 | F20: 17 | G20: =_xlfn.NORM.INV(RAND(),K$6,K$7) -> 0.023496606 | I20: 0.05 | J20: =100%-I20 -> 0.95 | K20: =_xlfn.PERCENTILE.INC($G$4:$G$10003,I20) -> -0.030646723 | L20: =$K$10*(1-K20) -> #REF! | M20: =$K$10-L20 -> #REF!
B21: 45461 | C21: 5039.3 | D21: =C21/C22-1 -> 2.3650295 | E21: 0.063154675 | F21: 18 | G21: =_xlfn.NORM.INV(RAND(),K$6,K$7) -> -0.019266868 | I21: 0.01 | J21: =100%-I21 -> 0.99 | K21: =_xlfn.PERCENTILE.INC($G$4:$G$10003,I21) -> -0.043698219 | L21: =$K$10*(1-K21) -> #REF! | M21: =$K$10-L21 -> #REF!
B22: 43245 | C22: 1497.55 | D22: =C22/C23-1 -> 0.26412865 | E22: 0.06216753 | F22: 19 | G22: =_xlfn.NORM.INV(RAND(),K$6,K$7) -> 0.031611413 | I22: 0.005 | J22: =100%-I22 -> 0.995 | K22: =_xlfn.PERCENTILE.INC($G$4:$G$10003,I22) -> -0.050049732 | L22: =$K$10*(1-K22) -> #REF! | M22: =$K$10-L22 -> #REF!
B23: 43018 | C23: 1184.65 | D23: =C23/C24-1 -> -0.57871622 | E23: 0.060801433 | F23: 20 | G23: =_xlfn.NORM.INV(RAND(),K$6,K$7) -> 0.0059743538
B24: 44228 | C24: 2812 | D24: =C24/C25-1 -> 0.15877529 | E24: 0.060531774 | F24: 21 | G24: =_xlfn.NORM.INV(RAND(),K$6,K$7) -> -1.5495538e-05
B25: 44166 | C25: 2426.7 | D25: =C25/C26-1 -> -0.38058044 | E25: 0.060064651 | F25: 22 | G25: =_xlfn.NORM.INV(RAND(),K$6,K$7) -> -0.021328798
B26: 45092 | C26: 3917.7 | D26: =C26/C27-1 -> 0.27467057 | E26: 0.057451719 | F26: 23 | G26: =_xlfn.NORM.INV(RAND(),K$6,K$7) -> 0.00023105891
B27: 44257 | C27: 3073.5 | D27: =C27/C28-1 -> 1.8519068 | E27: 0.05674844 | F27: 24 | G27: =_xlfn.NORM.INV(RAND(),K$6,K$7) -> 0.010292866
B28: 42983 | C28: 1077.7 | D28: =C28/C29-1 -> -0.48541279 | E28: 0.055895753 | F28: 25 | G28: =_xlfn.NORM.INV(RAND(),K$6,K$7) -> -0.019216587
B29: 44123 | C29: 2094.3 | D29: =C29/C30-1 -> -0.31475968 | E29: 0.055488358 | F29: 26 | G29: =_xlfn.NORM.INV(RAND(),K$6,K$7) -> 0.0023356248
B30: 44334 | C30: 3056.3 | D30: =C30/C31-1 -> 0.84676274 | E30: 0.0543692 | F30: 27 | G30: =_xlfn.NORM.INV(RAND(),K$6,K$7) -> 0.026461637
B31: 43462 | C31: 1654.95 | D31: =C31/C32-1 -> -0.47494408 | E31: 0.054007579 | F31: 28 | G31: =_xlfn.NORM.INV(RAND(),K$6,K$7) -> -0.007741092
B32: 44250 | C32: 3151.95 | D32: =C32/C33-1 -> 0.10102174 | E32: 0.053248012 | F32: 29 | G32: =_xlfn.NORM.INV(RAND(),K$6,K$7) -> -0.015469284
B33: 44218 | C33: 2862.75 | D33: =C33/C34-1 -> 1.2170378 | E33: 0.052810621 | F33: 30 | G33: =_xlfn.NORM.INV(RAND(),K$6,K$7) -> -0.020707224
B34: 43402 | C34: 1291.25 | D34: =C34/C35-1 -> 0.23428763 | E34: 0.052706669 | F34: 31 | G34: =_xlfn.NORM.INV(RAND(),K$6,K$7) -> 0.0048962701
... B2332: 43479 | C2332: 1397.4 | D2332: =C2332/C2333-1 -> 1.1883956 | E2332: -0.11087074 | F2332: 2329 | G2332: =_xlfn.NORM.INV(RAND(),K$6,K$7) -> 0.014549072
B2333: 42816 | C2333: 638.55 | F2333: 2330 | G2333: =_xlfn.NORM.INV(RAND(),K$6,K$7) -> -0.019011642
F2334: 2331 | G2334: =_xlfn.NORM.INV(RAND(),K$6,K$7) -> -0.035209667
F2335: 2332 | G2335: =_xlfn.NORM.INV(RAND(),K$6,K$7) -> -0.0014986717
F2336: 2333 | G2336: =_xlfn.NORM.INV(RAND(),K$6,K$7) -> 0.00017795721
F2337: 2334 | G2337: =_xlfn.NORM.INV(RAND(),K$6,K$7) -> -0.0068540515
F2338: 2335 | G2338: =_xlfn.NORM.INV(RAND(),K$6,K$7) -> 0.016960784
F2339: 2336 | G2339: =_xlfn.NORM.INV(RAND(),K$6,K$7) -> -0.027957443
F2340: 2337 | G2340: =_xlfn.NORM.INV(RAND(),K$6,K$7) -> 0.0044886186
F2341: 2338 | G2341: =_xlfn.NORM.INV(RAND(),K$6,K$7) -> 0.0019445806
F2342: 2339 | G2342: =_xlfn.NORM.INV(RAND(),K$6,K$7) -> -0.02418912
F2343: 2340 | G2343: =_xlfn.NORM.INV(RAND(),K$6,K$7) -> -0.033331764
F2344: 2341 | G2344: =_xlfn.NORM.INV(RAND(),K$6,K$7) -> -0.023130131
F2345: 2342 | G2345: =_xlfn.NORM.INV(RAND(),K$6,K$7) -> 0.0083635632
... F10003: 10000 | G10003: =_xlfn.NORM.INV(RAND(),K$6,K$7) -> -0.0042350467

Sheet Data >>

Sheet Data Sheet
A1: COMPANY NAME | B1: INDIAN HOTELS CO LTD | E1: =IF(B2<>B3, "A NEW VERSION OF THE WORKSHEET IS AVAILABLE", "")
A2: LATEST VERSION | B2: 2.1 | E2: PLEASE DO NOT MAKE ANY CHANGES TO THIS SHEET
A3: CURRENT VERSION | B3: 2.1
A5: META
A6: Number of shares | B6: =IF(B9>0, B9/B8, 0) -> 142.34322
A7: Face Value | B7: 1
A8: Current Price | B8: 718
A9: Market Capitalization | B9: 102202.43
A15: PROFIT & LOSS
A16: Report Date | B16: 42825 | C16: 43190 | D16: 43555 | E16: 43921 | F16: 44286 | G16: 44651 | H16: 45016 | I16: 45382 | J16: 45747 | K16: 46112
A17: Sales | B17: 4020.57 | C17: 4103.55 | D17: 4512 | E17: 4463.14 | F17: 1575.16 | G17: 3056.22 | H17: 5809.91 | I17: 6768.75 | J17: 8334.54 | K17: 9689.22
A18: Raw Material Cost | B18: 363.95 | C18: 376.44 | D18: 404.05 | E18: 370.56 | F18: 143.82 | G18: 257.23 | H18: 472.89 | I18: 520.83 | J18: 773.75 | K18: 950.89
A19: Change in Inventory
A20: Power and Fuel | B20: 258.61 | C20: 259.11 | D20: 273.57 | E20: 269.87 | F20: 172.85 | G20: 224.79 | H20: 303.09 | I20: 308.99 | J20: 360.66 | K20: 377.1
A21: Other Mfr. Exp | B21: 607.05 | C21: 603.49 | D21: 677.4 | E21: 808.11 | F21: 360.13 | G21: 574.32 | H21: 1045.5 | I21: 1249.06 | J21: 1105.74 | K21: 1262.95
A22: Employee Cost | B22: 1368.61 | C22: 1351.39 | D22: 1474.19 | E22: 1498.67 | F22: 896.13 | G22: 1153.4 | H22: 1588.69 | I22: 1811.08 | J22: 2156.67 | K22: 2491.75
A23: Selling and admin | B23: 681.21 | C23: 704.89 | D23: 723.09 | E23: 426.21 | F23: 263.68 | G23: 331.02 | H23: 472.94 | I23: 569.03 | J23: 988.62 | K23: 1174.6
A24: Other Expenses | B24: 131.52 | C24: 137.11 | D24: 129.97 | E24: 122.19 | F24: 100.31 | G24: 110.71 | H24: 122.24 | I24: 150.25 | J24: 179.77 | K24: 236.13
A25: Other Income | B25: 44.16 | C25: 83.41 | D25: 89.96 | E25: 173.37 | F25: 324.67 | G25: 170.78 | H25: 142.19 | I25: 180.54 | J25: 535.26 | K25: 556.57
A26: Depreciation | B26: 299.37 | C26: 301.2 | D26: 327.85 | E26: 404.24 | F26: 409.63 | G26: 406.05 | H26: 416.06 | I26: 454.3 | J26: 518.16 | K26: 605.16
A27: Interest | B27: 323.83 | C27: 269.04 | D27: 190.13 | E27: 341.12 | F27: 402.82 | G27: 427.66 | H27: 236.05 | I27: 220.22 | J27: 208.38 | K27: 221.35
A28: Profit before tax | B28: 30.58 | C28: 184.29 | D28: 401.71 | E28: 395.54 | F28: -849.54 | G28: -258.18 | H28: 1294.64 | I28: 1665.53 | J28: 2578.05 | K28: 2925.86
A29: Tax | B29: 113.74 | C29: 121.06 | D29: 157.12 | E29: 44.77 | F29: -155.33 | G29: -35.78 | H29: 323.21 | I29: 463.94 | J29: 616.8 | K29: 730.72
A30: Net profit | B30: -63.2 | C30: 100.87 | D30: 286.82 | E30: 354.42 | F30: -720.11 | G30: -247.72 | H30: 1002.59 | I30: 1259.07 | J30: 1907.59 | K30: 2084.38
A31: Dividend Amount | B31: 34.63 | C31: 47.57 | D31: 59.46 | E31: 59.46 | F31: 47.57 | G31: 56.82 | H31: 142.04 | I31: 249.1 | J31: 320.26 | K31: 462.6
A40: Quarters
A41: Report Date | B41: 45382 | C41: 45473 | D41: 45565 | E41: 45657 | F41: 45747 | G41: 45838 | H41: 45930 | I41: 46022 | J41: 46112 | K41: 46203
A42: Sales | B42: 1905.34 | C42: 1550.23 | D42: 1826.12 | E42: 2533.05 | F42: 2425.14 | G42: 2041.08 | H42: 2040.89 | I42: 2841.96 | J42: 2765.29 | K42: 2339.19
A43: Expenses | B43: 1245.54 | C43: 1100.63 | D43: 1324.85 | E43: 1571.37 | F43: 1568.36 | G43: 1465.05 | H43: 1470.77 | I43: 1766.14 | J43: 1792.61 | K43: 1666.48
A44: Other Income | B44: 46.12 | C44: 46.04 | D44: 371.46 | E44: 58.68 | F44: 59.08 | G44: 61.09 | H44: 83.36 | I44: 333.78 | J44: 79.49 | K44: 80.18
A45: Depreciation | B45: 119.73 | C45: 117.29 | D45: 124.93 | E45: 133.94 | F45: 142 | G45: 142.75 | H45: 144.72 | I45: 150.32 | J45: 167.37 | K45: 162.58
A46: Interest | B46: 51.5 | C46: 49.86 | D46: 52.23 | E46: 52.39 | F46: 53.9 | G46: 54.55 | H46: 56.05 | I46: 55.82 | J46: 54.93 | K46: 56.98
A47: Profit before tax | B47: 534.69 | C47: 328.49 | D47: 695.57 | E47: 834.03 | F47: 719.96 | G47: 439.82 | H47: 452.71 | I47: 1203.46 | J47: 829.87 | K47: 533.33
A48: Tax | B48: 141.6 | C48: 94.28 | D48: 122.36 | E48: 220.21 | F48: 179.95 | G48: 120.4 | H48: 136.53 | I48: 269.14 | J48: 204.65 | K48: 142.4
A49: Net profit | B49: 417.76 | C49: 248.39 | D49: 554.58 | E49: 582.32 | F49: 522.3 | G49: 296.37 | H49: 284.92 | I49: 903.23 | J49: 599.86 | K49: 357.9
A50: Operating Profit | B50: 659.8 | C50: 449.6 | D50: 501.27 | E50: 961.68 | F50: 856.78 | G50: 576.03 | H50: 570.12 | I50: 1075.82 | J50: 972.68 | K50: 672.71
A55: BALANCE SHEET
A56: Report Date | B56: 42825 | C56: 43190 | D56: 43555 | E56: 43921 | F56: 44286 | G56: 44651 | H56: 45016 | I56: 45382 | J56: 45747 | K56: 46112
A57: Equity Share Capital | B57: 98.93 | C57: 118.93 | D57: 118.93 | E57: 118.93 | F57: 118.93 | G57: 142.04 | H57: 142.04 | I57: 142.34 | J57: 142.34 | K57: 142.34
A58: Reserves | B58: 2418.76 | C58: 4062.17 | D58: 4229.07 | E58: 4237.88 | F58: 3529.51 | G58: 6920.21 | H58: 7839.92 | I58: 9314.31 | J58: 11018.37 | K58: 12909.95
A59: Borrowings | B59: 3382.98 | C59: 2427.43 | D59: 2325.98 | E59: 4500.78 | F59: 5518.33 | G59: 3887.87 | H59: 3139.01 | I59: 2736.23 | J59: 3084.27 | K59: 2836.55
A60: Other Liabilities | B60: 2698.4 | C60: 2705.87 | D60: 2840.34 | E60: 2584.17 | F60: 2267.89 | G60: 2051.92 | H60: 2391.07 | I60: 2540.54 | J60: 3371 | K60: 4331.88
A61: Total | B61: 8599.07 | C61: 9314.4 | D61: 9514.32 | E61: 11441.76 | F61: 11434.66 | G61: 13002.04 | H61: 13512.04 | I61: 14733.42 | J61: 17615.98 | K61: 20220.72
A62: Net Block | B62: 5815.39 | C62: 6162.63 | D62: 6422.25 | E62: 8058.85 | F62: 8437.7 | G62: 8415.34 | H62: 8818.53 | I62: 9311.34 | J62: 10918.18 | K62: 12210.06
A63: Capital Work in Progress | B63: 222.67 | C63: 196.98 | D63: 116.18 | E63: 244.08 | F63: 164.99 | G63: 193.54 | H63: 332.05 | I63: 255.52 | J63: 632.57 | K63: 787.31
A64: Investments | B64: 1243.71 | C64: 1511.42 | D64: 1335.14 | E64: 1426.59 | F64: 1483.17 | G64: 1966.8 | H64: 1891.04 | I64: 2261.2 | J64: 2278.76 | K64: 3606.43
A65: Other Assets | B65: 1317.3 | C65: 1443.37 | D65: 1640.75 | E65: 1712.24 | F65: 1348.8 | G65: 2426.36 | H65: 2470.42 | I65: 2905.36 | J65: 3786.47 | K65: 3616.92
A66: Total | B66: 8599.07 | C66: 9314.4 | D66: 9514.32 | E66: 11441.76 | F66: 11434.66 | G66: 13002.04 | H66: 13512.04 | I66: 14733.42 | J66: 17615.98 | K66: 20220.72
A67: Receivables | B67: 272.06 | C67: 328.56 | D67: 321.38 | E67: 290.02 | F67: 219.84 | G67: 255.34 | H67: 446.45 | I67: 476.46 | J67: 650.88 | K67: 726.82
... A70: No. of Equity Shares | B70: 989274015 | C70: 1189258445 | D70: 1189258445 | E70: 1189258445 | F70: 1189258445 | G70: 1420457199 | H70: 1420400342 | I70: 1423432227 | J70: 1423432227 | K70: 1423432227
A71: New Bonus Shares
A72: Face value | B72: 1 | C72: 1 | D72: 1 | E72: 1 | F72: 1 | G72: 1 | H72: 1 | I72: 1 | J72: 1 | K72: 1
A80: CASH FLOW:
A81: Report Date | B81: 42825 | C81: 43190 | D81: 43555 | E81: 43921 | F81: 44286 | G81: 44651 | H81: 45016 | I81: 45382 | J81: 45747 | K81: 46112
A82: Cash from Operating Activity | B82: 534.51 | C82: 492.05 | D82: 711.43 | E82: 823.47 | F82: -318.69 | G82: 671.63 | H82: 1618.99 | I82: 1935.14 | J82: 2194.37 | K82: 2471.41
A83: Cash from Investing Activity | B83: 848.32 | C83: -521.24 | D83: -386.72 | E83: -496.56 | F83: -118.23 | G83: -1641.15 | H83: -138.28 | I83: -1207.54 | J83: -1869.46 | K83: -1345.68
A84: Cash from Financing Activity | B84: -1381.36 | C84: 95.72 | D84: -343.26 | E84: -265.38 | F84: 280.37 | G84: 1658.78 | H84: -1527.85 | I84: -984.65 | J84: -547.34 | K84: -976.31
A85: Net Cash Flow | B85: 1.47 | C85: 66.53 | D85: -18.55 | E85: 61.53 | F85: -156.55 | G85: 689.26 | H85: -47.14 | I85: -257.05 | J85: -222.43 | K85: 149.42
A90: PRICE: | B90: 115.16 | C90: 125.48 | D90: 150.2 | E90: 72.73 | F90: 107.49 | G90: 238.5 | H90: 324.35 | I90: 591.15 | J90: 787.55 | K90: 570.95
A92: DERIVED:
A93: Adjusted Equity Shares in Cr | B93: 131.9 | C93: 132.14 | D93: 132.14 | E93: 132.14 | F93: 132.14 | G93: 142.04 | H93: 142.04 | I93: 142.34 | J93: 142.34 | K93: 142.34
A95: EV/EBITDA | E95: =DCF!$C$27/'Historicial Financials'!C19 -> 50.320135 | F95: =DCF!$C$27/'Historicial Financials'!D19 -> -134.5816 | G95: =DCF!$C$27/'Historicial Financials'!E19 -> 120.28719 | H95: =DCF!$C$27/'Historicial Financials'!F19 -> 26.979563 | I95: =DCF!$C$27/'Historicial Financials'!G19 -> 22.54504 | J95: =DCF!$C$27/'Historicial Financials'!H19 -> 17.580512 | K95: =DCF!$C$27/'Historicial Financials'!I19 -> 15.234445
A96: EV/Sales | E96: =DCF!$C$27/'Data Sheet'!E17 -> 10.908517 | F96: =DCF!$C$27/'Data Sheet'!F17 -> 30.908758 | G96: =DCF!$C$27/'Data Sheet'!G17 -> 15.930214 | H96: =DCF!$C$27/'Data Sheet'!H17 -> 8.3798613 | I96: =DCF!$C$27/'Data Sheet'!I17 -> 7.1927963 | J96: =DCF!$C$27/'Data Sheet'!J17 -> 5.841503 | K96: =DCF!$C$27/'Data Sheet'!K17 -> 5.0247842
A97: Book Value | E97: =SUM(E57:E58) -> 4356.81 | F97: =SUM(F57:F58) -> 3648.44 | G97: =SUM(G57:G58) -> 7062.25 | H97: =SUM(H57:H58) -> 7981.96 | I97: =SUM(I57:I58) -> 9456.65 | J97: =SUM(J57:J58) -> 11160.71 | K97: =SUM(K57:K58) -> 13052.29
A98: Price to Book | E98: =E90/E97 -> 0.016693406 | F98: =F90/F97 -> 0.029461907 | G98: =G90/G97 -> 0.033771107 | H98: =H90/H97 -> 0.040635383 | I98: =I90/I97 -> 0.062511566 | J98: =J90/J97 -> 0.070564507 | K98: =K90/K97 -> 0.043743282

Sheet Profit and Loss
A1: ='[1]Data Sheet'!B1 -> AVENUE SUPERMARTS LTD | H1: =UPDATE | M1: SCREENER.IN
A3: Narration | B3: ='[1]Data Sheet'!B16 -> 42825 | C3: ='[1]Data Sheet'!C16 -> 43190 | D3: ='[1]Data Sheet'!D16 -> 43555 | E3: ='[1]Data Sheet'!E16 -> 43921 | F3: ='[1]Data Sheet'!F16 -> 44286 | G3: ='[1]Data Sheet'!G16 -> 44651 | H3: ='[1]Data Sheet'!H16 -> 45016 | I3: ='[1]Data Sheet'!I16 -> 45382 | ... K3: ='[1]Data Sheet'!K16 -> 46112 | L3: Trailing | M3: Best Case | N3: Worst Case
A4: Sales | B4: ='[1]Data Sheet'!B17 -> 11897.7 | C4: ='[1]Data Sheet'!C17 -> 15033.2 | D4: ='[1]Data Sheet'!D17 -> 20004.52 | E4: ='[1]Data Sheet'!E17 -> 24870.2 | F4: ='[1]Data Sheet'!F17 -> 24143.06 | G4: ='[1]Data Sheet'!G17 -> 30976.27 | H4: ='[1]Data Sheet'!H17 -> 42839.56 | I4: ='[1]Data Sheet'!I17 -> 50788.83 | ... K4: ='[1]Data Sheet'!K17 -> 68820.74 | L4: =SUM([1]Quarters!H4:K4) -> 71255.57 | M4: =$K4+M23*K4 -> 80601.684 | N4: =$K4+N23*L4 -> 80180.098
A5: Expenses | B5: =SUM('[1]Data Sheet'!B18,'[1]Data Sheet'!B20:B24, -1*'[1]Data Sheet'!B19) -> 10928.52 | C5: =SUM('[1]Data Sheet'!C18,'[1]Data Sheet'!C20:C24, -1*'[1]Data Sheet'!C19) -> 13680.34 | D5: =SUM('[1]Data Sheet'!D18,'[1]Data Sheet'!D20:D24, -1*'[1]Data Sheet'!D19) -> 18371.21 | E5: =SUM('[1]Data Sheet'!E18,'[1]Data Sheet'!E20:E24, -1*'[1]Data Sheet'!E19) -> 22741.89 | F5: =SUM('[1]Data Sheet'!F18,'[1]Data Sheet'!F20:F24, -1*'[1]Data Sheet'!F19) -> 22398.23 | G5: =SUM('[1]Data Sheet'!G18,'[1]Data Sheet'!G20:G24, -1*'[1]Data Sheet'!G19) -> 28473.92 | H5: =SUM('[1]Data Sheet'!H18,'[1]Data Sheet'!H20:H24, -1*'[1]Data Sheet'!H19) -> 39200.79 | I5: =SUM('[1]Data Sheet'!I18,'[1]Data Sheet'!I20:I24, -1*'[1]Data Sheet'!I19) -> 46683.19 | ... K5: =SUM('[1]Data Sheet'!K18,'[1]Data Sheet'!K20:K24, -1*'[1]Data Sheet'!K19) -> 63631.95 | L5: =SUM([1]Quarters!H5:K5) -> 65868.68 | M5: =M4-M6 -> 74391.556 | N5: =N4-N6 -> 74118.518
A6: Operating Profit | B6: =B4-B5 -> 969.18 | C6: =C4-C5 -> 1352.86 | D6: =D4-D5 -> 1633.31 | E6: =E4-E5 -> 2128.31 | F6: =F4-F5 -> 1744.83 | G6: =G4-G5 -> 2502.35 | H6: =H4-H5 -> 3638.77 | I6: =I4-I5 -> 4105.64 | ... K6: =K4-K5 -> 5188.79 | L6: =SUM([1]Quarters!H6:K6) -> 5386.89 | M6: =M4*M24 -> 6210.1278 | N6: =N4*N24 -> 6061.5805
A7: Other Income | B7: ='[1]Data Sheet'!B25 -> 27.7 | C7: ='[1]Data Sheet'!C25 -> 87.75 | D7: ='[1]Data Sheet'!D25 -> 48.33 | E7: ='[1]Data Sheet'!E25 -> 59.99 | F7: ='[1]Data Sheet'!F25 -> 194.43 | G7: ='[1]Data Sheet'!G25 -> 113.64 | H7: ='[1]Data Sheet'!H25 -> 127.6 | I7: ='[1]Data Sheet'!I25 -> 144.58 | ... K7: ='[1]Data Sheet'!K25 -> 71.9 | L7: =SUM([1]Quarters!H7:K7) -> 80.45 | M7: 0 | N7: 0
A8: Depreciation | B8: ='[1]Data Sheet'!B26 -> 127.82 | C8: ='[1]Data Sheet'!C26 -> 159 | D8: ='[1]Data Sheet'!D26 -> 212.49 | E8: ='[1]Data Sheet'!E26 -> 374.41 | F8: ='[1]Data Sheet'!F26 -> 414.16 | G8: ='[1]Data Sheet'!G26 -> 498.08 | H8: ='[1]Data Sheet'!H26 -> 638.87 | I8: ='[1]Data Sheet'!I26 -> 730.76 | ... K8: ='[1]Data Sheet'!K26 -> 1037.02 | L8: =SUM([1]Quarters!H8:K8) -> 1093.02 | M8: =+$L8 -> 1093.02 | N8: =+$L8 -> 1093.02
A9: Interest | B9: ='[1]Data Sheet'!B27 -> 121.98 | C9: ='[1]Data Sheet'!C27 -> 59.54 | D9: ='[1]Data Sheet'!D27 -> 47.21 | E9: ='[1]Data Sheet'!E27 -> 69.12 | F9: ='[1]Data Sheet'!F27 -> 41.65 | G9: ='[1]Data Sheet'!G27 -> 53.79 | H9: ='[1]Data Sheet'!H27 -> 67.41 | I9: ='[1]Data Sheet'!I27 -> 58.13 | ... K9: ='[1]Data Sheet'!K27 -> 142.05 | L9: =SUM([1]Quarters!H9:K9) -> 167.03 | M9: =+$L9 -> 167.03 | N9: =+$L9 -> 167.03
A10: Profit before tax | B10: ='[1]Data Sheet'!B28 -> 747.08 | C10: ='[1]Data Sheet'!C28 -> 1222.07 | D10: ='[1]Data Sheet'!D28 -> 1421.94 | E10: ='[1]Data Sheet'!E28 -> 1744.77 | F10: ='[1]Data Sheet'!F28 -> 1483.45 | G10: ='[1]Data Sheet'!G28 -> 2064.12 | H10: ='[1]Data Sheet'!H28 -> 3060.09 | I10: ='[1]Data Sheet'!I28 -> 3461.33 | ... K10: ='[1]Data Sheet'!K28 -> 4081.62 | L10: =SUM([1]Quarters!H10:K10) -> 4207.29 | M10: =M6+M7-SUM(M8:M9) -> 4950.0778 | N10: =N6+N7-SUM(N8:N9) -> 4801.5305
A11: Tax | B11: ='[1]Data Sheet'!B29 -> 268.28 | C11: ='[1]Data Sheet'!C29 -> 415.79 | D11: ='[1]Data Sheet'!D29 -> 519.48 | E11: ='[1]Data Sheet'!E29 -> 443.79 | F11: ='[1]Data Sheet'!F29 -> 384.02 | G11: ='[1]Data Sheet'!G29 -> 571.72 | H11: ='[1]Data Sheet'!H29 -> 681.75 | I11: ='[1]Data Sheet'!I29 -> 925.72 | ... K11: ='[1]Data Sheet'!K29 -> 1111.76 | L11: =SUM([1]Quarters!H11:K11) -> 1149.8 | M11: =IF($L10>0,$L11/$L10,0) -> 0.27328756 | N11: =IF($L10>0,$L11/$L10,0) -> 0.27328756
A12: Net profit | B12: ='[1]Data Sheet'!B30 -> 478.75 | C12: ='[1]Data Sheet'!C30 -> 806.26 | D12: ='[1]Data Sheet'!D30 -> 902.54 | E12: ='[1]Data Sheet'!E30 -> 1301.08 | F12: ='[1]Data Sheet'!F30 -> 1099.49 | G12: ='[1]Data Sheet'!G30 -> 1492.55 | H12: ='[1]Data Sheet'!H30 -> 2378.51 | I12: ='[1]Data Sheet'!I30 -> 2536.17 | ... K12: ='[1]Data Sheet'!K30 -> 2970.49 | L12: =SUM([1]Quarters!H12:K12) -> 3058.13 | M12: =M10-M11*M10 -> 3597.2831 | N12: =N10-N11*N10 -> 3489.3319
A13: EPS | B13: =IF('[1]Data Sheet'!B93>0,B12/'[1]Data Sheet'!B93,0) -> 7.6710463 | C13: =IF('[1]Data Sheet'!C93>0,C12/'[1]Data Sheet'!C93,0) -> 12.918763 | D13: =IF('[1]Data Sheet'!D93>0,D12/'[1]Data Sheet'!D93,0) -> 14.461465 | E13: =IF('[1]Data Sheet'!E93>0,E12/'[1]Data Sheet'!E93,0) -> 20.084594 | F13: =IF('[1]Data Sheet'!F93>0,F12/'[1]Data Sheet'!F93,0) -> 16.972677 | G13: =IF('[1]Data Sheet'!G93>0,G12/'[1]Data Sheet'!G93,0) -> 23.04029 | H13: =IF('[1]Data Sheet'!H93>0,H12/'[1]Data Sheet'!H93,0) -> 36.688416 | I13: =IF('[1]Data Sheet'!I93>0,I12/'[1]Data Sheet'!I93,0) -> 38.976026 | ... K13: =IF('[1]Data Sheet'!K93>0,K12/'[1]Data Sheet'!K93,0) -> 45.559663 | L13: =IF('[1]Data Sheet'!$B6>0,'[1]Profit & Loss'!L12/'[1]Data Sheet'!$B6,0) -> 46.886146 | M13: =IF('[1]Data Sheet'!$B6>0,'[1]Profit & Loss'!M12/'[1]Data Sheet'!$B6,0) -> 55.152247 | N13: =IF('[1]Data Sheet'!$B6>0,'[1]Profit & Loss'!N12/'[1]Data Sheet'!$B6,0) -> 53.497179
A14: Price to earning | B14: =IF(B15>0,B15/B13,"") -> 83.150326 | C14: =IF(C15>0,C15/C13,"") -> 102.54852 | D14: =IF(D15>0,D15/D13,"") -> 101.72552 | E14: =IF(E15>0,E15/E13,"") -> 108.91433 | F14: =IF(F15>0,F15/F13,"") -> 168.45015 | G14: =IF(G15>0,G15/G13,"") -> 173.75432 | H14: =IF(H15>0,H15/H13,"") -> 92.700923 | I14: =IF(I15>0,I15/I13,"") -> 116.1124 | ... K14: =IF(K15>0,K15/K13,"") -> 86.848756 | L14: =IF(L13>0,L15/L13,0) -> 81.324662 | M14: =M25 -> 95.599877 | N14: =N25 -> 81.324662
A15: Price | B15: ='[1]Data Sheet'!B90 -> 637.85 | C15: ='[1]Data Sheet'!C90 -> 1324.8 | D15: ='[1]Data Sheet'!D90 -> 1471.1 | E15: ='[1]Data Sheet'!E90 -> 2187.5 | F15: ='[1]Data Sheet'!F90 -> 2859.05 | G15: ='[1]Data Sheet'!G90 -> 4003.35 | H15: ='[1]Data Sheet'!H90 -> 3401.05 | I15: ='[1]Data Sheet'!I90 -> 4525.6 | ... K15: ='[1]Data Sheet'!K90 -> 3956.8 | L15: ='[1]Data Sheet'!B8 -> 3813 | M15: =M13*M14 -> 5272.548 | N15: =N13*N14 -> 4350.64
A17: RATIOS:
A18: Dividend Payout | B18: =IF('[1]Data Sheet'!B30>0, '[1]Data Sheet'!B31/'[1]Data Sheet'!B30, 0) -> 0 | C18: =IF('[1]Data Sheet'!C30>0, '[1]Data Sheet'!C31/'[1]Data Sheet'!C30, 0) -> 0 | D18: =IF('[1]Data Sheet'!D30>0, '[1]Data Sheet'!D31/'[1]Data Sheet'!D30, 0) -> 0 | E18: =IF('[1]Data Sheet'!E30>0, '[1]Data Sheet'!E31/'[1]Data Sheet'!E30, 0) -> 0 | F18: =IF('[1]Data Sheet'!F30>0, '[1]Data Sheet'!F31/'[1]Data Sheet'!F30, 0) -> 0 | G18: =IF('[1]Data Sheet'!G30>0, '[1]Data Sheet'!G31/'[1]Data Sheet'!G30, 0) -> 0 | H18: =IF('[1]Data Sheet'!H30>0, '[1]Data Sheet'!H31/'[1]Data Sheet'!H30, 0) -> 0 | I18: =IF('[1]Data Sheet'!I30>0, '[1]Data Sheet'!I31/'[1]Data Sheet'!I30, 0) -> 0 | ... K18: =IF('[1]Data Sheet'!K30>0, '[1]Data Sheet'!K31/'[1]Data Sheet'!K30, 0) -> 0
A19: OPM | B19: =IF(B6>0,B6/B4,0) -> 0.081459442 | C19: =IF(C6>0,C6/C4,0) -> 0.089991486 | D19: =IF(D6>0,D6/D4,0) -> 0.081647048 | E19: =IF(E6>0,E6/E4,0) -> 0.085576714 | F19: =IF(F6>0,F6/F4,0) -> 0.072270458 | G19: =IF(G6>0,G6/G4,0) -> 0.080782806 | H19: =IF(H6>0,H6/H4,0) -> 0.084939481 | I19: =IF(I6>0,I6/I4,0) -> 0.08083746 | ... L19: =IF(L6>0,L6/L4,0) -> 0.075599564
G22: TRENDS: | H22: 10 YEARS | I22: 7 YEARS | J22: 5 YEARS | K22: 3 YEARS | L22: RECENT | M22: BEST | N22: WORST
G23: Sales Growth | H23: =IF(B4=0,"",POWER($K4/B4,1/9)-1) -> 0.2153326 | I23: =IF(D4=0,"",POWER($K4/D4,1/7)-1) -> 0.19304242 | J23: =IF(F4=0,"",POWER($K4/F4,1/5)-1) -> 0.23306339 | K23: =IF(H4=0,"",POWER($K4/H4, 1/3)-1) -> 0.17118305 | L23: =IF(ISERROR(MAX(IF(J4=0,"",(K4-J4)/J4),IF(K4=0,"",(L4-K4)/K4))),"",MAX(IF(J4=0,"",(K4-J4)/J4),IF(K4=0,"",(L4-K4)/K4))) -> 0.15941713 | M23: =MAX(K23:L23) -> 0.17118305 | N23: =MIN(H23:L23) -> 0.15941713
G24: OPM | H24: =IF(SUM(B4:$K$4)=0,"",SUMPRODUCT(B19:$K$19,B4:$K$4)/SUM(B4:$K$4)) -> 0.079598487 | I24: =IF(SUM(E4:$K$4)=0,"",SUMPRODUCT(E19:$K$19,E4:$K$4)/SUM(E4:$K$4)) -> 0.078871635 | J24: =IF(SUM(G4:$K$4)=0,"",SUMPRODUCT(G19:$K$19,G4:$K$4)/SUM(G4:$K$4)) -> 0.078842424 | K24: =IF(SUM(I4:$K$4)=0, "", SUMPRODUCT(I19:$K$19,I4:$K$4)/SUM(I4:$K$4)) -> 0.077047122 | L24: =L19 -> 0.075599564 | M24: =MAX(K24:L24) -> 0.077047122 | N24: =MIN(H24:L24) -> 0.075599564
G25: Price to Earning | H25: =IF(ISERROR(AVERAGEIF(B14:$L14,">0")),"",AVERAGEIF(B14:$L14,">0")) -> 110.33124 | I25: =IF(ISERROR(AVERAGEIF(E14:$L14,">0")),"",AVERAGEIF(E14:$L14,">0")) -> 115.7774 | J25: =IF(ISERROR(AVERAGEIF(G14:$L14,">0")),"",AVERAGEIF(G14:$L14,">0")) -> 108.14246 | K25: =IF(ISERROR(AVERAGEIF(I14:$L14,">0")),"",AVERAGEIF(I14:$L14,">0")) -> 95.599877 | L25: =L14 -> 81.324662 | M25: =MAX(K25:L25) -> 95.599877 | N25: =MIN(H25:L25) -> 81.324662

Sheet Data for IG
B3: Particulars | C3: 43891 | D3: 44256 | E3: 44621 | F3: 44986 | G3: 45352 | H3: 45717 | I3: 46082
B4: Equity Capital | C4: 648 | D4: 648 | E4: 648 | F4: 648 | G4: 651 | H4: 651 | I4: 652
B5: Reserves | C5: 10432 | D5: 11536 | E5: 13030 | F5: 15430 | G5: 18047 | H5: 20777 | I5: 23812
B6: Borrowings -
B7: Long term Borrowings | C7: 2126 | D7: 2224 | E7: 1388 | F7: 331 | G7: 47 | H7: 203 | I7: 47
B8: Short term Borrowings | C8: 166 | D8: 1409 | E8: 597 | F8: 487 | G8: 214 | H8: 22 | I8: 5
B9: Lease Liabilities | C9: 1899 | D9: 1885 | E9: 1903 | F9: 2321 | G9: 2476 | H9: 2860 | I9: 2785
B10: Other Borrowings | C10: 310 | D10: 0 | E10: 0 | F10: 0 | G10: 0 | H10: 0 | I10: 0
B11: Other Liabilities -
B12: Non controlling int | C12: 765 | D12: 635 | E12: 593 | F12: 660 | G12: 672 | H12: 1255 | I12: 1887
B13: Trade Payables | C13: 389 | D13: 318 | E13: 387 | F13: 477 | G13: 519 | H13: 578 | I13: 720
B14: Advance from Customers | C14: 124 | D14: 144 | E14: 183 | F14: 224 | G14: 252 | H14: 298 | I14: 317
B15: Other liability items | C15: 1306 | D15: 1172 | E15: 889 | F15: 1030 | G15: 1098 | H15: 1240 | I15: 1408
B16: Total Liabilities | C16: =SUM(C7:C10,C12:C15) -> 7085 | D16: =SUM(D7:D10,D12:D15) -> 7787 | E16: =SUM(E7:E10,E12:E15) -> 5940 | F16: =SUM(F7:F10,F12:F15) -> 5530 | G16: =SUM(G7:G10,G12:G15) -> 5278 | H16: =SUM(H7:H10,H12:H15) -> 6456 | I16: =SUM(I7:I10,I12:I15) -> 7169
B18: Fixed Assets -
B19: Land | C19: 460 | D19: 552 | E19: 569 | F19: 836 | G19: 871 | H19: 1482 | I19: 1410
B20: Building | C20: 5634 | D20: 6218 | E20: 6464 | F20: 6779 | G20: 7276 | H20: 8298 | I20: 9247
B21: Plant Machinery | C21: 1402 | D21: 1527 | E21: 1574 | F21: 1683 | G21: 1947 | H21: 2249 | I21: 2620
B22: Equipments | C22: 88 | D22: 93 | E22: 101 | F22: 106 | G22: 119 | H22: 139 | I22: 159
B23: Furniture n fittings | C23: 671 | D23: 743 | E23: 792 | F23: 856 | G23: 970 | H23: 1111 | I23: 1272
B24: Vehicles | C24: 14 | D24: 14 | E24: 15 | F24: 16 | G24: 16 | H24: 89 | I24: 102
B25: Intangible Assets | C25: 1259 | D25: 1255 | E25: 1269 | F25: 1306 | G25: 1317 | H25: 1366 | I25: 1891
B26: Other fixed assets | C26: 80 | D26: 84 | E26: 86 | F26: 94 | G26: 97 | H26: 161 | I26: 226
B27: Gross Block | C27: =SUM(C19:C26) -> 9608 | D27: =SUM(D19:D26) -> 10486 | E27: =SUM(E19:E26) -> 10870 | F27: =SUM(F19:F26) -> 11676 | G27: =SUM(G19:G26) -> 12613 | H27: =SUM(H19:H26) -> 14895 | I27: =SUM(I19:I26) -> 16927
B28: Accumulated Depreciation | C28: 1550 | D28: 2048 | E28: 2454 | F28: 2856 | G28: 3302 | H28: 3977 | I28: 4717
B29: Net Block | C29: =C27-C28 -> 8058 | D29: =D27-D28 -> 8438 | E29: =E27-E28 -> 8416 | F29: =F27-F28 -> 8820 | G29: =G27-G28 -> 9311 | H29: =H27-H28 -> 10918 | I29: =I27-I28 -> 12210
B31: CWIP | C31: 244 | D31: 165 | E31: 194 | F31: 332 | G31: 256 | H31: 633 | I31: 787
B32: Investments | C32: 1427 | D32: 1483 | E32: 1967 | F32: 1891 | G32: 2261 | H32: 2279 | I32: 3606
B34: Other Assets -
B35: Inventories | C35: 94 | D35: 93 | E35: 101 | F35: 109 | G35: 116 | H35: 135 | I35: 150
B36: Trade receivables | C36: 290 | D36: 220 | E36: 255 | F36: 446 | G36: 476 | H36: 651 | I36: 727
B37: Cash Equivalents | C37: 316 | D37: 154 | E37: 1188 | F37: 1053 | G37: 1486 | H37: 2182 | I37: 1831
B38: Loans n Advances | C38: 134 | D38: 144 | E38: 138 | F38: 144 | G38: 173 | H38: 176 | I38: 218
B39: Other asset items | C39: 879 | D39: 738 | E39: 744 | F39: 717 | G39: 654 | H39: 643 | I39: 691
B40: Total Assets | C40: 11442 | D40: 11435 | E40: 13002 | F40: 13512 | G40: 14733 | H40: 17616 | I40: 20221

Sheet Cashflow
C1: 43891 | D1: 44256 | E1: 44621 | F1: 44986 | G1: 45352 | H1: 45717 | I1: 46082
B2: Cash from Operating Activity - | K2: 823 | L2: -319 | M2: 672 | N2: 1619 | O2: 1935 | P2: 2194 | Q2: 2471
B3: Profit from operations | C3: 1006 | D3: -265 | E3: 495 | F3: 1845 | G3: 2208 | H3: 2829 | I3: 3201
B4: Receivables | C4: 0 | D4: 0 | E4: 0 | F4: 0 | G4: 0 | H4: -82 | I4: -146
B5: Inventory | C5: -13 | D5: 12 | E5: -8 | F5: -8 | G5: -7 | H5: -7 | I5: -10
B6: Payables | C6: 0 | D6: 0 | E6: 0 | F6: 0 | G6: 0 | H6: 36 | I6: 92
B7: Other WC items | C7: 37 | D7: -88 | E7: 129 | F7: 32 | G7: 43 | H7: 0 | I7: 0
B8: Working capital changes | C8: 23 | D8: -77 | E8: 121 | F8: 24 | G8: 36 | H8: -53 | I8: -63
B9: Direct taxes | C9: -206 | D9: 23 | E9: 55 | F9: -250 | G9: -309 | H9: -581 | I9: -667
B10: Cash from Investing Activity - | K10: -497 | L10: -118 | M10: -1641 | N10: -138 | O10: -1208 | P10: -1869 | Q10: -1346
B11: Fixed assets purchased | C11: -487 | D11: -215 | E11: -318 | F11: -471 | G11: -637 | H11: -1074 | I11: -1037
B12: Fixed assets sold | C12: 175 | D12: 28 | E12: 33 | F12: 43 | G12: 4 | H12: 12 | I12: 9
B13: Investments purchased | C13: -1938 | D13: -1512 | E13: -2339 | F13: -2069 | G13: -2525 | H13: -3156 | I13: -5438
B14: Investments sold | C14: 1712 | D14: 1591 | E14: 1893 | F14: 2250 | G14: 2597 | H14: 3037 | I14: 4568
B15: Subsidy received | C15: 0 | D15: 0 | E15: 0 | F15: 0 | G15: 0 | H15: 5 | I15: 0
B16: Interest received | C16: 16 | D16: 18 | E16: 12 | F16: 30 | G16: 53 | H16: 109 | I16: 107
B17: Dividends received | C17: 14 | D17: 7 | E17: 8 | F17: 5 | G17: 27 | H17: 44 | I17: 45
B18: Investment in group cos | C18: 0 | D18: -73 | E18: -544 | F18: 0 | G18: 0 | H18: 0 | I18: 0
B19: Redemp n Canc of Shares | C19: 30 | D19: 0 | E19: 0 | F19: 0 | G19: 0 | H19: 0 | I19: 0
B20: Acquisition of companies | C20: 0 | D20: 0 | E20: 0 | F20: 0 | G20: 0 | H20: -18 | I20: -412
B21: Other investing items | C21: -18 | D21: 39 | E21: -385 | F21: 73 | G21: -727 | H21: -829 | I21: 811
B22: Cash from Financing Activity - | L22: -265 | M22: 280 | N22: 1659 | O22: -1528 | P22: -985 | Q22: -547 | R22: -976
B23: Proceeds from shares | C23: 0 | D23: 0 | E23: 3982 | F23: 1 | G23: 6 | H23: 0 | I23: 0
B24: Redemption of debentures | C24: 0 | D24: 0 | E24: 0 | F24: 0 | G24: 0 | H24: 0 | I24: 0
B25: Proceeds from borrowings | C25: 1015 | D25: 1141 | E25: 1520 | F25: 59 | G25: 138 | H25: 275 | I25: 99
B26: Repayment of borrowings | C26: -793 | D26: -428 | E26: -3176 | F26: -1253 | G26: -709 | H26: -325 | I26: -461
B27: Interest paid fin | C27: -155 | D27: -232 | E27: -281 | F27: -83 | G27: -67 | H27: -27 | I27: -22
B28: Dividends paid | C28: -76 | D28: -60 | E28: -52 | F28: -64 | G28: -155 | H28: -252 | I28: -342
B29: Financial liabilities | C29: -136 | D29: -139 | E29: -151 | F29: -187 | G29: -198 | H29: -218 | I29: -263
B30: Other financing items | C30: -121 | D30: -1 | E30: -184 | F30: -1 | G30: 0 | H30: 0 | I30: 13
B31: Net Cash Flow | C31: 62 | D31: -157 | E31: 689 | F31: -47 | G31: -257 | H31: -222 | I31: 149

Sheet Data_Relative Comps
B1: S.No. | C1: Company | D1: CMP Rs. | E1: No. Eq. Shares Cr. | F1: Mar Cap Rs.Cr. | G1: Debt Rs.Cr. | H1: Cash End Rs.Cr. | I1: Net Debt | J1: EV Rs.Cr. | K1: Sales Rs.Cr. | L1: NP 12M Rs.Cr.
B2: 1 | C2: Indian Hotels Co | D2: 718 | E2: 142.34 | F2: 102202.43 | G2: 2836.55 | H2: 1831.19 | I2: =G2-H2 -> 1005.36 | J2: 103207.79 | K2: 9987.33 | L2: 2308.74
B3: 2 | C3: ITC Hotels | D3: 158.51 | E3: 208.31 | F3: 33018.65 | G3: 74.19 | H3: 765.36 | I3: =G3-H3 -> -691.17 | J3: 32327.48 | K3: 4259.88 | L3: 869.46
B4: 3 | C4: Leela Palaces Hotels | D4: 568.95 | E4: 33.4 | F4: 19000.53 | G4: 1810.95 | H4: 285.57 | I4: =G4-H4 -> 1525.38 | J4: 20525.91 | K4: 1604.46 | L4: 443.09
B5: 4 | C5: EIH | D5: 297.85 | E5: 62.54 | F5: 18626.47 | G5: 252.42 | H5: 933.96 | I5: =G5-H5 -> -681.54 | J5: 17944.93 | K5: 3023.01 | L5: 740.72
B6: 5 | C6: Chalet Hotels | D6: 830.25 | E6: 21.9 | F6: 18181.99 | G6: 2367.68 | H6: 308.5 | I6: =G6-H6 -> 2059.18 | J6: 20241.17 | K6: 2387.48 | L6: 528.03
B7: 6 | C7: Ventive Hospital | D7: 552.2 | E7: 23.35 | F7: 12896.17 | G7: 2574.43 | H7: 421.27 | I7: =G7-H7 -> 2153.16 | J7: 15049.33 | K7: 2496.42 | L7: 588.16
B8: 7 | C8: Lemon Tree Hotel | D8: 107.67 | E8: 79.22 | F8: 8530.12 | G8: 2003.65 | H8: 97.8 | I8: =G8-H8 -> 1905.85 | J8: 10435.97 | K8: 1473.34 | L8: 297.55
B10: S.No. | C10: Company | D10: CMP Rs. | E10: Sales Rs.Cr. | F10: EBITDA Margin % | G10: EBITDA | H10: PAT 12M Rs.Cr.
B11: 1 | C11: Indian Hotels Co | D11: 718 | E11: 9987.33 | F11: 35.97 | G11: =E11*F11 -> 359244.26 | H11: 1943.44
B12: 2 | C12: ITC Hotels | D12: 158.51 | E12: 4259.88 | F12: 39.65 | G12: =E12*F12 -> 168904.24 | H12: 921.57
B13: 3 | C13: Leela Palaces Hotels | D13: 568.95 | E13: 1604.46 | F13: 51.04 | G13: =E13*F13 -> 81891.638 | H13: 448.62
B14: 4 | C14: EIH | D14: 297.85 | E14: 3023.01 | F14: 41.5 | G14: =E14*F14 -> 125454.92 | H14: 726.07
B15: 5 | C15: Chalet Hotels | D15: 830.25 | E15: 2387.48 | F15: 46.16 | G15: =E15*F15 -> 110206.08 | H15: 535.27
B16: 6 | C16: Ventive Hospital | D16: 552.2 | E16: 2496.42 | F16: 55.45 | G16: =E16*F16 -> 138426.49 | H16: 484.72
B17: 7 | C17: Lemon Tree Hotel | D17: 107.67 | E17: 1473.34 | F17: 48.07 | G17: =E17*F17 -> 70823.454 | H17: 255.91

Sheet Data_One Pager
A1: Date | B1: Price
A2: 46301 | B2: 736 | P2: Category | Q2: Number of equity shares held | R2: % of holding
A3: 46300 | B3: 725 | P3: Promoters | Q3: 507655313 | R3: 0.3566 | T3: Promoters | U3: 0.3812
A4: 46296 | B4: 718 | P4: Other Entities of the Promoter Group | Q4: 34902429 | R4: 0.0245 | T4: DII | U4: 0.2447
A5: 46295 | B5: 728.65 | P5: Mutual Funds & UTI | Q5: 184481396 | R5: 0.1296 | T5: FII | U5: 0.2171
A6: 46294 | B6: 714.35 | P6: Banks, Financial Institutions, States and Central Government | Q6: 65963120 | R6: 0.0464 | T6: Public+Government | U6: 0.1572
A7: 46293 | B7: 711 | P7: Insurance Companies | Q7: 70490071 | R7: 0.0495
A8: 46290 | B8: 726.8 | P8: Foreign Institutional Investors and Foreign Portfolio Investors – Corporate | Q8: 330844614 | R8: 0.2324
A9: 46289 | B9: 728.8 | P9: NRI's / OCB's / Foreign Nationals | Q9: 12335274 | R9: 0.0087
A10: 46288 | B10: 743.7 | P10: Corporate Bodies / Trust | Q10: 14928531 | R10: 0.0105
A11: 46287 | B11: 736.25 | P11: Indian Public & Others | Q11: 196721749 | R11: 0.1382
A12: 46286 | B12: 745 | P12: Alternate Investment Fund | Q12: 1859488 | R12: 0.0013
A13: 46283 | B13: 732.75 | P13: IEPF account | Q13: 3250242 | R13: 0.0023
A14: 46282 | B14: 726.65
A15: 46281 | B15: 713.4
A16: 46280 | B16: 715
A17: 46276 | B17: 718.5 | P17: Name | Q17: % Increase in remuneration over the previous year | R17: Ratio to median Remuneration
A18: 46275 | B18: 715.75 | P18: Non-Executive Directors
A19: 46274 | B19: 722.75 | P19: Mr. N. Chandrasekaran¹ | Q19: - | R19: -
A20: 46273 | B20: 720 | P20: Mr. Nasser Munjee | Q20: 0.12 | R20: 18.7
A21: 46272 | B21: 716.2 | P21: Mr. Venkataramanan Anantharaman | Q21: 0.12 | R21: 17.8
A22: 46269 | B22: 720 | P22: Ms. Hema Ravichandar | Q22: 0.13 | R22: 17.8
A23: 46268 | B23: 732 | P23: Mr. Anupam Narayan | Q23: 0.13 | R23: 17.6
A24: 46267 | B24: 727.7 | P24: Executive Director
A25: 46266 | B25: 718 | P25: Mr. Puneet Chhatwal – Managing Director & Chief Executive Officer | Q25: 0.09 | R25: 521.7
A26: 46265 | B26: 737.9 | P26: Key Managerial Personnel
A27: 46262 | B27: 706.4 | P27: Mr. Ankur Dalwani- Executive Vice President & Chief Financial Officer² | Q27: *** | R27: ***
A28: 46261 | B28: 718.5 | P28: Mr. Beejal Desai, Executive VP – Corporate Affairs & Company Secretary (Group)³ | Q28: *** | R28: ***
A29: 46260 | B29: 721 | P29: Ms. Melisa Alva – Senior Vice President & Company Secretary4 | Q29: *** | R29: ***
A30: 46259 | B30: 730
A31: 46258 | B31: 728.9 | P31: ¹ As a policy, Mr. N Chandrasekaran, Chairman, has abstained from receiving commission from the Company.
A32: 46255 | B32: 730 | P32: ² Mr. Ankur Dalwani appointed w.e.f. July 1, 2024.
A33: 46254 | B33: 735.85 | P33: ³ Mr. Beejal Desai superannuated on February 12, 2026.
A34: 46253 | B34: 723.35 | P34: 4 Ms. Melisa Alva appointed w.e.f. February 13, 2026.
A35: 46252 | B35: 719 | P35: *** Since the remuneration is only for part of the year (either in current year or previous year), the percentage increase in remuneration and the ratio of their remuneration to median remuneration is not comparable and hence not stated.
A36: 46251 | B36: 720
A37: 46248 | B37: 720
A38: 46247 | B38: 721.75
A39: 46246 | B39: 724
A40: 46245 | B40: 724
A41: 46244 | B41: 728.7
A42: 46241 | B42: 731
A43: 46240 | B43: 736
A44: 46239 | B44: 741.05
A45: 46238 | B45: 750
A46: 46237 | B46: 752
A47: 46234 | B47: 738.55
... A50: 46231 | B50: 734.7
A51: 46230 | B51: 733.75 | E51: Particulars | F51: 43525 | G51: 43891 | H51: 44256 | I51: 44621 | J51: 44986 | K51: 45352 | L51: 45717 | M51: 46082
A52: 46227 | B52: 727.45 | E52: Room Income | F52: 1155.01 | G52: 1135.51 | H52: 471.55 | I52: 848.19 | J52: 1594.04 | K52: 1952.72 | L52: 2238.42 | M52: 2374.64
A53: 46226 | B53: 724.05 | E53: Food, Beverage & Banqueting Income | F53: 1136.65 | G53: 1091.72 | H53: 401.8 | I53: 714.47 | J53: 1381.47 | K53: 1562.9 | L53: 1650.32 | M53: 1803.48
A54: 46225 | B54: 724.85 | E54: Other Operating Income | F54: 488.75 | G54: 516.24 | H54: 169.32 | I54: 242.03 | J54: 338.08 | K54: 426.7 | L54: 483.94 | M54: 557.22
A55: 46224 | B55: 731.6 | E55: Management & Reimbursable Fees | F55: - | G55: - | H55: 90.48 | I55: 198.65 | J55: 390.65 | K55: 463.28 | L55: 543.86 | M55: 644.21
A56: 46223 | B56: 725.05 | E56: Non-operating Income | F56: 90.5 | G56: 134.41 | H56: 110.52 | I56: 149.08 | J56: 107.08 | K56: 184.51 | L56: 228.55 | M56: 260.61
A57: 46220 | B57: 727.9 | E57: Total Income | F57: 2870.91 | G57: 2877.88 | H57: 1243.67 | I57: 2152.42 | J57: 3811.32 | K57: 4590.11 | L57: 5145.09 | M57: 5640.16
A58: 46219 | B58: 731.45
A59: 46218 | B59: 743.2 | E59: Average Rate Per Room | F59: 11003 | G59: 10734 | H59: 7351 | I59: 9717 | J59: 13736 | K59: 15414 | L59: 17315 | M59: 18507
A60: 46217 | B60: 733.3 | E60: Revenue Per Available Room (RevPAR) | F60: - | G60: - | H60: - | I60: - | J60: 9851 | K60: 11821 | L60: 13368 | M60: 14390
A61: 46216 | B61: 738.55 | E61: Occupancy (%) | F61: 0.68 | G61: 0.67 | H61: 0.39 | I61: 0.53 | J61: 0.72 | K61: 0.77 | L61: 0.77 | M61: 0.78
A62: 46213 | B62: 752.3
A63: 46212 | B63: 731.45
A64: 46211 | B64: 722.9
A65: 46210 | B65: 745.95
A66: 46209 | B66: 738.15
A67: 46206 | B67: 728.6
A68: 46205 | B68: 720.7
A69: 46204 | B69: 718.75
A70: 46203 | B70: 713.95
A71: 46202 | B71: 707.05
A72: 46198 | B72: 720.65
A73: 46197 | B73: 725.5
... A992: 44841 | B992: 341.35

Sheet Economic One pager Input
F3: Inflation
F4: 2024 | G4: 2025E | H4: 2026F | I4: 2027F
E5: World | F5: 5.8 | G5: 4.1 | H5: 4.4 | I5: 3.7
E6: Advanced Economies | F6: 2.6 | G6: 2.5 | H6: 2.8 | I6: 2.2
E7: Emerging Economies | F7: 8 | G7: 5.2 | H7: 5.5 | I7: 4.6
E8: United States (US) | F8: 3 | G8: 2.7 | H8: 3.2 | I8: 2.1
E9: United Kingdom (UK) | F9: 2.5 | G9: 3.4 | H9: 3.2 | I9: 2.4
E10: India | F10: 4.6 | G10: 2.1 | H10: 4.7 | I10: 4
E11: China | F11: 0.2 | G11: 0 | H11: 1.2 | I11: 1.5
E12: Japan | F12: 2.7 | G12: 3.2 | H12: 2.2 | I12: 2.3
A14: Year | B14: FTAs in India (in Lakhs) | C14: NRI Arrivals (in Lakhs) | D14: International Tourist Arrivals (in Lakhs)
A15: 2019 | B15: 109.3 | C15: 69.8 | D15: 179.1
A16: 2020 | B16: 27.4 | C16: 35.9 | D16: 63.3
A17: 2021 | B17: 15.2 | C17: 54.8 | D17: 70
A18: 2022 | B18: 64.4 | C18: 78.9 | D18: 143.3
A19: 2023 | B19: 95.1 | C19: 93.8 | D19: 188.9
A20: 2024 | B20: 99.5 | C20: 106.2 | D20: 205.7
A21: 2025 | B21: 91.5 | C21: 110.7 | D21: 202.2
C24: % Distribution of FTAs by Purpose of Visit
A25: Source Territory/ Country | B25: FTAs (in numbers) | C25: Business and Professional | D25: Indian Diaspora | E25: Leisure Holiday and Recreation | F25: Medical | G25: Pilgrimage | H25: Student | I25: Others
A26: Grand Total | B26: 9148766 | C26: 0.1169 | D26: 0.3289 | E26: 0.3928 | F26: 0.0554 | G26: 0.0004 | H26: 0.0073 | I26: =9.22%+0.6% -> 0.0982
A30: Year
A31: previous year
A32: previous year | B32: IN INR Cr.
A33: 1991 | B33: 4318
A34: 2001 | B34: 15083
A35: 2011 | B35: 83037
A36: 2012 | B36: 95060
A37: 2013 | B37: 107563
A38: 2014 | B38: 120366
A39: 2015 | B39: 134843
A40: 2016 | B40: 150750
A41: 2017 | B41: 178189
A42: 2018 | B42: 195312
A43: 2019 | B43: 216467
A44: 2020 | B44: 95738
... A49: 2025 | B49: 276831
B52: Annual Growth Rate (%)
A53: Year | B53: Domestic | C53: Foreign
A54: 2019 | B54: 0.2526 | C54: 0.0886
A55: 2020 | B55: -0.7372 | C55: -0.7717
A56: 2021 | B56: 0.1105 | C56: -0.8529
A57: 2022 | B57: 1.5545 | C57: 7.1426
A58: 2023 | B58: 0.4493 | C58: 1.2406
A59: 2024 | B59: 0.174 | C59: 0.0822
A60: 2025 | B60: 0.4551 | C60: 0.2163
